Workbook

Sheet Base vs Growth vs Downside key
A1: Base vs Growth vs Downside: key metrics
A2: Summary · Downside
A4: Variable / dimension | B4: 2026-11 | C4: 2026-12 | D4: 2027-01 | E4: 2027-02 | F4: 2027-03 | G4: 2027-04 | H4: 2027-05 | I4: 2027-06 | J4: 2027-07 | K4: 2027-08 | L4: 2027-09 | M4: 2027-10 | N4: 2027-11 | O4: 2027-12 | P4: 2028-01 | Q4: 2028-02 | R4: 2028-03 | S4: 2028-04 | T4: 2028-05 | U4: 2028-06 | V4: 2028-07 | W4: 2028-08 | X4: 2028-09 | Y4: 2028-10
A5: Customers | B5: =SUM('Model inputs'!B7,'Model inputs'!B8) -> 0 | C5: =SUM('Model inputs'!C7,'Model inputs'!C8) -> 0 | D5: =SUM('Model inputs'!D7,'Model inputs'!D8) -> 0 | E5: =SUM('Model inputs'!E7,'Model inputs'!E8) -> 0 | F5: =SUM('Model inputs'!F7,'Model inputs'!F8) -> 0 | G5: =SUM('Model inputs'!G7,'Model inputs'!G8) -> 0 | H5: =SUM('Model inputs'!H7,'Model inputs'!H8) -> 2 | I5: =SUM('Model inputs'!I7,'Model inputs'!I8) -> 4 | ... Y5: =SUM('Model inputs'!Y7,'Model inputs'!Y8) -> 42
A6: Customers > Growth | B6: =SUM('Model inputs'!B10,'Model inputs'!B11) -> 0 | C6: =SUM('Model inputs'!C10,'Model inputs'!C11) -> 0 | D6: =SUM('Model inputs'!D10,'Model inputs'!D11) -> 0 | E6: =SUM('Model inputs'!E10,'Model inputs'!E11) -> 4 | F6: =SUM('Model inputs'!F10,'Model inputs'!F11) -> 8 | G6: =SUM('Model inputs'!G10,'Model inputs'!G11) -> 12 | H6: =SUM('Model inputs'!H10,'Model inputs'!H11) -> 17 | I6: =SUM('Model inputs'!I10,'Model inputs'!I11) -> 22 | ... Y6: =SUM('Model inputs'!Y10,'Model inputs'!Y11) -> 125
A7: Customers > delta | B7: ='Base vs Growth vs Downside key'!B6-'Base vs Growth vs Downside key'!B5 -> 0 | C7: ='Base vs Growth vs Downside key'!C6-'Base vs Growth vs Downside key'!C5 -> 0 | D7: ='Base vs Growth vs Downside key'!D6-'Base vs Growth vs Downside key'!D5 -> 0 | E7: ='Base vs Growth vs Downside key'!E6-'Base vs Growth vs Downside key'!E5 -> 4 | F7: ='Base vs Growth vs Downside key'!F6-'Base vs Growth vs Downside key'!F5 -> 8 | G7: ='Base vs Growth vs Downside key'!G6-'Base vs Growth vs Downside key'!G5 -> 12 | H7: ='Base vs Growth vs Downside key'!H6-'Base vs Growth vs Downside key'!H5 -> 15 | I7: ='Base vs Growth vs Downside key'!I6-'Base vs Growth vs Downside key'!I5 -> 18 | ... Y7: ='Base vs Growth vs Downside key'!Y6-'Base vs Growth vs Downside key'!Y5 -> 83
A8: Revenue | B8: =SUM('Model inputs'!B21,'Model inputs'!B22) -> 0 | C8: =SUM('Model inputs'!C21,'Model inputs'!C22) -> 0 | D8: =SUM('Model inputs'!D21,'Model inputs'!D22) -> 0 | E8: =SUM('Model inputs'!E21,'Model inputs'!E22) -> 0 | F8: =SUM('Model inputs'!F21,'Model inputs'!F22) -> 0 | G8: =SUM('Model inputs'!G21,'Model inputs'!G22) -> 0 | H8: =SUM('Model inputs'!H21,'Model inputs'!H22) -> 198 | I8: =SUM('Model inputs'!I21,'Model inputs'!I22) -> 696 | ... Y8: =SUM('Model inputs'!Y21,'Model inputs'!Y22) -> 6558
A9: Revenue > Growth | B9: =SUM('Model inputs'!B24,'Model inputs'!B25) -> 0 | C9: =SUM('Model inputs'!C24,'Model inputs'!C25) -> 0 | D9: =SUM('Model inputs'!D24,'Model inputs'!D25) -> 0 | E9: =SUM('Model inputs'!E24,'Model inputs'!E25) -> 696 | F9: =SUM('Model inputs'!F24,'Model inputs'!F25) -> 1092 | G9: =SUM('Model inputs'!G24,'Model inputs'!G25) -> 1788 | H9: =SUM('Model inputs'!H24,'Model inputs'!H25) -> 2583 | I9: =SUM('Model inputs'!I24,'Model inputs'!I25) -> 3378 | ... Y9: =SUM('Model inputs'!Y24,'Model inputs'!Y25) -> 19875
A10: Revenue > delta | B10: ='Base vs Growth vs Downside key'!B9-'Base vs Growth vs Downside key'!B8 -> 0 | C10: ='Base vs Growth vs Downside key'!C9-'Base vs Growth vs Downside key'!C8 -> 0 | D10: ='Base vs Growth vs Downside key'!D9-'Base vs Growth vs Downside key'!D8 -> 0 | E10: ='Base vs Growth vs Downside key'!E9-'Base vs Growth vs Downside key'!E8 -> 696 | F10: ='Base vs Growth vs Downside key'!F9-'Base vs Growth vs Downside key'!F8 -> 1092 | G10: ='Base vs Growth vs Downside key'!G9-'Base vs Growth vs Downside key'!G8 -> 1788 | H10: ='Base vs Growth vs Downside key'!H9-'Base vs Growth vs Downside key'!H8 -> 2385 | I10: ='Base vs Growth vs Downside key'!I9-'Base vs Growth vs Downside key'!I8 -> 2682 | ... Y10: ='Base vs Growth vs Downside key'!Y9-'Base vs Growth vs Downside key'!Y8 -> 13317
A11: Gross margin | B11: =IFERROR('Model inputs'!B14/'Base vs Growth vs Downside key'!B8,"") | C11: =IFERROR('Model inputs'!C14/'Base vs Growth vs Downside key'!C8,"") | D11: =IFERROR('Model inputs'!D14/'Base vs Growth vs Downside key'!D8,"") | E11: =IFERROR('Model inputs'!E14/'Base vs Growth vs Downside key'!E8,"") | F11: =IFERROR('Model inputs'!F14/'Base vs Growth vs Downside key'!F8,"") | G11: =IFERROR('Model inputs'!G14/'Base vs Growth vs Downside key'!G8,"") | H11: =IFERROR('Model inputs'!H14/'Base vs Growth vs Downside key'!H8,"") -> 0.29454545 | I11: =IFERROR('Model inputs'!I14/'Base vs Growth vs Downside key'!I8,"") -> 0.26275862 | ... Y11: =IFERROR('Model inputs'!Y14/'Base vs Growth vs Downside key'!Y8,"") -> 0.29537054
A12: Gross margin > Growth | B12: =IFERROR('Model inputs'!B15/'Base vs Growth vs Downside key'!B9,"") | C12: =IFERROR('Model inputs'!C15/'Base vs Growth vs Downside key'!C9,"") | D12: =IFERROR('Model inputs'!D15/'Base vs Growth vs Downside key'!D9,"") | E12: =IFERROR('Model inputs'!E15/'Base vs Growth vs Downside key'!E9,"") -> 0.68864368 | F12: =IFERROR('Model inputs'!F15/'Base vs Growth vs Downside key'!F9,"") -> 0.70928938 | G12: =IFERROR('Model inputs'!G15/'Base vs Growth vs Downside key'!G9,"") -> 0.70975391 | H12: =IFERROR('Model inputs'!H15/'Base vs Growth vs Downside key'!H9,"") -> 0.71132327 | I12: =IFERROR('Model inputs'!I15/'Base vs Growth vs Downside key'!I9,"") -> 0.71215394 | ... Y12: =IFERROR('Model inputs'!Y15/'Base vs Growth vs Downside key'!Y9,"") -> 0.71408805
A13: Gross margin > delta | H13: ='Base vs Growth vs Downside key'!H12-'Base vs Growth vs Downside key'!H11 -> 0.41677781 | I13: ='Base vs Growth vs Downside key'!I12-'Base vs Growth vs Downside key'!I11 -> 0.44939532 | J13: ='Base vs Growth vs Downside key'!J12-'Base vs Growth vs Downside key'!J11 -> 0.42662982 | K13: ='Base vs Growth vs Downside key'!K12-'Base vs Growth vs Downside key'!K11 -> 0.4115293 | L13: ='Base vs Growth vs Downside key'!L12-'Base vs Growth vs Downside key'!L11 -> 0.42797997 | M13: ='Base vs Growth vs Downside key'!M12-'Base vs Growth vs Downside key'!M11 -> 0.4186382 | N13: ='Base vs Growth vs Downside key'!N12-'Base vs Growth vs Downside key'!N11 -> 0.4115709 | O13: ='Base vs Growth vs Downside key'!O12-'Base vs Growth vs Downside key'!O11 -> 0.42153065 | ... Y13: ='Base vs Growth vs Downside key'!Y12-'Base vs Growth vs Downside key'!Y11 -> 0.41871751
A14: Net burn | B14: =-'Model inputs'!B18 -> 2115.2 | C14: =-'Model inputs'!C18 -> 2115.2 | D14: =-'Model inputs'!D18 -> 2115.2 | E14: =-'Model inputs'!E18 -> 2115.2 | F14: =-'Model inputs'!F18 -> 2115.2 | G14: =-'Model inputs'!G18 -> 2115.2 | H14: =-'Model inputs'!H18 -> 2041.68 | I14: =-'Model inputs'!I18 -> 1917.12 | ... Y14: =-'Model inputs'!Y18 -> 162.96
A15: Net burn > Growth | B15: =-'Model inputs'!B19 -> 2115.2 | C15: =-'Model inputs'!C19 -> 2115.2 | D15: =-'Model inputs'!D19 -> 2115.2 | E15: =-'Model inputs'!E19 -> 1620.704 | F15: =-'Model inputs'!F19 -> 1325.456 | G15: =-'Model inputs'!G19 -> 830.96 | H15: =-'Model inputs'!H19 -> 262.652 | I15: =-'Model inputs'!I19 -> -305.656 | ... Y15: =-'Model inputs'!Y19 -> -12092.5
A16: Net burn > delta | B16: ='Base vs Growth vs Downside key'!B15-'Base vs Growth vs Downside key'!B14 -> 0 | C16: ='Base vs Growth vs Downside key'!C15-'Base vs Growth vs Downside key'!C14 -> 0 | D16: ='Base vs Growth vs Downside key'!D15-'Base vs Growth vs Downside key'!D14 -> 0 | E16: ='Base vs Growth vs Downside key'!E15-'Base vs Growth vs Downside key'!E14 -> -494.496 | F16: ='Base vs Growth vs Downside key'!F15-'Base vs Growth vs Downside key'!F14 -> -789.744 | G16: ='Base vs Growth vs Downside key'!G15-'Base vs Growth vs Downside key'!G14 -> -1284.24 | H16: ='Base vs Growth vs Downside key'!H15-'Base vs Growth vs Downside key'!H14 -> -1779.028 | I16: ='Base vs Growth vs Downside key'!I15-'Base vs Growth vs Downside key'!I14 -> -2222.776 | ... Y16: ='Base vs Growth vs Downside key'!Y15-'Base vs Growth vs Downside key'!Y14 -> -12255.46
A17: Ending cash | B17: =IF(IF(IF(IF(ISERROR('Model inputs'!B16=1),'Model inputs'!B16=1,IF('Model inputs'!B16="","",'Model inputs'!B16=1))="",FALSE,IF(ISERROR('Model inputs'!B16=1),'Model inputs'!B16=1,IF('Model inputs'!B16="","",'Model inputs'!B16=1))),IF('Model inputs'!AB26="","",'Model inputs'!AB26),IF('Model inputs'!AA12="","",'Model inputs'!AA12))="",0,IF(IF(IF(ISERROR('Model inputs'!B16=1),'Model inputs'!B16=1,IF('Model inputs'!B16="","",'Model inputs'!B16=1))="",FALSE,IF(ISERROR('Model inputs'!B16=1),'Model inputs'!B16=1,IF('Model inputs'!B16="","",'Model inputs'!B16=1))),IF('Model inputs'!AB26="","",'Model inputs'!AB26),IF('Model inputs'!AA12="","",'Model inputs'!AA12)))+'Model inputs'!B18 -> 22884.8 | C17: =IF(IF(IF(IF(ISERROR('Model inputs'!C16=1),'Model inputs'!C16=1,IF('Model inputs'!C16="","",'Model inputs'!C16=1))="",FALSE,IF(ISERROR('Model inputs'!C16=1),'Model inputs'!C16=1,IF('Model inputs'!C16="","",'Model inputs'!C16=1))),IF('Model inputs'!AB26="","",'Model inputs'!AB26),IF('Base vs Growth vs Downside key'!B17="","",'Base vs Growth vs Downside key'!B17))="",0,IF(IF(IF(ISERROR('Model inputs'!C16=1),'Model inputs'!C16=1,IF('Model inputs'!C16="","",'Model inputs'!C16=1))="",FALSE,IF(ISERROR('Model inputs'!C16=1),'Model inputs'!C16=1,IF('Model inputs'!C16="","",'Model inputs'!C16=1))),IF('Model inputs'!AB26="","",'Model inputs'!AB26),IF('Base vs Growth vs Downside key'!B17="","",'Base vs Growth vs Downside key'!B17)))+'Model inputs'!C18 -> 20769.6 | D17: =IF(IF(IF(IF(ISERROR('Model inputs'!D16=1),'Model inputs'!D16=1,IF('Model inputs'!D16="","",'Model inputs'!D16=1))="",FALSE,IF(ISERROR('Model inputs'!D16=1),'Model inputs'!D16=1,IF('Model inputs'!D16="","",'Model inputs'!D16=1))),IF('Model inputs'!AB26="","",'Model inputs'!AB26),IF('Base vs Growth vs Downside key'!C17="","",'Base vs Growth vs Downside key'!C17))="",0,IF(IF(IF(ISERROR('Model inputs'!D16=1),'Model inputs'!D16=1,IF('Model inputs'!D16="","",'Model inputs'!D16=1))="",FALSE,IF(ISERROR('Model inputs'!D16=1),'Model inputs'!D16=1,IF('Model inputs'!D16="","",'Model inputs'!D16=1))),IF('Model inputs'!AB26="","",'Model inputs'!AB26),IF('Base vs Growth vs Downside key'!C17="","",'Base vs Growth vs Downside key'!C17)))+'Model inputs'!D18 -> 18654.4 | E17: =IF(IF(IF(IF(ISERROR('Model inputs'!E16=1),'Model inputs'!E16=1,IF('Model inputs'!E16="","",'Model inputs'!E16=1))="",FALSE,IF(ISERROR('Model inputs'!E16=1),'Model inputs'!E16=1,IF('Model inputs'!E16="","",'Model inputs'!E16=1))),IF('Model inputs'!AB26="","",'Model inputs'!AB26),IF('Base vs Growth vs Downside key'!D17="","",'Base vs Growth vs Downside key'!D17))="",0,IF(IF(IF(ISERROR('Model inputs'!E16=1),'Model inputs'!E16=1,IF('Model inputs'!E16="","",'Model inputs'!E16=1))="",FALSE,IF(ISERROR('Model inputs'!E16=1),'Model inputs'!E16=1,IF('Model inputs'!E16="","",'Model inputs'!E16=1))),IF('Model inputs'!AB26="","",'Model inputs'!AB26),IF('Base vs Growth vs Downside key'!D17="","",'Base vs Growth vs Downside key'!D17)))+'Model inputs'!E18 -> 16539.2 | F17: =IF(IF(IF(IF(ISERROR('Model inputs'!F16=1),'Model inputs'!F16=1,IF('Model inputs'!F16="","",'Model inputs'!F16=1))="",FALSE,IF(ISERROR('Model inputs'!F16=1),'Model inputs'!F16=1,IF('Model inputs'!F16="","",'Model inputs'!F16=1))),IF('Model inputs'!AB26="","",'Model inputs'!AB26),IF('Base vs Growth vs Downside key'!E17="","",'Base vs Growth vs Downside key'!E17))="",0,IF(IF(IF(ISERROR('Model inputs'!F16=1),'Model inputs'!F16=1,IF('Model inputs'!F16="","",'Model inputs'!F16=1))="",FALSE,IF(ISERROR('Model inputs'!F16=1),'Model inputs'!F16=1,IF('Model inputs'!F16="","",'Model inputs'!F16=1))),IF('Model inputs'!AB26="","",'Model inputs'!AB26),IF('Base vs Growth vs Downside key'!E17="","",'Base vs Growth vs Downside key'!E17)))+'Model inputs'!F18 -> 14424 | G17: =IF(IF(IF(IF(ISERROR('Model inputs'!G16=1),'Model inputs'!G16=1,IF('Model inputs'!G16="","",'Model inputs'!G16=1))="",FALSE,IF(ISERROR('Model inputs'!G16=1),'Model inputs'!G16=1,IF('Model inputs'!G16="","",'Model inputs'!G16=1))),IF('Model inputs'!AB26="","",'Model inputs'!AB26),IF('Base vs Growth vs Downside key'!F17="","",'Base vs Growth vs Downside key'!F17))="",0,IF(IF(IF(ISERROR('Model inputs'!G16=1),'Model inputs'!G16=1,IF('Model inputs'!G16="","",'Model inputs'!G16=1))="",FALSE,IF(ISERROR('Model inputs'!G16=1),'Model inputs'!G16=1,IF('Model inputs'!G16="","",'Model inputs'!G16=1))),IF('Model inputs'!AB26="","",'Model inputs'!AB26),IF('Base vs Growth vs Downside key'!F17="","",'Base vs Growth vs Downside key'!F17)))+'Model inputs'!G18 -> 12308.8 | H17: =IF(IF(IF(IF(ISERROR('Model inputs'!H16=1),'Model inputs'!H16=1,IF('Model inputs'!H16="","",'Model inputs'!H16=1))="",FALSE,IF(ISERROR('Model inputs'!H16=1),'Model inputs'!H16=1,IF('Model inputs'!H16="","",'Model inputs'!H16=1))),IF('Model inputs'!AB26="","",'Model inputs'!AB26),IF('Base vs Growth vs Downside key'!G17="","",'Base vs Growth vs Downside key'!G17))="",0,IF(IF(IF(ISERROR('Model inputs'!H16=1),'Model inputs'!H16=1,IF('Model inputs'!H16="","",'Model inputs'!H16=1))="",FALSE,IF(ISERROR('Model inputs'!H16=1),'Model inputs'!H16=1,IF('Model inputs'!H16="","",'Model inputs'!H16=1))),IF('Model inputs'!AB26="","",'Model inputs'!AB26),IF('Base vs Growth vs Downside key'!G17="","",'Base vs Growth vs Downside key'!G17)))+'Model inputs'!H18 -> 10267.12 | I17: =IF(IF(IF(IF(ISERROR('Model inputs'!I16=1),'Model inputs'!I16=1,IF('Model inputs'!I16="","",'Model inputs'!I16=1))="",FALSE,IF(ISERROR('Model inputs'!I16=1),'Model inputs'!I16=1,IF('Model inputs'!I16="","",'Model inputs'!I16=1))),IF('Model inputs'!AB26="","",'Model inputs'!AB26),IF('Base vs Growth vs Downside key'!H17="","",'Base vs Growth vs Downside key'!H17))="",0,IF(IF(IF(ISERROR('Model inputs'!I16=1),'Model inputs'!I16=1,IF('Model inputs'!I16="","",'Model inputs'!I16=1))="",FALSE,IF(ISERROR('Model inputs'!I16=1),'Model inputs'!I16=1,IF('Model inputs'!I16="","",'Model inputs'!I16=1))),IF('Model inputs'!AB26="","",'Model inputs'!AB26),IF('Base vs Growth vs Downside key'!H17="","",'Base vs Growth vs Downside key'!H17)))+'Model inputs'!I18 -> 8350 | J17: =IF(IF(IF(IF(ISERROR('Model inputs'!J16=1),'Model inputs'!J16=1,IF('Model inputs'!J16="","",'Model inputs'!J16=1))="",FALSE,IF(ISERROR('Model inputs'!J16=1),'Model inputs'!J16=1,IF('Model inputs'!J16="","",'Model inputs'!J16=1))),IF('Model inputs'!AB26="","",'Model inputs'!AB26),IF('Base vs Growth vs Downside key'!I17="","",'Base vs Growth vs Downside key'!I17))="",0,IF(IF(IF(ISERROR('Model inputs'!J16=1),'Model inputs'!J16=1,IF('Model inputs'!J16="","",'Model inputs'!J16=1))="",FALSE,IF(ISERROR('Model inputs'!J16=1),'Model inputs'!J16=1,IF('Model inputs'!J16="","",'Model inputs'!J16=1))),IF('Model inputs'!AB26="","",'Model inputs'!AB26),IF('Base vs Growth vs Downside key'!I17="","",'Base vs Growth vs Downside key'!I17)))+'Model inputs'!J18 -> 6506.4 | K17: =IF(IF(IF(IF(ISERROR('Model inputs'!K16=1),'Model inputs'!K16=1,IF('Model inputs'!K16="","",'Model inputs'!K16=1))="",FALSE,IF(ISERROR('Model inputs'!K16=1),'Model inputs'!K16=1,IF('Model inputs'!K16="","",'Model inputs'!K16=1))),IF('Model inputs'!AB26="","",'Model inputs'!AB26),IF('Base vs Growth vs Downside key'!J17="","",'Base vs Growth vs Downside key'!J17))="",0,IF(IF(IF(ISERROR('Model inputs'!K16=1),'Model inputs'!K16=1,IF('Model inputs'!K16="","",'Model inputs'!K16=1))="",FALSE,IF(ISERROR('Model inputs'!K16=1),'Model inputs'!K16=1,IF('Model inputs'!K16="","",'Model inputs'!K16=1))),IF('Model inputs'!AB26="","",'Model inputs'!AB26),IF('Base vs Growth vs Downside key'!J17="","",'Base vs Growth vs Downside key'!J17)))+'Model inputs'!K18 -> 4736.32 | L17: =IF(IF(IF(IF(ISERROR('Model inputs'!L16=1),'Model inputs'!L16=1,IF('Model inputs'!L16="","",'Model inputs'!L16=1))="",FALSE,IF(ISERROR('Model inputs'!L16=1),'Model inputs'!L16=1,IF('Model inputs'!L16="","",'Model inputs'!L16=1))),IF('Model inputs'!AB26="","",'Model inputs'!AB26),IF('Base vs Growth vs Downside key'!K17="","",'Base vs Growth vs Downside key'!K17))="",0,IF(IF(IF(ISERROR('Model inputs'!L16=1),'Model inputs'!L16=1,IF('Model inputs'!L16="","",'Model inputs'!L16=1))="",FALSE,IF(ISERROR('Model inputs'!L16=1),'Model inputs'!L16=1,IF('Model inputs'!L16="","",'Model inputs'!L16=1))),IF('Model inputs'!AB26="","",'Model inputs'!AB26),IF('Base vs Growth vs Downside key'!K17="","",'Base vs Growth vs Downside key'!K17)))+'Model inputs'!L18 -> 3090.8 | M17: =IF(IF(IF(IF(ISERROR('Model inputs'!M16=1),'Model inputs'!M16=1,IF('Model inputs'!M16="","",'Model inputs'!M16=1))="",FALSE,IF(ISERROR('Model inputs'!M16=1),'Model inputs'!M16=1,IF('Model inputs'!M16="","",'Model inputs'!M16=1))),IF('Model inputs'!AB26="","",'Model inputs'!AB26),IF('Base vs Growth vs Downside key'!L17="","",'Base vs Growth vs Downside key'!L17))="",0,IF(IF(IF(ISERROR('Model inputs'!M16=1),'Model inputs'!M16=1,IF('Model inputs'!M16="","",'Model inputs'!M16=1))="",FALSE,IF(ISERROR('Model inputs'!M16=1),'Model inputs'!M16=1,IF('Model inputs'!M16="","",'Model inputs'!M16=1))),IF('Model inputs'!AB26="","",'Model inputs'!AB26),IF('Base vs Growth vs Downside key'!L17="","",'Base vs Growth vs Downside key'!L17)))+'Model inputs'!M18 -> 1518.8 | N17: =IF(IF(IF(IF(ISERROR('Model inputs'!N16=1),'Model inputs'!N16=1,IF('Model inputs'!N16="","",'Model inputs'!N16=1))="",FALSE,IF(ISERROR('Model inputs'!N16=1),'Model inputs'!N16=1,IF('Model inputs'!N16="","",'Model inputs'!N16=1))),IF('Model inputs'!AB26="","",'Model inputs'!AB26),IF('Base vs Growth vs Downside key'!M17="","",'Base vs Growth vs Downside key'!M17))="",0,IF(IF(IF(ISERROR('Model inputs'!N16=1),'Model inputs'!N16=1,IF('Model inputs'!N16="","",'Model inputs'!N16=1))="",FALSE,IF(ISERROR('Model inputs'!N16=1),'Model inputs'!N16=1,IF('Model inputs'!N16="","",'Model inputs'!N16=1))),IF('Model inputs'!AB26="","",'Model inputs'!AB26),IF('Base vs Growth vs Downside key'!M17="","",'Base vs Growth vs Downside key'!M17)))+'Model inputs'!N18 -> 20.32 | O17: =IF(IF(IF(IF(ISERROR('Model inputs'!O16=1),'Model inputs'!O16=1,IF('Model inputs'!O16="","",'Model inputs'!O16=1))="",FALSE,IF(ISERROR('Model inputs'!O16=1),'Model inputs'!O16=1,IF('Model inputs'!O16="","",'Model inputs'!O16=1))),IF('Model inputs'!AB26="","",'Model inputs'!AB26),IF('Base vs Growth vs Downside key'!N17="","",'Base vs Growth vs Downside key'!N17))="",0,IF(IF(IF(ISERROR('Model inputs'!O16=1),'Model inputs'!O16=1,IF('Model inputs'!O16="","",'Model inputs'!O16=1))="",FALSE,IF(ISERROR('Model inputs'!O16=1),'Model inputs'!O16=1,IF('Model inputs'!O16="","",'Model inputs'!O16=1))),IF('Model inputs'!AB26="","",'Model inputs'!AB26),IF('Base vs Growth vs Downside key'!N17="","",'Base vs Growth vs Downside key'!N17)))+'Model inputs'!O18 -> -1353.6 | P17: =IF(IF(IF(IF(ISERROR('Model inputs'!P16=1),'Model inputs'!P16=1,IF('Model inputs'!P16="","",'Model inputs'!P16=1))="",FALSE,IF(ISERROR('Model inputs'!P16=1),'Model inputs'!P16=1,IF('Model inputs'!P16="","",'Model inputs'!P16=1))),IF('Model inputs'!AB26="","",'Model inputs'!AB26),IF('Base vs Growth vs Downside key'!O17="","",'Base vs Growth vs Downside key'!O17))="",0,IF(IF(IF(ISERROR('Model inputs'!P16=1),'Model inputs'!P16=1,IF('Model inputs'!P16="","",'Model inputs'!P16=1))="",FALSE,IF(ISERROR('Model inputs'!P16=1),'Model inputs'!P16=1,IF('Model inputs'!P16="","",'Model inputs'!P16=1))),IF('Model inputs'!AB26="","",'Model inputs'!AB26),IF('Base vs Growth vs Downside key'!O17="","",'Base vs Growth vs Downside key'!O17)))+'Model inputs'!P18 -> -2654 | Q17: =IF(IF(IF(IF(ISERROR('Model inputs'!Q16=1),'Model inputs'!Q16=1,IF('Model inputs'!Q16="","",'Model inputs'!Q16=1))="",FALSE,IF(ISERROR('Model inputs'!Q16=1),'Model inputs'!Q16=1,IF('Model inputs'!Q16="","",'Model inputs'!Q16=1))),IF('Model inputs'!AB26="","",'Model inputs'!AB26),IF('Base vs Growth vs Downside key'!P17="","",'Base vs Growth vs Downside key'!P17))="",0,IF(IF(IF(ISERROR('Model inputs'!Q16=1),'Model inputs'!Q16=1,IF('Model inputs'!Q16="","",'Model inputs'!Q16=1))="",FALSE,IF(ISERROR('Model inputs'!Q16=1),'Model inputs'!Q16=1,IF('Model inputs'!Q16="","",'Model inputs'!Q16=1))),IF('Model inputs'!AB26="","",'Model inputs'!AB26),IF('Base vs Growth vs Downside key'!P17="","",'Base vs Growth vs Downside key'!P17)))+'Model inputs'!Q18 -> -3793.08 | R17: =IF(IF(IF(IF(ISERROR('Model inputs'!R16=1),'Model inputs'!R16=1,IF('Model inputs'!R16="","",'Model inputs'!R16=1))="",FALSE,IF(ISERROR('Model inputs'!R16=1),'Model inputs'!R16=1,IF('Model inputs'!R16="","",'Model inputs'!R16=1))),IF('Model inputs'!AB26="","",'Model inputs'!AB26),IF('Base vs Growth vs Downside key'!Q17="","",'Base vs Growth vs Downside key'!Q17))="",0,IF(IF(IF(ISERROR('Model inputs'!R16=1),'Model inputs'!R16=1,IF('Model inputs'!R16="","",'Model inputs'!R16=1))="",FALSE,IF(ISERROR('Model inputs'!R16=1),'Model inputs'!R16=1,IF('Model inputs'!R16="","",'Model inputs'!R16=1))),IF('Model inputs'!AB26="","",'Model inputs'!AB26),IF('Base vs Growth vs Downside key'!Q17="","",'Base vs Growth vs Downside key'!Q17)))+'Model inputs'!R18 -> -4858.64 | S17: =IF(IF(IF(IF(ISERROR('Model inputs'!S16=1),'Model inputs'!S16=1,IF('Model inputs'!S16="","",'Model inputs'!S16=1))="",FALSE,IF(ISERROR('Model inputs'!S16=1),'Model inputs'!S16=1,IF('Model inputs'!S16="","",'Model inputs'!S16=1))),IF('Model inputs'!AB26="","",'Model inputs'!AB26),IF('Base vs Growth vs Downside key'!R17="","",'Base vs Growth vs Downside key'!R17))="",0,IF(IF(IF(ISERROR('Model inputs'!S16=1),'Model inputs'!S16=1,IF('Model inputs'!S16="","",'Model inputs'!S16=1))="",FALSE,IF(ISERROR('Model inputs'!S16=1),'Model inputs'!S16=1,IF('Model inputs'!S16="","",'Model inputs'!S16=1))),IF('Model inputs'!AB26="","",'Model inputs'!AB26),IF('Base vs Growth vs Downside key'!R17="","",'Base vs Growth vs Downside key'!R17)))+'Model inputs'!S18 -> -5762.88 | T17: =IF(IF(IF(IF(ISERROR('Model inputs'!T16=1),'Model inputs'!T16=1,IF('Model inputs'!T16="","",'Model inputs'!T16=1))="",FALSE,IF(ISERROR('Model inputs'!T16=1),'Model inputs'!T16=1,IF('Model inputs'!T16="","",'Model inputs'!T16=1))),IF('Model inputs'!AB26="","",'Model inputs'!AB26),IF('Base vs Growth vs Downside key'!S17="","",'Base vs Growth vs Downside key'!S17))="",0,IF(IF(IF(ISERROR('Model inputs'!T16=1),'Model inputs'!T16=1,IF('Model inputs'!T16="","",'Model inputs'!T16=1))="",FALSE,IF(ISERROR('Model inputs'!T16=1),'Model inputs'!T16=1,IF('Model inputs'!T16="","",'Model inputs'!T16=1))),IF('Model inputs'!AB26="","",'Model inputs'!AB26),IF('Base vs Growth vs Downside key'!S17="","",'Base vs Growth vs Downside key'!S17)))+'Model inputs'!T18 -> -6593.6 | U17: =IF(IF(IF(IF(ISERROR('Model inputs'!U16=1),'Model inputs'!U16=1,IF('Model inputs'!U16="","",'Model inputs'!U16=1))="",FALSE,IF(ISERROR('Model inputs'!U16=1),'Model inputs'!U16=1,IF('Model inputs'!U16="","",'Model inputs'!U16=1))),IF('Model inputs'!AB26="","",'Model inputs'!AB26),IF('Base vs Growth vs Downside key'!T17="","",'Base vs Growth vs Downside key'!T17))="",0,IF(IF(IF(ISERROR('Model inputs'!U16=1),'Model inputs'!U16=1,IF('Model inputs'!U16="","",'Model inputs'!U16=1))="",FALSE,IF(ISERROR('Model inputs'!U16=1),'Model inputs'!U16=1,IF('Model inputs'!U16="","",'Model inputs'!U16=1))),IF('Model inputs'!AB26="","",'Model inputs'!AB26),IF('Base vs Growth vs Downside key'!T17="","",'Base vs Growth vs Downside key'!T17)))+'Model inputs'!U18 -> -7263 | V17: =IF(IF(IF(IF(ISERROR('Model inputs'!V16=1),'Model inputs'!V16=1,IF('Model inputs'!V16="","",'Model inputs'!V16=1))="",FALSE,IF(ISERROR('Model inputs'!V16=1),'Model inputs'!V16=1,IF('Model inputs'!V16="","",'Model inputs'!V16=1))),IF('Model inputs'!AB26="","",'Model inputs'!AB26),IF('Base vs Growth vs Downside key'!U17="","",'Base vs Growth vs Downside key'!U17))="",0,IF(IF(IF(ISERROR('Model inputs'!V16=1),'Model inputs'!V16=1,IF('Model inputs'!V16="","",'Model inputs'!V16=1))="",FALSE,IF(ISERROR('Model inputs'!V16=1),'Model inputs'!V16=1,IF('Model inputs'!V16="","",'Model inputs'!V16=1))),IF('Model inputs'!AB26="","",'Model inputs'!AB26),IF('Base vs Growth vs Downside key'!U17="","",'Base vs Growth vs Downside key'!U17)))+'Model inputs'!V18 -> -7734.32 | W17: =IF(IF(IF(IF(ISERROR('Model inputs'!W16=1),'Model inputs'!W16=1,IF('Model inputs'!W16="","",'Model inputs'!W16=1))="",FALSE,IF(ISERROR('Model inputs'!W16=1),'Model inputs'!W16=1,IF('Model inputs'!W16="","",'Model inputs'!W16=1))),IF('Model inputs'!AB26="","",'Model inputs'!AB26),IF('Base vs Growth vs Downside key'!V17="","",'Base vs Growth vs Downside key'!V17))="",0,IF(IF(IF(ISERROR('Model inputs'!W16=1),'Model inputs'!W16=1,IF('Model inputs'!W16="","",'Model inputs'!W16=1))="",FALSE,IF(ISERROR('Model inputs'!W16=1),'Model inputs'!W16=1,IF('Model inputs'!W16="","",'Model inputs'!W16=1))),IF('Model inputs'!AB26="","",'Model inputs'!AB26),IF('Base vs Growth vs Downside key'!V17="","",'Base vs Growth vs Downside key'!V17)))+'Model inputs'!W18 -> -8132.12 | X17: =IF(IF(IF(IF(ISERROR('Model inputs'!X16=1),'Model inputs'!X16=1,IF('Model inputs'!X16="","",'Model inputs'!X16=1))="",FALSE,IF(ISERROR('Model inputs'!X16=1),'Model inputs'!X16=1,IF('Model inputs'!X16="","",'Model inputs'!X16=1))),IF('Model inputs'!AB26="","",'Model inputs'!AB26),IF('Base vs Growth vs Downside key'!W17="","",'Base vs Growth vs Downside key'!W17))="",0,IF(IF(IF(ISERROR('Model inputs'!X16=1),'Model inputs'!X16=1,IF('Model inputs'!X16="","",'Model inputs'!X16=1))="",FALSE,IF(ISERROR('Model inputs'!X16=1),'Model inputs'!X16=1,IF('Model inputs'!X16="","",'Model inputs'!X16=1))),IF('Model inputs'!AB26="","",'Model inputs'!AB26),IF('Base vs Growth vs Downside key'!W17="","",'Base vs Growth vs Downside key'!W17)))+'Model inputs'!X18 -> -8368.6 | Y17: =IF(IF(IF(IF(ISERROR('Model inputs'!Y16=1),'Model inputs'!Y16=1,IF('Model inputs'!Y16="","",'Model inputs'!Y16=1))="",FALSE,IF(ISERROR('Model inputs'!Y16=1),'Model inputs'!Y16=1,IF('Model inputs'!Y16="","",'Model inputs'!Y16=1))),IF('Model inputs'!AB26="","",'Model inputs'!AB26),IF('Base vs Growth vs Downside key'!X17="","",'Base vs Growth vs Downside key'!X17))="",0,IF(IF(IF(ISERROR('Model inputs'!Y16=1),'Model inputs'!Y16=1,IF('Model inputs'!Y16="","",'Model inputs'!Y16=1))="",FALSE,IF(ISERROR('Model inputs'!Y16=1),'Model inputs'!Y16=1,IF('Model inputs'!Y16="","",'Model inputs'!Y16=1))),IF('Model inputs'!AB26="","",'Model inputs'!AB26),IF('Base vs Growth vs Downside key'!X17="","",'Base vs Growth vs Downside key'!X17)))+'Model inputs'!Y18 -> -8531.56
A18: Ending cash > Growth | B18: =IF(IF(IF(IF(ISERROR('Model inputs'!B17=1),'Model inputs'!B17=1,IF('Model inputs'!B17="","",'Model inputs'!B17=1))="",FALSE,IF(ISERROR('Model inputs'!B17=1),'Model inputs'!B17=1,IF('Model inputs'!B17="","",'Model inputs'!B17=1))),IF('Model inputs'!AB27="","",'Model inputs'!AB27),IF('Model inputs'!AA13="","",'Model inputs'!AA13))="",0,IF(IF(IF(ISERROR('Model inputs'!B17=1),'Model inputs'!B17=1,IF('Model inputs'!B17="","",'Model inputs'!B17=1))="",FALSE,IF(ISERROR('Model inputs'!B17=1),'Model inputs'!B17=1,IF('Model inputs'!B17="","",'Model inputs'!B17=1))),IF('Model inputs'!AB27="","",'Model inputs'!AB27),IF('Model inputs'!AA13="","",'Model inputs'!AA13)))+'Model inputs'!B19 -> 22884.8 | C18: =IF(IF(IF(IF(ISERROR('Model inputs'!C17=1),'Model inputs'!C17=1,IF('Model inputs'!C17="","",'Model inputs'!C17=1))="",FALSE,IF(ISERROR('Model inputs'!C17=1),'Model inputs'!C17=1,IF('Model inputs'!C17="","",'Model inputs'!C17=1))),IF('Model inputs'!AB27="","",'Model inputs'!AB27),IF('Base vs Growth vs Downside key'!B18="","",'Base vs Growth vs Downside key'!B18))="",0,IF(IF(IF(ISERROR('Model inputs'!C17=1),'Model inputs'!C17=1,IF('Model inputs'!C17="","",'Model inputs'!C17=1))="",FALSE,IF(ISERROR('Model inputs'!C17=1),'Model inputs'!C17=1,IF('Model inputs'!C17="","",'Model inputs'!C17=1))),IF('Model inputs'!AB27="","",'Model inputs'!AB27),IF('Base vs Growth vs Downside key'!B18="","",'Base vs Growth vs Downside key'!B18)))+'Model inputs'!C19 -> 20769.6 | D18: =IF(IF(IF(IF(ISERROR('Model inputs'!D17=1),'Model inputs'!D17=1,IF('Model inputs'!D17="","",'Model inputs'!D17=1))="",FALSE,IF(ISERROR('Model inputs'!D17=1),'Model inputs'!D17=1,IF('Model inputs'!D17="","",'Model inputs'!D17=1))),IF('Model inputs'!AB27="","",'Model inputs'!AB27),IF('Base vs Growth vs Downside key'!C18="","",'Base vs Growth vs Downside key'!C18))="",0,IF(IF(IF(ISERROR('Model inputs'!D17=1),'Model inputs'!D17=1,IF('Model inputs'!D17="","",'Model inputs'!D17=1))="",FALSE,IF(ISERROR('Model inputs'!D17=1),'Model inputs'!D17=1,IF('Model inputs'!D17="","",'Model inputs'!D17=1))),IF('Model inputs'!AB27="","",'Model inputs'!AB27),IF('Base vs Growth vs Downside key'!C18="","",'Base vs Growth vs Downside key'!C18)))+'Model inputs'!D19 -> 18654.4 | E18: =IF(IF(IF(IF(ISERROR('Model inputs'!E17=1),'Model inputs'!E17=1,IF('Model inputs'!E17="","",'Model inputs'!E17=1))="",FALSE,IF(ISERROR('Model inputs'!E17=1),'Model inputs'!E17=1,IF('Model inputs'!E17="","",'Model inputs'!E17=1))),IF('Model inputs'!AB27="","",'Model inputs'!AB27),IF('Base vs Growth vs Downside key'!D18="","",'Base vs Growth vs Downside key'!D18))="",0,IF(IF(IF(ISERROR('Model inputs'!E17=1),'Model inputs'!E17=1,IF('Model inputs'!E17="","",'Model inputs'!E17=1))="",FALSE,IF(ISERROR('Model inputs'!E17=1),'Model inputs'!E17=1,IF('Model inputs'!E17="","",'Model inputs'!E17=1))),IF('Model inputs'!AB27="","",'Model inputs'!AB27),IF('Base vs Growth vs Downside key'!D18="","",'Base vs Growth vs Downside key'!D18)))+'Model inputs'!E19 -> 17033.696 | F18: =IF(IF(IF(IF(ISERROR('Model inputs'!F17=1),'Model inputs'!F17=1,IF('Model inputs'!F17="","",'Model inputs'!F17=1))="",FALSE,IF(ISERROR('Model inputs'!F17=1),'Model inputs'!F17=1,IF('Model inputs'!F17="","",'Model inputs'!F17=1))),IF('Model inputs'!AB27="","",'Model inputs'!AB27),IF('Base vs Growth vs Downside key'!E18="","",'Base vs Growth vs Downside key'!E18))="",0,IF(IF(IF(ISERROR('Model inputs'!F17=1),'Model inputs'!F17=1,IF('Model inputs'!F17="","",'Model inputs'!F17=1))="",FALSE,IF(ISERROR('Model inputs'!F17=1),'Model inputs'!F17=1,IF('Model inputs'!F17="","",'Model inputs'!F17=1))),IF('Model inputs'!AB27="","",'Model inputs'!AB27),IF('Base vs Growth vs Downside key'!E18="","",'Base vs Growth vs Downside key'!E18)))+'Model inputs'!F19 -> 15708.24 | G18: =IF(IF(IF(IF(ISERROR('Model inputs'!G17=1),'Model inputs'!G17=1,IF('Model inputs'!G17="","",'Model inputs'!G17=1))="",FALSE,IF(ISERROR('Model inputs'!G17=1),'Model inputs'!G17=1,IF('Model inputs'!G17="","",'Model inputs'!G17=1))),IF('Model inputs'!AB27="","",'Model inputs'!AB27),IF('Base vs Growth vs Downside key'!F18="","",'Base vs Growth vs Downside key'!F18))="",0,IF(IF(IF(ISERROR('Model inputs'!G17=1),'Model inputs'!G17=1,IF('Model inputs'!G17="","",'Model inputs'!G17=1))="",FALSE,IF(ISERROR('Model inputs'!G17=1),'Model inputs'!G17=1,IF('Model inputs'!G17="","",'Model inputs'!G17=1))),IF('Model inputs'!AB27="","",'Model inputs'!AB27),IF('Base vs Growth vs Downside key'!F18="","",'Base vs Growth vs Downside key'!F18)))+'Model inputs'!G19 -> 14877.28 | H18: =IF(IF(IF(IF(ISERROR('Model inputs'!H17=1),'Model inputs'!H17=1,IF('Model inputs'!H17="","",'Model inputs'!H17=1))="",FALSE,IF(ISERROR('Model inputs'!H17=1),'Model inputs'!H17=1,IF('Model inputs'!H17="","",'Model inputs'!H17=1))),IF('Model inputs'!AB27="","",'Model inputs'!AB27),IF('Base vs Growth vs Downside key'!G18="","",'Base vs Growth vs Downside key'!G18))="",0,IF(IF(IF(ISERROR('Model inputs'!H17=1),'Model inputs'!H17=1,IF('Model inputs'!H17="","",'Model inputs'!H17=1))="",FALSE,IF(ISERROR('Model inputs'!H17=1),'Model inputs'!H17=1,IF('Model inputs'!H17="","",'Model inputs'!H17=1))),IF('Model inputs'!AB27="","",'Model inputs'!AB27),IF('Base vs Growth vs Downside key'!G18="","",'Base vs Growth vs Downside key'!G18)))+'Model inputs'!H19 -> 14614.628 | I18: =IF(IF(IF(IF(ISERROR('Model inputs'!I17=1),'Model inputs'!I17=1,IF('Model inputs'!I17="","",'Model inputs'!I17=1))="",FALSE,IF(ISERROR('Model inputs'!I17=1),'Model inputs'!I17=1,IF('Model inputs'!I17="","",'Model inputs'!I17=1))),IF('Model inputs'!AB27="","",'Model inputs'!AB27),IF('Base vs Growth vs Downside key'!H18="","",'Base vs Growth vs Downside key'!H18))="",0,IF(IF(IF(ISERROR('Model inputs'!I17=1),'Model inputs'!I17=1,IF('Model inputs'!I17="","",'Model inputs'!I17=1))="",FALSE,IF(ISERROR('Model inputs'!I17=1),'Model inputs'!I17=1,IF('Model inputs'!I17="","",'Model inputs'!I17=1))),IF('Model inputs'!AB27="","",'Model inputs'!AB27),IF('Base vs Growth vs Downside key'!H18="","",'Base vs Growth vs Downside key'!H18)))+'Model inputs'!I19 -> 14920.284 | J18: =IF(IF(IF(IF(ISERROR('Model inputs'!J17=1),'Model inputs'!J17=1,IF('Model inputs'!J17="","",'Model inputs'!J17=1))="",FALSE,IF(ISERROR('Model inputs'!J17=1),'Model inputs'!J17=1,IF('Model inputs'!J17="","",'Model inputs'!J17=1))),IF('Model inputs'!AB27="","",'Model inputs'!AB27),IF('Base vs Growth vs Downside key'!I18="","",'Base vs Growth vs Downside key'!I18))="",0,IF(IF(IF(ISERROR('Model inputs'!J17=1),'Model inputs'!J17=1,IF('Model inputs'!J17="","",'Model inputs'!J17=1))="",FALSE,IF(ISERROR('Model inputs'!J17=1),'Model inputs'!J17=1,IF('Model inputs'!J17="","",'Model inputs'!J17=1))),IF('Model inputs'!AB27="","",'Model inputs'!AB27),IF('Base vs Growth vs Downside key'!I18="","",'Base vs Growth vs Downside key'!I18)))+'Model inputs'!J19 -> 15868.06 | K18: =IF(IF(IF(IF(ISERROR('Model inputs'!K17=1),'Model inputs'!K17=1,IF('Model inputs'!K17="","",'Model inputs'!K17=1))="",FALSE,IF(ISERROR('Model inputs'!K17=1),'Model inputs'!K17=1,IF('Model inputs'!K17="","",'Model inputs'!K17=1))),IF('Model inputs'!AB27="","",'Model inputs'!AB27),IF('Base vs Growth vs Downside key'!J18="","",'Base vs Growth vs Downside key'!J18))="",0,IF(IF(IF(ISERROR('Model inputs'!K17=1),'Model inputs'!K17=1,IF('Model inputs'!K17="","",'Model inputs'!K17=1))="",FALSE,IF(ISERROR('Model inputs'!K17=1),'Model inputs'!K17=1,IF('Model inputs'!K17="","",'Model inputs'!K17=1))),IF('Model inputs'!AB27="","",'Model inputs'!AB27),IF('Base vs Growth vs Downside key'!J18="","",'Base vs Growth vs Downside key'!J18)))+'Model inputs'!K19 -> 17384.144 | L18: =IF(IF(IF(IF(ISERROR('Model inputs'!L17=1),'Model inputs'!L17=1,IF('Model inputs'!L17="","",'Model inputs'!L17=1))="",FALSE,IF(ISERROR('Model inputs'!L17=1),'Model inputs'!L17=1,IF('Model inputs'!L17="","",'Model inputs'!L17=1))),IF('Model inputs'!AB27="","",'Model inputs'!AB27),IF('Base vs Growth vs Downside key'!K18="","",'Base vs Growth vs Downside key'!K18))="",0,IF(IF(IF(ISERROR('Model inputs'!L17=1),'Model inputs'!L17=1,IF('Model inputs'!L17="","",'Model inputs'!L17=1))="",FALSE,IF(ISERROR('Model inputs'!L17=1),'Model inputs'!L17=1,IF('Model inputs'!L17="","",'Model inputs'!L17=1))),IF('Model inputs'!AB27="","",'Model inputs'!AB27),IF('Base vs Growth vs Downside key'!K18="","",'Base vs Growth vs Downside key'!K18)))+'Model inputs'!L19 -> 19468.536 | M18: =IF(IF(IF(IF(ISERROR('Model inputs'!M17=1),'Model inputs'!M17=1,IF('Model inputs'!M17="","",'Model inputs'!M17=1))="",FALSE,IF(ISERROR('Model inputs'!M17=1),'Model inputs'!M17=1,IF('Model inputs'!M17="","",'Model inputs'!M17=1))),IF('Model inputs'!AB27="","",'Model inputs'!AB27),IF('Base vs Growth vs Downside key'!L18="","",'Base vs Growth vs Downside key'!L18))="",0,IF(IF(IF(ISERROR('Model inputs'!M17=1),'Model inputs'!M17=1,IF('Model inputs'!M17="","",'Model inputs'!M17=1))="",FALSE,IF(ISERROR('Model inputs'!M17=1),'Model inputs'!M17=1,IF('Model inputs'!M17="","",'Model inputs'!M17=1))),IF('Model inputs'!AB27="","",'Model inputs'!AB27),IF('Base vs Growth vs Downside key'!L18="","",'Base vs Growth vs Downside key'!L18)))+'Model inputs'!M19 -> 22121.236 | N18: =IF(IF(IF(IF(ISERROR('Model inputs'!N17=1),'Model inputs'!N17=1,IF('Model inputs'!N17="","",'Model inputs'!N17=1))="",FALSE,IF(ISERROR('Model inputs'!N17=1),'Model inputs'!N17=1,IF('Model inputs'!N17="","",'Model inputs'!N17=1))),IF('Model inputs'!AB27="","",'Model inputs'!AB27),IF('Base vs Growth vs Downside key'!M18="","",'Base vs Growth vs Downside key'!M18))="",0,IF(IF(IF(ISERROR('Model inputs'!N17=1),'Model inputs'!N17=1,IF('Model inputs'!N17="","",'Model inputs'!N17=1))="",FALSE,IF(ISERROR('Model inputs'!N17=1),'Model inputs'!N17=1,IF('Model inputs'!N17="","",'Model inputs'!N17=1))),IF('Model inputs'!AB27="","",'Model inputs'!AB27),IF('Base vs Growth vs Downside key'!M18="","",'Base vs Growth vs Downside key'!M18)))+'Model inputs'!N19 -> 25416.056 | O18: =IF(IF(IF(IF(ISERROR('Model inputs'!O17=1),'Model inputs'!O17=1,IF('Model inputs'!O17="","",'Model inputs'!O17=1))="",FALSE,IF(ISERROR('Model inputs'!O17=1),'Model inputs'!O17=1,IF('Model inputs'!O17="","",'Model inputs'!O17=1))),IF('Model inputs'!AB27="","",'Model inputs'!AB27),IF('Base vs Growth vs Downside key'!N18="","",'Base vs Growth vs Downside key'!N18))="",0,IF(IF(IF(ISERROR('Model inputs'!O17=1),'Model inputs'!O17=1,IF('Model inputs'!O17="","",'Model inputs'!O17=1))="",FALSE,IF(ISERROR('Model inputs'!O17=1),'Model inputs'!O17=1,IF('Model inputs'!O17="","",'Model inputs'!O17=1))),IF('Model inputs'!AB27="","",'Model inputs'!AB27),IF('Base vs Growth vs Downside key'!N18="","",'Base vs Growth vs Downside key'!N18)))+'Model inputs'!O19 -> 29699.868 | P18: =IF(IF(IF(IF(ISERROR('Model inputs'!P17=1),'Model inputs'!P17=1,IF('Model inputs'!P17="","",'Model inputs'!P17=1))="",FALSE,IF(ISERROR('Model inputs'!P17=1),'Model inputs'!P17=1,IF('Model inputs'!P17="","",'Model inputs'!P17=1))),IF('Model inputs'!AB27="","",'Model inputs'!AB27),IF('Base vs Growth vs Downside key'!O18="","",'Base vs Growth vs Downside key'!O18))="",0,IF(IF(IF(ISERROR('Model inputs'!P17=1),'Model inputs'!P17=1,IF('Model inputs'!P17="","",'Model inputs'!P17=1))="",FALSE,IF(ISERROR('Model inputs'!P17=1),'Model inputs'!P17=1,IF('Model inputs'!P17="","",'Model inputs'!P17=1))),IF('Model inputs'!AB27="","",'Model inputs'!AB27),IF('Base vs Growth vs Downside key'!O18="","",'Base vs Growth vs Downside key'!O18)))+'Model inputs'!P19 -> 34625.8 | Q18: =IF(IF(IF(IF(ISERROR('Model inputs'!Q17=1),'Model inputs'!Q17=1,IF('Model inputs'!Q17="","",'Model inputs'!Q17=1))="",FALSE,IF(ISERROR('Model inputs'!Q17=1),'Model inputs'!Q17=1,IF('Model inputs'!Q17="","",'Model inputs'!Q17=1))),IF('Model inputs'!AB27="","",'Model inputs'!AB27),IF('Base vs Growth vs Downside key'!P18="","",'Base vs Growth vs Downside key'!P18))="",0,IF(IF(IF(ISERROR('Model inputs'!Q17=1),'Model inputs'!Q17=1,IF('Model inputs'!Q17="","",'Model inputs'!Q17=1))="",FALSE,IF(ISERROR('Model inputs'!Q17=1),'Model inputs'!Q17=1,IF('Model inputs'!Q17="","",'Model inputs'!Q17=1))),IF('Model inputs'!AB27="","",'Model inputs'!AB27),IF('Base vs Growth vs Downside key'!P18="","",'Base vs Growth vs Downside key'!P18)))+'Model inputs'!Q19 -> 40540.724 | R18: =IF(IF(IF(IF(ISERROR('Model inputs'!R17=1),'Model inputs'!R17=1,IF('Model inputs'!R17="","",'Model inputs'!R17=1))="",FALSE,IF(ISERROR('Model inputs'!R17=1),'Model inputs'!R17=1,IF('Model inputs'!R17="","",'Model inputs'!R17=1))),IF('Model inputs'!AB27="","",'Model inputs'!AB27),IF('Base vs Growth vs Downside key'!Q18="","",'Base vs Growth vs Downside key'!Q18))="",0,IF(IF(IF(ISERROR('Model inputs'!R17=1),'Model inputs'!R17=1,IF('Model inputs'!R17="","",'Model inputs'!R17=1))="",FALSE,IF(ISERROR('Model inputs'!R17=1),'Model inputs'!R17=1,IF('Model inputs'!R17="","",'Model inputs'!R17=1))),IF('Model inputs'!AB27="","",'Model inputs'!AB27),IF('Base vs Growth vs Downside key'!Q18="","",'Base vs Growth vs Downside key'!Q18)))+'Model inputs'!R19 -> 47097.768 | S18: =IF(IF(IF(IF(ISERROR('Model inputs'!S17=1),'Model inputs'!S17=1,IF('Model inputs'!S17="","",'Model inputs'!S17=1))="",FALSE,IF(ISERROR('Model inputs'!S17=1),'Model inputs'!S17=1,IF('Model inputs'!S17="","",'Model inputs'!S17=1))),IF('Model inputs'!AB27="","",'Model inputs'!AB27),IF('Base vs Growth vs Downside key'!R18="","",'Base vs Growth vs Downside key'!R18))="",0,IF(IF(IF(ISERROR('Model inputs'!S17=1),'Model inputs'!S17=1,IF('Model inputs'!S17="","",'Model inputs'!S17=1))="",FALSE,IF(ISERROR('Model inputs'!S17=1),'Model inputs'!S17=1,IF('Model inputs'!S17="","",'Model inputs'!S17=1))),IF('Model inputs'!AB27="","",'Model inputs'!AB27),IF('Base vs Growth vs Downside key'!R18="","",'Base vs Growth vs Downside key'!R18)))+'Model inputs'!S19 -> 54643.804 | T18: =IF(IF(IF(IF(ISERROR('Model inputs'!T17=1),'Model inputs'!T17=1,IF('Model inputs'!T17="","",'Model inputs'!T17=1))="",FALSE,IF(ISERROR('Model inputs'!T17=1),'Model inputs'!T17=1,IF('Model inputs'!T17="","",'Model inputs'!T17=1))),IF('Model inputs'!AB27="","",'Model inputs'!AB27),IF('Base vs Growth vs Downside key'!S18="","",'Base vs Growth vs Downside key'!S18))="",0,IF(IF(IF(ISERROR('Model inputs'!T17=1),'Model inputs'!T17=1,IF('Model inputs'!T17="","",'Model inputs'!T17=1))="",FALSE,IF(ISERROR('Model inputs'!T17=1),'Model inputs'!T17=1,IF('Model inputs'!T17="","",'Model inputs'!T17=1))),IF('Model inputs'!AB27="","",'Model inputs'!AB27),IF('Base vs Growth vs Downside key'!S18="","",'Base vs Growth vs Downside key'!S18)))+'Model inputs'!T19 -> 62831.96 | U18: =IF(IF(IF(IF(ISERROR('Model inputs'!U17=1),'Model inputs'!U17=1,IF('Model inputs'!U17="","",'Model inputs'!U17=1))="",FALSE,IF(ISERROR('Model inputs'!U17=1),'Model inputs'!U17=1,IF('Model inputs'!U17="","",'Model inputs'!U17=1))),IF('Model inputs'!AB27="","",'Model inputs'!AB27),IF('Base vs Growth vs Downside key'!T18="","",'Base vs Growth vs Downside key'!T18))="",0,IF(IF(IF(ISERROR('Model inputs'!U17=1),'Model inputs'!U17=1,IF('Model inputs'!U17="","",'Model inputs'!U17=1))="",FALSE,IF(ISERROR('Model inputs'!U17=1),'Model inputs'!U17=1,IF('Model inputs'!U17="","",'Model inputs'!U17=1))),IF('Model inputs'!AB27="","",'Model inputs'!AB27),IF('Base vs Growth vs Downside key'!T18="","",'Base vs Growth vs Downside key'!T18)))+'Model inputs'!U19 -> 71662.236 | V18: =IF(IF(IF(IF(ISERROR('Model inputs'!V17=1),'Model inputs'!V17=1,IF('Model inputs'!V17="","",'Model inputs'!V17=1))="",FALSE,IF(ISERROR('Model inputs'!V17=1),'Model inputs'!V17=1,IF('Model inputs'!V17="","",'Model inputs'!V17=1))),IF('Model inputs'!AB27="","",'Model inputs'!AB27),IF('Base vs Growth vs Downside key'!U18="","",'Base vs Growth vs Downside key'!U18))="",0,IF(IF(IF(ISERROR('Model inputs'!V17=1),'Model inputs'!V17=1,IF('Model inputs'!V17="","",'Model inputs'!V17=1))="",FALSE,IF(ISERROR('Model inputs'!V17=1),'Model inputs'!V17=1,IF('Model inputs'!V17="","",'Model inputs'!V17=1))),IF('Model inputs'!AB27="","",'Model inputs'!AB27),IF('Base vs Growth vs Downside key'!U18="","",'Base vs Growth vs Downside key'!U18)))+'Model inputs'!V19 -> 81481.504 | W18: =IF(IF(IF(IF(ISERROR('Model inputs'!W17=1),'Model inputs'!W17=1,IF('Model inputs'!W17="","",'Model inputs'!W17=1))="",FALSE,IF(ISERROR('Model inputs'!W17=1),'Model inputs'!W17=1,IF('Model inputs'!W17="","",'Model inputs'!W17=1))),IF('Model inputs'!AB27="","",'Model inputs'!AB27),IF('Base vs Growth vs Downside key'!V18="","",'Base vs Growth vs Downside key'!V18))="",0,IF(IF(IF(ISERROR('Model inputs'!W17=1),'Model inputs'!W17=1,IF('Model inputs'!W17="","",'Model inputs'!W17=1))="",FALSE,IF(ISERROR('Model inputs'!W17=1),'Model inputs'!W17=1,IF('Model inputs'!W17="","",'Model inputs'!W17=1))),IF('Model inputs'!AB27="","",'Model inputs'!AB27),IF('Base vs Growth vs Downside key'!V18="","",'Base vs Growth vs Downside key'!V18)))+'Model inputs'!W19 -> 91942.892 | X18: =IF(IF(IF(IF(ISERROR('Model inputs'!X17=1),'Model inputs'!X17=1,IF('Model inputs'!X17="","",'Model inputs'!X17=1))="",FALSE,IF(ISERROR('Model inputs'!X17=1),'Model inputs'!X17=1,IF('Model inputs'!X17="","",'Model inputs'!X17=1))),IF('Model inputs'!AB27="","",'Model inputs'!AB27),IF('Base vs Growth vs Downside key'!W18="","",'Base vs Growth vs Downside key'!W18))="",0,IF(IF(IF(ISERROR('Model inputs'!X17=1),'Model inputs'!X17=1,IF('Model inputs'!X17="","",'Model inputs'!X17=1))="",FALSE,IF(ISERROR('Model inputs'!X17=1),'Model inputs'!X17=1,IF('Model inputs'!X17="","",'Model inputs'!X17=1))),IF('Model inputs'!AB27="","",'Model inputs'!AB27),IF('Base vs Growth vs Downside key'!W18="","",'Base vs Growth vs Downside key'!W18)))+'Model inputs'!X19 -> 103393.27 | Y18: =IF(IF(IF(IF(ISERROR('Model inputs'!Y17=1),'Model inputs'!Y17=1,IF('Model inputs'!Y17="","",'Model inputs'!Y17=1))="",FALSE,IF(ISERROR('Model inputs'!Y17=1),'Model inputs'!Y17=1,IF('Model inputs'!Y17="","",'Model inputs'!Y17=1))),IF('Model inputs'!AB27="","",'Model inputs'!AB27),IF('Base vs Growth vs Downside key'!X18="","",'Base vs Growth vs Downside key'!X18))="",0,IF(IF(IF(ISERROR('Model inputs'!Y17=1),'Model inputs'!Y17=1,IF('Model inputs'!Y17="","",'Model inputs'!Y17=1))="",FALSE,IF(ISERROR('Model inputs'!Y17=1),'Model inputs'!Y17=1,IF('Model inputs'!Y17="","",'Model inputs'!Y17=1))),IF('Model inputs'!AB27="","",'Model inputs'!AB27),IF('Base vs Growth vs Downside key'!X18="","",'Base vs Growth vs Downside key'!X18)))+'Model inputs'!Y19 -> 115485.77
A19: Ending cash > delta | B19: ='Base vs Growth vs Downside key'!B18-'Base vs Growth vs Downside key'!B17 -> 0 | C19: ='Base vs Growth vs Downside key'!C18-'Base vs Growth vs Downside key'!C17 -> 0 | D19: ='Base vs Growth vs Downside key'!D18-'Base vs Growth vs Downside key'!D17 -> 0 | E19: ='Base vs Growth vs Downside key'!E18-'Base vs Growth vs Downside key'!E17 -> 494.496 | F19: ='Base vs Growth vs Downside key'!F18-'Base vs Growth vs Downside key'!F17 -> 1284.24 | G19: ='Base vs Growth vs Downside key'!G18-'Base vs Growth vs Downside key'!G17 -> 2568.48 | H19: ='Base vs Growth vs Downside key'!H18-'Base vs Growth vs Downside key'!H17 -> 4347.508 | I19: ='Base vs Growth vs Downside key'!I18-'Base vs Growth vs Downside key'!I17 -> 6570.284 | ... Y19: ='Base vs Growth vs Downside key'!Y18-'Base vs Growth vs Downside key'!Y17 -> 124017.33
A20: Months of runway | B20: =IF(IF(IF(ISERROR('Base vs Growth vs Downside key'!B14>0),'Base vs Growth vs Downside key'!B14>0,IF('Base vs Growth vs Downside key'!B14="","",'Base vs Growth vs Downside key'!B14>0))="",FALSE,IF(ISERROR('Base vs Growth vs Downside key'!B14>0),'Base vs Growth vs Downside key'!B14>0,IF('Base vs Growth vs Downside key'!B14="","",'Base vs Growth vs Downside key'!B14>0))),'Base vs Growth vs Downside key'!B17/'Base vs Growth vs Downside key'!B14,"") -> 10.819213 | C20: =IF(IF(IF(ISERROR('Base vs Growth vs Downside key'!C14>0),'Base vs Growth vs Downside key'!C14>0,IF('Base vs Growth vs Downside key'!C14="","",'Base vs Growth vs Downside key'!C14>0))="",FALSE,IF(ISERROR('Base vs Growth vs Downside key'!C14>0),'Base vs Growth vs Downside key'!C14>0,IF('Base vs Growth vs Downside key'!C14="","",'Base vs Growth vs Downside key'!C14>0))),'Base vs Growth vs Downside key'!C17/'Base vs Growth vs Downside key'!C14,"") -> 9.8192133 | D20: =IF(IF(IF(ISERROR('Base vs Growth vs Downside key'!D14>0),'Base vs Growth vs Downside key'!D14>0,IF('Base vs Growth vs Downside key'!D14="","",'Base vs Growth vs Downside key'!D14>0))="",FALSE,IF(ISERROR('Base vs Growth vs Downside key'!D14>0),'Base vs Growth vs Downside key'!D14>0,IF('Base vs Growth vs Downside key'!D14="","",'Base vs Growth vs Downside key'!D14>0))),'Base vs Growth vs Downside key'!D17/'Base vs Growth vs Downside key'!D14,"") -> 8.8192133 | E20: =IF(IF(IF(ISERROR('Base vs Growth vs Downside key'!E14>0),'Base vs Growth vs Downside key'!E14>0,IF('Base vs Growth vs Downside key'!E14="","",'Base vs Growth vs Downside key'!E14>0))="",FALSE,IF(ISERROR('Base vs Growth vs Downside key'!E14>0),'Base vs Growth vs Downside key'!E14>0,IF('Base vs Growth vs Downside key'!E14="","",'Base vs Growth vs Downside key'!E14>0))),'Base vs Growth vs Downside key'!E17/'Base vs Growth vs Downside key'!E14,"") -> 7.8192133 | F20: =IF(IF(IF(ISERROR('Base vs Growth vs Downside key'!F14>0),'Base vs Growth vs Downside key'!F14>0,IF('Base vs Growth vs Downside key'!F14="","",'Base vs Growth vs Downside key'!F14>0))="",FALSE,IF(ISERROR('Base vs Growth vs Downside key'!F14>0),'Base vs Growth vs Downside key'!F14>0,IF('Base vs Growth vs Downside key'!F14="","",'Base vs Growth vs Downside key'!F14>0))),'Base vs Growth vs Downside key'!F17/'Base vs Growth vs Downside key'!F14,"") -> 6.8192133 | G20: =IF(IF(IF(ISERROR('Base vs Growth vs Downside key'!G14>0),'Base vs Growth vs Downside key'!G14>0,IF('Base vs Growth vs Downside key'!G14="","",'Base vs Growth vs Downside key'!G14>0))="",FALSE,IF(ISERROR('Base vs Growth vs Downside key'!G14>0),'Base vs Growth vs Downside key'!G14>0,IF('Base vs Growth vs Downside key'!G14="","",'Base vs Growth vs Downside key'!G14>0))),'Base vs Growth vs Downside key'!G17/'Base vs Growth vs Downside key'!G14,"") -> 5.8192133 | H20: =IF(IF(IF(ISERROR('Base vs Growth vs Downside key'!H14>0),'Base vs Growth vs Downside key'!H14>0,IF('Base vs Growth vs Downside key'!H14="","",'Base vs Growth vs Downside key'!H14>0))="",FALSE,IF(ISERROR('Base vs Growth vs Downside key'!H14>0),'Base vs Growth vs Downside key'!H14>0,IF('Base vs Growth vs Downside key'!H14="","",'Base vs Growth vs Downside key'!H14>0))),'Base vs Growth vs Downside key'!H17/'Base vs Growth vs Downside key'!H14,"") -> 5.0287606 | I20: =IF(IF(IF(ISERROR('Base vs Growth vs Downside key'!I14>0),'Base vs Growth vs Downside key'!I14>0,IF('Base vs Growth vs Downside key'!I14="","",'Base vs Growth vs Downside key'!I14>0))="",FALSE,IF(ISERROR('Base vs Growth vs Downside key'!I14>0),'Base vs Growth vs Downside key'!I14>0,IF('Base vs Growth vs Downside key'!I14="","",'Base vs Growth vs Downside key'!I14>0))),'Base vs Growth vs Downside key'!I17/'Base vs Growth vs Downside key'!I14,"") -> 4.3554916 | ... Y20: =IF(IF(IF(ISERROR('Base vs Growth vs Downside key'!Y14>0),'Base vs Growth vs Downside key'!Y14>0,IF('Base vs Growth vs Downside key'!Y14="","",'Base vs Growth vs Downside key'!Y14>0))="",FALSE,IF(ISERROR('Base vs Growth vs Downside key'!Y14>0),'Base vs Growth vs Downside key'!Y14>0,IF('Base vs Growth vs Downside key'!Y14="","",'Base vs Growth vs Downside key'!Y14>0))),'Base vs Growth vs Downside key'!Y17/'Base vs Growth vs Downside key'!Y14,"") -> -52.353706
A21: Months of runway > Growth | B21: =IF(IF(IF(ISERROR('Base vs Growth vs Downside key'!B15>0),'Base vs Growth vs Downside key'!B15>0,IF('Base vs Growth vs Downside key'!B15="","",'Base vs Growth vs Downside key'!B15>0))="",FALSE,IF(ISERROR('Base vs Growth vs Downside key'!B15>0),'Base vs Growth vs Downside key'!B15>0,IF('Base vs Growth vs Downside key'!B15="","",'Base vs Growth vs Downside key'!B15>0))),'Base vs Growth vs Downside key'!B18/'Base vs Growth vs Downside key'!B15,"") -> 10.819213 | C21: =IF(IF(IF(ISERROR('Base vs Growth vs Downside key'!C15>0),'Base vs Growth vs Downside key'!C15>0,IF('Base vs Growth vs Downside key'!C15="","",'Base vs Growth vs Downside key'!C15>0))="",FALSE,IF(ISERROR('Base vs Growth vs Downside key'!C15>0),'Base vs Growth vs Downside key'!C15>0,IF('Base vs Growth vs Downside key'!C15="","",'Base vs Growth vs Downside key'!C15>0))),'Base vs Growth vs Downside key'!C18/'Base vs Growth vs Downside key'!C15,"") -> 9.8192133 | D21: =IF(IF(IF(ISERROR('Base vs Growth vs Downside key'!D15>0),'Base vs Growth vs Downside key'!D15>0,IF('Base vs Growth vs Downside key'!D15="","",'Base vs Growth vs Downside key'!D15>0))="",FALSE,IF(ISERROR('Base vs Growth vs Downside key'!D15>0),'Base vs Growth vs Downside key'!D15>0,IF('Base vs Growth vs Downside key'!D15="","",'Base vs Growth vs Downside key'!D15>0))),'Base vs Growth vs Downside key'!D18/'Base vs Growth vs Downside key'!D15,"") -> 8.8192133 | E21: =IF(IF(IF(ISERROR('Base vs Growth vs Downside key'!E15>0),'Base vs Growth vs Downside key'!E15>0,IF('Base vs Growth vs Downside key'!E15="","",'Base vs Growth vs Downside key'!E15>0))="",FALSE,IF(ISERROR('Base vs Growth vs Downside key'!E15>0),'Base vs Growth vs Downside key'!E15>0,IF('Base vs Growth vs Downside key'!E15="","",'Base vs Growth vs Downside key'!E15>0))),'Base vs Growth vs Downside key'!E18/'Base vs Growth vs Downside key'!E15,"") -> 10.51006 | F21: =IF(IF(IF(ISERROR('Base vs Growth vs Downside key'!F15>0),'Base vs Growth vs Downside key'!F15>0,IF('Base vs Growth vs Downside key'!F15="","",'Base vs Growth vs Downside key'!F15>0))="",FALSE,IF(ISERROR('Base vs Growth vs Downside key'!F15>0),'Base vs Growth vs Downside key'!F15>0,IF('Base vs Growth vs Downside key'!F15="","",'Base vs Growth vs Downside key'!F15>0))),'Base vs Growth vs Downside key'!F18/'Base vs Growth vs Downside key'!F15,"") -> 11.851197 | G21: =IF(IF(IF(ISERROR('Base vs Growth vs Downside key'!G15>0),'Base vs Growth vs Downside key'!G15>0,IF('Base vs Growth vs Downside key'!G15="","",'Base vs Growth vs Downside key'!G15>0))="",FALSE,IF(ISERROR('Base vs Growth vs Downside key'!G15>0),'Base vs Growth vs Downside key'!G15>0,IF('Base vs Growth vs Downside key'!G15="","",'Base vs Growth vs Downside key'!G15>0))),'Base vs Growth vs Downside key'!G18/'Base vs Growth vs Downside key'!G15,"") -> 17.903726 | H21: =IF(IF(IF(ISERROR('Base vs Growth vs Downside key'!H15>0),'Base vs Growth vs Downside key'!H15>0,IF('Base vs Growth vs Downside key'!H15="","",'Base vs Growth vs Downside key'!H15>0))="",FALSE,IF(ISERROR('Base vs Growth vs Downside key'!H15>0),'Base vs Growth vs Downside key'!H15>0,IF('Base vs Growth vs Downside key'!H15="","",'Base vs Growth vs Downside key'!H15>0))),'Base vs Growth vs Downside key'!H18/'Base vs Growth vs Downside key'!H15,"") -> 55.642554 | I21: =IF(IF(IF(ISERROR('Base vs Growth vs Downside key'!I15>0),'Base vs Growth vs Downside key'!I15>0,IF('Base vs Growth vs Downside key'!I15="","",'Base vs Growth vs Downside key'!I15>0))="",FALSE,IF(ISERROR('Base vs Growth vs Downside key'!I15>0),'Base vs Growth vs Downside key'!I15>0,IF('Base vs Growth vs Downside key'!I15="","",'Base vs Growth vs Downside key'!I15>0))),'Base vs Growth vs Downside key'!I18/'Base vs Growth vs Downside key'!I15,"") | ... Y21: =IF(IF(IF(ISERROR('Base vs Growth vs Downside key'!Y15>0),'Base vs Growth vs Downside key'!Y15>0,IF('Base vs Growth vs Downside key'!Y15="","",'Base vs Growth vs Downside key'!Y15>0))="",FALSE,IF(ISERROR('Base vs Growth vs Downside key'!Y15>0),'Base vs Growth vs Downside key'!Y15>0,IF('Base vs Growth vs Downside key'!Y15="","",'Base vs Growth vs Downside key'!Y15>0))),'Base vs Growth vs Downside key'!Y18/'Base vs Growth vs Downside key'!Y15,"")
A22: Months of runway > delta | B22: ='Base vs Growth vs Downside key'!B21-'Base vs Growth vs Downside key'!B20 -> 0 | C22: ='Base vs Growth vs Downside key'!C21-'Base vs Growth vs Downside key'!C20 -> 0 | D22: ='Base vs Growth vs Downside key'!D21-'Base vs Growth vs Downside key'!D20 -> 0 | E22: ='Base vs Growth vs Downside key'!E21-'Base vs Growth vs Downside key'!E20 -> 2.6908465 | F22: ='Base vs Growth vs Downside key'!F21-'Base vs Growth vs Downside key'!F20 -> 5.0319836 | G22: ='Base vs Growth vs Downside key'!G21-'Base vs Growth vs Downside key'!G20 -> 12.084512 | H22: ='Base vs Growth vs Downside key'!H21-'Base vs Growth vs Downside key'!H20 -> 50.613793

Sheet Model inputs
A1: Model inputs
A2: Integration values are aggregated snapshots; raw source records are not included.
A4: Variables
A5: Variable / segment | B5: 2026-11 | C5: 2026-12 | D5: 2027-01 | E5: 2027-02 | F5: 2027-03 | G5: 2027-04 | H5: 2027-05 | I5: 2027-06 | J5: 2027-07 | K5: 2027-08 | L5: 2027-09 | M5: 2027-10 | N5: 2027-11 | O5: 2027-12 | P5: 2028-01 | Q5: 2028-02 | R5: 2028-03 | S5: 2028-04 | T5: 2028-05 | U5: 2028-06 | V5: 2028-07 | W5: 2028-08 | X5: 2028-09 | Y5: 2028-10 | Z5: 2026-09 | AA5: 2026-10 | AB5: Value
A6: Customers | B6: =SUM('Model inputs'!B7,'Model inputs'!B8) -> 0 | C6: =SUM('Model inputs'!C7,'Model inputs'!C8) -> 0 | D6: =SUM('Model inputs'!D7,'Model inputs'!D8) -> 0 | E6: =SUM('Model inputs'!E7,'Model inputs'!E8) -> 0 | F6: =SUM('Model inputs'!F7,'Model inputs'!F8) -> 0 | G6: =SUM('Model inputs'!G7,'Model inputs'!G8) -> 0 | H6: =SUM('Model inputs'!H7,'Model inputs'!H8) -> 2 | I6: =SUM('Model inputs'!I7,'Model inputs'!I8) -> 4 | ... Y6: =SUM('Model inputs'!Y7,'Model inputs'!Y8) -> 42
A7: Customers > Starter | B7: =IF(IF(('Model inputs'!B16-'Model inputs'!AB60)<1="",FALSE,('Model inputs'!B16-'Model inputs'!AB60)<1),0,ROUND(IF(IF(('Model inputs'!B16-'Model inputs'!AB60)<=3="",FALSE,('Model inputs'!B16-'Model inputs'!AB60)<=3),IF('Model inputs'!AB49="","",'Model inputs'!AB49),IF(IF(('Model inputs'!B16-'Model inputs'!AB60)<=6="",FALSE,('Model inputs'!B16-'Model inputs'!AB60)<=6),'Model inputs'!AB49+('Model inputs'!AB55-'Model inputs'!AB49)*(('Model inputs'!B16-'Model inputs'!AB60)-3)/3,IF(IF(('Model inputs'!B16-'Model inputs'!AB60)<=12="",FALSE,('Model inputs'!B16-'Model inputs'!AB60)<=12),'Model inputs'!AB55+('Model inputs'!AB37-'Model inputs'!AB55)*(('Model inputs'!B16-'Model inputs'!AB60)-6)/6,'Model inputs'!AB37+('Model inputs'!AB43-'Model inputs'!AB37)*(('Model inputs'!B16-'Model inputs'!AB60)-12)/12))),0)) -> 0 | C7: =IF(IF(('Model inputs'!C16-'Model inputs'!AB60)<1="",FALSE,('Model inputs'!C16-'Model inputs'!AB60)<1),0,ROUND(IF(IF(('Model inputs'!C16-'Model inputs'!AB60)<=3="",FALSE,('Model inputs'!C16-'Model inputs'!AB60)<=3),IF('Model inputs'!AB49="","",'Model inputs'!AB49),IF(IF(('Model inputs'!C16-'Model inputs'!AB60)<=6="",FALSE,('Model inputs'!C16-'Model inputs'!AB60)<=6),'Model inputs'!AB49+('Model inputs'!AB55-'Model inputs'!AB49)*(('Model inputs'!C16-'Model inputs'!AB60)-3)/3,IF(IF(('Model inputs'!C16-'Model inputs'!AB60)<=12="",FALSE,('Model inputs'!C16-'Model inputs'!AB60)<=12),'Model inputs'!AB55+('Model inputs'!AB37-'Model inputs'!AB55)*(('Model inputs'!C16-'Model inputs'!AB60)-6)/6,'Model inputs'!AB37+('Model inputs'!AB43-'Model inputs'!AB37)*(('Model inputs'!C16-'Model inputs'!AB60)-12)/12))),0)) -> 0 | D7: =IF(IF(('Model inputs'!D16-'Model inputs'!AB60)<1="",FALSE,('Model inputs'!D16-'Model inputs'!AB60)<1),0,ROUND(IF(IF(('Model inputs'!D16-'Model inputs'!AB60)<=3="",FALSE,('Model inputs'!D16-'Model inputs'!AB60)<=3),IF('Model inputs'!AB49="","",'Model inputs'!AB49),IF(IF(('Model inputs'!D16-'Model inputs'!AB60)<=6="",FALSE,('Model inputs'!D16-'Model inputs'!AB60)<=6),'Model inputs'!AB49+('Model inputs'!AB55-'Model inputs'!AB49)*(('Model inputs'!D16-'Model inputs'!AB60)-3)/3,IF(IF(('Model inputs'!D16-'Model inputs'!AB60)<=12="",FALSE,('Model inputs'!D16-'Model inputs'!AB60)<=12),'Model inputs'!AB55+('Model inputs'!AB37-'Model inputs'!AB55)*(('Model inputs'!D16-'Model inputs'!AB60)-6)/6,'Model inputs'!AB37+('Model inputs'!AB43-'Model inputs'!AB37)*(('Model inputs'!D16-'Model inputs'!AB60)-12)/12))),0)) -> 0 | E7: =IF(IF(('Model inputs'!E16-'Model inputs'!AB60)<1="",FALSE,('Model inputs'!E16-'Model inputs'!AB60)<1),0,ROUND(IF(IF(('Model inputs'!E16-'Model inputs'!AB60)<=3="",FALSE,('Model inputs'!E16-'Model inputs'!AB60)<=3),IF('Model inputs'!AB49="","",'Model inputs'!AB49),IF(IF(('Model inputs'!E16-'Model inputs'!AB60)<=6="",FALSE,('Model inputs'!E16-'Model inputs'!AB60)<=6),'Model inputs'!AB49+('Model inputs'!AB55-'Model inputs'!AB49)*(('Model inputs'!E16-'Model inputs'!AB60)-3)/3,IF(IF(('Model inputs'!E16-'Model inputs'!AB60)<=12="",FALSE,('Model inputs'!E16-'Model inputs'!AB60)<=12),'Model inputs'!AB55+('Model inputs'!AB37-'Model inputs'!AB55)*(('Model inputs'!E16-'Model inputs'!AB60)-6)/6,'Model inputs'!AB37+('Model inputs'!AB43-'Model inputs'!AB37)*(('Model inputs'!E16-'Model inputs'!AB60)-12)/12))),0)) -> 0 | F7: =IF(IF(('Model inputs'!F16-'Model inputs'!AB60)<1="",FALSE,('Model inputs'!F16-'Model inputs'!AB60)<1),0,ROUND(IF(IF(('Model inputs'!F16-'Model inputs'!AB60)<=3="",FALSE,('Model inputs'!F16-'Model inputs'!AB60)<=3),IF('Model inputs'!AB49="","",'Model inputs'!AB49),IF(IF(('Model inputs'!F16-'Model inputs'!AB60)<=6="",FALSE,('Model inputs'!F16-'Model inputs'!AB60)<=6),'Model inputs'!AB49+('Model inputs'!AB55-'Model inputs'!AB49)*(('Model inputs'!F16-'Model inputs'!AB60)-3)/3,IF(IF(('Model inputs'!F16-'Model inputs'!AB60)<=12="",FALSE,('Model inputs'!F16-'Model inputs'!AB60)<=12),'Model inputs'!AB55+('Model inputs'!AB37-'Model inputs'!AB55)*(('Model inputs'!F16-'Model inputs'!AB60)-6)/6,'Model inputs'!AB37+('Model inputs'!AB43-'Model inputs'!AB37)*(('Model inputs'!F16-'Model inputs'!AB60)-12)/12))),0)) -> 0 | G7: =IF(IF(('Model inputs'!G16-'Model inputs'!AB60)<1="",FALSE,('Model inputs'!G16-'Model inputs'!AB60)<1),0,ROUND(IF(IF(('Model inputs'!G16-'Model inputs'!AB60)<=3="",FALSE,('Model inputs'!G16-'Model inputs'!AB60)<=3),IF('Model inputs'!AB49="","",'Model inputs'!AB49),IF(IF(('Model inputs'!G16-'Model inputs'!AB60)<=6="",FALSE,('Model inputs'!G16-'Model inputs'!AB60)<=6),'Model inputs'!AB49+('Model inputs'!AB55-'Model inputs'!AB49)*(('Model inputs'!G16-'Model inputs'!AB60)-3)/3,IF(IF(('Model inputs'!G16-'Model inputs'!AB60)<=12="",FALSE,('Model inputs'!G16-'Model inputs'!AB60)<=12),'Model inputs'!AB55+('Model inputs'!AB37-'Model inputs'!AB55)*(('Model inputs'!G16-'Model inputs'!AB60)-6)/6,'Model inputs'!AB37+('Model inputs'!AB43-'Model inputs'!AB37)*(('Model inputs'!G16-'Model inputs'!AB60)-12)/12))),0)) -> 0 | H7: =IF(IF(('Model inputs'!H16-'Model inputs'!AB60)<1="",FALSE,('Model inputs'!H16-'Model inputs'!AB60)<1),0,ROUND(IF(IF(('Model inputs'!H16-'Model inputs'!AB60)<=3="",FALSE,('Model inputs'!H16-'Model inputs'!AB60)<=3),IF('Model inputs'!AB49="","",'Model inputs'!AB49),IF(IF(('Model inputs'!H16-'Model inputs'!AB60)<=6="",FALSE,('Model inputs'!H16-'Model inputs'!AB60)<=6),'Model inputs'!AB49+('Model inputs'!AB55-'Model inputs'!AB49)*(('Model inputs'!H16-'Model inputs'!AB60)-3)/3,IF(IF(('Model inputs'!H16-'Model inputs'!AB60)<=12="",FALSE,('Model inputs'!H16-'Model inputs'!AB60)<=12),'Model inputs'!AB55+('Model inputs'!AB37-'Model inputs'!AB55)*(('Model inputs'!H16-'Model inputs'!AB60)-6)/6,'Model inputs'!AB37+('Model inputs'!AB43-'Model inputs'!AB37)*(('Model inputs'!H16-'Model inputs'!AB60)-12)/12))),0)) -> 2 | I7: =IF(IF(('Model inputs'!I16-'Model inputs'!AB60)<1="",FALSE,('Model inputs'!I16-'Model inputs'!AB60)<1),0,ROUND(IF(IF(('Model inputs'!I16-'Model inputs'!AB60)<=3="",FALSE,('Model inputs'!I16-'Model inputs'!AB60)<=3),IF('Model inputs'!AB49="","",'Model inputs'!AB49),IF(IF(('Model inputs'!I16-'Model inputs'!AB60)<=6="",FALSE,('Model inputs'!I16-'Model inputs'!AB60)<=6),'Model inputs'!AB49+('Model inputs'!AB55-'Model inputs'!AB49)*(('Model inputs'!I16-'Model inputs'!AB60)-3)/3,IF(IF(('Model inputs'!I16-'Model inputs'!AB60)<=12="",FALSE,('Model inputs'!I16-'Model inputs'!AB60)<=12),'Model inputs'!AB55+('Model inputs'!AB37-'Model inputs'!AB55)*(('Model inputs'!I16-'Model inputs'!AB60)-6)/6,'Model inputs'!AB37+('Model inputs'!AB43-'Model inputs'!AB37)*(('Model inputs'!I16-'Model inputs'!AB60)-12)/12))),0)) -> 3 | J7: =IF(IF(('Model inputs'!J16-'Model inputs'!AB60)<1="",FALSE,('Model inputs'!J16-'Model inputs'!AB60)<1),0,ROUND(IF(IF(('Model inputs'!J16-'Model inputs'!AB60)<=3="",FALSE,('Model inputs'!J16-'Model inputs'!AB60)<=3),IF('Model inputs'!AB49="","",'Model inputs'!AB49),IF(IF(('Model inputs'!J16-'Model inputs'!AB60)<=6="",FALSE,('Model inputs'!J16-'Model inputs'!AB60)<=6),'Model inputs'!AB49+('Model inputs'!AB55-'Model inputs'!AB49)*(('Model inputs'!J16-'Model inputs'!AB60)-3)/3,IF(IF(('Model inputs'!J16-'Model inputs'!AB60)<=12="",FALSE,('Model inputs'!J16-'Model inputs'!AB60)<=12),'Model inputs'!AB55+('Model inputs'!AB37-'Model inputs'!AB55)*(('Model inputs'!J16-'Model inputs'!AB60)-6)/6,'Model inputs'!AB37+('Model inputs'!AB43-'Model inputs'!AB37)*(('Model inputs'!J16-'Model inputs'!AB60)-12)/12))),0)) -> 5 | K7: =IF(IF(('Model inputs'!K16-'Model inputs'!AB60)<1="",FALSE,('Model inputs'!K16-'Model inputs'!AB60)<1),0,ROUND(IF(IF(('Model inputs'!K16-'Model inputs'!AB60)<=3="",FALSE,('Model inputs'!K16-'Model inputs'!AB60)<=3),IF('Model inputs'!AB49="","",'Model inputs'!AB49),IF(IF(('Model inputs'!K16-'Model inputs'!AB60)<=6="",FALSE,('Model inputs'!K16-'Model inputs'!AB60)<=6),'Model inputs'!AB49+('Model inputs'!AB55-'Model inputs'!AB49)*(('Model inputs'!K16-'Model inputs'!AB60)-3)/3,IF(IF(('Model inputs'!K16-'Model inputs'!AB60)<=12="",FALSE,('Model inputs'!K16-'Model inputs'!AB60)<=12),'Model inputs'!AB55+('Model inputs'!AB37-'Model inputs'!AB55)*(('Model inputs'!K16-'Model inputs'!AB60)-6)/6,'Model inputs'!AB37+('Model inputs'!AB43-'Model inputs'!AB37)*(('Model inputs'!K16-'Model inputs'!AB60)-12)/12))),0)) -> 7 | L7: =IF(IF(('Model inputs'!L16-'Model inputs'!AB60)<1="",FALSE,('Model inputs'!L16-'Model inputs'!AB60)<1),0,ROUND(IF(IF(('Model inputs'!L16-'Model inputs'!AB60)<=3="",FALSE,('Model inputs'!L16-'Model inputs'!AB60)<=3),IF('Model inputs'!AB49="","",'Model inputs'!AB49),IF(IF(('Model inputs'!L16-'Model inputs'!AB60)<=6="",FALSE,('Model inputs'!L16-'Model inputs'!AB60)<=6),'Model inputs'!AB49+('Model inputs'!AB55-'Model inputs'!AB49)*(('Model inputs'!L16-'Model inputs'!AB60)-3)/3,IF(IF(('Model inputs'!L16-'Model inputs'!AB60)<=12="",FALSE,('Model inputs'!L16-'Model inputs'!AB60)<=12),'Model inputs'!AB55+('Model inputs'!AB37-'Model inputs'!AB55)*(('Model inputs'!L16-'Model inputs'!AB60)-6)/6,'Model inputs'!AB37+('Model inputs'!AB43-'Model inputs'!AB37)*(('Model inputs'!L16-'Model inputs'!AB60)-12)/12))),0)) -> 8 | M7: =IF(IF(('Model inputs'!M16-'Model inputs'!AB60)<1="",FALSE,('Model inputs'!M16-'Model inputs'!AB60)<1),0,ROUND(IF(IF(('Model inputs'!M16-'Model inputs'!AB60)<=3="",FALSE,('Model inputs'!M16-'Model inputs'!AB60)<=3),IF('Model inputs'!AB49="","",'Model inputs'!AB49),IF(IF(('Model inputs'!M16-'Model inputs'!AB60)<=6="",FALSE,('Model inputs'!M16-'Model inputs'!AB60)<=6),'Model inputs'!AB49+('Model inputs'!AB55-'Model inputs'!AB49)*(('Model inputs'!M16-'Model inputs'!AB60)-3)/3,IF(IF(('Model inputs'!M16-'Model inputs'!AB60)<=12="",FALSE,('Model inputs'!M16-'Model inputs'!AB60)<=12),'Model inputs'!AB55+('Model inputs'!AB37-'Model inputs'!AB55)*(('Model inputs'!M16-'Model inputs'!AB60)-6)/6,'Model inputs'!AB37+('Model inputs'!AB43-'Model inputs'!AB37)*(('Model inputs'!M16-'Model inputs'!AB60)-12)/12))),0)) -> 10 | N7: =IF(IF(('Model inputs'!N16-'Model inputs'!AB60)<1="",FALSE,('Model inputs'!N16-'Model inputs'!AB60)<1),0,ROUND(IF(IF(('Model inputs'!N16-'Model inputs'!AB60)<=3="",FALSE,('Model inputs'!N16-'Model inputs'!AB60)<=3),IF('Model inputs'!AB49="","",'Model inputs'!AB49),IF(IF(('Model inputs'!N16-'Model inputs'!AB60)<=6="",FALSE,('Model inputs'!N16-'Model inputs'!AB60)<=6),'Model inputs'!AB49+('Model inputs'!AB55-'Model inputs'!AB49)*(('Model inputs'!N16-'Model inputs'!AB60)-3)/3,IF(IF(('Model inputs'!N16-'Model inputs'!AB60)<=12="",FALSE,('Model inputs'!N16-'Model inputs'!AB60)<=12),'Model inputs'!AB55+('Model inputs'!AB37-'Model inputs'!AB55)*(('Model inputs'!N16-'Model inputs'!AB60)-6)/6,'Model inputs'!AB37+('Model inputs'!AB43-'Model inputs'!AB37)*(('Model inputs'!N16-'Model inputs'!AB60)-12)/12))),0)) -> 12 | O7: =IF(IF(('Model inputs'!O16-'Model inputs'!AB60)<1="",FALSE,('Model inputs'!O16-'Model inputs'!AB60)<1),0,ROUND(IF(IF(('Model inputs'!O16-'Model inputs'!AB60)<=3="",FALSE,('Model inputs'!O16-'Model inputs'!AB60)<=3),IF('Model inputs'!AB49="","",'Model inputs'!AB49),IF(IF(('Model inputs'!O16-'Model inputs'!AB60)<=6="",FALSE,('Model inputs'!O16-'Model inputs'!AB60)<=6),'Model inputs'!AB49+('Model inputs'!AB55-'Model inputs'!AB49)*(('Model inputs'!O16-'Model inputs'!AB60)-3)/3,IF(IF(('Model inputs'!O16-'Model inputs'!AB60)<=12="",FALSE,('Model inputs'!O16-'Model inputs'!AB60)<=12),'Model inputs'!AB55+('Model inputs'!AB37-'Model inputs'!AB55)*(('Model inputs'!O16-'Model inputs'!AB60)-6)/6,'Model inputs'!AB37+('Model inputs'!AB43-'Model inputs'!AB37)*(('Model inputs'!O16-'Model inputs'!AB60)-12)/12))),0)) -> 13 | P7: =IF(IF(('Model inputs'!P16-'Model inputs'!AB60)<1="",FALSE,('Model inputs'!P16-'Model inputs'!AB60)<1),0,ROUND(IF(IF(('Model inputs'!P16-'Model inputs'!AB60)<=3="",FALSE,('Model inputs'!P16-'Model inputs'!AB60)<=3),IF('Model inputs'!AB49="","",'Model inputs'!AB49),IF(IF(('Model inputs'!P16-'Model inputs'!AB60)<=6="",FALSE,('Model inputs'!P16-'Model inputs'!AB60)<=6),'Model inputs'!AB49+('Model inputs'!AB55-'Model inputs'!AB49)*(('Model inputs'!P16-'Model inputs'!AB60)-3)/3,IF(IF(('Model inputs'!P16-'Model inputs'!AB60)<=12="",FALSE,('Model inputs'!P16-'Model inputs'!AB60)<=12),'Model inputs'!AB55+('Model inputs'!AB37-'Model inputs'!AB55)*(('Model inputs'!P16-'Model inputs'!AB60)-6)/6,'Model inputs'!AB37+('Model inputs'!AB43-'Model inputs'!AB37)*(('Model inputs'!P16-'Model inputs'!AB60)-12)/12))),0)) -> 15 | Q7: =IF(IF(('Model inputs'!Q16-'Model inputs'!AB60)<1="",FALSE,('Model inputs'!Q16-'Model inputs'!AB60)<1),0,ROUND(IF(IF(('Model inputs'!Q16-'Model inputs'!AB60)<=3="",FALSE,('Model inputs'!Q16-'Model inputs'!AB60)<=3),IF('Model inputs'!AB49="","",'Model inputs'!AB49),IF(IF(('Model inputs'!Q16-'Model inputs'!AB60)<=6="",FALSE,('Model inputs'!Q16-'Model inputs'!AB60)<=6),'Model inputs'!AB49+('Model inputs'!AB55-'Model inputs'!AB49)*(('Model inputs'!Q16-'Model inputs'!AB60)-3)/3,IF(IF(('Model inputs'!Q16-'Model inputs'!AB60)<=12="",FALSE,('Model inputs'!Q16-'Model inputs'!AB60)<=12),'Model inputs'!AB55+('Model inputs'!AB37-'Model inputs'!AB55)*(('Model inputs'!Q16-'Model inputs'!AB60)-6)/6,'Model inputs'!AB37+('Model inputs'!AB43-'Model inputs'!AB37)*(('Model inputs'!Q16-'Model inputs'!AB60)-12)/12))),0)) -> 17 | R7: =IF(IF(('Model inputs'!R16-'Model inputs'!AB60)<1="",FALSE,('Model inputs'!R16-'Model inputs'!AB60)<1),0,ROUND(IF(IF(('Model inputs'!R16-'Model inputs'!AB60)<=3="",FALSE,('Model inputs'!R16-'Model inputs'!AB60)<=3),IF('Model inputs'!AB49="","",'Model inputs'!AB49),IF(IF(('Model inputs'!R16-'Model inputs'!AB60)<=6="",FALSE,('Model inputs'!R16-'Model inputs'!AB60)<=6),'Model inputs'!AB49+('Model inputs'!AB55-'Model inputs'!AB49)*(('Model inputs'!R16-'Model inputs'!AB60)-3)/3,IF(IF(('Model inputs'!R16-'Model inputs'!AB60)<=12="",FALSE,('Model inputs'!R16-'Model inputs'!AB60)<=12),'Model inputs'!AB55+('Model inputs'!AB37-'Model inputs'!AB55)*(('Model inputs'!R16-'Model inputs'!AB60)-6)/6,'Model inputs'!AB37+('Model inputs'!AB43-'Model inputs'!AB37)*(('Model inputs'!R16-'Model inputs'!AB60)-12)/12))),0)) -> 19 | S7: =IF(IF(('Model inputs'!S16-'Model inputs'!AB60)<1="",FALSE,('Model inputs'!S16-'Model inputs'!AB60)<1),0,ROUND(IF(IF(('Model inputs'!S16-'Model inputs'!AB60)<=3="",FALSE,('Model inputs'!S16-'Model inputs'!AB60)<=3),IF('Model inputs'!AB49="","",'Model inputs'!AB49),IF(IF(('Model inputs'!S16-'Model inputs'!AB60)<=6="",FALSE,('Model inputs'!S16-'Model inputs'!AB60)<=6),'Model inputs'!AB49+('Model inputs'!AB55-'Model inputs'!AB49)*(('Model inputs'!S16-'Model inputs'!AB60)-3)/3,IF(IF(('Model inputs'!S16-'Model inputs'!AB60)<=12="",FALSE,('Model inputs'!S16-'Model inputs'!AB60)<=12),'Model inputs'!AB55+('Model inputs'!AB37-'Model inputs'!AB55)*(('Model inputs'!S16-'Model inputs'!AB60)-6)/6,'Model inputs'!AB37+('Model inputs'!AB43-'Model inputs'!AB37)*(('Model inputs'!S16-'Model inputs'!AB60)-12)/12))),0)) -> 21 | T7: =IF(IF(('Model inputs'!T16-'Model inputs'!AB60)<1="",FALSE,('Model inputs'!T16-'Model inputs'!AB60)<1),0,ROUND(IF(IF(('Model inputs'!T16-'Model inputs'!AB60)<=3="",FALSE,('Model inputs'!T16-'Model inputs'!AB60)<=3),IF('Model inputs'!AB49="","",'Model inputs'!AB49),IF(IF(('Model inputs'!T16-'Model inputs'!AB60)<=6="",FALSE,('Model inputs'!T16-'Model inputs'!AB60)<=6),'Model inputs'!AB49+('Model inputs'!AB55-'Model inputs'!AB49)*(('Model inputs'!T16-'Model inputs'!AB60)-3)/3,IF(IF(('Model inputs'!T16-'Model inputs'!AB60)<=12="",FALSE,('Model inputs'!T16-'Model inputs'!AB60)<=12),'Model inputs'!AB55+('Model inputs'!AB37-'Model inputs'!AB55)*(('Model inputs'!T16-'Model inputs'!AB60)-6)/6,'Model inputs'!AB37+('Model inputs'!AB43-'Model inputs'!AB37)*(('Model inputs'!T16-'Model inputs'!AB60)-12)/12))),0)) -> 23 | U7: =IF(IF(('Model inputs'!U16-'Model inputs'!AB60)<1="",FALSE,('Model inputs'!U16-'Model inputs'!AB60)<1),0,ROUND(IF(IF(('Model inputs'!U16-'Model inputs'!AB60)<=3="",FALSE,('Model inputs'!U16-'Model inputs'!AB60)<=3),IF('Model inputs'!AB49="","",'Model inputs'!AB49),IF(IF(('Model inputs'!U16-'Model inputs'!AB60)<=6="",FALSE,('Model inputs'!U16-'Model inputs'!AB60)<=6),'Model inputs'!AB49+('Model inputs'!AB55-'Model inputs'!AB49)*(('Model inputs'!U16-'Model inputs'!AB60)-3)/3,IF(IF(('Model inputs'!U16-'Model inputs'!AB60)<=12="",FALSE,('Model inputs'!U16-'Model inputs'!AB60)<=12),'Model inputs'!AB55+('Model inputs'!AB37-'Model inputs'!AB55)*(('Model inputs'!U16-'Model inputs'!AB60)-6)/6,'Model inputs'!AB37+('Model inputs'!AB43-'Model inputs'!AB37)*(('Model inputs'!U16-'Model inputs'!AB60)-12)/12))),0)) -> 25 | V7: =IF(IF(('Model inputs'!V16-'Model inputs'!AB60)<1="",FALSE,('Model inputs'!V16-'Model inputs'!AB60)<1),0,ROUND(IF(IF(('Model inputs'!V16-'Model inputs'!AB60)<=3="",FALSE,('Model inputs'!V16-'Model inputs'!AB60)<=3),IF('Model inputs'!AB49="","",'Model inputs'!AB49),IF(IF(('Model inputs'!V16-'Model inputs'!AB60)<=6="",FALSE,('Model inputs'!V16-'Model inputs'!AB60)<=6),'Model inputs'!AB49+('Model inputs'!AB55-'Model inputs'!AB49)*(('Model inputs'!V16-'Model inputs'!AB60)-3)/3,IF(IF(('Model inputs'!V16-'Model inputs'!AB60)<=12="",FALSE,('Model inputs'!V16-'Model inputs'!AB60)<=12),'Model inputs'!AB55+('Model inputs'!AB37-'Model inputs'!AB55)*(('Model inputs'!V16-'Model inputs'!AB60)-6)/6,'Model inputs'!AB37+('Model inputs'!AB43-'Model inputs'!AB37)*(('Model inputs'!V16-'Model inputs'!AB60)-12)/12))),0)) -> 28 | W7: =IF(IF(('Model inputs'!W16-'Model inputs'!AB60)<1="",FALSE,('Model inputs'!W16-'Model inputs'!AB60)<1),0,ROUND(IF(IF(('Model inputs'!W16-'Model inputs'!AB60)<=3="",FALSE,('Model inputs'!W16-'Model inputs'!AB60)<=3),IF('Model inputs'!AB49="","",'Model inputs'!AB49),IF(IF(('Model inputs'!W16-'Model inputs'!AB60)<=6="",FALSE,('Model inputs'!W16-'Model inputs'!AB60)<=6),'Model inputs'!AB49+('Model inputs'!AB55-'Model inputs'!AB49)*(('Model inputs'!W16-'Model inputs'!AB60)-3)/3,IF(IF(('Model inputs'!W16-'Model inputs'!AB60)<=12="",FALSE,('Model inputs'!W16-'Model inputs'!AB60)<=12),'Model inputs'!AB55+('Model inputs'!AB37-'Model inputs'!AB55)*(('Model inputs'!W16-'Model inputs'!AB60)-6)/6,'Model inputs'!AB37+('Model inputs'!AB43-'Model inputs'!AB37)*(('Model inputs'!W16-'Model inputs'!AB60)-12)/12))),0)) -> 30 | X7: =IF(IF(('Model inputs'!X16-'Model inputs'!AB60)<1="",FALSE,('Model inputs'!X16-'Model inputs'!AB60)<1),0,ROUND(IF(IF(('Model inputs'!X16-'Model inputs'!AB60)<=3="",FALSE,('Model inputs'!X16-'Model inputs'!AB60)<=3),IF('Model inputs'!AB49="","",'Model inputs'!AB49),IF(IF(('Model inputs'!X16-'Model inputs'!AB60)<=6="",FALSE,('Model inputs'!X16-'Model inputs'!AB60)<=6),'Model inputs'!AB49+('Model inputs'!AB55-'Model inputs'!AB49)*(('Model inputs'!X16-'Model inputs'!AB60)-3)/3,IF(IF(('Model inputs'!X16-'Model inputs'!AB60)<=12="",FALSE,('Model inputs'!X16-'Model inputs'!AB60)<=12),'Model inputs'!AB55+('Model inputs'!AB37-'Model inputs'!AB55)*(('Model inputs'!X16-'Model inputs'!AB60)-6)/6,'Model inputs'!AB37+('Model inputs'!AB43-'Model inputs'!AB37)*(('Model inputs'!X16-'Model inputs'!AB60)-12)/12))),0)) -> 32 | Y7: =IF(IF(('Model inputs'!Y16-'Model inputs'!AB60)<1="",FALSE,('Model inputs'!Y16-'Model inputs'!AB60)<1),0,ROUND(IF(IF(('Model inputs'!Y16-'Model inputs'!AB60)<=3="",FALSE,('Model inputs'!Y16-'Model inputs'!AB60)<=3),IF('Model inputs'!AB49="","",'Model inputs'!AB49),IF(IF(('Model inputs'!Y16-'Model inputs'!AB60)<=6="",FALSE,('Model inputs'!Y16-'Model inputs'!AB60)<=6),'Model inputs'!AB49+('Model inputs'!AB55-'Model inputs'!AB49)*(('Model inputs'!Y16-'Model inputs'!AB60)-3)/3,IF(IF(('Model inputs'!Y16-'Model inputs'!AB60)<=12="",FALSE,('Model inputs'!Y16-'Model inputs'!AB60)<=12),'Model inputs'!AB55+('Model inputs'!AB37-'Model inputs'!AB55)*(('Model inputs'!Y16-'Model inputs'!AB60)-6)/6,'Model inputs'!AB37+('Model inputs'!AB43-'Model inputs'!AB37)*(('Model inputs'!Y16-'Model inputs'!AB60)-12)/12))),0)) -> 34
A8: Customers > Team | B8: =IF(IF(('Model inputs'!B16-'Model inputs'!AB60)<1="",FALSE,('Model inputs'!B16-'Model inputs'!AB60)<1),0,ROUND(IF(IF(('Model inputs'!B16-'Model inputs'!AB60)<=3="",FALSE,('Model inputs'!B16-'Model inputs'!AB60)<=3),IF('Model inputs'!AB50="","",'Model inputs'!AB50),IF(IF(('Model inputs'!B16-'Model inputs'!AB60)<=6="",FALSE,('Model inputs'!B16-'Model inputs'!AB60)<=6),'Model inputs'!AB50+('Model inputs'!AB56-'Model inputs'!AB50)*(('Model inputs'!B16-'Model inputs'!AB60)-3)/3,IF(IF(('Model inputs'!B16-'Model inputs'!AB60)<=12="",FALSE,('Model inputs'!B16-'Model inputs'!AB60)<=12),'Model inputs'!AB56+('Model inputs'!AB38-'Model inputs'!AB56)*(('Model inputs'!B16-'Model inputs'!AB60)-6)/6,'Model inputs'!AB38+('Model inputs'!AB44-'Model inputs'!AB38)*(('Model inputs'!B16-'Model inputs'!AB60)-12)/12))),0)) -> 0 | C8: =IF(IF(('Model inputs'!C16-'Model inputs'!AB60)<1="",FALSE,('Model inputs'!C16-'Model inputs'!AB60)<1),0,ROUND(IF(IF(('Model inputs'!C16-'Model inputs'!AB60)<=3="",FALSE,('Model inputs'!C16-'Model inputs'!AB60)<=3),IF('Model inputs'!AB50="","",'Model inputs'!AB50),IF(IF(('Model inputs'!C16-'Model inputs'!AB60)<=6="",FALSE,('Model inputs'!C16-'Model inputs'!AB60)<=6),'Model inputs'!AB50+('Model inputs'!AB56-'Model inputs'!AB50)*(('Model inputs'!C16-'Model inputs'!AB60)-3)/3,IF(IF(('Model inputs'!C16-'Model inputs'!AB60)<=12="",FALSE,('Model inputs'!C16-'Model inputs'!AB60)<=12),'Model inputs'!AB56+('Model inputs'!AB38-'Model inputs'!AB56)*(('Model inputs'!C16-'Model inputs'!AB60)-6)/6,'Model inputs'!AB38+('Model inputs'!AB44-'Model inputs'!AB38)*(('Model inputs'!C16-'Model inputs'!AB60)-12)/12))),0)) -> 0 | D8: =IF(IF(('Model inputs'!D16-'Model inputs'!AB60)<1="",FALSE,('Model inputs'!D16-'Model inputs'!AB60)<1),0,ROUND(IF(IF(('Model inputs'!D16-'Model inputs'!AB60)<=3="",FALSE,('Model inputs'!D16-'Model inputs'!AB60)<=3),IF('Model inputs'!AB50="","",'Model inputs'!AB50),IF(IF(('Model inputs'!D16-'Model inputs'!AB60)<=6="",FALSE,('Model inputs'!D16-'Model inputs'!AB60)<=6),'Model inputs'!AB50+('Model inputs'!AB56-'Model inputs'!AB50)*(('Model inputs'!D16-'Model inputs'!AB60)-3)/3,IF(IF(('Model inputs'!D16-'Model inputs'!AB60)<=12="",FALSE,('Model inputs'!D16-'Model inputs'!AB60)<=12),'Model inputs'!AB56+('Model inputs'!AB38-'Model inputs'!AB56)*(('Model inputs'!D16-'Model inputs'!AB60)-6)/6,'Model inputs'!AB38+('Model inputs'!AB44-'Model inputs'!AB38)*(('Model inputs'!D16-'Model inputs'!AB60)-12)/12))),0)) -> 0 | E8: =IF(IF(('Model inputs'!E16-'Model inputs'!AB60)<1="",FALSE,('Model inputs'!E16-'Model inputs'!AB60)<1),0,ROUND(IF(IF(('Model inputs'!E16-'Model inputs'!AB60)<=3="",FALSE,('Model inputs'!E16-'Model inputs'!AB60)<=3),IF('Model inputs'!AB50="","",'Model inputs'!AB50),IF(IF(('Model inputs'!E16-'Model inputs'!AB60)<=6="",FALSE,('Model inputs'!E16-'Model inputs'!AB60)<=6),'Model inputs'!AB50+('Model inputs'!AB56-'Model inputs'!AB50)*(('Model inputs'!E16-'Model inputs'!AB60)-3)/3,IF(IF(('Model inputs'!E16-'Model inputs'!AB60)<=12="",FALSE,('Model inputs'!E16-'Model inputs'!AB60)<=12),'Model inputs'!AB56+('Model inputs'!AB38-'Model inputs'!AB56)*(('Model inputs'!E16-'Model inputs'!AB60)-6)/6,'Model inputs'!AB38+('Model inputs'!AB44-'Model inputs'!AB38)*(('Model inputs'!E16-'Model inputs'!AB60)-12)/12))),0)) -> 0 | F8: =IF(IF(('Model inputs'!F16-'Model inputs'!AB60)<1="",FALSE,('Model inputs'!F16-'Model inputs'!AB60)<1),0,ROUND(IF(IF(('Model inputs'!F16-'Model inputs'!AB60)<=3="",FALSE,('Model inputs'!F16-'Model inputs'!AB60)<=3),IF('Model inputs'!AB50="","",'Model inputs'!AB50),IF(IF(('Model inputs'!F16-'Model inputs'!AB60)<=6="",FALSE,('Model inputs'!F16-'Model inputs'!AB60)<=6),'Model inputs'!AB50+('Model inputs'!AB56-'Model inputs'!AB50)*(('Model inputs'!F16-'Model inputs'!AB60)-3)/3,IF(IF(('Model inputs'!F16-'Model inputs'!AB60)<=12="",FALSE,('Model inputs'!F16-'Model inputs'!AB60)<=12),'Model inputs'!AB56+('Model inputs'!AB38-'Model inputs'!AB56)*(('Model inputs'!F16-'Model inputs'!AB60)-6)/6,'Model inputs'!AB38+('Model inputs'!AB44-'Model inputs'!AB38)*(('Model inputs'!F16-'Model inputs'!AB60)-12)/12))),0)) -> 0 | G8: =IF(IF(('Model inputs'!G16-'Model inputs'!AB60)<1="",FALSE,('Model inputs'!G16-'Model inputs'!AB60)<1),0,ROUND(IF(IF(('Model inputs'!G16-'Model inputs'!AB60)<=3="",FALSE,('Model inputs'!G16-'Model inputs'!AB60)<=3),IF('Model inputs'!AB50="","",'Model inputs'!AB50),IF(IF(('Model inputs'!G16-'Model inputs'!AB60)<=6="",FALSE,('Model inputs'!G16-'Model inputs'!AB60)<=6),'Model inputs'!AB50+('Model inputs'!AB56-'Model inputs'!AB50)*(('Model inputs'!G16-'Model inputs'!AB60)-3)/3,IF(IF(('Model inputs'!G16-'Model inputs'!AB60)<=12="",FALSE,('Model inputs'!G16-'Model inputs'!AB60)<=12),'Model inputs'!AB56+('Model inputs'!AB38-'Model inputs'!AB56)*(('Model inputs'!G16-'Model inputs'!AB60)-6)/6,'Model inputs'!AB38+('Model inputs'!AB44-'Model inputs'!AB38)*(('Model inputs'!G16-'Model inputs'!AB60)-12)/12))),0)) -> 0 | H8: =IF(IF(('Model inputs'!H16-'Model inputs'!AB60)<1="",FALSE,('Model inputs'!H16-'Model inputs'!AB60)<1),0,ROUND(IF(IF(('Model inputs'!H16-'Model inputs'!AB60)<=3="",FALSE,('Model inputs'!H16-'Model inputs'!AB60)<=3),IF('Model inputs'!AB50="","",'Model inputs'!AB50),IF(IF(('Model inputs'!H16-'Model inputs'!AB60)<=6="",FALSE,('Model inputs'!H16-'Model inputs'!AB60)<=6),'Model inputs'!AB50+('Model inputs'!AB56-'Model inputs'!AB50)*(('Model inputs'!H16-'Model inputs'!AB60)-3)/3,IF(IF(('Model inputs'!H16-'Model inputs'!AB60)<=12="",FALSE,('Model inputs'!H16-'Model inputs'!AB60)<=12),'Model inputs'!AB56+('Model inputs'!AB38-'Model inputs'!AB56)*(('Model inputs'!H16-'Model inputs'!AB60)-6)/6,'Model inputs'!AB38+('Model inputs'!AB44-'Model inputs'!AB38)*(('Model inputs'!H16-'Model inputs'!AB60)-12)/12))),0)) -> 0 | I8: =IF(IF(('Model inputs'!I16-'Model inputs'!AB60)<1="",FALSE,('Model inputs'!I16-'Model inputs'!AB60)<1),0,ROUND(IF(IF(('Model inputs'!I16-'Model inputs'!AB60)<=3="",FALSE,('Model inputs'!I16-'Model inputs'!AB60)<=3),IF('Model inputs'!AB50="","",'Model inputs'!AB50),IF(IF(('Model inputs'!I16-'Model inputs'!AB60)<=6="",FALSE,('Model inputs'!I16-'Model inputs'!AB60)<=6),'Model inputs'!AB50+('Model inputs'!AB56-'Model inputs'!AB50)*(('Model inputs'!I16-'Model inputs'!AB60)-3)/3,IF(IF(('Model inputs'!I16-'Model inputs'!AB60)<=12="",FALSE,('Model inputs'!I16-'Model inputs'!AB60)<=12),'Model inputs'!AB56+('Model inputs'!AB38-'Model inputs'!AB56)*(('Model inputs'!I16-'Model inputs'!AB60)-6)/6,'Model inputs'!AB38+('Model inputs'!AB44-'Model inputs'!AB38)*(('Model inputs'!I16-'Model inputs'!AB60)-12)/12))),0)) -> 1 | J8: =IF(IF(('Model inputs'!J16-'Model inputs'!AB60)<1="",FALSE,('Model inputs'!J16-'Model inputs'!AB60)<1),0,ROUND(IF(IF(('Model inputs'!J16-'Model inputs'!AB60)<=3="",FALSE,('Model inputs'!J16-'Model inputs'!AB60)<=3),IF('Model inputs'!AB50="","",'Model inputs'!AB50),IF(IF(('Model inputs'!J16-'Model inputs'!AB60)<=6="",FALSE,('Model inputs'!J16-'Model inputs'!AB60)<=6),'Model inputs'!AB50+('Model inputs'!AB56-'Model inputs'!AB50)*(('Model inputs'!J16-'Model inputs'!AB60)-3)/3,IF(IF(('Model inputs'!J16-'Model inputs'!AB60)<=12="",FALSE,('Model inputs'!J16-'Model inputs'!AB60)<=12),'Model inputs'!AB56+('Model inputs'!AB38-'Model inputs'!AB56)*(('Model inputs'!J16-'Model inputs'!AB60)-6)/6,'Model inputs'!AB38+('Model inputs'!AB44-'Model inputs'!AB38)*(('Model inputs'!J16-'Model inputs'!AB60)-12)/12))),0)) -> 1 | K8: =IF(IF(('Model inputs'!K16-'Model inputs'!AB60)<1="",FALSE,('Model inputs'!K16-'Model inputs'!AB60)<1),0,ROUND(IF(IF(('Model inputs'!K16-'Model inputs'!AB60)<=3="",FALSE,('Model inputs'!K16-'Model inputs'!AB60)<=3),IF('Model inputs'!AB50="","",'Model inputs'!AB50),IF(IF(('Model inputs'!K16-'Model inputs'!AB60)<=6="",FALSE,('Model inputs'!K16-'Model inputs'!AB60)<=6),'Model inputs'!AB50+('Model inputs'!AB56-'Model inputs'!AB50)*(('Model inputs'!K16-'Model inputs'!AB60)-3)/3,IF(IF(('Model inputs'!K16-'Model inputs'!AB60)<=12="",FALSE,('Model inputs'!K16-'Model inputs'!AB60)<=12),'Model inputs'!AB56+('Model inputs'!AB38-'Model inputs'!AB56)*(('Model inputs'!K16-'Model inputs'!AB60)-6)/6,'Model inputs'!AB38+('Model inputs'!AB44-'Model inputs'!AB38)*(('Model inputs'!K16-'Model inputs'!AB60)-12)/12))),0)) -> 1 | L8: =IF(IF(('Model inputs'!L16-'Model inputs'!AB60)<1="",FALSE,('Model inputs'!L16-'Model inputs'!AB60)<1),0,ROUND(IF(IF(('Model inputs'!L16-'Model inputs'!AB60)<=3="",FALSE,('Model inputs'!L16-'Model inputs'!AB60)<=3),IF('Model inputs'!AB50="","",'Model inputs'!AB50),IF(IF(('Model inputs'!L16-'Model inputs'!AB60)<=6="",FALSE,('Model inputs'!L16-'Model inputs'!AB60)<=6),'Model inputs'!AB50+('Model inputs'!AB56-'Model inputs'!AB50)*(('Model inputs'!L16-'Model inputs'!AB60)-3)/3,IF(IF(('Model inputs'!L16-'Model inputs'!AB60)<=12="",FALSE,('Model inputs'!L16-'Model inputs'!AB60)<=12),'Model inputs'!AB56+('Model inputs'!AB38-'Model inputs'!AB56)*(('Model inputs'!L16-'Model inputs'!AB60)-6)/6,'Model inputs'!AB38+('Model inputs'!AB44-'Model inputs'!AB38)*(('Model inputs'!L16-'Model inputs'!AB60)-12)/12))),0)) -> 2 | M8: =IF(IF(('Model inputs'!M16-'Model inputs'!AB60)<1="",FALSE,('Model inputs'!M16-'Model inputs'!AB60)<1),0,ROUND(IF(IF(('Model inputs'!M16-'Model inputs'!AB60)<=3="",FALSE,('Model inputs'!M16-'Model inputs'!AB60)<=3),IF('Model inputs'!AB50="","",'Model inputs'!AB50),IF(IF(('Model inputs'!M16-'Model inputs'!AB60)<=6="",FALSE,('Model inputs'!M16-'Model inputs'!AB60)<=6),'Model inputs'!AB50+('Model inputs'!AB56-'Model inputs'!AB50)*(('Model inputs'!M16-'Model inputs'!AB60)-3)/3,IF(IF(('Model inputs'!M16-'Model inputs'!AB60)<=12="",FALSE,('Model inputs'!M16-'Model inputs'!AB60)<=12),'Model inputs'!AB56+('Model inputs'!AB38-'Model inputs'!AB56)*(('Model inputs'!M16-'Model inputs'!AB60)-6)/6,'Model inputs'!AB38+('Model inputs'!AB44-'Model inputs'!AB38)*(('Model inputs'!M16-'Model inputs'!AB60)-12)/12))),0)) -> 2 | N8: =IF(IF(('Model inputs'!N16-'Model inputs'!AB60)<1="",FALSE,('Model inputs'!N16-'Model inputs'!AB60)<1),0,ROUND(IF(IF(('Model inputs'!N16-'Model inputs'!AB60)<=3="",FALSE,('Model inputs'!N16-'Model inputs'!AB60)<=3),IF('Model inputs'!AB50="","",'Model inputs'!AB50),IF(IF(('Model inputs'!N16-'Model inputs'!AB60)<=6="",FALSE,('Model inputs'!N16-'Model inputs'!AB60)<=6),'Model inputs'!AB50+('Model inputs'!AB56-'Model inputs'!AB50)*(('Model inputs'!N16-'Model inputs'!AB60)-3)/3,IF(IF(('Model inputs'!N16-'Model inputs'!AB60)<=12="",FALSE,('Model inputs'!N16-'Model inputs'!AB60)<=12),'Model inputs'!AB56+('Model inputs'!AB38-'Model inputs'!AB56)*(('Model inputs'!N16-'Model inputs'!AB60)-6)/6,'Model inputs'!AB38+('Model inputs'!AB44-'Model inputs'!AB38)*(('Model inputs'!N16-'Model inputs'!AB60)-12)/12))),0)) -> 2 | O8: =IF(IF(('Model inputs'!O16-'Model inputs'!AB60)<1="",FALSE,('Model inputs'!O16-'Model inputs'!AB60)<1),0,ROUND(IF(IF(('Model inputs'!O16-'Model inputs'!AB60)<=3="",FALSE,('Model inputs'!O16-'Model inputs'!AB60)<=3),IF('Model inputs'!AB50="","",'Model inputs'!AB50),IF(IF(('Model inputs'!O16-'Model inputs'!AB60)<=6="",FALSE,('Model inputs'!O16-'Model inputs'!AB60)<=6),'Model inputs'!AB50+('Model inputs'!AB56-'Model inputs'!AB50)*(('Model inputs'!O16-'Model inputs'!AB60)-3)/3,IF(IF(('Model inputs'!O16-'Model inputs'!AB60)<=12="",FALSE,('Model inputs'!O16-'Model inputs'!AB60)<=12),'Model inputs'!AB56+('Model inputs'!AB38-'Model inputs'!AB56)*(('Model inputs'!O16-'Model inputs'!AB60)-6)/6,'Model inputs'!AB38+('Model inputs'!AB44-'Model inputs'!AB38)*(('Model inputs'!O16-'Model inputs'!AB60)-12)/12))),0)) -> 3 | P8: =IF(IF(('Model inputs'!P16-'Model inputs'!AB60)<1="",FALSE,('Model inputs'!P16-'Model inputs'!AB60)<1),0,ROUND(IF(IF(('Model inputs'!P16-'Model inputs'!AB60)<=3="",FALSE,('Model inputs'!P16-'Model inputs'!AB60)<=3),IF('Model inputs'!AB50="","",'Model inputs'!AB50),IF(IF(('Model inputs'!P16-'Model inputs'!AB60)<=6="",FALSE,('Model inputs'!P16-'Model inputs'!AB60)<=6),'Model inputs'!AB50+('Model inputs'!AB56-'Model inputs'!AB50)*(('Model inputs'!P16-'Model inputs'!AB60)-3)/3,IF(IF(('Model inputs'!P16-'Model inputs'!AB60)<=12="",FALSE,('Model inputs'!P16-'Model inputs'!AB60)<=12),'Model inputs'!AB56+('Model inputs'!AB38-'Model inputs'!AB56)*(('Model inputs'!P16-'Model inputs'!AB60)-6)/6,'Model inputs'!AB38+('Model inputs'!AB44-'Model inputs'!AB38)*(('Model inputs'!P16-'Model inputs'!AB60)-12)/12))),0)) -> 3 | Q8: =IF(IF(('Model inputs'!Q16-'Model inputs'!AB60)<1="",FALSE,('Model inputs'!Q16-'Model inputs'!AB60)<1),0,ROUND(IF(IF(('Model inputs'!Q16-'Model inputs'!AB60)<=3="",FALSE,('Model inputs'!Q16-'Model inputs'!AB60)<=3),IF('Model inputs'!AB50="","",'Model inputs'!AB50),IF(IF(('Model inputs'!Q16-'Model inputs'!AB60)<=6="",FALSE,('Model inputs'!Q16-'Model inputs'!AB60)<=6),'Model inputs'!AB50+('Model inputs'!AB56-'Model inputs'!AB50)*(('Model inputs'!Q16-'Model inputs'!AB60)-3)/3,IF(IF(('Model inputs'!Q16-'Model inputs'!AB60)<=12="",FALSE,('Model inputs'!Q16-'Model inputs'!AB60)<=12),'Model inputs'!AB56+('Model inputs'!AB38-'Model inputs'!AB56)*(('Model inputs'!Q16-'Model inputs'!AB60)-6)/6,'Model inputs'!AB38+('Model inputs'!AB44-'Model inputs'!AB38)*(('Model inputs'!Q16-'Model inputs'!AB60)-12)/12))),0)) -> 4 | R8: =IF(IF(('Model inputs'!R16-'Model inputs'!AB60)<1="",FALSE,('Model inputs'!R16-'Model inputs'!AB60)<1),0,ROUND(IF(IF(('Model inputs'!R16-'Model inputs'!AB60)<=3="",FALSE,('Model inputs'!R16-'Model inputs'!AB60)<=3),IF('Model inputs'!AB50="","",'Model inputs'!AB50),IF(IF(('Model inputs'!R16-'Model inputs'!AB60)<=6="",FALSE,('Model inputs'!R16-'Model inputs'!AB60)<=6),'Model inputs'!AB50+('Model inputs'!AB56-'Model inputs'!AB50)*(('Model inputs'!R16-'Model inputs'!AB60)-3)/3,IF(IF(('Model inputs'!R16-'Model inputs'!AB60)<=12="",FALSE,('Model inputs'!R16-'Model inputs'!AB60)<=12),'Model inputs'!AB56+('Model inputs'!AB38-'Model inputs'!AB56)*(('Model inputs'!R16-'Model inputs'!AB60)-6)/6,'Model inputs'!AB38+('Model inputs'!AB44-'Model inputs'!AB38)*(('Model inputs'!R16-'Model inputs'!AB60)-12)/12))),0)) -> 4 | S8: =IF(IF(('Model inputs'!S16-'Model inputs'!AB60)<1="",FALSE,('Model inputs'!S16-'Model inputs'!AB60)<1),0,ROUND(IF(IF(('Model inputs'!S16-'Model inputs'!AB60)<=3="",FALSE,('Model inputs'!S16-'Model inputs'!AB60)<=3),IF('Model inputs'!AB50="","",'Model inputs'!AB50),IF(IF(('Model inputs'!S16-'Model inputs'!AB60)<=6="",FALSE,('Model inputs'!S16-'Model inputs'!AB60)<=6),'Model inputs'!AB50+('Model inputs'!AB56-'Model inputs'!AB50)*(('Model inputs'!S16-'Model inputs'!AB60)-3)/3,IF(IF(('Model inputs'!S16-'Model inputs'!AB60)<=12="",FALSE,('Model inputs'!S16-'Model inputs'!AB60)<=12),'Model inputs'!AB56+('Model inputs'!AB38-'Model inputs'!AB56)*(('Model inputs'!S16-'Model inputs'!AB60)-6)/6,'Model inputs'!AB38+('Model inputs'!AB44-'Model inputs'!AB38)*(('Model inputs'!S16-'Model inputs'!AB60)-12)/12))),0)) -> 5 | T8: =IF(IF(('Model inputs'!T16-'Model inputs'!AB60)<1="",FALSE,('Model inputs'!T16-'Model inputs'!AB60)<1),0,ROUND(IF(IF(('Model inputs'!T16-'Model inputs'!AB60)<=3="",FALSE,('Model inputs'!T16-'Model inputs'!AB60)<=3),IF('Model inputs'!AB50="","",'Model inputs'!AB50),IF(IF(('Model inputs'!T16-'Model inputs'!AB60)<=6="",FALSE,('Model inputs'!T16-'Model inputs'!AB60)<=6),'Model inputs'!AB50+('Model inputs'!AB56-'Model inputs'!AB50)*(('Model inputs'!T16-'Model inputs'!AB60)-3)/3,IF(IF(('Model inputs'!T16-'Model inputs'!AB60)<=12="",FALSE,('Model inputs'!T16-'Model inputs'!AB60)<=12),'Model inputs'!AB56+('Model inputs'!AB38-'Model inputs'!AB56)*(('Model inputs'!T16-'Model inputs'!AB60)-6)/6,'Model inputs'!AB38+('Model inputs'!AB44-'Model inputs'!AB38)*(('Model inputs'!T16-'Model inputs'!AB60)-12)/12))),0)) -> 5 | U8: =IF(IF(('Model inputs'!U16-'Model inputs'!AB60)<1="",FALSE,('Model inputs'!U16-'Model inputs'!AB60)<1),0,ROUND(IF(IF(('Model inputs'!U16-'Model inputs'!AB60)<=3="",FALSE,('Model inputs'!U16-'Model inputs'!AB60)<=3),IF('Model inputs'!AB50="","",'Model inputs'!AB50),IF(IF(('Model inputs'!U16-'Model inputs'!AB60)<=6="",FALSE,('Model inputs'!U16-'Model inputs'!AB60)<=6),'Model inputs'!AB50+('Model inputs'!AB56-'Model inputs'!AB50)*(('Model inputs'!U16-'Model inputs'!AB60)-3)/3,IF(IF(('Model inputs'!U16-'Model inputs'!AB60)<=12="",FALSE,('Model inputs'!U16-'Model inputs'!AB60)<=12),'Model inputs'!AB56+('Model inputs'!AB38-'Model inputs'!AB56)*(('Model inputs'!U16-'Model inputs'!AB60)-6)/6,'Model inputs'!AB38+('Model inputs'!AB44-'Model inputs'!AB38)*(('Model inputs'!U16-'Model inputs'!AB60)-12)/12))),0)) -> 6 | V8: =IF(IF(('Model inputs'!V16-'Model inputs'!AB60)<1="",FALSE,('Model inputs'!V16-'Model inputs'!AB60)<1),0,ROUND(IF(IF(('Model inputs'!V16-'Model inputs'!AB60)<=3="",FALSE,('Model inputs'!V16-'Model inputs'!AB60)<=3),IF('Model inputs'!AB50="","",'Model inputs'!AB50),IF(IF(('Model inputs'!V16-'Model inputs'!AB60)<=6="",FALSE,('Model inputs'!V16-'Model inputs'!AB60)<=6),'Model inputs'!AB50+('Model inputs'!AB56-'Model inputs'!AB50)*(('Model inputs'!V16-'Model inputs'!AB60)-3)/3,IF(IF(('Model inputs'!V16-'Model inputs'!AB60)<=12="",FALSE,('Model inputs'!V16-'Model inputs'!AB60)<=12),'Model inputs'!AB56+('Model inputs'!AB38-'Model inputs'!AB56)*(('Model inputs'!V16-'Model inputs'!AB60)-6)/6,'Model inputs'!AB38+('Model inputs'!AB44-'Model inputs'!AB38)*(('Model inputs'!V16-'Model inputs'!AB60)-12)/12))),0)) -> 7 | W8: =IF(IF(('Model inputs'!W16-'Model inputs'!AB60)<1="",FALSE,('Model inputs'!W16-'Model inputs'!AB60)<1),0,ROUND(IF(IF(('Model inputs'!W16-'Model inputs'!AB60)<=3="",FALSE,('Model inputs'!W16-'Model inputs'!AB60)<=3),IF('Model inputs'!AB50="","",'Model inputs'!AB50),IF(IF(('Model inputs'!W16-'Model inputs'!AB60)<=6="",FALSE,('Model inputs'!W16-'Model inputs'!AB60)<=6),'Model inputs'!AB50+('Model inputs'!AB56-'Model inputs'!AB50)*(('Model inputs'!W16-'Model inputs'!AB60)-3)/3,IF(IF(('Model inputs'!W16-'Model inputs'!AB60)<=12="",FALSE,('Model inputs'!W16-'Model inputs'!AB60)<=12),'Model inputs'!AB56+('Model inputs'!AB38-'Model inputs'!AB56)*(('Model inputs'!W16-'Model inputs'!AB60)-6)/6,'Model inputs'!AB38+('Model inputs'!AB44-'Model inputs'!AB38)*(('Model inputs'!W16-'Model inputs'!AB60)-12)/12))),0)) -> 7 | X8: =IF(IF(('Model inputs'!X16-'Model inputs'!AB60)<1="",FALSE,('Model inputs'!X16-'Model inputs'!AB60)<1),0,ROUND(IF(IF(('Model inputs'!X16-'Model inputs'!AB60)<=3="",FALSE,('Model inputs'!X16-'Model inputs'!AB60)<=3),IF('Model inputs'!AB50="","",'Model inputs'!AB50),IF(IF(('Model inputs'!X16-'Model inputs'!AB60)<=6="",FALSE,('Model inputs'!X16-'Model inputs'!AB60)<=6),'Model inputs'!AB50+('Model inputs'!AB56-'Model inputs'!AB50)*(('Model inputs'!X16-'Model inputs'!AB60)-3)/3,IF(IF(('Model inputs'!X16-'Model inputs'!AB60)<=12="",FALSE,('Model inputs'!X16-'Model inputs'!AB60)<=12),'Model inputs'!AB56+('Model inputs'!AB38-'Model inputs'!AB56)*(('Model inputs'!X16-'Model inputs'!AB60)-6)/6,'Model inputs'!AB38+('Model inputs'!AB44-'Model inputs'!AB38)*(('Model inputs'!X16-'Model inputs'!AB60)-12)/12))),0)) -> 8 | Y8: =IF(IF(('Model inputs'!Y16-'Model inputs'!AB60)<1="",FALSE,('Model inputs'!Y16-'Model inputs'!AB60)<1),0,ROUND(IF(IF(('Model inputs'!Y16-'Model inputs'!AB60)<=3="",FALSE,('Model inputs'!Y16-'Model inputs'!AB60)<=3),IF('Model inputs'!AB50="","",'Model inputs'!AB50),IF(IF(('Model inputs'!Y16-'Model inputs'!AB60)<=6="",FALSE,('Model inputs'!Y16-'Model inputs'!AB60)<=6),'Model inputs'!AB50+('Model inputs'!AB56-'Model inputs'!AB50)*(('Model inputs'!Y16-'Model inputs'!AB60)-3)/3,IF(IF(('Model inputs'!Y16-'Model inputs'!AB60)<=12="",FALSE,('Model inputs'!Y16-'Model inputs'!AB60)<=12),'Model inputs'!AB56+('Model inputs'!AB38-'Model inputs'!AB56)*(('Model inputs'!Y16-'Model inputs'!AB60)-6)/6,'Model inputs'!AB38+('Model inputs'!AB44-'Model inputs'!AB38)*(('Model inputs'!Y16-'Model inputs'!AB60)-12)/12))),0)) -> 8
A9: Customers | B9: =SUM('Model inputs'!B10,'Model inputs'!B11) -> 0 | C9: =SUM('Model inputs'!C10,'Model inputs'!C11) -> 0 | D9: =SUM('Model inputs'!D10,'Model inputs'!D11) -> 0 | E9: =SUM('Model inputs'!E10,'Model inputs'!E11) -> 4 | F9: =SUM('Model inputs'!F10,'Model inputs'!F11) -> 8 | G9: =SUM('Model inputs'!G10,'Model inputs'!G11) -> 12 | H9: =SUM('Model inputs'!H10,'Model inputs'!H11) -> 17 | I9: =SUM('Model inputs'!I10,'Model inputs'!I11) -> 22 | ... Y9: =SUM('Model inputs'!Y10,'Model inputs'!Y11) -> 125
A10: Customers > Starter | B10: =IF(IF(('Model inputs'!B17-'Model inputs'!AB61)<1="",FALSE,('Model inputs'!B17-'Model inputs'!AB61)<1),0,ROUND(IF(IF(('Model inputs'!B17-'Model inputs'!AB61)<=3="",FALSE,('Model inputs'!B17-'Model inputs'!AB61)<=3),IF('Model inputs'!AB52="","",'Model inputs'!AB52),IF(IF(('Model inputs'!B17-'Model inputs'!AB61)<=6="",FALSE,('Model inputs'!B17-'Model inputs'!AB61)<=6),'Model inputs'!AB52+('Model inputs'!AB58-'Model inputs'!AB52)*(('Model inputs'!B17-'Model inputs'!AB61)-3)/3,IF(IF(('Model inputs'!B17-'Model inputs'!AB61)<=12="",FALSE,('Model inputs'!B17-'Model inputs'!AB61)<=12),'Model inputs'!AB58+('Model inputs'!AB40-'Model inputs'!AB58)*(('Model inputs'!B17-'Model inputs'!AB61)-6)/6,'Model inputs'!AB40+('Model inputs'!AB46-'Model inputs'!AB40)*(('Model inputs'!B17-'Model inputs'!AB61)-12)/12))),0)) -> 0 | C10: =IF(IF(('Model inputs'!C17-'Model inputs'!AB61)<1="",FALSE,('Model inputs'!C17-'Model inputs'!AB61)<1),0,ROUND(IF(IF(('Model inputs'!C17-'Model inputs'!AB61)<=3="",FALSE,('Model inputs'!C17-'Model inputs'!AB61)<=3),IF('Model inputs'!AB52="","",'Model inputs'!AB52),IF(IF(('Model inputs'!C17-'Model inputs'!AB61)<=6="",FALSE,('Model inputs'!C17-'Model inputs'!AB61)<=6),'Model inputs'!AB52+('Model inputs'!AB58-'Model inputs'!AB52)*(('Model inputs'!C17-'Model inputs'!AB61)-3)/3,IF(IF(('Model inputs'!C17-'Model inputs'!AB61)<=12="",FALSE,('Model inputs'!C17-'Model inputs'!AB61)<=12),'Model inputs'!AB58+('Model inputs'!AB40-'Model inputs'!AB58)*(('Model inputs'!C17-'Model inputs'!AB61)-6)/6,'Model inputs'!AB40+('Model inputs'!AB46-'Model inputs'!AB40)*(('Model inputs'!C17-'Model inputs'!AB61)-12)/12))),0)) -> 0 | D10: =IF(IF(('Model inputs'!D17-'Model inputs'!AB61)<1="",FALSE,('Model inputs'!D17-'Model inputs'!AB61)<1),0,ROUND(IF(IF(('Model inputs'!D17-'Model inputs'!AB61)<=3="",FALSE,('Model inputs'!D17-'Model inputs'!AB61)<=3),IF('Model inputs'!AB52="","",'Model inputs'!AB52),IF(IF(('Model inputs'!D17-'Model inputs'!AB61)<=6="",FALSE,('Model inputs'!D17-'Model inputs'!AB61)<=6),'Model inputs'!AB52+('Model inputs'!AB58-'Model inputs'!AB52)*(('Model inputs'!D17-'Model inputs'!AB61)-3)/3,IF(IF(('Model inputs'!D17-'Model inputs'!AB61)<=12="",FALSE,('Model inputs'!D17-'Model inputs'!AB61)<=12),'Model inputs'!AB58+('Model inputs'!AB40-'Model inputs'!AB58)*(('Model inputs'!D17-'Model inputs'!AB61)-6)/6,'Model inputs'!AB40+('Model inputs'!AB46-'Model inputs'!AB40)*(('Model inputs'!D17-'Model inputs'!AB61)-12)/12))),0)) -> 0 | E10: =IF(IF(('Model inputs'!E17-'Model inputs'!AB61)<1="",FALSE,('Model inputs'!E17-'Model inputs'!AB61)<1),0,ROUND(IF(IF(('Model inputs'!E17-'Model inputs'!AB61)<=3="",FALSE,('Model inputs'!E17-'Model inputs'!AB61)<=3),IF('Model inputs'!AB52="","",'Model inputs'!AB52),IF(IF(('Model inputs'!E17-'Model inputs'!AB61)<=6="",FALSE,('Model inputs'!E17-'Model inputs'!AB61)<=6),'Model inputs'!AB52+('Model inputs'!AB58-'Model inputs'!AB52)*(('Model inputs'!E17-'Model inputs'!AB61)-3)/3,IF(IF(('Model inputs'!E17-'Model inputs'!AB61)<=12="",FALSE,('Model inputs'!E17-'Model inputs'!AB61)<=12),'Model inputs'!AB58+('Model inputs'!AB40-'Model inputs'!AB58)*(('Model inputs'!E17-'Model inputs'!AB61)-6)/6,'Model inputs'!AB40+('Model inputs'!AB46-'Model inputs'!AB40)*(('Model inputs'!E17-'Model inputs'!AB61)-12)/12))),0)) -> 3 | F10: =IF(IF(('Model inputs'!F17-'Model inputs'!AB61)<1="",FALSE,('Model inputs'!F17-'Model inputs'!AB61)<1),0,ROUND(IF(IF(('Model inputs'!F17-'Model inputs'!AB61)<=3="",FALSE,('Model inputs'!F17-'Model inputs'!AB61)<=3),IF('Model inputs'!AB52="","",'Model inputs'!AB52),IF(IF(('Model inputs'!F17-'Model inputs'!AB61)<=6="",FALSE,('Model inputs'!F17-'Model inputs'!AB61)<=6),'Model inputs'!AB52+('Model inputs'!AB58-'Model inputs'!AB52)*(('Model inputs'!F17-'Model inputs'!AB61)-3)/3,IF(IF(('Model inputs'!F17-'Model inputs'!AB61)<=12="",FALSE,('Model inputs'!F17-'Model inputs'!AB61)<=12),'Model inputs'!AB58+('Model inputs'!AB40-'Model inputs'!AB58)*(('Model inputs'!F17-'Model inputs'!AB61)-6)/6,'Model inputs'!AB40+('Model inputs'!AB46-'Model inputs'!AB40)*(('Model inputs'!F17-'Model inputs'!AB61)-12)/12))),0)) -> 7 | G10: =IF(IF(('Model inputs'!G17-'Model inputs'!AB61)<1="",FALSE,('Model inputs'!G17-'Model inputs'!AB61)<1),0,ROUND(IF(IF(('Model inputs'!G17-'Model inputs'!AB61)<=3="",FALSE,('Model inputs'!G17-'Model inputs'!AB61)<=3),IF('Model inputs'!AB52="","",'Model inputs'!AB52),IF(IF(('Model inputs'!G17-'Model inputs'!AB61)<=6="",FALSE,('Model inputs'!G17-'Model inputs'!AB61)<=6),'Model inputs'!AB52+('Model inputs'!AB58-'Model inputs'!AB52)*(('Model inputs'!G17-'Model inputs'!AB61)-3)/3,IF(IF(('Model inputs'!G17-'Model inputs'!AB61)<=12="",FALSE,('Model inputs'!G17-'Model inputs'!AB61)<=12),'Model inputs'!AB58+('Model inputs'!AB40-'Model inputs'!AB58)*(('Model inputs'!G17-'Model inputs'!AB61)-6)/6,'Model inputs'!AB40+('Model inputs'!AB46-'Model inputs'!AB40)*(('Model inputs'!G17-'Model inputs'!AB61)-12)/12))),0)) -> 10 | H10: =IF(IF(('Model inputs'!H17-'Model inputs'!AB61)<1="",FALSE,('Model inputs'!H17-'Model inputs'!AB61)<1),0,ROUND(IF(IF(('Model inputs'!H17-'Model inputs'!AB61)<=3="",FALSE,('Model inputs'!H17-'Model inputs'!AB61)<=3),IF('Model inputs'!AB52="","",'Model inputs'!AB52),IF(IF(('Model inputs'!H17-'Model inputs'!AB61)<=6="",FALSE,('Model inputs'!H17-'Model inputs'!AB61)<=6),'Model inputs'!AB52+('Model inputs'!AB58-'Model inputs'!AB52)*(('Model inputs'!H17-'Model inputs'!AB61)-3)/3,IF(IF(('Model inputs'!H17-'Model inputs'!AB61)<=12="",FALSE,('Model inputs'!H17-'Model inputs'!AB61)<=12),'Model inputs'!AB58+('Model inputs'!AB40-'Model inputs'!AB58)*(('Model inputs'!H17-'Model inputs'!AB61)-6)/6,'Model inputs'!AB40+('Model inputs'!AB46-'Model inputs'!AB40)*(('Model inputs'!H17-'Model inputs'!AB61)-12)/12))),0)) -> 14 | I10: =IF(IF(('Model inputs'!I17-'Model inputs'!AB61)<1="",FALSE,('Model inputs'!I17-'Model inputs'!AB61)<1),0,ROUND(IF(IF(('Model inputs'!I17-'Model inputs'!AB61)<=3="",FALSE,('Model inputs'!I17-'Model inputs'!AB61)<=3),IF('Model inputs'!AB52="","",'Model inputs'!AB52),IF(IF(('Model inputs'!I17-'Model inputs'!AB61)<=6="",FALSE,('Model inputs'!I17-'Model inputs'!AB61)<=6),'Model inputs'!AB52+('Model inputs'!AB58-'Model inputs'!AB52)*(('Model inputs'!I17-'Model inputs'!AB61)-3)/3,IF(IF(('Model inputs'!I17-'Model inputs'!AB61)<=12="",FALSE,('Model inputs'!I17-'Model inputs'!AB61)<=12),'Model inputs'!AB58+('Model inputs'!AB40-'Model inputs'!AB58)*(('Model inputs'!I17-'Model inputs'!AB61)-6)/6,'Model inputs'!AB40+('Model inputs'!AB46-'Model inputs'!AB40)*(('Model inputs'!I17-'Model inputs'!AB61)-12)/12))),0)) -> 18 | J10: =IF(IF(('Model inputs'!J17-'Model inputs'!AB61)<1="",FALSE,('Model inputs'!J17-'Model inputs'!AB61)<1),0,ROUND(IF(IF(('Model inputs'!J17-'Model inputs'!AB61)<=3="",FALSE,('Model inputs'!J17-'Model inputs'!AB61)<=3),IF('Model inputs'!AB52="","",'Model inputs'!AB52),IF(IF(('Model inputs'!J17-'Model inputs'!AB61)<=6="",FALSE,('Model inputs'!J17-'Model inputs'!AB61)<=6),'Model inputs'!AB52+('Model inputs'!AB58-'Model inputs'!AB52)*(('Model inputs'!J17-'Model inputs'!AB61)-3)/3,IF(IF(('Model inputs'!J17-'Model inputs'!AB61)<=12="",FALSE,('Model inputs'!J17-'Model inputs'!AB61)<=12),'Model inputs'!AB58+('Model inputs'!AB40-'Model inputs'!AB58)*(('Model inputs'!J17-'Model inputs'!AB61)-6)/6,'Model inputs'!AB40+('Model inputs'!AB46-'Model inputs'!AB40)*(('Model inputs'!J17-'Model inputs'!AB61)-12)/12))),0)) -> 23 | K10: =IF(IF(('Model inputs'!K17-'Model inputs'!AB61)<1="",FALSE,('Model inputs'!K17-'Model inputs'!AB61)<1),0,ROUND(IF(IF(('Model inputs'!K17-'Model inputs'!AB61)<=3="",FALSE,('Model inputs'!K17-'Model inputs'!AB61)<=3),IF('Model inputs'!AB52="","",'Model inputs'!AB52),IF(IF(('Model inputs'!K17-'Model inputs'!AB61)<=6="",FALSE,('Model inputs'!K17-'Model inputs'!AB61)<=6),'Model inputs'!AB52+('Model inputs'!AB58-'Model inputs'!AB52)*(('Model inputs'!K17-'Model inputs'!AB61)-3)/3,IF(IF(('Model inputs'!K17-'Model inputs'!AB61)<=12="",FALSE,('Model inputs'!K17-'Model inputs'!AB61)<=12),'Model inputs'!AB58+('Model inputs'!AB40-'Model inputs'!AB58)*(('Model inputs'!K17-'Model inputs'!AB61)-6)/6,'Model inputs'!AB40+('Model inputs'!AB46-'Model inputs'!AB40)*(('Model inputs'!K17-'Model inputs'!AB61)-12)/12))),0)) -> 27 | L10: =IF(IF(('Model inputs'!L17-'Model inputs'!AB61)<1="",FALSE,('Model inputs'!L17-'Model inputs'!AB61)<1),0,ROUND(IF(IF(('Model inputs'!L17-'Model inputs'!AB61)<=3="",FALSE,('Model inputs'!L17-'Model inputs'!AB61)<=3),IF('Model inputs'!AB52="","",'Model inputs'!AB52),IF(IF(('Model inputs'!L17-'Model inputs'!AB61)<=6="",FALSE,('Model inputs'!L17-'Model inputs'!AB61)<=6),'Model inputs'!AB52+('Model inputs'!AB58-'Model inputs'!AB52)*(('Model inputs'!L17-'Model inputs'!AB61)-3)/3,IF(IF(('Model inputs'!L17-'Model inputs'!AB61)<=12="",FALSE,('Model inputs'!L17-'Model inputs'!AB61)<=12),'Model inputs'!AB58+('Model inputs'!AB40-'Model inputs'!AB58)*(('Model inputs'!L17-'Model inputs'!AB61)-6)/6,'Model inputs'!AB40+('Model inputs'!AB46-'Model inputs'!AB40)*(('Model inputs'!L17-'Model inputs'!AB61)-12)/12))),0)) -> 31 | M10: =IF(IF(('Model inputs'!M17-'Model inputs'!AB61)<1="",FALSE,('Model inputs'!M17-'Model inputs'!AB61)<1),0,ROUND(IF(IF(('Model inputs'!M17-'Model inputs'!AB61)<=3="",FALSE,('Model inputs'!M17-'Model inputs'!AB61)<=3),IF('Model inputs'!AB52="","",'Model inputs'!AB52),IF(IF(('Model inputs'!M17-'Model inputs'!AB61)<=6="",FALSE,('Model inputs'!M17-'Model inputs'!AB61)<=6),'Model inputs'!AB52+('Model inputs'!AB58-'Model inputs'!AB52)*(('Model inputs'!M17-'Model inputs'!AB61)-3)/3,IF(IF(('Model inputs'!M17-'Model inputs'!AB61)<=12="",FALSE,('Model inputs'!M17-'Model inputs'!AB61)<=12),'Model inputs'!AB58+('Model inputs'!AB40-'Model inputs'!AB58)*(('Model inputs'!M17-'Model inputs'!AB61)-6)/6,'Model inputs'!AB40+('Model inputs'!AB46-'Model inputs'!AB40)*(('Model inputs'!M17-'Model inputs'!AB61)-12)/12))),0)) -> 35 | N10: =IF(IF(('Model inputs'!N17-'Model inputs'!AB61)<1="",FALSE,('Model inputs'!N17-'Model inputs'!AB61)<1),0,ROUND(IF(IF(('Model inputs'!N17-'Model inputs'!AB61)<=3="",FALSE,('Model inputs'!N17-'Model inputs'!AB61)<=3),IF('Model inputs'!AB52="","",'Model inputs'!AB52),IF(IF(('Model inputs'!N17-'Model inputs'!AB61)<=6="",FALSE,('Model inputs'!N17-'Model inputs'!AB61)<=6),'Model inputs'!AB52+('Model inputs'!AB58-'Model inputs'!AB52)*(('Model inputs'!N17-'Model inputs'!AB61)-3)/3,IF(IF(('Model inputs'!N17-'Model inputs'!AB61)<=12="",FALSE,('Model inputs'!N17-'Model inputs'!AB61)<=12),'Model inputs'!AB58+('Model inputs'!AB40-'Model inputs'!AB58)*(('Model inputs'!N17-'Model inputs'!AB61)-6)/6,'Model inputs'!AB40+('Model inputs'!AB46-'Model inputs'!AB40)*(('Model inputs'!N17-'Model inputs'!AB61)-12)/12))),0)) -> 40 | O10: =IF(IF(('Model inputs'!O17-'Model inputs'!AB61)<1="",FALSE,('Model inputs'!O17-'Model inputs'!AB61)<1),0,ROUND(IF(IF(('Model inputs'!O17-'Model inputs'!AB61)<=3="",FALSE,('Model inputs'!O17-'Model inputs'!AB61)<=3),IF('Model inputs'!AB52="","",'Model inputs'!AB52),IF(IF(('Model inputs'!O17-'Model inputs'!AB61)<=6="",FALSE,('Model inputs'!O17-'Model inputs'!AB61)<=6),'Model inputs'!AB52+('Model inputs'!AB58-'Model inputs'!AB52)*(('Model inputs'!O17-'Model inputs'!AB61)-3)/3,IF(IF(('Model inputs'!O17-'Model inputs'!AB61)<=12="",FALSE,('Model inputs'!O17-'Model inputs'!AB61)<=12),'Model inputs'!AB58+('Model inputs'!AB40-'Model inputs'!AB58)*(('Model inputs'!O17-'Model inputs'!AB61)-6)/6,'Model inputs'!AB40+('Model inputs'!AB46-'Model inputs'!AB40)*(('Model inputs'!O17-'Model inputs'!AB61)-12)/12))),0)) -> 46 | P10: =IF(IF(('Model inputs'!P17-'Model inputs'!AB61)<1="",FALSE,('Model inputs'!P17-'Model inputs'!AB61)<1),0,ROUND(IF(IF(('Model inputs'!P17-'Model inputs'!AB61)<=3="",FALSE,('Model inputs'!P17-'Model inputs'!AB61)<=3),IF('Model inputs'!AB52="","",'Model inputs'!AB52),IF(IF(('Model inputs'!P17-'Model inputs'!AB61)<=6="",FALSE,('Model inputs'!P17-'Model inputs'!AB61)<=6),'Model inputs'!AB52+('Model inputs'!AB58-'Model inputs'!AB52)*(('Model inputs'!P17-'Model inputs'!AB61)-3)/3,IF(IF(('Model inputs'!P17-'Model inputs'!AB61)<=12="",FALSE,('Model inputs'!P17-'Model inputs'!AB61)<=12),'Model inputs'!AB58+('Model inputs'!AB40-'Model inputs'!AB58)*(('Model inputs'!P17-'Model inputs'!AB61)-6)/6,'Model inputs'!AB40+('Model inputs'!AB46-'Model inputs'!AB40)*(('Model inputs'!P17-'Model inputs'!AB61)-12)/12))),0)) -> 51 | Q10: =IF(IF(('Model inputs'!Q17-'Model inputs'!AB61)<1="",FALSE,('Model inputs'!Q17-'Model inputs'!AB61)<1),0,ROUND(IF(IF(('Model inputs'!Q17-'Model inputs'!AB61)<=3="",FALSE,('Model inputs'!Q17-'Model inputs'!AB61)<=3),IF('Model inputs'!AB52="","",'Model inputs'!AB52),IF(IF(('Model inputs'!Q17-'Model inputs'!AB61)<=6="",FALSE,('Model inputs'!Q17-'Model inputs'!AB61)<=6),'Model inputs'!AB52+('Model inputs'!AB58-'Model inputs'!AB52)*(('Model inputs'!Q17-'Model inputs'!AB61)-3)/3,IF(IF(('Model inputs'!Q17-'Model inputs'!AB61)<=12="",FALSE,('Model inputs'!Q17-'Model inputs'!AB61)<=12),'Model inputs'!AB58+('Model inputs'!AB40-'Model inputs'!AB58)*(('Model inputs'!Q17-'Model inputs'!AB61)-6)/6,'Model inputs'!AB40+('Model inputs'!AB46-'Model inputs'!AB40)*(('Model inputs'!Q17-'Model inputs'!AB61)-12)/12))),0)) -> 57 | R10: =IF(IF(('Model inputs'!R17-'Model inputs'!AB61)<1="",FALSE,('Model inputs'!R17-'Model inputs'!AB61)<1),0,ROUND(IF(IF(('Model inputs'!R17-'Model inputs'!AB61)<=3="",FALSE,('Model inputs'!R17-'Model inputs'!AB61)<=3),IF('Model inputs'!AB52="","",'Model inputs'!AB52),IF(IF(('Model inputs'!R17-'Model inputs'!AB61)<=6="",FALSE,('Model inputs'!R17-'Model inputs'!AB61)<=6),'Model inputs'!AB52+('Model inputs'!AB58-'Model inputs'!AB52)*(('Model inputs'!R17-'Model inputs'!AB61)-3)/3,IF(IF(('Model inputs'!R17-'Model inputs'!AB61)<=12="",FALSE,('Model inputs'!R17-'Model inputs'!AB61)<=12),'Model inputs'!AB58+('Model inputs'!AB40-'Model inputs'!AB58)*(('Model inputs'!R17-'Model inputs'!AB61)-6)/6,'Model inputs'!AB40+('Model inputs'!AB46-'Model inputs'!AB40)*(('Model inputs'!R17-'Model inputs'!AB61)-12)/12))),0)) -> 62 | S10: =IF(IF(('Model inputs'!S17-'Model inputs'!AB61)<1="",FALSE,('Model inputs'!S17-'Model inputs'!AB61)<1),0,ROUND(IF(IF(('Model inputs'!S17-'Model inputs'!AB61)<=3="",FALSE,('Model inputs'!S17-'Model inputs'!AB61)<=3),IF('Model inputs'!AB52="","",'Model inputs'!AB52),IF(IF(('Model inputs'!S17-'Model inputs'!AB61)<=6="",FALSE,('Model inputs'!S17-'Model inputs'!AB61)<=6),'Model inputs'!AB52+('Model inputs'!AB58-'Model inputs'!AB52)*(('Model inputs'!S17-'Model inputs'!AB61)-3)/3,IF(IF(('Model inputs'!S17-'Model inputs'!AB61)<=12="",FALSE,('Model inputs'!S17-'Model inputs'!AB61)<=12),'Model inputs'!AB58+('Model inputs'!AB40-'Model inputs'!AB58)*(('Model inputs'!S17-'Model inputs'!AB61)-6)/6,'Model inputs'!AB40+('Model inputs'!AB46-'Model inputs'!AB40)*(('Model inputs'!S17-'Model inputs'!AB61)-12)/12))),0)) -> 68 | T10: =IF(IF(('Model inputs'!T17-'Model inputs'!AB61)<1="",FALSE,('Model inputs'!T17-'Model inputs'!AB61)<1),0,ROUND(IF(IF(('Model inputs'!T17-'Model inputs'!AB61)<=3="",FALSE,('Model inputs'!T17-'Model inputs'!AB61)<=3),IF('Model inputs'!AB52="","",'Model inputs'!AB52),IF(IF(('Model inputs'!T17-'Model inputs'!AB61)<=6="",FALSE,('Model inputs'!T17-'Model inputs'!AB61)<=6),'Model inputs'!AB52+('Model inputs'!AB58-'Model inputs'!AB52)*(('Model inputs'!T17-'Model inputs'!AB61)-3)/3,IF(IF(('Model inputs'!T17-'Model inputs'!AB61)<=12="",FALSE,('Model inputs'!T17-'Model inputs'!AB61)<=12),'Model inputs'!AB58+('Model inputs'!AB40-'Model inputs'!AB58)*(('Model inputs'!T17-'Model inputs'!AB61)-6)/6,'Model inputs'!AB40+('Model inputs'!AB46-'Model inputs'!AB40)*(('Model inputs'!T17-'Model inputs'!AB61)-12)/12))),0)) -> 73 | U10: =IF(IF(('Model inputs'!U17-'Model inputs'!AB61)<1="",FALSE,('Model inputs'!U17-'Model inputs'!AB61)<1),0,ROUND(IF(IF(('Model inputs'!U17-'Model inputs'!AB61)<=3="",FALSE,('Model inputs'!U17-'Model inputs'!AB61)<=3),IF('Model inputs'!AB52="","",'Model inputs'!AB52),IF(IF(('Model inputs'!U17-'Model inputs'!AB61)<=6="",FALSE,('Model inputs'!U17-'Model inputs'!AB61)<=6),'Model inputs'!AB52+('Model inputs'!AB58-'Model inputs'!AB52)*(('Model inputs'!U17-'Model inputs'!AB61)-3)/3,IF(IF(('Model inputs'!U17-'Model inputs'!AB61)<=12="",FALSE,('Model inputs'!U17-'Model inputs'!AB61)<=12),'Model inputs'!AB58+('Model inputs'!AB40-'Model inputs'!AB58)*(('Model inputs'!U17-'Model inputs'!AB61)-6)/6,'Model inputs'!AB40+('Model inputs'!AB46-'Model inputs'!AB40)*(('Model inputs'!U17-'Model inputs'!AB61)-12)/12))),0)) -> 78 | V10: =IF(IF(('Model inputs'!V17-'Model inputs'!AB61)<1="",FALSE,('Model inputs'!V17-'Model inputs'!AB61)<1),0,ROUND(IF(IF(('Model inputs'!V17-'Model inputs'!AB61)<=3="",FALSE,('Model inputs'!V17-'Model inputs'!AB61)<=3),IF('Model inputs'!AB52="","",'Model inputs'!AB52),IF(IF(('Model inputs'!V17-'Model inputs'!AB61)<=6="",FALSE,('Model inputs'!V17-'Model inputs'!AB61)<=6),'Model inputs'!AB52+('Model inputs'!AB58-'Model inputs'!AB52)*(('Model inputs'!V17-'Model inputs'!AB61)-3)/3,IF(IF(('Model inputs'!V17-'Model inputs'!AB61)<=12="",FALSE,('Model inputs'!V17-'Model inputs'!AB61)<=12),'Model inputs'!AB58+('Model inputs'!AB40-'Model inputs'!AB58)*(('Model inputs'!V17-'Model inputs'!AB61)-6)/6,'Model inputs'!AB40+('Model inputs'!AB46-'Model inputs'!AB40)*(('Model inputs'!V17-'Model inputs'!AB61)-12)/12))),0)) -> 84 | W10: =IF(IF(('Model inputs'!W17-'Model inputs'!AB61)<1="",FALSE,('Model inputs'!W17-'Model inputs'!AB61)<1),0,ROUND(IF(IF(('Model inputs'!W17-'Model inputs'!AB61)<=3="",FALSE,('Model inputs'!W17-'Model inputs'!AB61)<=3),IF('Model inputs'!AB52="","",'Model inputs'!AB52),IF(IF(('Model inputs'!W17-'Model inputs'!AB61)<=6="",FALSE,('Model inputs'!W17-'Model inputs'!AB61)<=6),'Model inputs'!AB52+('Model inputs'!AB58-'Model inputs'!AB52)*(('Model inputs'!W17-'Model inputs'!AB61)-3)/3,IF(IF(('Model inputs'!W17-'Model inputs'!AB61)<=12="",FALSE,('Model inputs'!W17-'Model inputs'!AB61)<=12),'Model inputs'!AB58+('Model inputs'!AB40-'Model inputs'!AB58)*(('Model inputs'!W17-'Model inputs'!AB61)-6)/6,'Model inputs'!AB40+('Model inputs'!AB46-'Model inputs'!AB40)*(('Model inputs'!W17-'Model inputs'!AB61)-12)/12))),0)) -> 89 | X10: =IF(IF(('Model inputs'!X17-'Model inputs'!AB61)<1="",FALSE,('Model inputs'!X17-'Model inputs'!AB61)<1),0,ROUND(IF(IF(('Model inputs'!X17-'Model inputs'!AB61)<=3="",FALSE,('Model inputs'!X17-'Model inputs'!AB61)<=3),IF('Model inputs'!AB52="","",'Model inputs'!AB52),IF(IF(('Model inputs'!X17-'Model inputs'!AB61)<=6="",FALSE,('Model inputs'!X17-'Model inputs'!AB61)<=6),'Model inputs'!AB52+('Model inputs'!AB58-'Model inputs'!AB52)*(('Model inputs'!X17-'Model inputs'!AB61)-3)/3,IF(IF(('Model inputs'!X17-'Model inputs'!AB61)<=12="",FALSE,('Model inputs'!X17-'Model inputs'!AB61)<=12),'Model inputs'!AB58+('Model inputs'!AB40-'Model inputs'!AB58)*(('Model inputs'!X17-'Model inputs'!AB61)-6)/6,'Model inputs'!AB40+('Model inputs'!AB46-'Model inputs'!AB40)*(('Model inputs'!X17-'Model inputs'!AB61)-12)/12))),0)) -> 95 | Y10: =IF(IF(('Model inputs'!Y17-'Model inputs'!AB61)<1="",FALSE,('Model inputs'!Y17-'Model inputs'!AB61)<1),0,ROUND(IF(IF(('Model inputs'!Y17-'Model inputs'!AB61)<=3="",FALSE,('Model inputs'!Y17-'Model inputs'!AB61)<=3),IF('Model inputs'!AB52="","",'Model inputs'!AB52),IF(IF(('Model inputs'!Y17-'Model inputs'!AB61)<=6="",FALSE,('Model inputs'!Y17-'Model inputs'!AB61)<=6),'Model inputs'!AB52+('Model inputs'!AB58-'Model inputs'!AB52)*(('Model inputs'!Y17-'Model inputs'!AB61)-3)/3,IF(IF(('Model inputs'!Y17-'Model inputs'!AB61)<=12="",FALSE,('Model inputs'!Y17-'Model inputs'!AB61)<=12),'Model inputs'!AB58+('Model inputs'!AB40-'Model inputs'!AB58)*(('Model inputs'!Y17-'Model inputs'!AB61)-6)/6,'Model inputs'!AB40+('Model inputs'!AB46-'Model inputs'!AB40)*(('Model inputs'!Y17-'Model inputs'!AB61)-12)/12))),0)) -> 100
A11: Customers > Team | B11: =IF(IF(('Model inputs'!B17-'Model inputs'!AB61)<1="",FALSE,('Model inputs'!B17-'Model inputs'!AB61)<1),0,ROUND(IF(IF(('Model inputs'!B17-'Model inputs'!AB61)<=3="",FALSE,('Model inputs'!B17-'Model inputs'!AB61)<=3),IF('Model inputs'!AB53="","",'Model inputs'!AB53),IF(IF(('Model inputs'!B17-'Model inputs'!AB61)<=6="",FALSE,('Model inputs'!B17-'Model inputs'!AB61)<=6),'Model inputs'!AB53+('Model inputs'!AB59-'Model inputs'!AB53)*(('Model inputs'!B17-'Model inputs'!AB61)-3)/3,IF(IF(('Model inputs'!B17-'Model inputs'!AB61)<=12="",FALSE,('Model inputs'!B17-'Model inputs'!AB61)<=12),'Model inputs'!AB59+('Model inputs'!AB41-'Model inputs'!AB59)*(('Model inputs'!B17-'Model inputs'!AB61)-6)/6,'Model inputs'!AB41+('Model inputs'!AB47-'Model inputs'!AB41)*(('Model inputs'!B17-'Model inputs'!AB61)-12)/12))),0)) -> 0 | C11: =IF(IF(('Model inputs'!C17-'Model inputs'!AB61)<1="",FALSE,('Model inputs'!C17-'Model inputs'!AB61)<1),0,ROUND(IF(IF(('Model inputs'!C17-'Model inputs'!AB61)<=3="",FALSE,('Model inputs'!C17-'Model inputs'!AB61)<=3),IF('Model inputs'!AB53="","",'Model inputs'!AB53),IF(IF(('Model inputs'!C17-'Model inputs'!AB61)<=6="",FALSE,('Model inputs'!C17-'Model inputs'!AB61)<=6),'Model inputs'!AB53+('Model inputs'!AB59-'Model inputs'!AB53)*(('Model inputs'!C17-'Model inputs'!AB61)-3)/3,IF(IF(('Model inputs'!C17-'Model inputs'!AB61)<=12="",FALSE,('Model inputs'!C17-'Model inputs'!AB61)<=12),'Model inputs'!AB59+('Model inputs'!AB41-'Model inputs'!AB59)*(('Model inputs'!C17-'Model inputs'!AB61)-6)/6,'Model inputs'!AB41+('Model inputs'!AB47-'Model inputs'!AB41)*(('Model inputs'!C17-'Model inputs'!AB61)-12)/12))),0)) -> 0 | D11: =IF(IF(('Model inputs'!D17-'Model inputs'!AB61)<1="",FALSE,('Model inputs'!D17-'Model inputs'!AB61)<1),0,ROUND(IF(IF(('Model inputs'!D17-'Model inputs'!AB61)<=3="",FALSE,('Model inputs'!D17-'Model inputs'!AB61)<=3),IF('Model inputs'!AB53="","",'Model inputs'!AB53),IF(IF(('Model inputs'!D17-'Model inputs'!AB61)<=6="",FALSE,('Model inputs'!D17-'Model inputs'!AB61)<=6),'Model inputs'!AB53+('Model inputs'!AB59-'Model inputs'!AB53)*(('Model inputs'!D17-'Model inputs'!AB61)-3)/3,IF(IF(('Model inputs'!D17-'Model inputs'!AB61)<=12="",FALSE,('Model inputs'!D17-'Model inputs'!AB61)<=12),'Model inputs'!AB59+('Model inputs'!AB41-'Model inputs'!AB59)*(('Model inputs'!D17-'Model inputs'!AB61)-6)/6,'Model inputs'!AB41+('Model inputs'!AB47-'Model inputs'!AB41)*(('Model inputs'!D17-'Model inputs'!AB61)-12)/12))),0)) -> 0 | E11: =IF(IF(('Model inputs'!E17-'Model inputs'!AB61)<1="",FALSE,('Model inputs'!E17-'Model inputs'!AB61)<1),0,ROUND(IF(IF(('Model inputs'!E17-'Model inputs'!AB61)<=3="",FALSE,('Model inputs'!E17-'Model inputs'!AB61)<=3),IF('Model inputs'!AB53="","",'Model inputs'!AB53),IF(IF(('Model inputs'!E17-'Model inputs'!AB61)<=6="",FALSE,('Model inputs'!E17-'Model inputs'!AB61)<=6),'Model inputs'!AB53+('Model inputs'!AB59-'Model inputs'!AB53)*(('Model inputs'!E17-'Model inputs'!AB61)-3)/3,IF(IF(('Model inputs'!E17-'Model inputs'!AB61)<=12="",FALSE,('Model inputs'!E17-'Model inputs'!AB61)<=12),'Model inputs'!AB59+('Model inputs'!AB41-'Model inputs'!AB59)*(('Model inputs'!E17-'Model inputs'!AB61)-6)/6,'Model inputs'!AB41+('Model inputs'!AB47-'Model inputs'!AB41)*(('Model inputs'!E17-'Model inputs'!AB61)-12)/12))),0)) -> 1 | F11: =IF(IF(('Model inputs'!F17-'Model inputs'!AB61)<1="",FALSE,('Model inputs'!F17-'Model inputs'!AB61)<1),0,ROUND(IF(IF(('Model inputs'!F17-'Model inputs'!AB61)<=3="",FALSE,('Model inputs'!F17-'Model inputs'!AB61)<=3),IF('Model inputs'!AB53="","",'Model inputs'!AB53),IF(IF(('Model inputs'!F17-'Model inputs'!AB61)<=6="",FALSE,('Model inputs'!F17-'Model inputs'!AB61)<=6),'Model inputs'!AB53+('Model inputs'!AB59-'Model inputs'!AB53)*(('Model inputs'!F17-'Model inputs'!AB61)-3)/3,IF(IF(('Model inputs'!F17-'Model inputs'!AB61)<=12="",FALSE,('Model inputs'!F17-'Model inputs'!AB61)<=12),'Model inputs'!AB59+('Model inputs'!AB41-'Model inputs'!AB59)*(('Model inputs'!F17-'Model inputs'!AB61)-6)/6,'Model inputs'!AB41+('Model inputs'!AB47-'Model inputs'!AB41)*(('Model inputs'!F17-'Model inputs'!AB61)-12)/12))),0)) -> 1 | G11: =IF(IF(('Model inputs'!G17-'Model inputs'!AB61)<1="",FALSE,('Model inputs'!G17-'Model inputs'!AB61)<1),0,ROUND(IF(IF(('Model inputs'!G17-'Model inputs'!AB61)<=3="",FALSE,('Model inputs'!G17-'Model inputs'!AB61)<=3),IF('Model inputs'!AB53="","",'Model inputs'!AB53),IF(IF(('Model inputs'!G17-'Model inputs'!AB61)<=6="",FALSE,('Model inputs'!G17-'Model inputs'!AB61)<=6),'Model inputs'!AB53+('Model inputs'!AB59-'Model inputs'!AB53)*(('Model inputs'!G17-'Model inputs'!AB61)-3)/3,IF(IF(('Model inputs'!G17-'Model inputs'!AB61)<=12="",FALSE,('Model inputs'!G17-'Model inputs'!AB61)<=12),'Model inputs'!AB59+('Model inputs'!AB41-'Model inputs'!AB59)*(('Model inputs'!G17-'Model inputs'!AB61)-6)/6,'Model inputs'!AB41+('Model inputs'!AB47-'Model inputs'!AB41)*(('Model inputs'!G17-'Model inputs'!AB61)-12)/12))),0)) -> 2 | H11: =IF(IF(('Model inputs'!H17-'Model inputs'!AB61)<1="",FALSE,('Model inputs'!H17-'Model inputs'!AB61)<1),0,ROUND(IF(IF(('Model inputs'!H17-'Model inputs'!AB61)<=3="",FALSE,('Model inputs'!H17-'Model inputs'!AB61)<=3),IF('Model inputs'!AB53="","",'Model inputs'!AB53),IF(IF(('Model inputs'!H17-'Model inputs'!AB61)<=6="",FALSE,('Model inputs'!H17-'Model inputs'!AB61)<=6),'Model inputs'!AB53+('Model inputs'!AB59-'Model inputs'!AB53)*(('Model inputs'!H17-'Model inputs'!AB61)-3)/3,IF(IF(('Model inputs'!H17-'Model inputs'!AB61)<=12="",FALSE,('Model inputs'!H17-'Model inputs'!AB61)<=12),'Model inputs'!AB59+('Model inputs'!AB41-'Model inputs'!AB59)*(('Model inputs'!H17-'Model inputs'!AB61)-6)/6,'Model inputs'!AB41+('Model inputs'!AB47-'Model inputs'!AB41)*(('Model inputs'!H17-'Model inputs'!AB61)-12)/12))),0)) -> 3 | I11: =IF(IF(('Model inputs'!I17-'Model inputs'!AB61)<1="",FALSE,('Model inputs'!I17-'Model inputs'!AB61)<1),0,ROUND(IF(IF(('Model inputs'!I17-'Model inputs'!AB61)<=3="",FALSE,('Model inputs'!I17-'Model inputs'!AB61)<=3),IF('Model inputs'!AB53="","",'Model inputs'!AB53),IF(IF(('Model inputs'!I17-'Model inputs'!AB61)<=6="",FALSE,('Model inputs'!I17-'Model inputs'!AB61)<=6),'Model inputs'!AB53+('Model inputs'!AB59-'Model inputs'!AB53)*(('Model inputs'!I17-'Model inputs'!AB61)-3)/3,IF(IF(('Model inputs'!I17-'Model inputs'!AB61)<=12="",FALSE,('Model inputs'!I17-'Model inputs'!AB61)<=12),'Model inputs'!AB59+('Model inputs'!AB41-'Model inputs'!AB59)*(('Model inputs'!I17-'Model inputs'!AB61)-6)/6,'Model inputs'!AB41+('Model inputs'!AB47-'Model inputs'!AB41)*(('Model inputs'!I17-'Model inputs'!AB61)-12)/12))),0)) -> 4 | J11: =IF(IF(('Model inputs'!J17-'Model inputs'!AB61)<1="",FALSE,('Model inputs'!J17-'Model inputs'!AB61)<1),0,ROUND(IF(IF(('Model inputs'!J17-'Model inputs'!AB61)<=3="",FALSE,('Model inputs'!J17-'Model inputs'!AB61)<=3),IF('Model inputs'!AB53="","",'Model inputs'!AB53),IF(IF(('Model inputs'!J17-'Model inputs'!AB61)<=6="",FALSE,('Model inputs'!J17-'Model inputs'!AB61)<=6),'Model inputs'!AB53+('Model inputs'!AB59-'Model inputs'!AB53)*(('Model inputs'!J17-'Model inputs'!AB61)-3)/3,IF(IF(('Model inputs'!J17-'Model inputs'!AB61)<=12="",FALSE,('Model inputs'!J17-'Model inputs'!AB61)<=12),'Model inputs'!AB59+('Model inputs'!AB41-'Model inputs'!AB59)*(('Model inputs'!J17-'Model inputs'!AB61)-6)/6,'Model inputs'!AB41+('Model inputs'!AB47-'Model inputs'!AB41)*(('Model inputs'!J17-'Model inputs'!AB61)-12)/12))),0)) -> 5 | K11: =IF(IF(('Model inputs'!K17-'Model inputs'!AB61)<1="",FALSE,('Model inputs'!K17-'Model inputs'!AB61)<1),0,ROUND(IF(IF(('Model inputs'!K17-'Model inputs'!AB61)<=3="",FALSE,('Model inputs'!K17-'Model inputs'!AB61)<=3),IF('Model inputs'!AB53="","",'Model inputs'!AB53),IF(IF(('Model inputs'!K17-'Model inputs'!AB61)<=6="",FALSE,('Model inputs'!K17-'Model inputs'!AB61)<=6),'Model inputs'!AB53+('Model inputs'!AB59-'Model inputs'!AB53)*(('Model inputs'!K17-'Model inputs'!AB61)-3)/3,IF(IF(('Model inputs'!K17-'Model inputs'!AB61)<=12="",FALSE,('Model inputs'!K17-'Model inputs'!AB61)<=12),'Model inputs'!AB59+('Model inputs'!AB41-'Model inputs'!AB59)*(('Model inputs'!K17-'Model inputs'!AB61)-6)/6,'Model inputs'!AB41+('Model inputs'!AB47-'Model inputs'!AB41)*(('Model inputs'!K17-'Model inputs'!AB61)-12)/12))),0)) -> 6 | L11: =IF(IF(('Model inputs'!L17-'Model inputs'!AB61)<1="",FALSE,('Model inputs'!L17-'Model inputs'!AB61)<1),0,ROUND(IF(IF(('Model inputs'!L17-'Model inputs'!AB61)<=3="",FALSE,('Model inputs'!L17-'Model inputs'!AB61)<=3),IF('Model inputs'!AB53="","",'Model inputs'!AB53),IF(IF(('Model inputs'!L17-'Model inputs'!AB61)<=6="",FALSE,('Model inputs'!L17-'Model inputs'!AB61)<=6),'Model inputs'!AB53+('Model inputs'!AB59-'Model inputs'!AB53)*(('Model inputs'!L17-'Model inputs'!AB61)-3)/3,IF(IF(('Model inputs'!L17-'Model inputs'!AB61)<=12="",FALSE,('Model inputs'!L17-'Model inputs'!AB61)<=12),'Model inputs'!AB59+('Model inputs'!AB41-'Model inputs'!AB59)*(('Model inputs'!L17-'Model inputs'!AB61)-6)/6,'Model inputs'!AB41+('Model inputs'!AB47-'Model inputs'!AB41)*(('Model inputs'!L17-'Model inputs'!AB61)-12)/12))),0)) -> 7 | M11: =IF(IF(('Model inputs'!M17-'Model inputs'!AB61)<1="",FALSE,('Model inputs'!M17-'Model inputs'!AB61)<1),0,ROUND(IF(IF(('Model inputs'!M17-'Model inputs'!AB61)<=3="",FALSE,('Model inputs'!M17-'Model inputs'!AB61)<=3),IF('Model inputs'!AB53="","",'Model inputs'!AB53),IF(IF(('Model inputs'!M17-'Model inputs'!AB61)<=6="",FALSE,('Model inputs'!M17-'Model inputs'!AB61)<=6),'Model inputs'!AB53+('Model inputs'!AB59-'Model inputs'!AB53)*(('Model inputs'!M17-'Model inputs'!AB61)-3)/3,IF(IF(('Model inputs'!M17-'Model inputs'!AB61)<=12="",FALSE,('Model inputs'!M17-'Model inputs'!AB61)<=12),'Model inputs'!AB59+('Model inputs'!AB41-'Model inputs'!AB59)*(('Model inputs'!M17-'Model inputs'!AB61)-6)/6,'Model inputs'!AB41+('Model inputs'!AB47-'Model inputs'!AB41)*(('Model inputs'!M17-'Model inputs'!AB61)-12)/12))),0)) -> 8 | N11: =IF(IF(('Model inputs'!N17-'Model inputs'!AB61)<1="",FALSE,('Model inputs'!N17-'Model inputs'!AB61)<1),0,ROUND(IF(IF(('Model inputs'!N17-'Model inputs'!AB61)<=3="",FALSE,('Model inputs'!N17-'Model inputs'!AB61)<=3),IF('Model inputs'!AB53="","",'Model inputs'!AB53),IF(IF(('Model inputs'!N17-'Model inputs'!AB61)<=6="",FALSE,('Model inputs'!N17-'Model inputs'!AB61)<=6),'Model inputs'!AB53+('Model inputs'!AB59-'Model inputs'!AB53)*(('Model inputs'!N17-'Model inputs'!AB61)-3)/3,IF(IF(('Model inputs'!N17-'Model inputs'!AB61)<=12="",FALSE,('Model inputs'!N17-'Model inputs'!AB61)<=12),'Model inputs'!AB59+('Model inputs'!AB41-'Model inputs'!AB59)*(('Model inputs'!N17-'Model inputs'!AB61)-6)/6,'Model inputs'!AB41+('Model inputs'!AB47-'Model inputs'!AB41)*(('Model inputs'!N17-'Model inputs'!AB61)-12)/12))),0)) -> 9 | O11: =IF(IF(('Model inputs'!O17-'Model inputs'!AB61)<1="",FALSE,('Model inputs'!O17-'Model inputs'!AB61)<1),0,ROUND(IF(IF(('Model inputs'!O17-'Model inputs'!AB61)<=3="",FALSE,('Model inputs'!O17-'Model inputs'!AB61)<=3),IF('Model inputs'!AB53="","",'Model inputs'!AB53),IF(IF(('Model inputs'!O17-'Model inputs'!AB61)<=6="",FALSE,('Model inputs'!O17-'Model inputs'!AB61)<=6),'Model inputs'!AB53+('Model inputs'!AB59-'Model inputs'!AB53)*(('Model inputs'!O17-'Model inputs'!AB61)-3)/3,IF(IF(('Model inputs'!O17-'Model inputs'!AB61)<=12="",FALSE,('Model inputs'!O17-'Model inputs'!AB61)<=12),'Model inputs'!AB59+('Model inputs'!AB41-'Model inputs'!AB59)*(('Model inputs'!O17-'Model inputs'!AB61)-6)/6,'Model inputs'!AB41+('Model inputs'!AB47-'Model inputs'!AB41)*(('Model inputs'!O17-'Model inputs'!AB61)-12)/12))),0)) -> 11 | P11: =IF(IF(('Model inputs'!P17-'Model inputs'!AB61)<1="",FALSE,('Model inputs'!P17-'Model inputs'!AB61)<1),0,ROUND(IF(IF(('Model inputs'!P17-'Model inputs'!AB61)<=3="",FALSE,('Model inputs'!P17-'Model inputs'!AB61)<=3),IF('Model inputs'!AB53="","",'Model inputs'!AB53),IF(IF(('Model inputs'!P17-'Model inputs'!AB61)<=6="",FALSE,('Model inputs'!P17-'Model inputs'!AB61)<=6),'Model inputs'!AB53+('Model inputs'!AB59-'Model inputs'!AB53)*(('Model inputs'!P17-'Model inputs'!AB61)-3)/3,IF(IF(('Model inputs'!P17-'Model inputs'!AB61)<=12="",FALSE,('Model inputs'!P17-'Model inputs'!AB61)<=12),'Model inputs'!AB59+('Model inputs'!AB41-'Model inputs'!AB59)*(('Model inputs'!P17-'Model inputs'!AB61)-6)/6,'Model inputs'!AB41+('Model inputs'!AB47-'Model inputs'!AB41)*(('Model inputs'!P17-'Model inputs'!AB61)-12)/12))),0)) -> 12 | Q11: =IF(IF(('Model inputs'!Q17-'Model inputs'!AB61)<1="",FALSE,('Model inputs'!Q17-'Model inputs'!AB61)<1),0,ROUND(IF(IF(('Model inputs'!Q17-'Model inputs'!AB61)<=3="",FALSE,('Model inputs'!Q17-'Model inputs'!AB61)<=3),IF('Model inputs'!AB53="","",'Model inputs'!AB53),IF(IF(('Model inputs'!Q17-'Model inputs'!AB61)<=6="",FALSE,('Model inputs'!Q17-'Model inputs'!AB61)<=6),'Model inputs'!AB53+('Model inputs'!AB59-'Model inputs'!AB53)*(('Model inputs'!Q17-'Model inputs'!AB61)-3)/3,IF(IF(('Model inputs'!Q17-'Model inputs'!AB61)<=12="",FALSE,('Model inputs'!Q17-'Model inputs'!AB61)<=12),'Model inputs'!AB59+('Model inputs'!AB41-'Model inputs'!AB59)*(('Model inputs'!Q17-'Model inputs'!AB61)-6)/6,'Model inputs'!AB41+('Model inputs'!AB47-'Model inputs'!AB41)*(('Model inputs'!Q17-'Model inputs'!AB61)-12)/12))),0)) -> 14 | R11: =IF(IF(('Model inputs'!R17-'Model inputs'!AB61)<1="",FALSE,('Model inputs'!R17-'Model inputs'!AB61)<1),0,ROUND(IF(IF(('Model inputs'!R17-'Model inputs'!AB61)<=3="",FALSE,('Model inputs'!R17-'Model inputs'!AB61)<=3),IF('Model inputs'!AB53="","",'Model inputs'!AB53),IF(IF(('Model inputs'!R17-'Model inputs'!AB61)<=6="",FALSE,('Model inputs'!R17-'Model inputs'!AB61)<=6),'Model inputs'!AB53+('Model inputs'!AB59-'Model inputs'!AB53)*(('Model inputs'!R17-'Model inputs'!AB61)-3)/3,IF(IF(('Model inputs'!R17-'Model inputs'!AB61)<=12="",FALSE,('Model inputs'!R17-'Model inputs'!AB61)<=12),'Model inputs'!AB59+('Model inputs'!AB41-'Model inputs'!AB59)*(('Model inputs'!R17-'Model inputs'!AB61)-6)/6,'Model inputs'!AB41+('Model inputs'!AB47-'Model inputs'!AB41)*(('Model inputs'!R17-'Model inputs'!AB61)-12)/12))),0)) -> 15 | S11: =IF(IF(('Model inputs'!S17-'Model inputs'!AB61)<1="",FALSE,('Model inputs'!S17-'Model inputs'!AB61)<1),0,ROUND(IF(IF(('Model inputs'!S17-'Model inputs'!AB61)<=3="",FALSE,('Model inputs'!S17-'Model inputs'!AB61)<=3),IF('Model inputs'!AB53="","",'Model inputs'!AB53),IF(IF(('Model inputs'!S17-'Model inputs'!AB61)<=6="",FALSE,('Model inputs'!S17-'Model inputs'!AB61)<=6),'Model inputs'!AB53+('Model inputs'!AB59-'Model inputs'!AB53)*(('Model inputs'!S17-'Model inputs'!AB61)-3)/3,IF(IF(('Model inputs'!S17-'Model inputs'!AB61)<=12="",FALSE,('Model inputs'!S17-'Model inputs'!AB61)<=12),'Model inputs'!AB59+('Model inputs'!AB41-'Model inputs'!AB59)*(('Model inputs'!S17-'Model inputs'!AB61)-6)/6,'Model inputs'!AB41+('Model inputs'!AB47-'Model inputs'!AB41)*(('Model inputs'!S17-'Model inputs'!AB61)-12)/12))),0)) -> 17 | T11: =IF(IF(('Model inputs'!T17-'Model inputs'!AB61)<1="",FALSE,('Model inputs'!T17-'Model inputs'!AB61)<1),0,ROUND(IF(IF(('Model inputs'!T17-'Model inputs'!AB61)<=3="",FALSE,('Model inputs'!T17-'Model inputs'!AB61)<=3),IF('Model inputs'!AB53="","",'Model inputs'!AB53),IF(IF(('Model inputs'!T17-'Model inputs'!AB61)<=6="",FALSE,('Model inputs'!T17-'Model inputs'!AB61)<=6),'Model inputs'!AB53+('Model inputs'!AB59-'Model inputs'!AB53)*(('Model inputs'!T17-'Model inputs'!AB61)-3)/3,IF(IF(('Model inputs'!T17-'Model inputs'!AB61)<=12="",FALSE,('Model inputs'!T17-'Model inputs'!AB61)<=12),'Model inputs'!AB59+('Model inputs'!AB41-'Model inputs'!AB59)*(('Model inputs'!T17-'Model inputs'!AB61)-6)/6,'Model inputs'!AB41+('Model inputs'!AB47-'Model inputs'!AB41)*(('Model inputs'!T17-'Model inputs'!AB61)-12)/12))),0)) -> 18 | U11: =IF(IF(('Model inputs'!U17-'Model inputs'!AB61)<1="",FALSE,('Model inputs'!U17-'Model inputs'!AB61)<1),0,ROUND(IF(IF(('Model inputs'!U17-'Model inputs'!AB61)<=3="",FALSE,('Model inputs'!U17-'Model inputs'!AB61)<=3),IF('Model inputs'!AB53="","",'Model inputs'!AB53),IF(IF(('Model inputs'!U17-'Model inputs'!AB61)<=6="",FALSE,('Model inputs'!U17-'Model inputs'!AB61)<=6),'Model inputs'!AB53+('Model inputs'!AB59-'Model inputs'!AB53)*(('Model inputs'!U17-'Model inputs'!AB61)-3)/3,IF(IF(('Model inputs'!U17-'Model inputs'!AB61)<=12="",FALSE,('Model inputs'!U17-'Model inputs'!AB61)<=12),'Model inputs'!AB59+('Model inputs'!AB41-'Model inputs'!AB59)*(('Model inputs'!U17-'Model inputs'!AB61)-6)/6,'Model inputs'!AB41+('Model inputs'!AB47-'Model inputs'!AB41)*(('Model inputs'!U17-'Model inputs'!AB61)-12)/12))),0)) -> 19 | V11: =IF(IF(('Model inputs'!V17-'Model inputs'!AB61)<1="",FALSE,('Model inputs'!V17-'Model inputs'!AB61)<1),0,ROUND(IF(IF(('Model inputs'!V17-'Model inputs'!AB61)<=3="",FALSE,('Model inputs'!V17-'Model inputs'!AB61)<=3),IF('Model inputs'!AB53="","",'Model inputs'!AB53),IF(IF(('Model inputs'!V17-'Model inputs'!AB61)<=6="",FALSE,('Model inputs'!V17-'Model inputs'!AB61)<=6),'Model inputs'!AB53+('Model inputs'!AB59-'Model inputs'!AB53)*(('Model inputs'!V17-'Model inputs'!AB61)-3)/3,IF(IF(('Model inputs'!V17-'Model inputs'!AB61)<=12="",FALSE,('Model inputs'!V17-'Model inputs'!AB61)<=12),'Model inputs'!AB59+('Model inputs'!AB41-'Model inputs'!AB59)*(('Model inputs'!V17-'Model inputs'!AB61)-6)/6,'Model inputs'!AB41+('Model inputs'!AB47-'Model inputs'!AB41)*(('Model inputs'!V17-'Model inputs'!AB61)-12)/12))),0)) -> 21 | W11: =IF(IF(('Model inputs'!W17-'Model inputs'!AB61)<1="",FALSE,('Model inputs'!W17-'Model inputs'!AB61)<1),0,ROUND(IF(IF(('Model inputs'!W17-'Model inputs'!AB61)<=3="",FALSE,('Model inputs'!W17-'Model inputs'!AB61)<=3),IF('Model inputs'!AB53="","",'Model inputs'!AB53),IF(IF(('Model inputs'!W17-'Model inputs'!AB61)<=6="",FALSE,('Model inputs'!W17-'Model inputs'!AB61)<=6),'Model inputs'!AB53+('Model inputs'!AB59-'Model inputs'!AB53)*(('Model inputs'!W17-'Model inputs'!AB61)-3)/3,IF(IF(('Model inputs'!W17-'Model inputs'!AB61)<=12="",FALSE,('Model inputs'!W17-'Model inputs'!AB61)<=12),'Model inputs'!AB59+('Model inputs'!AB41-'Model inputs'!AB59)*(('Model inputs'!W17-'Model inputs'!AB61)-6)/6,'Model inputs'!AB41+('Model inputs'!AB47-'Model inputs'!AB41)*(('Model inputs'!W17-'Model inputs'!AB61)-12)/12))),0)) -> 22 | X11: =IF(IF(('Model inputs'!X17-'Model inputs'!AB61)<1="",FALSE,('Model inputs'!X17-'Model inputs'!AB61)<1),0,ROUND(IF(IF(('Model inputs'!X17-'Model inputs'!AB61)<=3="",FALSE,('Model inputs'!X17-'Model inputs'!AB61)<=3),IF('Model inputs'!AB53="","",'Model inputs'!AB53),IF(IF(('Model inputs'!X17-'Model inputs'!AB61)<=6="",FALSE,('Model inputs'!X17-'Model inputs'!AB61)<=6),'Model inputs'!AB53+('Model inputs'!AB59-'Model inputs'!AB53)*(('Model inputs'!X17-'Model inputs'!AB61)-3)/3,IF(IF(('Model inputs'!X17-'Model inputs'!AB61)<=12="",FALSE,('Model inputs'!X17-'Model inputs'!AB61)<=12),'Model inputs'!AB59+('Model inputs'!AB41-'Model inputs'!AB59)*(('Model inputs'!X17-'Model inputs'!AB61)-6)/6,'Model inputs'!AB41+('Model inputs'!AB47-'Model inputs'!AB41)*(('Model inputs'!X17-'Model inputs'!AB61)-12)/12))),0)) -> 24 | Y11: =IF(IF(('Model inputs'!Y17-'Model inputs'!AB61)<1="",FALSE,('Model inputs'!Y17-'Model inputs'!AB61)<1),0,ROUND(IF(IF(('Model inputs'!Y17-'Model inputs'!AB61)<=3="",FALSE,('Model inputs'!Y17-'Model inputs'!AB61)<=3),IF('Model inputs'!AB53="","",'Model inputs'!AB53),IF(IF(('Model inputs'!Y17-'Model inputs'!AB61)<=6="",FALSE,('Model inputs'!Y17-'Model inputs'!AB61)<=6),'Model inputs'!AB53+('Model inputs'!AB59-'Model inputs'!AB53)*(('Model inputs'!Y17-'Model inputs'!AB61)-3)/3,IF(IF(('Model inputs'!Y17-'Model inputs'!AB61)<=12="",FALSE,('Model inputs'!Y17-'Model inputs'!AB61)<=12),'Model inputs'!AB59+('Model inputs'!AB41-'Model inputs'!AB59)*(('Model inputs'!Y17-'Model inputs'!AB61)-6)/6,'Model inputs'!AB41+('Model inputs'!AB47-'Model inputs'!AB41)*(('Model inputs'!Y17-'Model inputs'!AB61)-12)/12))),0)) -> 25
A12: Ending cash · Downside | B12: =IF(IF(IF(IF(ISERROR('Model inputs'!B16=1),'Model inputs'!B16=1,IF('Model inputs'!B16="","",'Model inputs'!B16=1))="",FALSE,IF(ISERROR('Model inputs'!B16=1),'Model inputs'!B16=1,IF('Model inputs'!B16="","",'Model inputs'!B16=1))),IF('Model inputs'!AB26="","",'Model inputs'!AB26),IF('Model inputs'!AA12="","",'Model inputs'!AA12))="",0,IF(IF(IF(ISERROR('Model inputs'!B16=1),'Model inputs'!B16=1,IF('Model inputs'!B16="","",'Model inputs'!B16=1))="",FALSE,IF(ISERROR('Model inputs'!B16=1),'Model inputs'!B16=1,IF('Model inputs'!B16="","",'Model inputs'!B16=1))),IF('Model inputs'!AB26="","",'Model inputs'!AB26),IF('Model inputs'!AA12="","",'Model inputs'!AA12)))+'Model inputs'!B18 -> 22884.8 | C12: =IF(IF(IF(IF(ISERROR('Model inputs'!C16=1),'Model inputs'!C16=1,IF('Model inputs'!C16="","",'Model inputs'!C16=1))="",FALSE,IF(ISERROR('Model inputs'!C16=1),'Model inputs'!C16=1,IF('Model inputs'!C16="","",'Model inputs'!C16=1))),IF('Model inputs'!AB26="","",'Model inputs'!AB26),IF('Model inputs'!B12="","",'Model inputs'!B12))="",0,IF(IF(IF(ISERROR('Model inputs'!C16=1),'Model inputs'!C16=1,IF('Model inputs'!C16="","",'Model inputs'!C16=1))="",FALSE,IF(ISERROR('Model inputs'!C16=1),'Model inputs'!C16=1,IF('Model inputs'!C16="","",'Model inputs'!C16=1))),IF('Model inputs'!AB26="","",'Model inputs'!AB26),IF('Model inputs'!B12="","",'Model inputs'!B12)))+'Model inputs'!C18 -> 20769.6 | D12: =IF(IF(IF(IF(ISERROR('Model inputs'!D16=1),'Model inputs'!D16=1,IF('Model inputs'!D16="","",'Model inputs'!D16=1))="",FALSE,IF(ISERROR('Model inputs'!D16=1),'Model inputs'!D16=1,IF('Model inputs'!D16="","",'Model inputs'!D16=1))),IF('Model inputs'!AB26="","",'Model inputs'!AB26),IF('Model inputs'!C12="","",'Model inputs'!C12))="",0,IF(IF(IF(ISERROR('Model inputs'!D16=1),'Model inputs'!D16=1,IF('Model inputs'!D16="","",'Model inputs'!D16=1))="",FALSE,IF(ISERROR('Model inputs'!D16=1),'Model inputs'!D16=1,IF('Model inputs'!D16="","",'Model inputs'!D16=1))),IF('Model inputs'!AB26="","",'Model inputs'!AB26),IF('Model inputs'!C12="","",'Model inputs'!C12)))+'Model inputs'!D18 -> 18654.4 | E12: =IF(IF(IF(IF(ISERROR('Model inputs'!E16=1),'Model inputs'!E16=1,IF('Model inputs'!E16="","",'Model inputs'!E16=1))="",FALSE,IF(ISERROR('Model inputs'!E16=1),'Model inputs'!E16=1,IF('Model inputs'!E16="","",'Model inputs'!E16=1))),IF('Model inputs'!AB26="","",'Model inputs'!AB26),IF('Model inputs'!D12="","",'Model inputs'!D12))="",0,IF(IF(IF(ISERROR('Model inputs'!E16=1),'Model inputs'!E16=1,IF('Model inputs'!E16="","",'Model inputs'!E16=1))="",FALSE,IF(ISERROR('Model inputs'!E16=1),'Model inputs'!E16=1,IF('Model inputs'!E16="","",'Model inputs'!E16=1))),IF('Model inputs'!AB26="","",'Model inputs'!AB26),IF('Model inputs'!D12="","",'Model inputs'!D12)))+'Model inputs'!E18 -> 16539.2 | F12: =IF(IF(IF(IF(ISERROR('Model inputs'!F16=1),'Model inputs'!F16=1,IF('Model inputs'!F16="","",'Model inputs'!F16=1))="",FALSE,IF(ISERROR('Model inputs'!F16=1),'Model inputs'!F16=1,IF('Model inputs'!F16="","",'Model inputs'!F16=1))),IF('Model inputs'!AB26="","",'Model inputs'!AB26),IF('Model inputs'!E12="","",'Model inputs'!E12))="",0,IF(IF(IF(ISERROR('Model inputs'!F16=1),'Model inputs'!F16=1,IF('Model inputs'!F16="","",'Model inputs'!F16=1))="",FALSE,IF(ISERROR('Model inputs'!F16=1),'Model inputs'!F16=1,IF('Model inputs'!F16="","",'Model inputs'!F16=1))),IF('Model inputs'!AB26="","",'Model inputs'!AB26),IF('Model inputs'!E12="","",'Model inputs'!E12)))+'Model inputs'!F18 -> 14424 | G12: =IF(IF(IF(IF(ISERROR('Model inputs'!G16=1),'Model inputs'!G16=1,IF('Model inputs'!G16="","",'Model inputs'!G16=1))="",FALSE,IF(ISERROR('Model inputs'!G16=1),'Model inputs'!G16=1,IF('Model inputs'!G16="","",'Model inputs'!G16=1))),IF('Model inputs'!AB26="","",'Model inputs'!AB26),IF('Model inputs'!F12="","",'Model inputs'!F12))="",0,IF(IF(IF(ISERROR('Model inputs'!G16=1),'Model inputs'!G16=1,IF('Model inputs'!G16="","",'Model inputs'!G16=1))="",FALSE,IF(ISERROR('Model inputs'!G16=1),'Model inputs'!G16=1,IF('Model inputs'!G16="","",'Model inputs'!G16=1))),IF('Model inputs'!AB26="","",'Model inputs'!AB26),IF('Model inputs'!F12="","",'Model inputs'!F12)))+'Model inputs'!G18 -> 12308.8 | H12: =IF(IF(IF(IF(ISERROR('Model inputs'!H16=1),'Model inputs'!H16=1,IF('Model inputs'!H16="","",'Model inputs'!H16=1))="",FALSE,IF(ISERROR('Model inputs'!H16=1),'Model inputs'!H16=1,IF('Model inputs'!H16="","",'Model inputs'!H16=1))),IF('Model inputs'!AB26="","",'Model inputs'!AB26),IF('Model inputs'!G12="","",'Model inputs'!G12))="",0,IF(IF(IF(ISERROR('Model inputs'!H16=1),'Model inputs'!H16=1,IF('Model inputs'!H16="","",'Model inputs'!H16=1))="",FALSE,IF(ISERROR('Model inputs'!H16=1),'Model inputs'!H16=1,IF('Model inputs'!H16="","",'Model inputs'!H16=1))),IF('Model inputs'!AB26="","",'Model inputs'!AB26),IF('Model inputs'!G12="","",'Model inputs'!G12)))+'Model inputs'!H18 -> 10267.12 | I12: =IF(IF(IF(IF(ISERROR('Model inputs'!I16=1),'Model inputs'!I16=1,IF('Model inputs'!I16="","",'Model inputs'!I16=1))="",FALSE,IF(ISERROR('Model inputs'!I16=1),'Model inputs'!I16=1,IF('Model inputs'!I16="","",'Model inputs'!I16=1))),IF('Model inputs'!AB26="","",'Model inputs'!AB26),IF('Model inputs'!H12="","",'Model inputs'!H12))="",0,IF(IF(IF(ISERROR('Model inputs'!I16=1),'Model inputs'!I16=1,IF('Model inputs'!I16="","",'Model inputs'!I16=1))="",FALSE,IF(ISERROR('Model inputs'!I16=1),'Model inputs'!I16=1,IF('Model inputs'!I16="","",'Model inputs'!I16=1))),IF('Model inputs'!AB26="","",'Model inputs'!AB26),IF('Model inputs'!H12="","",'Model inputs'!H12)))+'Model inputs'!I18 -> 8350 | J12: =IF(IF(IF(IF(ISERROR('Model inputs'!J16=1),'Model inputs'!J16=1,IF('Model inputs'!J16="","",'Model inputs'!J16=1))="",FALSE,IF(ISERROR('Model inputs'!J16=1),'Model inputs'!J16=1,IF('Model inputs'!J16="","",'Model inputs'!J16=1))),IF('Model inputs'!AB26="","",'Model inputs'!AB26),IF('Model inputs'!I12="","",'Model inputs'!I12))="",0,IF(IF(IF(ISERROR('Model inputs'!J16=1),'Model inputs'!J16=1,IF('Model inputs'!J16="","",'Model inputs'!J16=1))="",FALSE,IF(ISERROR('Model inputs'!J16=1),'Model inputs'!J16=1,IF('Model inputs'!J16="","",'Model inputs'!J16=1))),IF('Model inputs'!AB26="","",'Model inputs'!AB26),IF('Model inputs'!I12="","",'Model inputs'!I12)))+'Model inputs'!J18 -> 6506.4 | K12: =IF(IF(IF(IF(ISERROR('Model inputs'!K16=1),'Model inputs'!K16=1,IF('Model inputs'!K16="","",'Model inputs'!K16=1))="",FALSE,IF(ISERROR('Model inputs'!K16=1),'Model inputs'!K16=1,IF('Model inputs'!K16="","",'Model inputs'!K16=1))),IF('Model inputs'!AB26="","",'Model inputs'!AB26),IF('Model inputs'!J12="","",'Model inputs'!J12))="",0,IF(IF(IF(ISERROR('Model inputs'!K16=1),'Model inputs'!K16=1,IF('Model inputs'!K16="","",'Model inputs'!K16=1))="",FALSE,IF(ISERROR('Model inputs'!K16=1),'Model inputs'!K16=1,IF('Model inputs'!K16="","",'Model inputs'!K16=1))),IF('Model inputs'!AB26="","",'Model inputs'!AB26),IF('Model inputs'!J12="","",'Model inputs'!J12)))+'Model inputs'!K18 -> 4736.32 | L12: =IF(IF(IF(IF(ISERROR('Model inputs'!L16=1),'Model inputs'!L16=1,IF('Model inputs'!L16="","",'Model inputs'!L16=1))="",FALSE,IF(ISERROR('Model inputs'!L16=1),'Model inputs'!L16=1,IF('Model inputs'!L16="","",'Model inputs'!L16=1))),IF('Model inputs'!AB26="","",'Model inputs'!AB26),IF('Model inputs'!K12="","",'Model inputs'!K12))="",0,IF(IF(IF(ISERROR('Model inputs'!L16=1),'Model inputs'!L16=1,IF('Model inputs'!L16="","",'Model inputs'!L16=1))="",FALSE,IF(ISERROR('Model inputs'!L16=1),'Model inputs'!L16=1,IF('Model inputs'!L16="","",'Model inputs'!L16=1))),IF('Model inputs'!AB26="","",'Model inputs'!AB26),IF('Model inputs'!K12="","",'Model inputs'!K12)))+'Model inputs'!L18 -> 3090.8 | M12: =IF(IF(IF(IF(ISERROR('Model inputs'!M16=1),'Model inputs'!M16=1,IF('Model inputs'!M16="","",'Model inputs'!M16=1))="",FALSE,IF(ISERROR('Model inputs'!M16=1),'Model inputs'!M16=1,IF('Model inputs'!M16="","",'Model inputs'!M16=1))),IF('Model inputs'!AB26="","",'Model inputs'!AB26),IF('Model inputs'!L12="","",'Model inputs'!L12))="",0,IF(IF(IF(ISERROR('Model inputs'!M16=1),'Model inputs'!M16=1,IF('Model inputs'!M16="","",'Model inputs'!M16=1))="",FALSE,IF(ISERROR('Model inputs'!M16=1),'Model inputs'!M16=1,IF('Model inputs'!M16="","",'Model inputs'!M16=1))),IF('Model inputs'!AB26="","",'Model inputs'!AB26),IF('Model inputs'!L12="","",'Model inputs'!L12)))+'Model inputs'!M18 -> 1518.8 | N12: =IF(IF(IF(IF(ISERROR('Model inputs'!N16=1),'Model inputs'!N16=1,IF('Model inputs'!N16="","",'Model inputs'!N16=1))="",FALSE,IF(ISERROR('Model inputs'!N16=1),'Model inputs'!N16=1,IF('Model inputs'!N16="","",'Model inputs'!N16=1))),IF('Model inputs'!AB26="","",'Model inputs'!AB26),IF('Model inputs'!M12="","",'Model inputs'!M12))="",0,IF(IF(IF(ISERROR('Model inputs'!N16=1),'Model inputs'!N16=1,IF('Model inputs'!N16="","",'Model inputs'!N16=1))="",FALSE,IF(ISERROR('Model inputs'!N16=1),'Model inputs'!N16=1,IF('Model inputs'!N16="","",'Model inputs'!N16=1))),IF('Model inputs'!AB26="","",'Model inputs'!AB26),IF('Model inputs'!M12="","",'Model inputs'!M12)))+'Model inputs'!N18 -> 20.32 | O12: =IF(IF(IF(IF(ISERROR('Model inputs'!O16=1),'Model inputs'!O16=1,IF('Model inputs'!O16="","",'Model inputs'!O16=1))="",FALSE,IF(ISERROR('Model inputs'!O16=1),'Model inputs'!O16=1,IF('Model inputs'!O16="","",'Model inputs'!O16=1))),IF('Model inputs'!AB26="","",'Model inputs'!AB26),IF('Model inputs'!N12="","",'Model inputs'!N12))="",0,IF(IF(IF(ISERROR('Model inputs'!O16=1),'Model inputs'!O16=1,IF('Model inputs'!O16="","",'Model inputs'!O16=1))="",FALSE,IF(ISERROR('Model inputs'!O16=1),'Model inputs'!O16=1,IF('Model inputs'!O16="","",'Model inputs'!O16=1))),IF('Model inputs'!AB26="","",'Model inputs'!AB26),IF('Model inputs'!N12="","",'Model inputs'!N12)))+'Model inputs'!O18 -> -1353.6 | P12: =IF(IF(IF(IF(ISERROR('Model inputs'!P16=1),'Model inputs'!P16=1,IF('Model inputs'!P16="","",'Model inputs'!P16=1))="",FALSE,IF(ISERROR('Model inputs'!P16=1),'Model inputs'!P16=1,IF('Model inputs'!P16="","",'Model inputs'!P16=1))),IF('Model inputs'!AB26="","",'Model inputs'!AB26),IF('Model inputs'!O12="","",'Model inputs'!O12))="",0,IF(IF(IF(ISERROR('Model inputs'!P16=1),'Model inputs'!P16=1,IF('Model inputs'!P16="","",'Model inputs'!P16=1))="",FALSE,IF(ISERROR('Model inputs'!P16=1),'Model inputs'!P16=1,IF('Model inputs'!P16="","",'Model inputs'!P16=1))),IF('Model inputs'!AB26="","",'Model inputs'!AB26),IF('Model inputs'!O12="","",'Model inputs'!O12)))+'Model inputs'!P18 -> -2654 | Q12: =IF(IF(IF(IF(ISERROR('Model inputs'!Q16=1),'Model inputs'!Q16=1,IF('Model inputs'!Q16="","",'Model inputs'!Q16=1))="",FALSE,IF(ISERROR('Model inputs'!Q16=1),'Model inputs'!Q16=1,IF('Model inputs'!Q16="","",'Model inputs'!Q16=1))),IF('Model inputs'!AB26="","",'Model inputs'!AB26),IF('Model inputs'!P12="","",'Model inputs'!P12))="",0,IF(IF(IF(ISERROR('Model inputs'!Q16=1),'Model inputs'!Q16=1,IF('Model inputs'!Q16="","",'Model inputs'!Q16=1))="",FALSE,IF(ISERROR('Model inputs'!Q16=1),'Model inputs'!Q16=1,IF('Model inputs'!Q16="","",'Model inputs'!Q16=1))),IF('Model inputs'!AB26="","",'Model inputs'!AB26),IF('Model inputs'!P12="","",'Model inputs'!P12)))+'Model inputs'!Q18 -> -3793.08 | R12: =IF(IF(IF(IF(ISERROR('Model inputs'!R16=1),'Model inputs'!R16=1,IF('Model inputs'!R16="","",'Model inputs'!R16=1))="",FALSE,IF(ISERROR('Model inputs'!R16=1),'Model inputs'!R16=1,IF('Model inputs'!R16="","",'Model inputs'!R16=1))),IF('Model inputs'!AB26="","",'Model inputs'!AB26),IF('Model inputs'!Q12="","",'Model inputs'!Q12))="",0,IF(IF(IF(ISERROR('Model inputs'!R16=1),'Model inputs'!R16=1,IF('Model inputs'!R16="","",'Model inputs'!R16=1))="",FALSE,IF(ISERROR('Model inputs'!R16=1),'Model inputs'!R16=1,IF('Model inputs'!R16="","",'Model inputs'!R16=1))),IF('Model inputs'!AB26="","",'Model inputs'!AB26),IF('Model inputs'!Q12="","",'Model inputs'!Q12)))+'Model inputs'!R18 -> -4858.64 | S12: =IF(IF(IF(IF(ISERROR('Model inputs'!S16=1),'Model inputs'!S16=1,IF('Model inputs'!S16="","",'Model inputs'!S16=1))="",FALSE,IF(ISERROR('Model inputs'!S16=1),'Model inputs'!S16=1,IF('Model inputs'!S16="","",'Model inputs'!S16=1))),IF('Model inputs'!AB26="","",'Model inputs'!AB26),IF('Model inputs'!R12="","",'Model inputs'!R12))="",0,IF(IF(IF(ISERROR('Model inputs'!S16=1),'Model inputs'!S16=1,IF('Model inputs'!S16="","",'Model inputs'!S16=1))="",FALSE,IF(ISERROR('Model inputs'!S16=1),'Model inputs'!S16=1,IF('Model inputs'!S16="","",'Model inputs'!S16=1))),IF('Model inputs'!AB26="","",'Model inputs'!AB26),IF('Model inputs'!R12="","",'Model inputs'!R12)))+'Model inputs'!S18 -> -5762.88 | T12: =IF(IF(IF(IF(ISERROR('Model inputs'!T16=1),'Model inputs'!T16=1,IF('Model inputs'!T16="","",'Model inputs'!T16=1))="",FALSE,IF(ISERROR('Model inputs'!T16=1),'Model inputs'!T16=1,IF('Model inputs'!T16="","",'Model inputs'!T16=1))),IF('Model inputs'!AB26="","",'Model inputs'!AB26),IF('Model inputs'!S12="","",'Model inputs'!S12))="",0,IF(IF(IF(ISERROR('Model inputs'!T16=1),'Model inputs'!T16=1,IF('Model inputs'!T16="","",'Model inputs'!T16=1))="",FALSE,IF(ISERROR('Model inputs'!T16=1),'Model inputs'!T16=1,IF('Model inputs'!T16="","",'Model inputs'!T16=1))),IF('Model inputs'!AB26="","",'Model inputs'!AB26),IF('Model inputs'!S12="","",'Model inputs'!S12)))+'Model inputs'!T18 -> -6593.6 | U12: =IF(IF(IF(IF(ISERROR('Model inputs'!U16=1),'Model inputs'!U16=1,IF('Model inputs'!U16="","",'Model inputs'!U16=1))="",FALSE,IF(ISERROR('Model inputs'!U16=1),'Model inputs'!U16=1,IF('Model inputs'!U16="","",'Model inputs'!U16=1))),IF('Model inputs'!AB26="","",'Model inputs'!AB26),IF('Model inputs'!T12="","",'Model inputs'!T12))="",0,IF(IF(IF(ISERROR('Model inputs'!U16=1),'Model inputs'!U16=1,IF('Model inputs'!U16="","",'Model inputs'!U16=1))="",FALSE,IF(ISERROR('Model inputs'!U16=1),'Model inputs'!U16=1,IF('Model inputs'!U16="","",'Model inputs'!U16=1))),IF('Model inputs'!AB26="","",'Model inputs'!AB26),IF('Model inputs'!T12="","",'Model inputs'!T12)))+'Model inputs'!U18 -> -7263 | V12: =IF(IF(IF(IF(ISERROR('Model inputs'!V16=1),'Model inputs'!V16=1,IF('Model inputs'!V16="","",'Model inputs'!V16=1))="",FALSE,IF(ISERROR('Model inputs'!V16=1),'Model inputs'!V16=1,IF('Model inputs'!V16="","",'Model inputs'!V16=1))),IF('Model inputs'!AB26="","",'Model inputs'!AB26),IF('Model inputs'!U12="","",'Model inputs'!U12))="",0,IF(IF(IF(ISERROR('Model inputs'!V16=1),'Model inputs'!V16=1,IF('Model inputs'!V16="","",'Model inputs'!V16=1))="",FALSE,IF(ISERROR('Model inputs'!V16=1),'Model inputs'!V16=1,IF('Model inputs'!V16="","",'Model inputs'!V16=1))),IF('Model inputs'!AB26="","",'Model inputs'!AB26),IF('Model inputs'!U12="","",'Model inputs'!U12)))+'Model inputs'!V18 -> -7734.32 | W12: =IF(IF(IF(IF(ISERROR('Model inputs'!W16=1),'Model inputs'!W16=1,IF('Model inputs'!W16="","",'Model inputs'!W16=1))="",FALSE,IF(ISERROR('Model inputs'!W16=1),'Model inputs'!W16=1,IF('Model inputs'!W16="","",'Model inputs'!W16=1))),IF('Model inputs'!AB26="","",'Model inputs'!AB26),IF('Model inputs'!V12="","",'Model inputs'!V12))="",0,IF(IF(IF(ISERROR('Model inputs'!W16=1),'Model inputs'!W16=1,IF('Model inputs'!W16="","",'Model inputs'!W16=1))="",FALSE,IF(ISERROR('Model inputs'!W16=1),'Model inputs'!W16=1,IF('Model inputs'!W16="","",'Model inputs'!W16=1))),IF('Model inputs'!AB26="","",'Model inputs'!AB26),IF('Model inputs'!V12="","",'Model inputs'!V12)))+'Model inputs'!W18 -> -8132.12 | X12: =IF(IF(IF(IF(ISERROR('Model inputs'!X16=1),'Model inputs'!X16=1,IF('Model inputs'!X16="","",'Model inputs'!X16=1))="",FALSE,IF(ISERROR('Model inputs'!X16=1),'Model inputs'!X16=1,IF('Model inputs'!X16="","",'Model inputs'!X16=1))),IF('Model inputs'!AB26="","",'Model inputs'!AB26),IF('Model inputs'!W12="","",'Model inputs'!W12))="",0,IF(IF(IF(ISERROR('Model inputs'!X16=1),'Model inputs'!X16=1,IF('Model inputs'!X16="","",'Model inputs'!X16=1))="",FALSE,IF(ISERROR('Model inputs'!X16=1),'Model inputs'!X16=1,IF('Model inputs'!X16="","",'Model inputs'!X16=1))),IF('Model inputs'!AB26="","",'Model inputs'!AB26),IF('Model inputs'!W12="","",'Model inputs'!W12)))+'Model inputs'!X18 -> -8368.6 | Y12: =IF(IF(IF(IF(ISERROR('Model inputs'!Y16=1),'Model inputs'!Y16=1,IF('Model inputs'!Y16="","",'Model inputs'!Y16=1))="",FALSE,IF(ISERROR('Model inputs'!Y16=1),'Model inputs'!Y16=1,IF('Model inputs'!Y16="","",'Model inputs'!Y16=1))),IF('Model inputs'!AB26="","",'Model inputs'!AB26),IF('Model inputs'!X12="","",'Model inputs'!X12))="",0,IF(IF(IF(ISERROR('Model inputs'!Y16=1),'Model inputs'!Y16=1,IF('Model inputs'!Y16="","",'Model inputs'!Y16=1))="",FALSE,IF(ISERROR('Model inputs'!Y16=1),'Model inputs'!Y16=1,IF('Model inputs'!Y16="","",'Model inputs'!Y16=1))),IF('Model inputs'!AB26="","",'Model inputs'!AB26),IF('Model inputs'!X12="","",'Model inputs'!X12)))+'Model inputs'!Y18 -> -8531.56 | Z12: 0 | AA12: =IF(IF(IF(IF(ISERROR('Model inputs'!AA16=1),'Model inputs'!AA16=1,IF('Model inputs'!AA16="","",'Model inputs'!AA16=1))="",FALSE,IF(ISERROR('Model inputs'!AA16=1),'Model inputs'!AA16=1,IF('Model inputs'!AA16="","",'Model inputs'!AA16=1))),IF('Model inputs'!AB26="","",'Model inputs'!AB26),IF('Model inputs'!Z12="","",'Model inputs'!Z12))="",0,IF(IF(IF(ISERROR('Model inputs'!AA16=1),'Model inputs'!AA16=1,IF('Model inputs'!AA16="","",'Model inputs'!AA16=1))="",FALSE,IF(ISERROR('Model inputs'!AA16=1),'Model inputs'!AA16=1,IF('Model inputs'!AA16="","",'Model inputs'!AA16=1))),IF('Model inputs'!AB26="","",'Model inputs'!AB26),IF('Model inputs'!Z12="","",'Model inputs'!Z12)))+'Model inputs'!AA18 -> 0
A13: Ending cash · Growth | B13: =IF(IF(IF(IF(ISERROR('Model inputs'!B17=1),'Model inputs'!B17=1,IF('Model inputs'!B17="","",'Model inputs'!B17=1))="",FALSE,IF(ISERROR('Model inputs'!B17=1),'Model inputs'!B17=1,IF('Model inputs'!B17="","",'Model inputs'!B17=1))),IF('Model inputs'!AB27="","",'Model inputs'!AB27),IF('Model inputs'!AA13="","",'Model inputs'!AA13))="",0,IF(IF(IF(ISERROR('Model inputs'!B17=1),'Model inputs'!B17=1,IF('Model inputs'!B17="","",'Model inputs'!B17=1))="",FALSE,IF(ISERROR('Model inputs'!B17=1),'Model inputs'!B17=1,IF('Model inputs'!B17="","",'Model inputs'!B17=1))),IF('Model inputs'!AB27="","",'Model inputs'!AB27),IF('Model inputs'!AA13="","",'Model inputs'!AA13)))+'Model inputs'!B19 -> 22884.8 | C13: =IF(IF(IF(IF(ISERROR('Model inputs'!C17=1),'Model inputs'!C17=1,IF('Model inputs'!C17="","",'Model inputs'!C17=1))="",FALSE,IF(ISERROR('Model inputs'!C17=1),'Model inputs'!C17=1,IF('Model inputs'!C17="","",'Model inputs'!C17=1))),IF('Model inputs'!AB27="","",'Model inputs'!AB27),IF('Model inputs'!B13="","",'Model inputs'!B13))="",0,IF(IF(IF(ISERROR('Model inputs'!C17=1),'Model inputs'!C17=1,IF('Model inputs'!C17="","",'Model inputs'!C17=1))="",FALSE,IF(ISERROR('Model inputs'!C17=1),'Model inputs'!C17=1,IF('Model inputs'!C17="","",'Model inputs'!C17=1))),IF('Model inputs'!AB27="","",'Model inputs'!AB27),IF('Model inputs'!B13="","",'Model inputs'!B13)))+'Model inputs'!C19 -> 20769.6 | D13: =IF(IF(IF(IF(ISERROR('Model inputs'!D17=1),'Model inputs'!D17=1,IF('Model inputs'!D17="","",'Model inputs'!D17=1))="",FALSE,IF(ISERROR('Model inputs'!D17=1),'Model inputs'!D17=1,IF('Model inputs'!D17="","",'Model inputs'!D17=1))),IF('Model inputs'!AB27="","",'Model inputs'!AB27),IF('Model inputs'!C13="","",'Model inputs'!C13))="",0,IF(IF(IF(ISERROR('Model inputs'!D17=1),'Model inputs'!D17=1,IF('Model inputs'!D17="","",'Model inputs'!D17=1))="",FALSE,IF(ISERROR('Model inputs'!D17=1),'Model inputs'!D17=1,IF('Model inputs'!D17="","",'Model inputs'!D17=1))),IF('Model inputs'!AB27="","",'Model inputs'!AB27),IF('Model inputs'!C13="","",'Model inputs'!C13)))+'Model inputs'!D19 -> 18654.4 | E13: =IF(IF(IF(IF(ISERROR('Model inputs'!E17=1),'Model inputs'!E17=1,IF('Model inputs'!E17="","",'Model inputs'!E17=1))="",FALSE,IF(ISERROR('Model inputs'!E17=1),'Model inputs'!E17=1,IF('Model inputs'!E17="","",'Model inputs'!E17=1))),IF('Model inputs'!AB27="","",'Model inputs'!AB27),IF('Model inputs'!D13="","",'Model inputs'!D13))="",0,IF(IF(IF(ISERROR('Model inputs'!E17=1),'Model inputs'!E17=1,IF('Model inputs'!E17="","",'Model inputs'!E17=1))="",FALSE,IF(ISERROR('Model inputs'!E17=1),'Model inputs'!E17=1,IF('Model inputs'!E17="","",'Model inputs'!E17=1))),IF('Model inputs'!AB27="","",'Model inputs'!AB27),IF('Model inputs'!D13="","",'Model inputs'!D13)))+'Model inputs'!E19 -> 17033.696 | F13: =IF(IF(IF(IF(ISERROR('Model inputs'!F17=1),'Model inputs'!F17=1,IF('Model inputs'!F17="","",'Model inputs'!F17=1))="",FALSE,IF(ISERROR('Model inputs'!F17=1),'Model inputs'!F17=1,IF('Model inputs'!F17="","",'Model inputs'!F17=1))),IF('Model inputs'!AB27="","",'Model inputs'!AB27),IF('Model inputs'!E13="","",'Model inputs'!E13))="",0,IF(IF(IF(ISERROR('Model inputs'!F17=1),'Model inputs'!F17=1,IF('Model inputs'!F17="","",'Model inputs'!F17=1))="",FALSE,IF(ISERROR('Model inputs'!F17=1),'Model inputs'!F17=1,IF('Model inputs'!F17="","",'Model inputs'!F17=1))),IF('Model inputs'!AB27="","",'Model inputs'!AB27),IF('Model inputs'!E13="","",'Model inputs'!E13)))+'Model inputs'!F19 -> 15708.24 | G13: =IF(IF(IF(IF(ISERROR('Model inputs'!G17=1),'Model inputs'!G17=1,IF('Model inputs'!G17="","",'Model inputs'!G17=1))="",FALSE,IF(ISERROR('Model inputs'!G17=1),'Model inputs'!G17=1,IF('Model inputs'!G17="","",'Model inputs'!G17=1))),IF('Model inputs'!AB27="","",'Model inputs'!AB27),IF('Model inputs'!F13="","",'Model inputs'!F13))="",0,IF(IF(IF(ISERROR('Model inputs'!G17=1),'Model inputs'!G17=1,IF('Model inputs'!G17="","",'Model inputs'!G17=1))="",FALSE,IF(ISERROR('Model inputs'!G17=1),'Model inputs'!G17=1,IF('Model inputs'!G17="","",'Model inputs'!G17=1))),IF('Model inputs'!AB27="","",'Model inputs'!AB27),IF('Model inputs'!F13="","",'Model inputs'!F13)))+'Model inputs'!G19 -> 14877.28 | H13: =IF(IF(IF(IF(ISERROR('Model inputs'!H17=1),'Model inputs'!H17=1,IF('Model inputs'!H17="","",'Model inputs'!H17=1))="",FALSE,IF(ISERROR('Model inputs'!H17=1),'Model inputs'!H17=1,IF('Model inputs'!H17="","",'Model inputs'!H17=1))),IF('Model inputs'!AB27="","",'Model inputs'!AB27),IF('Model inputs'!G13="","",'Model inputs'!G13))="",0,IF(IF(IF(ISERROR('Model inputs'!H17=1),'Model inputs'!H17=1,IF('Model inputs'!H17="","",'Model inputs'!H17=1))="",FALSE,IF(ISERROR('Model inputs'!H17=1),'Model inputs'!H17=1,IF('Model inputs'!H17="","",'Model inputs'!H17=1))),IF('Model inputs'!AB27="","",'Model inputs'!AB27),IF('Model inputs'!G13="","",'Model inputs'!G13)))+'Model inputs'!H19 -> 14614.628 | I13: =IF(IF(IF(IF(ISERROR('Model inputs'!I17=1),'Model inputs'!I17=1,IF('Model inputs'!I17="","",'Model inputs'!I17=1))="",FALSE,IF(ISERROR('Model inputs'!I17=1),'Model inputs'!I17=1,IF('Model inputs'!I17="","",'Model inputs'!I17=1))),IF('Model inputs'!AB27="","",'Model inputs'!AB27),IF('Model inputs'!H13="","",'Model inputs'!H13))="",0,IF(IF(IF(ISERROR('Model inputs'!I17=1),'Model inputs'!I17=1,IF('Model inputs'!I17="","",'Model inputs'!I17=1))="",FALSE,IF(ISERROR('Model inputs'!I17=1),'Model inputs'!I17=1,IF('Model inputs'!I17="","",'Model inputs'!I17=1))),IF('Model inputs'!AB27="","",'Model inputs'!AB27),IF('Model inputs'!H13="","",'Model inputs'!H13)))+'Model inputs'!I19 -> 14920.284 | J13: =IF(IF(IF(IF(ISERROR('Model inputs'!J17=1),'Model inputs'!J17=1,IF('Model inputs'!J17="","",'Model inputs'!J17=1))="",FALSE,IF(ISERROR('Model inputs'!J17=1),'Model inputs'!J17=1,IF('Model inputs'!J17="","",'Model inputs'!J17=1))),IF('Model inputs'!AB27="","",'Model inputs'!AB27),IF('Model inputs'!I13="","",'Model inputs'!I13))="",0,IF(IF(IF(ISERROR('Model inputs'!J17=1),'Model inputs'!J17=1,IF('Model inputs'!J17="","",'Model inputs'!J17=1))="",FALSE,IF(ISERROR('Model inputs'!J17=1),'Model inputs'!J17=1,IF('Model inputs'!J17="","",'Model inputs'!J17=1))),IF('Model inputs'!AB27="","",'Model inputs'!AB27),IF('Model inputs'!I13="","",'Model inputs'!I13)))+'Model inputs'!J19 -> 15868.06 | K13: =IF(IF(IF(IF(ISERROR('Model inputs'!K17=1),'Model inputs'!K17=1,IF('Model inputs'!K17="","",'Model inputs'!K17=1))="",FALSE,IF(ISERROR('Model inputs'!K17=1),'Model inputs'!K17=1,IF('Model inputs'!K17="","",'Model inputs'!K17=1))),IF('Model inputs'!AB27="","",'Model inputs'!AB27),IF('Model inputs'!J13="","",'Model inputs'!J13))="",0,IF(IF(IF(ISERROR('Model inputs'!K17=1),'Model inputs'!K17=1,IF('Model inputs'!K17="","",'Model inputs'!K17=1))="",FALSE,IF(ISERROR('Model inputs'!K17=1),'Model inputs'!K17=1,IF('Model inputs'!K17="","",'Model inputs'!K17=1))),IF('Model inputs'!AB27="","",'Model inputs'!AB27),IF('Model inputs'!J13="","",'Model inputs'!J13)))+'Model inputs'!K19 -> 17384.144 | L13: =IF(IF(IF(IF(ISERROR('Model inputs'!L17=1),'Model inputs'!L17=1,IF('Model inputs'!L17="","",'Model inputs'!L17=1))="",FALSE,IF(ISERROR('Model inputs'!L17=1),'Model inputs'!L17=1,IF('Model inputs'!L17="","",'Model inputs'!L17=1))),IF('Model inputs'!AB27="","",'Model inputs'!AB27),IF('Model inputs'!K13="","",'Model inputs'!K13))="",0,IF(IF(IF(ISERROR('Model inputs'!L17=1),'Model inputs'!L17=1,IF('Model inputs'!L17="","",'Model inputs'!L17=1))="",FALSE,IF(ISERROR('Model inputs'!L17=1),'Model inputs'!L17=1,IF('Model inputs'!L17="","",'Model inputs'!L17=1))),IF('Model inputs'!AB27="","",'Model inputs'!AB27),IF('Model inputs'!K13="","",'Model inputs'!K13)))+'Model inputs'!L19 -> 19468.536 | M13: =IF(IF(IF(IF(ISERROR('Model inputs'!M17=1),'Model inputs'!M17=1,IF('Model inputs'!M17="","",'Model inputs'!M17=1))="",FALSE,IF(ISERROR('Model inputs'!M17=1),'Model inputs'!M17=1,IF('Model inputs'!M17="","",'Model inputs'!M17=1))),IF('Model inputs'!AB27="","",'Model inputs'!AB27),IF('Model inputs'!L13="","",'Model inputs'!L13))="",0,IF(IF(IF(ISERROR('Model inputs'!M17=1),'Model inputs'!M17=1,IF('Model inputs'!M17="","",'Model inputs'!M17=1))="",FALSE,IF(ISERROR('Model inputs'!M17=1),'Model inputs'!M17=1,IF('Model inputs'!M17="","",'Model inputs'!M17=1))),IF('Model inputs'!AB27="","",'Model inputs'!AB27),IF('Model inputs'!L13="","",'Model inputs'!L13)))+'Model inputs'!M19 -> 22121.236 | N13: =IF(IF(IF(IF(ISERROR('Model inputs'!N17=1),'Model inputs'!N17=1,IF('Model inputs'!N17="","",'Model inputs'!N17=1))="",FALSE,IF(ISERROR('Model inputs'!N17=1),'Model inputs'!N17=1,IF('Model inputs'!N17="","",'Model inputs'!N17=1))),IF('Model inputs'!AB27="","",'Model inputs'!AB27),IF('Model inputs'!M13="","",'Model inputs'!M13))="",0,IF(IF(IF(ISERROR('Model inputs'!N17=1),'Model inputs'!N17=1,IF('Model inputs'!N17="","",'Model inputs'!N17=1))="",FALSE,IF(ISERROR('Model inputs'!N17=1),'Model inputs'!N17=1,IF('Model inputs'!N17="","",'Model inputs'!N17=1))),IF('Model inputs'!AB27="","",'Model inputs'!AB27),IF('Model inputs'!M13="","",'Model inputs'!M13)))+'Model inputs'!N19 -> 25416.056 | O13: =IF(IF(IF(IF(ISERROR('Model inputs'!O17=1),'Model inputs'!O17=1,IF('Model inputs'!O17="","",'Model inputs'!O17=1))="",FALSE,IF(ISERROR('Model inputs'!O17=1),'Model inputs'!O17=1,IF('Model inputs'!O17="","",'Model inputs'!O17=1))),IF('Model inputs'!AB27="","",'Model inputs'!AB27),IF('Model inputs'!N13="","",'Model inputs'!N13))="",0,IF(IF(IF(ISERROR('Model inputs'!O17=1),'Model inputs'!O17=1,IF('Model inputs'!O17="","",'Model inputs'!O17=1))="",FALSE,IF(ISERROR('Model inputs'!O17=1),'Model inputs'!O17=1,IF('Model inputs'!O17="","",'Model inputs'!O17=1))),IF('Model inputs'!AB27="","",'Model inputs'!AB27),IF('Model inputs'!N13="","",'Model inputs'!N13)))+'Model inputs'!O19 -> 29699.868 | P13: =IF(IF(IF(IF(ISERROR('Model inputs'!P17=1),'Model inputs'!P17=1,IF('Model inputs'!P17="","",'Model inputs'!P17=1))="",FALSE,IF(ISERROR('Model inputs'!P17=1),'Model inputs'!P17=1,IF('Model inputs'!P17="","",'Model inputs'!P17=1))),IF('Model inputs'!AB27="","",'Model inputs'!AB27),IF('Model inputs'!O13="","",'Model inputs'!O13))="",0,IF(IF(IF(ISERROR('Model inputs'!P17=1),'Model inputs'!P17=1,IF('Model inputs'!P17="","",'Model inputs'!P17=1))="",FALSE,IF(ISERROR('Model inputs'!P17=1),'Model inputs'!P17=1,IF('Model inputs'!P17="","",'Model inputs'!P17=1))),IF('Model inputs'!AB27="","",'Model inputs'!AB27),IF('Model inputs'!O13="","",'Model inputs'!O13)))+'Model inputs'!P19 -> 34625.8 | Q13: =IF(IF(IF(IF(ISERROR('Model inputs'!Q17=1),'Model inputs'!Q17=1,IF('Model inputs'!Q17="","",'Model inputs'!Q17=1))="",FALSE,IF(ISERROR('Model inputs'!Q17=1),'Model inputs'!Q17=1,IF('Model inputs'!Q17="","",'Model inputs'!Q17=1))),IF('Model inputs'!AB27="","",'Model inputs'!AB27),IF('Model inputs'!P13="","",'Model inputs'!P13))="",0,IF(IF(IF(ISERROR('Model inputs'!Q17=1),'Model inputs'!Q17=1,IF('Model inputs'!Q17="","",'Model inputs'!Q17=1))="",FALSE,IF(ISERROR('Model inputs'!Q17=1),'Model inputs'!Q17=1,IF('Model inputs'!Q17="","",'Model inputs'!Q17=1))),IF('Model inputs'!AB27="","",'Model inputs'!AB27),IF('Model inputs'!P13="","",'Model inputs'!P13)))+'Model inputs'!Q19 -> 40540.724 | R13: =IF(IF(IF(IF(ISERROR('Model inputs'!R17=1),'Model inputs'!R17=1,IF('Model inputs'!R17="","",'Model inputs'!R17=1))="",FALSE,IF(ISERROR('Model inputs'!R17=1),'Model inputs'!R17=1,IF('Model inputs'!R17="","",'Model inputs'!R17=1))),IF('Model inputs'!AB27="","",'Model inputs'!AB27),IF('Model inputs'!Q13="","",'Model inputs'!Q13))="",0,IF(IF(IF(ISERROR('Model inputs'!R17=1),'Model inputs'!R17=1,IF('Model inputs'!R17="","",'Model inputs'!R17=1))="",FALSE,IF(ISERROR('Model inputs'!R17=1),'Model inputs'!R17=1,IF('Model inputs'!R17="","",'Model inputs'!R17=1))),IF('Model inputs'!AB27="","",'Model inputs'!AB27),IF('Model inputs'!Q13="","",'Model inputs'!Q13)))+'Model inputs'!R19 -> 47097.768 | S13: =IF(IF(IF(IF(ISERROR('Model inputs'!S17=1),'Model inputs'!S17=1,IF('Model inputs'!S17="","",'Model inputs'!S17=1))="",FALSE,IF(ISERROR('Model inputs'!S17=1),'Model inputs'!S17=1,IF('Model inputs'!S17="","",'Model inputs'!S17=1))),IF('Model inputs'!AB27="","",'Model inputs'!AB27),IF('Model inputs'!R13="","",'Model inputs'!R13))="",0,IF(IF(IF(ISERROR('Model inputs'!S17=1),'Model inputs'!S17=1,IF('Model inputs'!S17="","",'Model inputs'!S17=1))="",FALSE,IF(ISERROR('Model inputs'!S17=1),'Model inputs'!S17=1,IF('Model inputs'!S17="","",'Model inputs'!S17=1))),IF('Model inputs'!AB27="","",'Model inputs'!AB27),IF('Model inputs'!R13="","",'Model inputs'!R13)))+'Model inputs'!S19 -> 54643.804 | T13: =IF(IF(IF(IF(ISERROR('Model inputs'!T17=1),'Model inputs'!T17=1,IF('Model inputs'!T17="","",'Model inputs'!T17=1))="",FALSE,IF(ISERROR('Model inputs'!T17=1),'Model inputs'!T17=1,IF('Model inputs'!T17="","",'Model inputs'!T17=1))),IF('Model inputs'!AB27="","",'Model inputs'!AB27),IF('Model inputs'!S13="","",'Model inputs'!S13))="",0,IF(IF(IF(ISERROR('Model inputs'!T17=1),'Model inputs'!T17=1,IF('Model inputs'!T17="","",'Model inputs'!T17=1))="",FALSE,IF(ISERROR('Model inputs'!T17=1),'Model inputs'!T17=1,IF('Model inputs'!T17="","",'Model inputs'!T17=1))),IF('Model inputs'!AB27="","",'Model inputs'!AB27),IF('Model inputs'!S13="","",'Model inputs'!S13)))+'Model inputs'!T19 -> 62831.96 | U13: =IF(IF(IF(IF(ISERROR('Model inputs'!U17=1),'Model inputs'!U17=1,IF('Model inputs'!U17="","",'Model inputs'!U17=1))="",FALSE,IF(ISERROR('Model inputs'!U17=1),'Model inputs'!U17=1,IF('Model inputs'!U17="","",'Model inputs'!U17=1))),IF('Model inputs'!AB27="","",'Model inputs'!AB27),IF('Model inputs'!T13="","",'Model inputs'!T13))="",0,IF(IF(IF(ISERROR('Model inputs'!U17=1),'Model inputs'!U17=1,IF('Model inputs'!U17="","",'Model inputs'!U17=1))="",FALSE,IF(ISERROR('Model inputs'!U17=1),'Model inputs'!U17=1,IF('Model inputs'!U17="","",'Model inputs'!U17=1))),IF('Model inputs'!AB27="","",'Model inputs'!AB27),IF('Model inputs'!T13="","",'Model inputs'!T13)))+'Model inputs'!U19 -> 71662.236 | V13: =IF(IF(IF(IF(ISERROR('Model inputs'!V17=1),'Model inputs'!V17=1,IF('Model inputs'!V17="","",'Model inputs'!V17=1))="",FALSE,IF(ISERROR('Model inputs'!V17=1),'Model inputs'!V17=1,IF('Model inputs'!V17="","",'Model inputs'!V17=1))),IF('Model inputs'!AB27="","",'Model inputs'!AB27),IF('Model inputs'!U13="","",'Model inputs'!U13))="",0,IF(IF(IF(ISERROR('Model inputs'!V17=1),'Model inputs'!V17=1,IF('Model inputs'!V17="","",'Model inputs'!V17=1))="",FALSE,IF(ISERROR('Model inputs'!V17=1),'Model inputs'!V17=1,IF('Model inputs'!V17="","",'Model inputs'!V17=1))),IF('Model inputs'!AB27="","",'Model inputs'!AB27),IF('Model inputs'!U13="","",'Model inputs'!U13)))+'Model inputs'!V19 -> 81481.504 | W13: =IF(IF(IF(IF(ISERROR('Model inputs'!W17=1),'Model inputs'!W17=1,IF('Model inputs'!W17="","",'Model inputs'!W17=1))="",FALSE,IF(ISERROR('Model inputs'!W17=1),'Model inputs'!W17=1,IF('Model inputs'!W17="","",'Model inputs'!W17=1))),IF('Model inputs'!AB27="","",'Model inputs'!AB27),IF('Model inputs'!V13="","",'Model inputs'!V13))="",0,IF(IF(IF(ISERROR('Model inputs'!W17=1),'Model inputs'!W17=1,IF('Model inputs'!W17="","",'Model inputs'!W17=1))="",FALSE,IF(ISERROR('Model inputs'!W17=1),'Model inputs'!W17=1,IF('Model inputs'!W17="","",'Model inputs'!W17=1))),IF('Model inputs'!AB27="","",'Model inputs'!AB27),IF('Model inputs'!V13="","",'Model inputs'!V13)))+'Model inputs'!W19 -> 91942.892 | X13: =IF(IF(IF(IF(ISERROR('Model inputs'!X17=1),'Model inputs'!X17=1,IF('Model inputs'!X17="","",'Model inputs'!X17=1))="",FALSE,IF(ISERROR('Model inputs'!X17=1),'Model inputs'!X17=1,IF('Model inputs'!X17="","",'Model inputs'!X17=1))),IF('Model inputs'!AB27="","",'Model inputs'!AB27),IF('Model inputs'!W13="","",'Model inputs'!W13))="",0,IF(IF(IF(ISERROR('Model inputs'!X17=1),'Model inputs'!X17=1,IF('Model inputs'!X17="","",'Model inputs'!X17=1))="",FALSE,IF(ISERROR('Model inputs'!X17=1),'Model inputs'!X17=1,IF('Model inputs'!X17="","",'Model inputs'!X17=1))),IF('Model inputs'!AB27="","",'Model inputs'!AB27),IF('Model inputs'!W13="","",'Model inputs'!W13)))+'Model inputs'!X19 -> 103393.27 | Y13: =IF(IF(IF(IF(ISERROR('Model inputs'!Y17=1),'Model inputs'!Y17=1,IF('Model inputs'!Y17="","",'Model inputs'!Y17=1))="",FALSE,IF(ISERROR('Model inputs'!Y17=1),'Model inputs'!Y17=1,IF('Model inputs'!Y17="","",'Model inputs'!Y17=1))),IF('Model inputs'!AB27="","",'Model inputs'!AB27),IF('Model inputs'!X13="","",'Model inputs'!X13))="",0,IF(IF(IF(ISERROR('Model inputs'!Y17=1),'Model inputs'!Y17=1,IF('Model inputs'!Y17="","",'Model inputs'!Y17=1))="",FALSE,IF(ISERROR('Model inputs'!Y17=1),'Model inputs'!Y17=1,IF('Model inputs'!Y17="","",'Model inputs'!Y17=1))),IF('Model inputs'!AB27="","",'Model inputs'!AB27),IF('Model inputs'!X13="","",'Model inputs'!X13)))+'Model inputs'!Y19 -> 115485.77 | Z13: 0 | AA13: =IF(IF(IF(IF(ISERROR('Model inputs'!AA17=1),'Model inputs'!AA17=1,IF('Model inputs'!AA17="","",'Model inputs'!AA17=1))="",FALSE,IF(ISERROR('Model inputs'!AA17=1),'Model inputs'!AA17=1,IF('Model inputs'!AA17="","",'Model inputs'!AA17=1))),IF('Model inputs'!AB27="","",'Model inputs'!AB27),IF('Model inputs'!Z13="","",'Model inputs'!Z13))="",0,IF(IF(IF(ISERROR('Model inputs'!AA17=1),'Model inputs'!AA17=1,IF('Model inputs'!AA17="","",'Model inputs'!AA17=1))="",FALSE,IF(ISERROR('Model inputs'!AA17=1),'Model inputs'!AA17=1,IF('Model inputs'!AA17="","",'Model inputs'!AA17=1))),IF('Model inputs'!AB27="","",'Model inputs'!AB27),IF('Model inputs'!Z13="","",'Model inputs'!Z13)))+'Model inputs'!AA19 -> 0
A14: Gross profit · Downside | B14: ='Model inputs'!B20-'Model inputs'!B28 -> -15.2 | C14: ='Model inputs'!C20-'Model inputs'!C28 -> -15.2 | D14: ='Model inputs'!D20-'Model inputs'!D28 -> -15.2 | E14: ='Model inputs'!E20-'Model inputs'!E28 -> -15.2 | F14: ='Model inputs'!F20-'Model inputs'!F28 -> -15.2 | G14: ='Model inputs'!G20-'Model inputs'!G28 -> -15.2 | H14: ='Model inputs'!H20-'Model inputs'!H28 -> 58.32 | I14: ='Model inputs'!I20-'Model inputs'!I28 -> 182.88 | ... Y14: ='Model inputs'!Y20-'Model inputs'!Y28 -> 1937.04 | Z14: 0 | AA14: ='Model inputs'!AA64-'Model inputs'!AA28 -> 0
A15: Gross profit · Growth | B15: ='Model inputs'!B23-'Model inputs'!B29 -> -15.2 | C15: ='Model inputs'!C23-'Model inputs'!C29 -> -15.2 | D15: ='Model inputs'!D23-'Model inputs'!D29 -> -15.2 | E15: ='Model inputs'!E23-'Model inputs'!E29 -> 479.296 | F15: ='Model inputs'!F23-'Model inputs'!F29 -> 774.544 | G15: ='Model inputs'!G23-'Model inputs'!G29 -> 1269.04 | H15: ='Model inputs'!H23-'Model inputs'!H29 -> 1837.348 | I15: ='Model inputs'!I23-'Model inputs'!I29 -> 2405.656 | ... Y15: ='Model inputs'!Y23-'Model inputs'!Y29 -> 14192.5 | Z15: 0 | AA15: ='Model inputs'!AA67-'Model inputs'!AA29 -> 0
A16: Model month · Downside | B16: =IFERROR(DATEDIF(DATE(2026,11,1),DATE(2026,11,1),"M")+1,0) -> 1 | C16: =IFERROR(DATEDIF(DATE(2026,11,1),DATE(2026,12,1),"M")+1,0) -> 2 | D16: =IFERROR(DATEDIF(DATE(2026,11,1),DATE(2027,1,1),"M")+1,0) -> 3 | E16: =IFERROR(DATEDIF(DATE(2026,11,1),DATE(2027,2,1),"M")+1,0) -> 4 | F16: =IFERROR(DATEDIF(DATE(2026,11,1),DATE(2027,3,1),"M")+1,0) -> 5 | G16: =IFERROR(DATEDIF(DATE(2026,11,1),DATE(2027,4,1),"M")+1,0) -> 6 | H16: =IFERROR(DATEDIF(DATE(2026,11,1),DATE(2027,5,1),"M")+1,0) -> 7 | I16: =IFERROR(DATEDIF(DATE(2026,11,1),DATE(2027,6,1),"M")+1,0) -> 8 | J16: =IFERROR(DATEDIF(DATE(2026,11,1),DATE(2027,7,1),"M")+1,0) -> 9 | K16: =IFERROR(DATEDIF(DATE(2026,11,1),DATE(2027,8,1),"M")+1,0) -> 10 | L16: =IFERROR(DATEDIF(DATE(2026,11,1),DATE(2027,9,1),"M")+1,0) -> 11 | M16: =IFERROR(DATEDIF(DATE(2026,11,1),DATE(2027,10,1),"M")+1,0) -> 12 | N16: =IFERROR(DATEDIF(DATE(2026,11,1),DATE(2027,11,1),"M")+1,0) -> 13 | O16: =IFERROR(DATEDIF(DATE(2026,11,1),DATE(2027,12,1),"M")+1,0) -> 14 | P16: =IFERROR(DATEDIF(DATE(2026,11,1),DATE(2028,1,1),"M")+1,0) -> 15 | Q16: =IFERROR(DATEDIF(DATE(2026,11,1),DATE(2028,2,1),"M")+1,0) -> 16 | R16: =IFERROR(DATEDIF(DATE(2026,11,1),DATE(2028,3,1),"M")+1,0) -> 17 | S16: =IFERROR(DATEDIF(DATE(2026,11,1),DATE(2028,4,1),"M")+1,0) -> 18 | T16: =IFERROR(DATEDIF(DATE(2026,11,1),DATE(2028,5,1),"M")+1,0) -> 19 | U16: =IFERROR(DATEDIF(DATE(2026,11,1),DATE(2028,6,1),"M")+1,0) -> 20 | V16: =IFERROR(DATEDIF(DATE(2026,11,1),DATE(2028,7,1),"M")+1,0) -> 21 | W16: =IFERROR(DATEDIF(DATE(2026,11,1),DATE(2028,8,1),"M")+1,0) -> 22 | X16: =IFERROR(DATEDIF(DATE(2026,11,1),DATE(2028,9,1),"M")+1,0) -> 23 | Y16: =IFERROR(DATEDIF(DATE(2026,11,1),DATE(2028,10,1),"M")+1,0) -> 24 | Z16: 0 | AA16: =IFERROR(DATEDIF(DATE(2026,11,1),DATE(2026,10,1),"M")+1,0) -> 0
A17: Model month · Growth | B17: =IFERROR(DATEDIF(DATE(2026,11,1),DATE(2026,11,1),"M")+1,0) -> 1 | C17: =IFERROR(DATEDIF(DATE(2026,11,1),DATE(2026,12,1),"M")+1,0) -> 2 | D17: =IFERROR(DATEDIF(DATE(2026,11,1),DATE(2027,1,1),"M")+1,0) -> 3 | E17: =IFERROR(DATEDIF(DATE(2026,11,1),DATE(2027,2,1),"M")+1,0) -> 4 | F17: =IFERROR(DATEDIF(DATE(2026,11,1),DATE(2027,3,1),"M")+1,0) -> 5 | G17: =IFERROR(DATEDIF(DATE(2026,11,1),DATE(2027,4,1),"M")+1,0) -> 6 | H17: =IFERROR(DATEDIF(DATE(2026,11,1),DATE(2027,5,1),"M")+1,0) -> 7 | I17: =IFERROR(DATEDIF(DATE(2026,11,1),DATE(2027,6,1),"M")+1,0) -> 8 | J17: =IFERROR(DATEDIF(DATE(2026,11,1),DATE(2027,7,1),"M")+1,0) -> 9 | K17: =IFERROR(DATEDIF(DATE(2026,11,1),DATE(2027,8,1),"M")+1,0) -> 10 | L17: =IFERROR(DATEDIF(DATE(2026,11,1),DATE(2027,9,1),"M")+1,0) -> 11 | M17: =IFERROR(DATEDIF(DATE(2026,11,1),DATE(2027,10,1),"M")+1,0) -> 12 | N17: =IFERROR(DATEDIF(DATE(2026,11,1),DATE(2027,11,1),"M")+1,0) -> 13 | O17: =IFERROR(DATEDIF(DATE(2026,11,1),DATE(2027,12,1),"M")+1,0) -> 14 | P17: =IFERROR(DATEDIF(DATE(2026,11,1),DATE(2028,1,1),"M")+1,0) -> 15 | Q17: =IFERROR(DATEDIF(DATE(2026,11,1),DATE(2028,2,1),"M")+1,0) -> 16 | R17: =IFERROR(DATEDIF(DATE(2026,11,1),DATE(2028,3,1),"M")+1,0) -> 17 | S17: =IFERROR(DATEDIF(DATE(2026,11,1),DATE(2028,4,1),"M")+1,0) -> 18 | T17: =IFERROR(DATEDIF(DATE(2026,11,1),DATE(2028,5,1),"M")+1,0) -> 19 | U17: =IFERROR(DATEDIF(DATE(2026,11,1),DATE(2028,6,1),"M")+1,0) -> 20 | V17: =IFERROR(DATEDIF(DATE(2026,11,1),DATE(2028,7,1),"M")+1,0) -> 21 | W17: =IFERROR(DATEDIF(DATE(2026,11,1),DATE(2028,8,1),"M")+1,0) -> 22 | X17: =IFERROR(DATEDIF(DATE(2026,11,1),DATE(2028,9,1),"M")+1,0) -> 23 | Y17: =IFERROR(DATEDIF(DATE(2026,11,1),DATE(2028,10,1),"M")+1,0) -> 24 | Z17: 0 | AA17: =IFERROR(DATEDIF(DATE(2026,11,1),DATE(2026,10,1),"M")+1,0) -> 0
A18: Net cash flow · Downside | B18: ='Model inputs'!B14-'Model inputs'!B62 -> -2115.2 | C18: ='Model inputs'!C14-'Model inputs'!C62 -> -2115.2 | D18: ='Model inputs'!D14-'Model inputs'!D62 -> -2115.2 | E18: ='Model inputs'!E14-'Model inputs'!E62 -> -2115.2 | F18: ='Model inputs'!F14-'Model inputs'!F62 -> -2115.2 | G18: ='Model inputs'!G14-'Model inputs'!G62 -> -2115.2 | H18: ='Model inputs'!H14-'Model inputs'!H62 -> -2041.68 | I18: ='Model inputs'!I14-'Model inputs'!I62 -> -1917.12 | ... Y18: ='Model inputs'!Y14-'Model inputs'!Y62 -> -162.96 | Z18: 0 | AA18: ='Model inputs'!AA14-'Model inputs'!AA62 -> 0
A19: Net cash flow · Growth | B19: ='Model inputs'!B15-'Model inputs'!B63 -> -2115.2 | C19: ='Model inputs'!C15-'Model inputs'!C63 -> -2115.2 | D19: ='Model inputs'!D15-'Model inputs'!D63 -> -2115.2 | E19: ='Model inputs'!E15-'Model inputs'!E63 -> -1620.704 | F19: ='Model inputs'!F15-'Model inputs'!F63 -> -1325.456 | G19: ='Model inputs'!G15-'Model inputs'!G63 -> -830.96 | H19: ='Model inputs'!H15-'Model inputs'!H63 -> -262.652 | I19: ='Model inputs'!I15-'Model inputs'!I63 -> 305.656 | ... Y19: ='Model inputs'!Y15-'Model inputs'!Y63 -> 12092.5 | Z19: 0 | AA19: ='Model inputs'!AA15-'Model inputs'!AA63 -> 0
A20: Revenue | B20: =SUM('Model inputs'!B21,'Model inputs'!B22) -> 0 | C20: =SUM('Model inputs'!C21,'Model inputs'!C22) -> 0 | D20: =SUM('Model inputs'!D21,'Model inputs'!D22) -> 0 | E20: =SUM('Model inputs'!E21,'Model inputs'!E22) -> 0 | F20: =SUM('Model inputs'!F21,'Model inputs'!F22) -> 0 | G20: =SUM('Model inputs'!G21,'Model inputs'!G22) -> 0 | H20: =SUM('Model inputs'!H21,'Model inputs'!H22) -> 198 | I20: =SUM('Model inputs'!I21,'Model inputs'!I22) -> 696 | ... Y20: =SUM('Model inputs'!Y21,'Model inputs'!Y22) -> 6558
A21: Revenue > Starter | B21: ='Model inputs'!B7*'Model inputs'!AB71 -> 0 | C21: ='Model inputs'!C7*'Model inputs'!AB71 -> 0 | D21: ='Model inputs'!D7*'Model inputs'!AB71 -> 0 | E21: ='Model inputs'!E7*'Model inputs'!AB71 -> 0 | F21: ='Model inputs'!F7*'Model inputs'!AB71 -> 0 | G21: ='Model inputs'!G7*'Model inputs'!AB71 -> 0 | H21: ='Model inputs'!H7*'Model inputs'!AB71 -> 198 | I21: ='Model inputs'!I7*'Model inputs'!AB71 -> 297 | J21: ='Model inputs'!J7*'Model inputs'!AB71 -> 495 | K21: ='Model inputs'!K7*'Model inputs'!AB71 -> 693 | L21: ='Model inputs'!L7*'Model inputs'!AB71 -> 792 | M21: ='Model inputs'!M7*'Model inputs'!AB71 -> 990 | N21: ='Model inputs'!N7*'Model inputs'!AB71 -> 1188 | O21: ='Model inputs'!O7*'Model inputs'!AB71 -> 1287 | P21: ='Model inputs'!P7*'Model inputs'!AB71 -> 1485 | Q21: ='Model inputs'!Q7*'Model inputs'!AB71 -> 1683 | R21: ='Model inputs'!R7*'Model inputs'!AB71 -> 1881 | S21: ='Model inputs'!S7*'Model inputs'!AB71 -> 2079 | T21: ='Model inputs'!T7*'Model inputs'!AB71 -> 2277 | U21: ='Model inputs'!U7*'Model inputs'!AB71 -> 2475 | V21: ='Model inputs'!V7*'Model inputs'!AB71 -> 2772 | W21: ='Model inputs'!W7*'Model inputs'!AB71 -> 2970 | X21: ='Model inputs'!X7*'Model inputs'!AB71 -> 3168 | Y21: ='Model inputs'!Y7*'Model inputs'!AB71 -> 3366
A22: Revenue > Team | B22: ='Model inputs'!B8*'Model inputs'!AB72 -> 0 | C22: ='Model inputs'!C8*'Model inputs'!AB72 -> 0 | D22: ='Model inputs'!D8*'Model inputs'!AB72 -> 0 | E22: ='Model inputs'!E8*'Model inputs'!AB72 -> 0 | F22: ='Model inputs'!F8*'Model inputs'!AB72 -> 0 | G22: ='Model inputs'!G8*'Model inputs'!AB72 -> 0 | H22: ='Model inputs'!H8*'Model inputs'!AB72 -> 0 | I22: ='Model inputs'!I8*'Model inputs'!AB72 -> 399 | J22: ='Model inputs'!J8*'Model inputs'!AB72 -> 399 | K22: ='Model inputs'!K8*'Model inputs'!AB72 -> 399 | L22: ='Model inputs'!L8*'Model inputs'!AB72 -> 798 | M22: ='Model inputs'!M8*'Model inputs'!AB72 -> 798 | N22: ='Model inputs'!N8*'Model inputs'!AB72 -> 798 | O22: ='Model inputs'!O8*'Model inputs'!AB72 -> 1197 | P22: ='Model inputs'!P8*'Model inputs'!AB72 -> 1197 | Q22: ='Model inputs'!Q8*'Model inputs'!AB72 -> 1596 | R22: ='Model inputs'!R8*'Model inputs'!AB72 -> 1596 | S22: ='Model inputs'!S8*'Model inputs'!AB72 -> 1995 | T22: ='Model inputs'!T8*'Model inputs'!AB72 -> 1995 | U22: ='Model inputs'!U8*'Model inputs'!AB72 -> 2394 | V22: ='Model inputs'!V8*'Model inputs'!AB72 -> 2793 | W22: ='Model inputs'!W8*'Model inputs'!AB72 -> 2793 | X22: ='Model inputs'!X8*'Model inputs'!AB72 -> 3192 | Y22: ='Model inputs'!Y8*'Model inputs'!AB72 -> 3192
A23: Revenue | B23: =SUM('Model inputs'!B24,'Model inputs'!B25) -> 0 | C23: =SUM('Model inputs'!C24,'Model inputs'!C25) -> 0 | D23: =SUM('Model inputs'!D24,'Model inputs'!D25) -> 0 | E23: =SUM('Model inputs'!E24,'Model inputs'!E25) -> 696 | F23: =SUM('Model inputs'!F24,'Model inputs'!F25) -> 1092 | G23: =SUM('Model inputs'!G24,'Model inputs'!G25) -> 1788 | H23: =SUM('Model inputs'!H24,'Model inputs'!H25) -> 2583 | I23: =SUM('Model inputs'!I24,'Model inputs'!I25) -> 3378 | ... Y23: =SUM('Model inputs'!Y24,'Model inputs'!Y25) -> 19875
A24: Revenue > Starter | B24: ='Model inputs'!B10*'Model inputs'!AB74 -> 0 | C24: ='Model inputs'!C10*'Model inputs'!AB74 -> 0 | D24: ='Model inputs'!D10*'Model inputs'!AB74 -> 0 | E24: ='Model inputs'!E10*'Model inputs'!AB74 -> 297 | F24: ='Model inputs'!F10*'Model inputs'!AB74 -> 693 | G24: ='Model inputs'!G10*'Model inputs'!AB74 -> 990 | H24: ='Model inputs'!H10*'Model inputs'!AB74 -> 1386 | I24: ='Model inputs'!I10*'Model inputs'!AB74 -> 1782 | J24: ='Model inputs'!J10*'Model inputs'!AB74 -> 2277 | K24: ='Model inputs'!K10*'Model inputs'!AB74 -> 2673 | L24: ='Model inputs'!L10*'Model inputs'!AB74 -> 3069 | M24: ='Model inputs'!M10*'Model inputs'!AB74 -> 3465 | N24: ='Model inputs'!N10*'Model inputs'!AB74 -> 3960 | O24: ='Model inputs'!O10*'Model inputs'!AB74 -> 4554 | P24: ='Model inputs'!P10*'Model inputs'!AB74 -> 5049 | Q24: ='Model inputs'!Q10*'Model inputs'!AB74 -> 5643 | R24: ='Model inputs'!R10*'Model inputs'!AB74 -> 6138 | S24: ='Model inputs'!S10*'Model inputs'!AB74 -> 6732 | T24: ='Model inputs'!T10*'Model inputs'!AB74 -> 7227 | U24: ='Model inputs'!U10*'Model inputs'!AB74 -> 7722 | V24: ='Model inputs'!V10*'Model inputs'!AB74 -> 8316 | W24: ='Model inputs'!W10*'Model inputs'!AB74 -> 8811 | X24: ='Model inputs'!X10*'Model inputs'!AB74 -> 9405 | Y24: ='Model inputs'!Y10*'Model inputs'!AB74 -> 9900
A25: Revenue > Team | B25: ='Model inputs'!B11*'Model inputs'!AB75 -> 0 | C25: ='Model inputs'!C11*'Model inputs'!AB75 -> 0 | D25: ='Model inputs'!D11*'Model inputs'!AB75 -> 0 | E25: ='Model inputs'!E11*'Model inputs'!AB75 -> 399 | F25: ='Model inputs'!F11*'Model inputs'!AB75 -> 399 | G25: ='Model inputs'!G11*'Model inputs'!AB75 -> 798 | H25: ='Model inputs'!H11*'Model inputs'!AB75 -> 1197 | I25: ='Model inputs'!I11*'Model inputs'!AB75 -> 1596 | J25: ='Model inputs'!J11*'Model inputs'!AB75 -> 1995 | K25: ='Model inputs'!K11*'Model inputs'!AB75 -> 2394 | L25: ='Model inputs'!L11*'Model inputs'!AB75 -> 2793 | M25: ='Model inputs'!M11*'Model inputs'!AB75 -> 3192 | N25: ='Model inputs'!N11*'Model inputs'!AB75 -> 3591 | O25: ='Model inputs'!O11*'Model inputs'!AB75 -> 4389 | P25: ='Model inputs'!P11*'Model inputs'!AB75 -> 4788 | Q25: ='Model inputs'!Q11*'Model inputs'!AB75 -> 5586 | R25: ='Model inputs'!R11*'Model inputs'!AB75 -> 5985 | S25: ='Model inputs'!S11*'Model inputs'!AB75 -> 6783 | T25: ='Model inputs'!T11*'Model inputs'!AB75 -> 7182 | U25: ='Model inputs'!U11*'Model inputs'!AB75 -> 7581 | V25: ='Model inputs'!V11*'Model inputs'!AB75 -> 8379 | W25: ='Model inputs'!W11*'Model inputs'!AB75 -> 8778 | X25: ='Model inputs'!X11*'Model inputs'!AB75 -> 9576 | Y25: ='Model inputs'!Y11*'Model inputs'!AB75 -> 9975
A26: Starting cash · Downside | AB26: =25000 -> 25000
A27: Starting cash · Growth | AB27: =25000 -> 25000
A28: COGS · Downside | B28: ='Model inputs'!B82+'Model inputs'!B76+'Model inputs'!B80 -> 15.2 | C28: ='Model inputs'!C82+'Model inputs'!C76+'Model inputs'!C80 -> 15.2 | D28: ='Model inputs'!D82+'Model inputs'!D76+'Model inputs'!D80 -> 15.2 | E28: ='Model inputs'!E82+'Model inputs'!E76+'Model inputs'!E80 -> 15.2 | F28: ='Model inputs'!F82+'Model inputs'!F76+'Model inputs'!F80 -> 15.2 | G28: ='Model inputs'!G82+'Model inputs'!G76+'Model inputs'!G80 -> 15.2 | H28: ='Model inputs'!H82+'Model inputs'!H76+'Model inputs'!H80 -> 139.68 | I28: ='Model inputs'!I82+'Model inputs'!I76+'Model inputs'!I80 -> 513.12 | ... Y28: ='Model inputs'!Y82+'Model inputs'!Y76+'Model inputs'!Y80 -> 4620.96 | Z28: 0 | AA28: ='Model inputs'!AA82+'Model inputs'!AA76+'Model inputs'!AA80 -> 0
A29: COGS · Growth | B29: ='Model inputs'!B83+'Model inputs'!B77+'Model inputs'!B81 -> 15.2 | C29: ='Model inputs'!C83+'Model inputs'!C77+'Model inputs'!C81 -> 15.2 | D29: ='Model inputs'!D83+'Model inputs'!D77+'Model inputs'!D81 -> 15.2 | E29: ='Model inputs'!E83+'Model inputs'!E77+'Model inputs'!E81 -> 216.704 | F29: ='Model inputs'!F83+'Model inputs'!F77+'Model inputs'!F81 -> 317.456 | G29: ='Model inputs'!G83+'Model inputs'!G77+'Model inputs'!G81 -> 518.96 | H29: ='Model inputs'!H83+'Model inputs'!H77+'Model inputs'!H81 -> 745.652 | I29: ='Model inputs'!I83+'Model inputs'!I77+'Model inputs'!I81 -> 972.344 | ... Y29: ='Model inputs'!Y83+'Model inputs'!Y77+'Model inputs'!Y81 -> 5682.5 | Z29: 0 | AA29: ='Model inputs'!AA83+'Model inputs'!AA77+'Model inputs'!AA81 -> 0
A30: Customers | B30: =IF('Model inputs'!B6="","",'Model inputs'!B6) -> 0 | C30: =IF('Model inputs'!C6="","",'Model inputs'!C6) -> 0 | D30: =IF('Model inputs'!D6="","",'Model inputs'!D6) -> 0 | E30: =IF('Model inputs'!E6="","",'Model inputs'!E6) -> 0 | F30: =IF('Model inputs'!F6="","",'Model inputs'!F6) -> 0 | G30: =IF('Model inputs'!G6="","",'Model inputs'!G6) -> 0 | H30: =IF('Model inputs'!H6="","",'Model inputs'!H6) -> 2 | I30: =IF('Model inputs'!I6="","",'Model inputs'!I6) -> 4 | ... Y30: =IF('Model inputs'!Y6="","",'Model inputs'!Y6) -> 42 | Z30: =SUM('Model inputs'!Z31,'Model inputs'!Z32) -> 0 | AA30: =SUM('Model inputs'!AA31,'Model inputs'!AA32) -> 0
A31: Customers > Starter | B31: =IF('Model inputs'!B7="","",'Model inputs'!B7) -> 0 | C31: =IF('Model inputs'!C7="","",'Model inputs'!C7) -> 0 | D31: =IF('Model inputs'!D7="","",'Model inputs'!D7) -> 0 | E31: =IF('Model inputs'!E7="","",'Model inputs'!E7) -> 0 | F31: =IF('Model inputs'!F7="","",'Model inputs'!F7) -> 0 | G31: =IF('Model inputs'!G7="","",'Model inputs'!G7) -> 0 | H31: =IF('Model inputs'!H7="","",'Model inputs'!H7) -> 2 | I31: =IF('Model inputs'!I7="","",'Model inputs'!I7) -> 3 | ... Y31: =IF('Model inputs'!Y7="","",'Model inputs'!Y7) -> 34 | Z31: =0 -> 0 | AA31: =IF(IF(('Model inputs'!AA16-'Model inputs'!AB60)<1="",FALSE,('Model inputs'!AA16-'Model inputs'!AB60)<1),0,ROUND(IF(IF(('Model inputs'!AA16-'Model inputs'!AB60)<=3="",FALSE,('Model inputs'!AA16-'Model inputs'!AB60)<=3),IF('Model inputs'!AB49="","",'Model inputs'!AB49),IF(IF(('Model inputs'!AA16-'Model inputs'!AB60)<=6="",FALSE,('Model inputs'!AA16-'Model inputs'!AB60)<=6),'Model inputs'!AB49+('Model inputs'!AB55-'Model inputs'!AB49)*(('Model inputs'!AA16-'Model inputs'!AB60)-3)/3,IF(IF(('Model inputs'!AA16-'Model inputs'!AB60)<=12="",FALSE,('Model inputs'!AA16-'Model inputs'!AB60)<=12),'Model inputs'!AB55+('Model inputs'!AB37-'Model inputs'!AB55)*(('Model inputs'!AA16-'Model inputs'!AB60)-6)/6,'Model inputs'!AB37+('Model inputs'!AB43-'Model inputs'!AB37)*(('Model inputs'!AA16-'Model inputs'!AB60)-12)/12))),0)) -> 0
A32: Customers > Team | B32: =IF('Model inputs'!B8="","",'Model inputs'!B8) -> 0 | C32: =IF('Model inputs'!C8="","",'Model inputs'!C8) -> 0 | D32: =IF('Model inputs'!D8="","",'Model inputs'!D8) -> 0 | E32: =IF('Model inputs'!E8="","",'Model inputs'!E8) -> 0 | F32: =IF('Model inputs'!F8="","",'Model inputs'!F8) -> 0 | G32: =IF('Model inputs'!G8="","",'Model inputs'!G8) -> 0 | H32: =IF('Model inputs'!H8="","",'Model inputs'!H8) -> 0 | I32: =IF('Model inputs'!I8="","",'Model inputs'!I8) -> 1 | ... Y32: =IF('Model inputs'!Y8="","",'Model inputs'!Y8) -> 8 | Z32: =0 -> 0 | AA32: =IF(IF(('Model inputs'!AA16-'Model inputs'!AB60)<1="",FALSE,('Model inputs'!AA16-'Model inputs'!AB60)<1),0,ROUND(IF(IF(('Model inputs'!AA16-'Model inputs'!AB60)<=3="",FALSE,('Model inputs'!AA16-'Model inputs'!AB60)<=3),IF('Model inputs'!AB50="","",'Model inputs'!AB50),IF(IF(('Model inputs'!AA16-'Model inputs'!AB60)<=6="",FALSE,('Model inputs'!AA16-'Model inputs'!AB60)<=6),'Model inputs'!AB50+('Model inputs'!AB56-'Model inputs'!AB50)*(('Model inputs'!AA16-'Model inputs'!AB60)-3)/3,IF(IF(('Model inputs'!AA16-'Model inputs'!AB60)<=12="",FALSE,('Model inputs'!AA16-'Model inputs'!AB60)<=12),'Model inputs'!AB56+('Model inputs'!AB38-'Model inputs'!AB56)*(('Model inputs'!AA16-'Model inputs'!AB60)-6)/6,'Model inputs'!AB38+('Model inputs'!AB44-'Model inputs'!AB38)*(('Model inputs'!AA16-'Model inputs'!AB60)-12)/12))),0)) -> 0
A33: Customers | B33: =IF('Model inputs'!B9="","",'Model inputs'!B9) -> 0 | C33: =IF('Model inputs'!C9="","",'Model inputs'!C9) -> 0 | D33: =IF('Model inputs'!D9="","",'Model inputs'!D9) -> 0 | E33: =IF('Model inputs'!E9="","",'Model inputs'!E9) -> 4 | F33: =IF('Model inputs'!F9="","",'Model inputs'!F9) -> 8 | G33: =IF('Model inputs'!G9="","",'Model inputs'!G9) -> 12 | H33: =IF('Model inputs'!H9="","",'Model inputs'!H9) -> 17 | I33: =IF('Model inputs'!I9="","",'Model inputs'!I9) -> 22 | ... Y33: =IF('Model inputs'!Y9="","",'Model inputs'!Y9) -> 125 | Z33: =SUM('Model inputs'!Z34,'Model inputs'!Z35) -> 0 | AA33: =SUM('Model inputs'!AA34,'Model inputs'!AA35) -> 0
A34: Customers > Starter | B34: =IF('Model inputs'!B10="","",'Model inputs'!B10) -> 0 | C34: =IF('Model inputs'!C10="","",'Model inputs'!C10) -> 0 | D34: =IF('Model inputs'!D10="","",'Model inputs'!D10) -> 0 | E34: =IF('Model inputs'!E10="","",'Model inputs'!E10) -> 3 | F34: =IF('Model inputs'!F10="","",'Model inputs'!F10) -> 7 | G34: =IF('Model inputs'!G10="","",'Model inputs'!G10) -> 10 | H34: =IF('Model inputs'!H10="","",'Model inputs'!H10) -> 14 | I34: =IF('Model inputs'!I10="","",'Model inputs'!I10) -> 18 | ... Y34: =IF('Model inputs'!Y10="","",'Model inputs'!Y10) -> 100 | Z34: =0 -> 0 | AA34: =IF(IF(('Model inputs'!AA17-'Model inputs'!AB61)<1="",FALSE,('Model inputs'!AA17-'Model inputs'!AB61)<1),0,ROUND(IF(IF(('Model inputs'!AA17-'Model inputs'!AB61)<=3="",FALSE,('Model inputs'!AA17-'Model inputs'!AB61)<=3),IF('Model inputs'!AB52="","",'Model inputs'!AB52),IF(IF(('Model inputs'!AA17-'Model inputs'!AB61)<=6="",FALSE,('Model inputs'!AA17-'Model inputs'!AB61)<=6),'Model inputs'!AB52+('Model inputs'!AB58-'Model inputs'!AB52)*(('Model inputs'!AA17-'Model inputs'!AB61)-3)/3,IF(IF(('Model inputs'!AA17-'Model inputs'!AB61)<=12="",FALSE,('Model inputs'!AA17-'Model inputs'!AB61)<=12),'Model inputs'!AB58+('Model inputs'!AB40-'Model inputs'!AB58)*(('Model inputs'!AA17-'Model inputs'!AB61)-6)/6,'Model inputs'!AB40+('Model inputs'!AB46-'Model inputs'!AB40)*(('Model inputs'!AA17-'Model inputs'!AB61)-12)/12))),0)) -> 0
A35: Customers > Team | B35: =IF('Model inputs'!B11="","",'Model inputs'!B11) -> 0 | C35: =IF('Model inputs'!C11="","",'Model inputs'!C11) -> 0 | D35: =IF('Model inputs'!D11="","",'Model inputs'!D11) -> 0 | E35: =IF('Model inputs'!E11="","",'Model inputs'!E11) -> 1 | F35: =IF('Model inputs'!F11="","",'Model inputs'!F11) -> 1 | G35: =IF('Model inputs'!G11="","",'Model inputs'!G11) -> 2 | H35: =IF('Model inputs'!H11="","",'Model inputs'!H11) -> 3 | I35: =IF('Model inputs'!I11="","",'Model inputs'!I11) -> 4 | ... Y35: =IF('Model inputs'!Y11="","",'Model inputs'!Y11) -> 25 | Z35: =0 -> 0 | AA35: =IF(IF(('Model inputs'!AA17-'Model inputs'!AB61)<1="",FALSE,('Model inputs'!AA17-'Model inputs'!AB61)<1),0,ROUND(IF(IF(('Model inputs'!AA17-'Model inputs'!AB61)<=3="",FALSE,('Model inputs'!AA17-'Model inputs'!AB61)<=3),IF('Model inputs'!AB53="","",'Model inputs'!AB53),IF(IF(('Model inputs'!AA17-'Model inputs'!AB61)<=6="",FALSE,('Model inputs'!AA17-'Model inputs'!AB61)<=6),'Model inputs'!AB53+('Model inputs'!AB59-'Model inputs'!AB53)*(('Model inputs'!AA17-'Model inputs'!AB61)-3)/3,IF(IF(('Model inputs'!AA17-'Model inputs'!AB61)<=12="",FALSE,('Model inputs'!AA17-'Model inputs'!AB61)<=12),'Model inputs'!AB59+('Model inputs'!AB41-'Model inputs'!AB59)*(('Model inputs'!AA17-'Model inputs'!AB61)-6)/6,'Model inputs'!AB41+('Model inputs'!AB47-'Model inputs'!AB41)*(('Model inputs'!AA17-'Model inputs'!AB61)-12)/12))),0)) -> 0
A36: Customers by month 12 | AB36: 0
A37: Customers by month 12 > Starter | AB37: =15 -> 15
A38: Customers by month 12 > Team | AB38: =3 -> 3
A39: Customers by month 12 | AB39: 0
A40: Customers by month 12 > Starter | AB40: =35 -> 35
A41: Customers by month 12 > Team | AB41: =8 -> 8
A42: Customers by month 24 | AB42: 0
A43: Customers by month 24 > Starter | AB43: =40 -> 40
A44: Customers by month 24 > Team | AB44: =10 -> 10
A45: Customers by month 24 | AB45: 0
A46: Customers by month 24 > Starter | AB46: =100 -> 100
A47: Customers by month 24 > Team | AB47: =25 -> 25
A48: Customers by month 3 | AB48: 0
A49: Customers by month 3 > Starter | AB49: =0 -> 0
A50: Customers by month 3 > Team | AB50: =0 -> 0
A51: Customers by month 3 | AB51: 0
A52: Customers by month 3 > Starter | AB52: =0 -> 0
A53: Customers by month 3 > Team | AB53: =0 -> 0
A54: Customers by month 6 | AB54: 0
A55: Customers by month 6 > Starter | AB55: =5 -> 5
A56: Customers by month 6 > Team | AB56: =1 -> 1
A57: Customers by month 6 | AB57: 0
A58: Customers by month 6 > Starter | AB58: =10 -> 10
A59: Customers by month 6 > Team | AB59: =2 -> 2
A60: Milestone delay months · Customers · Downside · Downside | AB60: =3 -> 3
A61: Milestone delay months · Customers · Growth · Growth | AB61: =0 -> 0
A62: Operating expenses · Downside | B62: ='Model inputs'!B78+'Model inputs'!B84 -> 2100 | C62: ='Model inputs'!C78+'Model inputs'!C84 -> 2100 | D62: ='Model inputs'!D78+'Model inputs'!D84 -> 2100 | E62: ='Model inputs'!E78+'Model inputs'!E84 -> 2100 | F62: ='Model inputs'!F78+'Model inputs'!F84 -> 2100 | G62: ='Model inputs'!G78+'Model inputs'!G84 -> 2100 | H62: ='Model inputs'!H78+'Model inputs'!H84 -> 2100 | I62: ='Model inputs'!I78+'Model inputs'!I84 -> 2100 | ... Y62: ='Model inputs'!Y78+'Model inputs'!Y84 -> 2100 | Z62: 0 | AA62: ='Model inputs'!AA78+'Model inputs'!AA84 -> 0
A63: Operating expenses · Growth | B63: ='Model inputs'!B79+'Model inputs'!B85 -> 2100 | C63: ='Model inputs'!C79+'Model inputs'!C85 -> 2100 | D63: ='Model inputs'!D79+'Model inputs'!D85 -> 2100 | E63: ='Model inputs'!E79+'Model inputs'!E85 -> 2100 | F63: ='Model inputs'!F79+'Model inputs'!F85 -> 2100 | G63: ='Model inputs'!G79+'Model inputs'!G85 -> 2100 | H63: ='Model inputs'!H79+'Model inputs'!H85 -> 2100 | I63: ='Model inputs'!I79+'Model inputs'!I85 -> 2100 | ... Y63: ='Model inputs'!Y79+'Model inputs'!Y85 -> 2100 | Z63: 0 | AA63: ='Model inputs'!AA79+'Model inputs'!AA85 -> 0
A64: Revenue | B64: =IF('Model inputs'!B20="","",'Model inputs'!B20) -> 0 | C64: =IF('Model inputs'!C20="","",'Model inputs'!C20) -> 0 | D64: =IF('Model inputs'!D20="","",'Model inputs'!D20) -> 0 | E64: =IF('Model inputs'!E20="","",'Model inputs'!E20) -> 0 | F64: =IF('Model inputs'!F20="","",'Model inputs'!F20) -> 0 | G64: =IF('Model inputs'!G20="","",'Model inputs'!G20) -> 0 | H64: =IF('Model inputs'!H20="","",'Model inputs'!H20) -> 198 | I64: =IF('Model inputs'!I20="","",'Model inputs'!I20) -> 696 | ... Y64: =IF('Model inputs'!Y20="","",'Model inputs'!Y20) -> 6558 | Z64: =SUM('Model inputs'!Z65,'Model inputs'!Z66) -> 0 | AA64: =SUM('Model inputs'!AA65,'Model inputs'!AA66) -> 0
A65: Revenue > Starter | B65: =IF('Model inputs'!B21="","",'Model inputs'!B21) -> 0 | C65: =IF('Model inputs'!C21="","",'Model inputs'!C21) -> 0 | D65: =IF('Model inputs'!D21="","",'Model inputs'!D21) -> 0 | E65: =IF('Model inputs'!E21="","",'Model inputs'!E21) -> 0 | F65: =IF('Model inputs'!F21="","",'Model inputs'!F21) -> 0 | G65: =IF('Model inputs'!G21="","",'Model inputs'!G21) -> 0 | H65: =IF('Model inputs'!H21="","",'Model inputs'!H21) -> 198 | I65: =IF('Model inputs'!I21="","",'Model inputs'!I21) -> 297 | ... Y65: =IF('Model inputs'!Y21="","",'Model inputs'!Y21) -> 3366 | Z65: =0 -> 0 | AA65: ='Model inputs'!AA31*'Model inputs'!AB71 -> 0
A66: Revenue > Team | B66: =IF('Model inputs'!B22="","",'Model inputs'!B22) -> 0 | C66: =IF('Model inputs'!C22="","",'Model inputs'!C22) -> 0 | D66: =IF('Model inputs'!D22="","",'Model inputs'!D22) -> 0 | E66: =IF('Model inputs'!E22="","",'Model inputs'!E22) -> 0 | F66: =IF('Model inputs'!F22="","",'Model inputs'!F22) -> 0 | G66: =IF('Model inputs'!G22="","",'Model inputs'!G22) -> 0 | H66: =IF('Model inputs'!H22="","",'Model inputs'!H22) -> 0 | I66: =IF('Model inputs'!I22="","",'Model inputs'!I22) -> 399 | ... Y66: =IF('Model inputs'!Y22="","",'Model inputs'!Y22) -> 3192 | Z66: =0 -> 0 | AA66: ='Model inputs'!AA32*'Model inputs'!AB72 -> 0
A67: Revenue | B67: =IF('Model inputs'!B23="","",'Model inputs'!B23) -> 0 | C67: =IF('Model inputs'!C23="","",'Model inputs'!C23) -> 0 | D67: =IF('Model inputs'!D23="","",'Model inputs'!D23) -> 0 | E67: =IF('Model inputs'!E23="","",'Model inputs'!E23) -> 696 | F67: =IF('Model inputs'!F23="","",'Model inputs'!F23) -> 1092 | G67: =IF('Model inputs'!G23="","",'Model inputs'!G23) -> 1788 | H67: =IF('Model inputs'!H23="","",'Model inputs'!H23) -> 2583 | I67: =IF('Model inputs'!I23="","",'Model inputs'!I23) -> 3378 | ... Y67: =IF('Model inputs'!Y23="","",'Model inputs'!Y23) -> 19875 | Z67: =SUM('Model inputs'!Z68,'Model inputs'!Z69) -> 0 | AA67: =SUM('Model inputs'!AA68,'Model inputs'!AA69) -> 0
A68: Revenue > Starter | B68: =IF('Model inputs'!B24="","",'Model inputs'!B24) -> 0 | C68: =IF('Model inputs'!C24="","",'Model inputs'!C24) -> 0 | D68: =IF('Model inputs'!D24="","",'Model inputs'!D24) -> 0 | E68: =IF('Model inputs'!E24="","",'Model inputs'!E24) -> 297 | F68: =IF('Model inputs'!F24="","",'Model inputs'!F24) -> 693 | G68: =IF('Model inputs'!G24="","",'Model inputs'!G24) -> 990 | H68: =IF('Model inputs'!H24="","",'Model inputs'!H24) -> 1386 | I68: =IF('Model inputs'!I24="","",'Model inputs'!I24) -> 1782 | ... Y68: =IF('Model inputs'!Y24="","",'Model inputs'!Y24) -> 9900 | Z68: =0 -> 0 | AA68: ='Model inputs'!AA34*'Model inputs'!AB74 -> 0
A69: Revenue > Team | B69: =IF('Model inputs'!B25="","",'Model inputs'!B25) -> 0 | C69: =IF('Model inputs'!C25="","",'Model inputs'!C25) -> 0 | D69: =IF('Model inputs'!D25="","",'Model inputs'!D25) -> 0 | E69: =IF('Model inputs'!E25="","",'Model inputs'!E25) -> 399 | F69: =IF('Model inputs'!F25="","",'Model inputs'!F25) -> 399 | G69: =IF('Model inputs'!G25="","",'Model inputs'!G25) -> 798 | H69: =IF('Model inputs'!H25="","",'Model inputs'!H25) -> 1197 | I69: =IF('Model inputs'!I25="","",'Model inputs'!I25) -> 1596 | ... Y69: =IF('Model inputs'!Y25="","",'Model inputs'!Y25) -> 9975 | Z69: =0 -> 0 | AA69: ='Model inputs'!AA35*'Model inputs'!AB75 -> 0
A70: Price per month | AB70: 0
A71: Price per month > Starter | AB71: =99 -> 99
A72: Price per month > Team | AB72: =399 -> 399
A73: Price per month | AB73: 0
A74: Price per month > Starter | AB74: =99 -> 99
A75: Price per month > Team | AB75: =399 -> 399
A76: Crustdata cost · Downside | B76: =SUM('Model inputs'!B87,'Model inputs'!B88) -> 0 | C76: =SUM('Model inputs'!C87,'Model inputs'!C88) -> 0 | D76: =SUM('Model inputs'!D87,'Model inputs'!D88) -> 0 | E76: =SUM('Model inputs'!E87,'Model inputs'!E88) -> 0 | F76: =SUM('Model inputs'!F87,'Model inputs'!F88) -> 0 | G76: =SUM('Model inputs'!G87,'Model inputs'!G88) -> 0 | H76: =SUM('Model inputs'!H87,'Model inputs'!H88) -> 123.84 | I76: =SUM('Model inputs'!I87,'Model inputs'!I88) -> 495.36 | ... AA76: =SUM('Model inputs'!AA87,'Model inputs'!AA88) -> 0
A77: Crustdata cost · Growth | B77: =SUM('Model inputs'!B90,'Model inputs'!B91) -> 0 | C77: =SUM('Model inputs'!C90,'Model inputs'!C91) -> 0 | D77: =SUM('Model inputs'!D90,'Model inputs'!D91) -> 0 | E77: =SUM('Model inputs'!E90,'Model inputs'!E91) -> 199.68 | F77: =SUM('Model inputs'!F90,'Model inputs'!F91) -> 299.52 | G77: =SUM('Model inputs'!G90,'Model inputs'!G91) -> 499.2 | H77: =SUM('Model inputs'!H90,'Model inputs'!H91) -> 723.84 | I77: =SUM('Model inputs'!I90,'Model inputs'!I91) -> 948.48 | ... AA77: =SUM('Model inputs'!AA90,'Model inputs'!AA91) -> 0
