Workbook

Sheet Monthly P&L, cash and runway
A1: Monthly P&L, cash and runway
A2: Monthly P&L & Cash · Main Scenario
A4: Variable / dimension | B4: 2026-11 | C4: 2026-12 | D4: 2027-01 | E4: 2027-02 | F4: 2027-03 | G4: 2027-04 | H4: 2027-05 | I4: 2027-06 | J4: 2027-07 | K4: 2027-08 | L4: 2027-09 | M4: 2027-10 | N4: 2027-11 | O4: 2027-12 | P4: 2028-01 | Q4: 2028-02 | R4: 2028-03 | S4: 2028-04 | T4: 2028-05 | U4: 2028-06 | V4: 2028-07 | W4: 2028-08 | X4: 2028-09 | Y4: 2028-10
A5: Model month | B5: =IFERROR(DATEDIF(DATE(2026,11,1),DATE(2026,11,1),"M")+1,0) -> 1 | C5: =IFERROR(DATEDIF(DATE(2026,11,1),DATE(2026,12,1),"M")+1,0) -> 2 | D5: =IFERROR(DATEDIF(DATE(2026,11,1),DATE(2027,1,1),"M")+1,0) -> 3 | E5: =IFERROR(DATEDIF(DATE(2026,11,1),DATE(2027,2,1),"M")+1,0) -> 4 | F5: =IFERROR(DATEDIF(DATE(2026,11,1),DATE(2027,3,1),"M")+1,0) -> 5 | G5: =IFERROR(DATEDIF(DATE(2026,11,1),DATE(2027,4,1),"M")+1,0) -> 6 | H5: =IFERROR(DATEDIF(DATE(2026,11,1),DATE(2027,5,1),"M")+1,0) -> 7 | I5: =IFERROR(DATEDIF(DATE(2026,11,1),DATE(2027,6,1),"M")+1,0) -> 8 | J5: =IFERROR(DATEDIF(DATE(2026,11,1),DATE(2027,7,1),"M")+1,0) -> 9 | K5: =IFERROR(DATEDIF(DATE(2026,11,1),DATE(2027,8,1),"M")+1,0) -> 10 | L5: =IFERROR(DATEDIF(DATE(2026,11,1),DATE(2027,9,1),"M")+1,0) -> 11 | M5: =IFERROR(DATEDIF(DATE(2026,11,1),DATE(2027,10,1),"M")+1,0) -> 12 | N5: =IFERROR(DATEDIF(DATE(2026,11,1),DATE(2027,11,1),"M")+1,0) -> 13 | O5: =IFERROR(DATEDIF(DATE(2026,11,1),DATE(2027,12,1),"M")+1,0) -> 14 | P5: =IFERROR(DATEDIF(DATE(2026,11,1),DATE(2028,1,1),"M")+1,0) -> 15 | Q5: =IFERROR(DATEDIF(DATE(2026,11,1),DATE(2028,2,1),"M")+1,0) -> 16 | R5: =IFERROR(DATEDIF(DATE(2026,11,1),DATE(2028,3,1),"M")+1,0) -> 17 | S5: =IFERROR(DATEDIF(DATE(2026,11,1),DATE(2028,4,1),"M")+1,0) -> 18 | T5: =IFERROR(DATEDIF(DATE(2026,11,1),DATE(2028,5,1),"M")+1,0) -> 19 | U5: =IFERROR(DATEDIF(DATE(2026,11,1),DATE(2028,6,1),"M")+1,0) -> 20 | V5: =IFERROR(DATEDIF(DATE(2026,11,1),DATE(2028,7,1),"M")+1,0) -> 21 | W5: =IFERROR(DATEDIF(DATE(2026,11,1),DATE(2028,8,1),"M")+1,0) -> 22 | X5: =IFERROR(DATEDIF(DATE(2026,11,1),DATE(2028,9,1),"M")+1,0) -> 23 | Y5: =IFERROR(DATEDIF(DATE(2026,11,1),DATE(2028,10,1),"M")+1,0) -> 24
A6: Customers | B6: =SUM('Monthly P&L, cash and runway'!B7,'Monthly P&L, cash and runway'!B8) -> 0 | C6: =SUM('Monthly P&L, cash and runway'!C7,'Monthly P&L, cash and runway'!C8) -> 0 | D6: =SUM('Monthly P&L, cash and runway'!D7,'Monthly P&L, cash and runway'!D8) -> 0 | E6: =SUM('Monthly P&L, cash and runway'!E7,'Monthly P&L, cash and runway'!E8) -> 2 | F6: =SUM('Monthly P&L, cash and runway'!F7,'Monthly P&L, cash and runway'!F8) -> 4 | G6: =SUM('Monthly P&L, cash and runway'!G7,'Monthly P&L, cash and runway'!G8) -> 6 | H6: =SUM('Monthly P&L, cash and runway'!H7,'Monthly P&L, cash and runway'!H8) -> 8 | I6: =SUM('Monthly P&L, cash and runway'!I7,'Monthly P&L, cash and runway'!I8) -> 10 | ... Y6: =SUM('Monthly P&L, cash and runway'!Y7,'Monthly P&L, cash and runway'!Y8) -> 50
A7: Starter | B7: =IF(IF(IF(ISERROR('Monthly P&L, cash and runway'!B5<1),'Monthly P&L, cash and runway'!B5<1,IF('Monthly P&L, cash and runway'!B5="","",'Monthly P&L, cash and runway'!B5<1))="",FALSE,IF(ISERROR('Monthly P&L, cash and runway'!B5<1),'Monthly P&L, cash and runway'!B5<1,IF('Monthly P&L, cash and runway'!B5="","",'Monthly P&L, cash and runway'!B5<1))),0,ROUND(IF(IF(IF(ISERROR('Monthly P&L, cash and runway'!B5<=3),'Monthly P&L, cash and runway'!B5<=3,IF('Monthly P&L, cash and runway'!B5="","",'Monthly P&L, cash and runway'!B5<=3))="",FALSE,IF(ISERROR('Monthly P&L, cash and runway'!B5<=3),'Monthly P&L, cash and runway'!B5<=3,IF('Monthly P&L, cash and runway'!B5="","",'Monthly P&L, cash and runway'!B5<=3))),IF('Model inputs'!B52="","",'Model inputs'!B52),IF(IF(IF(ISERROR('Monthly P&L, cash and runway'!B5<=6),'Monthly P&L, cash and runway'!B5<=6,IF('Monthly P&L, cash and runway'!B5="","",'Monthly P&L, cash and runway'!B5<=6))="",FALSE,IF(ISERROR('Monthly P&L, cash and runway'!B5<=6),'Monthly P&L, cash and runway'!B5<=6,IF('Monthly P&L, cash and runway'!B5="","",'Monthly P&L, cash and runway'!B5<=6))),'Model inputs'!B52+('Model inputs'!B55-'Model inputs'!B52)*('Monthly P&L, cash and runway'!B5-3)/3,IF(IF(IF(ISERROR('Monthly P&L, cash and runway'!B5<=12),'Monthly P&L, cash and runway'!B5<=12,IF('Monthly P&L, cash and runway'!B5="","",'Monthly P&L, cash and runway'!B5<=12))="",FALSE,IF(ISERROR('Monthly P&L, cash and runway'!B5<=12),'Monthly P&L, cash and runway'!B5<=12,IF('Monthly P&L, cash and runway'!B5="","",'Monthly P&L, cash and runway'!B5<=12))),'Model inputs'!B55+('Model inputs'!B46-'Model inputs'!B55)*('Monthly P&L, cash and runway'!B5-6)/6,'Model inputs'!B46+('Model inputs'!B49-'Model inputs'!B46)*('Monthly P&L, cash and runway'!B5-12)/12))),0)) -> 0 | C7: =IF(IF(IF(ISERROR('Monthly P&L, cash and runway'!C5<1),'Monthly P&L, cash and runway'!C5<1,IF('Monthly P&L, cash and runway'!C5="","",'Monthly P&L, cash and runway'!C5<1))="",FALSE,IF(ISERROR('Monthly P&L, cash and runway'!C5<1),'Monthly P&L, cash and runway'!C5<1,IF('Monthly P&L, cash and runway'!C5="","",'Monthly P&L, cash and runway'!C5<1))),0,ROUND(IF(IF(IF(ISERROR('Monthly P&L, cash and runway'!C5<=3),'Monthly P&L, cash and runway'!C5<=3,IF('Monthly P&L, cash and runway'!C5="","",'Monthly P&L, cash and runway'!C5<=3))="",FALSE,IF(ISERROR('Monthly P&L, cash and runway'!C5<=3),'Monthly P&L, cash and runway'!C5<=3,IF('Monthly P&L, cash and runway'!C5="","",'Monthly P&L, cash and runway'!C5<=3))),IF('Model inputs'!B52="","",'Model inputs'!B52),IF(IF(IF(ISERROR('Monthly P&L, cash and runway'!C5<=6),'Monthly P&L, cash and runway'!C5<=6,IF('Monthly P&L, cash and runway'!C5="","",'Monthly P&L, cash and runway'!C5<=6))="",FALSE,IF(ISERROR('Monthly P&L, cash and runway'!C5<=6),'Monthly P&L, cash and runway'!C5<=6,IF('Monthly P&L, cash and runway'!C5="","",'Monthly P&L, cash and runway'!C5<=6))),'Model inputs'!B52+('Model inputs'!B55-'Model inputs'!B52)*('Monthly P&L, cash and runway'!C5-3)/3,IF(IF(IF(ISERROR('Monthly P&L, cash and runway'!C5<=12),'Monthly P&L, cash and runway'!C5<=12,IF('Monthly P&L, cash and runway'!C5="","",'Monthly P&L, cash and runway'!C5<=12))="",FALSE,IF(ISERROR('Monthly P&L, cash and runway'!C5<=12),'Monthly P&L, cash and runway'!C5<=12,IF('Monthly P&L, cash and runway'!C5="","",'Monthly P&L, cash and runway'!C5<=12))),'Model inputs'!B55+('Model inputs'!B46-'Model inputs'!B55)*('Monthly P&L, cash and runway'!C5-6)/6,'Model inputs'!B46+('Model inputs'!B49-'Model inputs'!B46)*('Monthly P&L, cash and runway'!C5-12)/12))),0)) -> 0 | D7: =IF(IF(IF(ISERROR('Monthly P&L, cash and runway'!D5<1),'Monthly P&L, cash and runway'!D5<1,IF('Monthly P&L, cash and runway'!D5="","",'Monthly P&L, cash and runway'!D5<1))="",FALSE,IF(ISERROR('Monthly P&L, cash and runway'!D5<1),'Monthly P&L, cash and runway'!D5<1,IF('Monthly P&L, cash and runway'!D5="","",'Monthly P&L, cash and runway'!D5<1))),0,ROUND(IF(IF(IF(ISERROR('Monthly P&L, cash and runway'!D5<=3),'Monthly P&L, cash and runway'!D5<=3,IF('Monthly P&L, cash and runway'!D5="","",'Monthly P&L, cash and runway'!D5<=3))="",FALSE,IF(ISERROR('Monthly P&L, cash and runway'!D5<=3),'Monthly P&L, cash and runway'!D5<=3,IF('Monthly P&L, cash and runway'!D5="","",'Monthly P&L, cash and runway'!D5<=3))),IF('Model inputs'!B52="","",'Model inputs'!B52),IF(IF(IF(ISERROR('Monthly P&L, cash and runway'!D5<=6),'Monthly P&L, cash and runway'!D5<=6,IF('Monthly P&L, cash and runway'!D5="","",'Monthly P&L, cash and runway'!D5<=6))="",FALSE,IF(ISERROR('Monthly P&L, cash and runway'!D5<=6),'Monthly P&L, cash and runway'!D5<=6,IF('Monthly P&L, cash and runway'!D5="","",'Monthly P&L, cash and runway'!D5<=6))),'Model inputs'!B52+('Model inputs'!B55-'Model inputs'!B52)*('Monthly P&L, cash and runway'!D5-3)/3,IF(IF(IF(ISERROR('Monthly P&L, cash and runway'!D5<=12),'Monthly P&L, cash and runway'!D5<=12,IF('Monthly P&L, cash and runway'!D5="","",'Monthly P&L, cash and runway'!D5<=12))="",FALSE,IF(ISERROR('Monthly P&L, cash and runway'!D5<=12),'Monthly P&L, cash and runway'!D5<=12,IF('Monthly P&L, cash and runway'!D5="","",'Monthly P&L, cash and runway'!D5<=12))),'Model inputs'!B55+('Model inputs'!B46-'Model inputs'!B55)*('Monthly P&L, cash and runway'!D5-6)/6,'Model inputs'!B46+('Model inputs'!B49-'Model inputs'!B46)*('Monthly P&L, cash and runway'!D5-12)/12))),0)) -> 0 | E7: =IF(IF(IF(ISERROR('Monthly P&L, cash and runway'!E5<1),'Monthly P&L, cash and runway'!E5<1,IF('Monthly P&L, cash and runway'!E5="","",'Monthly P&L, cash and runway'!E5<1))="",FALSE,IF(ISERROR('Monthly P&L, cash and runway'!E5<1),'Monthly P&L, cash and runway'!E5<1,IF('Monthly P&L, cash and runway'!E5="","",'Monthly P&L, cash and runway'!E5<1))),0,ROUND(IF(IF(IF(ISERROR('Monthly P&L, cash and runway'!E5<=3),'Monthly P&L, cash and runway'!E5<=3,IF('Monthly P&L, cash and runway'!E5="","",'Monthly P&L, cash and runway'!E5<=3))="",FALSE,IF(ISERROR('Monthly P&L, cash and runway'!E5<=3),'Monthly P&L, cash and runway'!E5<=3,IF('Monthly P&L, cash and runway'!E5="","",'Monthly P&L, cash and runway'!E5<=3))),IF('Model inputs'!B52="","",'Model inputs'!B52),IF(IF(IF(ISERROR('Monthly P&L, cash and runway'!E5<=6),'Monthly P&L, cash and runway'!E5<=6,IF('Monthly P&L, cash and runway'!E5="","",'Monthly P&L, cash and runway'!E5<=6))="",FALSE,IF(ISERROR('Monthly P&L, cash and runway'!E5<=6),'Monthly P&L, cash and runway'!E5<=6,IF('Monthly P&L, cash and runway'!E5="","",'Monthly P&L, cash and runway'!E5<=6))),'Model inputs'!B52+('Model inputs'!B55-'Model inputs'!B52)*('Monthly P&L, cash and runway'!E5-3)/3,IF(IF(IF(ISERROR('Monthly P&L, cash and runway'!E5<=12),'Monthly P&L, cash and runway'!E5<=12,IF('Monthly P&L, cash and runway'!E5="","",'Monthly P&L, cash and runway'!E5<=12))="",FALSE,IF(ISERROR('Monthly P&L, cash and runway'!E5<=12),'Monthly P&L, cash and runway'!E5<=12,IF('Monthly P&L, cash and runway'!E5="","",'Monthly P&L, cash and runway'!E5<=12))),'Model inputs'!B55+('Model inputs'!B46-'Model inputs'!B55)*('Monthly P&L, cash and runway'!E5-6)/6,'Model inputs'!B46+('Model inputs'!B49-'Model inputs'!B46)*('Monthly P&L, cash and runway'!E5-12)/12))),0)) -> 2 | F7: =IF(IF(IF(ISERROR('Monthly P&L, cash and runway'!F5<1),'Monthly P&L, cash and runway'!F5<1,IF('Monthly P&L, cash and runway'!F5="","",'Monthly P&L, cash and runway'!F5<1))="",FALSE,IF(ISERROR('Monthly P&L, cash and runway'!F5<1),'Monthly P&L, cash and runway'!F5<1,IF('Monthly P&L, cash and runway'!F5="","",'Monthly P&L, cash and runway'!F5<1))),0,ROUND(IF(IF(IF(ISERROR('Monthly P&L, cash and runway'!F5<=3),'Monthly P&L, cash and runway'!F5<=3,IF('Monthly P&L, cash and runway'!F5="","",'Monthly P&L, cash and runway'!F5<=3))="",FALSE,IF(ISERROR('Monthly P&L, cash and runway'!F5<=3),'Monthly P&L, cash and runway'!F5<=3,IF('Monthly P&L, cash and runway'!F5="","",'Monthly P&L, cash and runway'!F5<=3))),IF('Model inputs'!B52="","",'Model inputs'!B52),IF(IF(IF(ISERROR('Monthly P&L, cash and runway'!F5<=6),'Monthly P&L, cash and runway'!F5<=6,IF('Monthly P&L, cash and runway'!F5="","",'Monthly P&L, cash and runway'!F5<=6))="",FALSE,IF(ISERROR('Monthly P&L, cash and runway'!F5<=6),'Monthly P&L, cash and runway'!F5<=6,IF('Monthly P&L, cash and runway'!F5="","",'Monthly P&L, cash and runway'!F5<=6))),'Model inputs'!B52+('Model inputs'!B55-'Model inputs'!B52)*('Monthly P&L, cash and runway'!F5-3)/3,IF(IF(IF(ISERROR('Monthly P&L, cash and runway'!F5<=12),'Monthly P&L, cash and runway'!F5<=12,IF('Monthly P&L, cash and runway'!F5="","",'Monthly P&L, cash and runway'!F5<=12))="",FALSE,IF(ISERROR('Monthly P&L, cash and runway'!F5<=12),'Monthly P&L, cash and runway'!F5<=12,IF('Monthly P&L, cash and runway'!F5="","",'Monthly P&L, cash and runway'!F5<=12))),'Model inputs'!B55+('Model inputs'!B46-'Model inputs'!B55)*('Monthly P&L, cash and runway'!F5-6)/6,'Model inputs'!B46+('Model inputs'!B49-'Model inputs'!B46)*('Monthly P&L, cash and runway'!F5-12)/12))),0)) -> 3 | G7: =IF(IF(IF(ISERROR('Monthly P&L, cash and runway'!G5<1),'Monthly P&L, cash and runway'!G5<1,IF('Monthly P&L, cash and runway'!G5="","",'Monthly P&L, cash and runway'!G5<1))="",FALSE,IF(ISERROR('Monthly P&L, cash and runway'!G5<1),'Monthly P&L, cash and runway'!G5<1,IF('Monthly P&L, cash and runway'!G5="","",'Monthly P&L, cash and runway'!G5<1))),0,ROUND(IF(IF(IF(ISERROR('Monthly P&L, cash and runway'!G5<=3),'Monthly P&L, cash and runway'!G5<=3,IF('Monthly P&L, cash and runway'!G5="","",'Monthly P&L, cash and runway'!G5<=3))="",FALSE,IF(ISERROR('Monthly P&L, cash and runway'!G5<=3),'Monthly P&L, cash and runway'!G5<=3,IF('Monthly P&L, cash and runway'!G5="","",'Monthly P&L, cash and runway'!G5<=3))),IF('Model inputs'!B52="","",'Model inputs'!B52),IF(IF(IF(ISERROR('Monthly P&L, cash and runway'!G5<=6),'Monthly P&L, cash and runway'!G5<=6,IF('Monthly P&L, cash and runway'!G5="","",'Monthly P&L, cash and runway'!G5<=6))="",FALSE,IF(ISERROR('Monthly P&L, cash and runway'!G5<=6),'Monthly P&L, cash and runway'!G5<=6,IF('Monthly P&L, cash and runway'!G5="","",'Monthly P&L, cash and runway'!G5<=6))),'Model inputs'!B52+('Model inputs'!B55-'Model inputs'!B52)*('Monthly P&L, cash and runway'!G5-3)/3,IF(IF(IF(ISERROR('Monthly P&L, cash and runway'!G5<=12),'Monthly P&L, cash and runway'!G5<=12,IF('Monthly P&L, cash and runway'!G5="","",'Monthly P&L, cash and runway'!G5<=12))="",FALSE,IF(ISERROR('Monthly P&L, cash and runway'!G5<=12),'Monthly P&L, cash and runway'!G5<=12,IF('Monthly P&L, cash and runway'!G5="","",'Monthly P&L, cash and runway'!G5<=12))),'Model inputs'!B55+('Model inputs'!B46-'Model inputs'!B55)*('Monthly P&L, cash and runway'!G5-6)/6,'Model inputs'!B46+('Model inputs'!B49-'Model inputs'!B46)*('Monthly P&L, cash and runway'!G5-12)/12))),0)) -> 5 | H7: =IF(IF(IF(ISERROR('Monthly P&L, cash and runway'!H5<1),'Monthly P&L, cash and runway'!H5<1,IF('Monthly P&L, cash and runway'!H5="","",'Monthly P&L, cash and runway'!H5<1))="",FALSE,IF(ISERROR('Monthly P&L, cash and runway'!H5<1),'Monthly P&L, cash and runway'!H5<1,IF('Monthly P&L, cash and runway'!H5="","",'Monthly P&L, cash and runway'!H5<1))),0,ROUND(IF(IF(IF(ISERROR('Monthly P&L, cash and runway'!H5<=3),'Monthly P&L, cash and runway'!H5<=3,IF('Monthly P&L, cash and runway'!H5="","",'Monthly P&L, cash and runway'!H5<=3))="",FALSE,IF(ISERROR('Monthly P&L, cash and runway'!H5<=3),'Monthly P&L, cash and runway'!H5<=3,IF('Monthly P&L, cash and runway'!H5="","",'Monthly P&L, cash and runway'!H5<=3))),IF('Model inputs'!B52="","",'Model inputs'!B52),IF(IF(IF(ISERROR('Monthly P&L, cash and runway'!H5<=6),'Monthly P&L, cash and runway'!H5<=6,IF('Monthly P&L, cash and runway'!H5="","",'Monthly P&L, cash and runway'!H5<=6))="",FALSE,IF(ISERROR('Monthly P&L, cash and runway'!H5<=6),'Monthly P&L, cash and runway'!H5<=6,IF('Monthly P&L, cash and runway'!H5="","",'Monthly P&L, cash and runway'!H5<=6))),'Model inputs'!B52+('Model inputs'!B55-'Model inputs'!B52)*('Monthly P&L, cash and runway'!H5-3)/3,IF(IF(IF(ISERROR('Monthly P&L, cash and runway'!H5<=12),'Monthly P&L, cash and runway'!H5<=12,IF('Monthly P&L, cash and runway'!H5="","",'Monthly P&L, cash and runway'!H5<=12))="",FALSE,IF(ISERROR('Monthly P&L, cash and runway'!H5<=12),'Monthly P&L, cash and runway'!H5<=12,IF('Monthly P&L, cash and runway'!H5="","",'Monthly P&L, cash and runway'!H5<=12))),'Model inputs'!B55+('Model inputs'!B46-'Model inputs'!B55)*('Monthly P&L, cash and runway'!H5-6)/6,'Model inputs'!B46+('Model inputs'!B49-'Model inputs'!B46)*('Monthly P&L, cash and runway'!H5-12)/12))),0)) -> 7 | I7: =IF(IF(IF(ISERROR('Monthly P&L, cash and runway'!I5<1),'Monthly P&L, cash and runway'!I5<1,IF('Monthly P&L, cash and runway'!I5="","",'Monthly P&L, cash and runway'!I5<1))="",FALSE,IF(ISERROR('Monthly P&L, cash and runway'!I5<1),'Monthly P&L, cash and runway'!I5<1,IF('Monthly P&L, cash and runway'!I5="","",'Monthly P&L, cash and runway'!I5<1))),0,ROUND(IF(IF(IF(ISERROR('Monthly P&L, cash and runway'!I5<=3),'Monthly P&L, cash and runway'!I5<=3,IF('Monthly P&L, cash and runway'!I5="","",'Monthly P&L, cash and runway'!I5<=3))="",FALSE,IF(ISERROR('Monthly P&L, cash and runway'!I5<=3),'Monthly P&L, cash and runway'!I5<=3,IF('Monthly P&L, cash and runway'!I5="","",'Monthly P&L, cash and runway'!I5<=3))),IF('Model inputs'!B52="","",'Model inputs'!B52),IF(IF(IF(ISERROR('Monthly P&L, cash and runway'!I5<=6),'Monthly P&L, cash and runway'!I5<=6,IF('Monthly P&L, cash and runway'!I5="","",'Monthly P&L, cash and runway'!I5<=6))="",FALSE,IF(ISERROR('Monthly P&L, cash and runway'!I5<=6),'Monthly P&L, cash and runway'!I5<=6,IF('Monthly P&L, cash and runway'!I5="","",'Monthly P&L, cash and runway'!I5<=6))),'Model inputs'!B52+('Model inputs'!B55-'Model inputs'!B52)*('Monthly P&L, cash and runway'!I5-3)/3,IF(IF(IF(ISERROR('Monthly P&L, cash and runway'!I5<=12),'Monthly P&L, cash and runway'!I5<=12,IF('Monthly P&L, cash and runway'!I5="","",'Monthly P&L, cash and runway'!I5<=12))="",FALSE,IF(ISERROR('Monthly P&L, cash and runway'!I5<=12),'Monthly P&L, cash and runway'!I5<=12,IF('Monthly P&L, cash and runway'!I5="","",'Monthly P&L, cash and runway'!I5<=12))),'Model inputs'!B55+('Model inputs'!B46-'Model inputs'!B55)*('Monthly P&L, cash and runway'!I5-6)/6,'Model inputs'!B46+('Model inputs'!B49-'Model inputs'!B46)*('Monthly P&L, cash and runway'!I5-12)/12))),0)) -> 8 | J7: =IF(IF(IF(ISERROR('Monthly P&L, cash and runway'!J5<1),'Monthly P&L, cash and runway'!J5<1,IF('Monthly P&L, cash and runway'!J5="","",'Monthly P&L, cash and runway'!J5<1))="",FALSE,IF(ISERROR('Monthly P&L, cash and runway'!J5<1),'Monthly P&L, cash and runway'!J5<1,IF('Monthly P&L, cash and runway'!J5="","",'Monthly P&L, cash and runway'!J5<1))),0,ROUND(IF(IF(IF(ISERROR('Monthly P&L, cash and runway'!J5<=3),'Monthly P&L, cash and runway'!J5<=3,IF('Monthly P&L, cash and runway'!J5="","",'Monthly P&L, cash and runway'!J5<=3))="",FALSE,IF(ISERROR('Monthly P&L, cash and runway'!J5<=3),'Monthly P&L, cash and runway'!J5<=3,IF('Monthly P&L, cash and runway'!J5="","",'Monthly P&L, cash and runway'!J5<=3))),IF('Model inputs'!B52="","",'Model inputs'!B52),IF(IF(IF(ISERROR('Monthly P&L, cash and runway'!J5<=6),'Monthly P&L, cash and runway'!J5<=6,IF('Monthly P&L, cash and runway'!J5="","",'Monthly P&L, cash and runway'!J5<=6))="",FALSE,IF(ISERROR('Monthly P&L, cash and runway'!J5<=6),'Monthly P&L, cash and runway'!J5<=6,IF('Monthly P&L, cash and runway'!J5="","",'Monthly P&L, cash and runway'!J5<=6))),'Model inputs'!B52+('Model inputs'!B55-'Model inputs'!B52)*('Monthly P&L, cash and runway'!J5-3)/3,IF(IF(IF(ISERROR('Monthly P&L, cash and runway'!J5<=12),'Monthly P&L, cash and runway'!J5<=12,IF('Monthly P&L, cash and runway'!J5="","",'Monthly P&L, cash and runway'!J5<=12))="",FALSE,IF(ISERROR('Monthly P&L, cash and runway'!J5<=12),'Monthly P&L, cash and runway'!J5<=12,IF('Monthly P&L, cash and runway'!J5="","",'Monthly P&L, cash and runway'!J5<=12))),'Model inputs'!B55+('Model inputs'!B46-'Model inputs'!B55)*('Monthly P&L, cash and runway'!J5-6)/6,'Model inputs'!B46+('Model inputs'!B49-'Model inputs'!B46)*('Monthly P&L, cash and runway'!J5-12)/12))),0)) -> 10 | K7: =IF(IF(IF(ISERROR('Monthly P&L, cash and runway'!K5<1),'Monthly P&L, cash and runway'!K5<1,IF('Monthly P&L, cash and runway'!K5="","",'Monthly P&L, cash and runway'!K5<1))="",FALSE,IF(ISERROR('Monthly P&L, cash and runway'!K5<1),'Monthly P&L, cash and runway'!K5<1,IF('Monthly P&L, cash and runway'!K5="","",'Monthly P&L, cash and runway'!K5<1))),0,ROUND(IF(IF(IF(ISERROR('Monthly P&L, cash and runway'!K5<=3),'Monthly P&L, cash and runway'!K5<=3,IF('Monthly P&L, cash and runway'!K5="","",'Monthly P&L, cash and runway'!K5<=3))="",FALSE,IF(ISERROR('Monthly P&L, cash and runway'!K5<=3),'Monthly P&L, cash and runway'!K5<=3,IF('Monthly P&L, cash and runway'!K5="","",'Monthly P&L, cash and runway'!K5<=3))),IF('Model inputs'!B52="","",'Model inputs'!B52),IF(IF(IF(ISERROR('Monthly P&L, cash and runway'!K5<=6),'Monthly P&L, cash and runway'!K5<=6,IF('Monthly P&L, cash and runway'!K5="","",'Monthly P&L, cash and runway'!K5<=6))="",FALSE,IF(ISERROR('Monthly P&L, cash and runway'!K5<=6),'Monthly P&L, cash and runway'!K5<=6,IF('Monthly P&L, cash and runway'!K5="","",'Monthly P&L, cash and runway'!K5<=6))),'Model inputs'!B52+('Model inputs'!B55-'Model inputs'!B52)*('Monthly P&L, cash and runway'!K5-3)/3,IF(IF(IF(ISERROR('Monthly P&L, cash and runway'!K5<=12),'Monthly P&L, cash and runway'!K5<=12,IF('Monthly P&L, cash and runway'!K5="","",'Monthly P&L, cash and runway'!K5<=12))="",FALSE,IF(ISERROR('Monthly P&L, cash and runway'!K5<=12),'Monthly P&L, cash and runway'!K5<=12,IF('Monthly P&L, cash and runway'!K5="","",'Monthly P&L, cash and runway'!K5<=12))),'Model inputs'!B55+('Model inputs'!B46-'Model inputs'!B55)*('Monthly P&L, cash and runway'!K5-6)/6,'Model inputs'!B46+('Model inputs'!B49-'Model inputs'!B46)*('Monthly P&L, cash and runway'!K5-12)/12))),0)) -> 12 | L7: =IF(IF(IF(ISERROR('Monthly P&L, cash and runway'!L5<1),'Monthly P&L, cash and runway'!L5<1,IF('Monthly P&L, cash and runway'!L5="","",'Monthly P&L, cash and runway'!L5<1))="",FALSE,IF(ISERROR('Monthly P&L, cash and runway'!L5<1),'Monthly P&L, cash and runway'!L5<1,IF('Monthly P&L, cash and runway'!L5="","",'Monthly P&L, cash and runway'!L5<1))),0,ROUND(IF(IF(IF(ISERROR('Monthly P&L, cash and runway'!L5<=3),'Monthly P&L, cash and runway'!L5<=3,IF('Monthly P&L, cash and runway'!L5="","",'Monthly P&L, cash and runway'!L5<=3))="",FALSE,IF(ISERROR('Monthly P&L, cash and runway'!L5<=3),'Monthly P&L, cash and runway'!L5<=3,IF('Monthly P&L, cash and runway'!L5="","",'Monthly P&L, cash and runway'!L5<=3))),IF('Model inputs'!B52="","",'Model inputs'!B52),IF(IF(IF(ISERROR('Monthly P&L, cash and runway'!L5<=6),'Monthly P&L, cash and runway'!L5<=6,IF('Monthly P&L, cash and runway'!L5="","",'Monthly P&L, cash and runway'!L5<=6))="",FALSE,IF(ISERROR('Monthly P&L, cash and runway'!L5<=6),'Monthly P&L, cash and runway'!L5<=6,IF('Monthly P&L, cash and runway'!L5="","",'Monthly P&L, cash and runway'!L5<=6))),'Model inputs'!B52+('Model inputs'!B55-'Model inputs'!B52)*('Monthly P&L, cash and runway'!L5-3)/3,IF(IF(IF(ISERROR('Monthly P&L, cash and runway'!L5<=12),'Monthly P&L, cash and runway'!L5<=12,IF('Monthly P&L, cash and runway'!L5="","",'Monthly P&L, cash and runway'!L5<=12))="",FALSE,IF(ISERROR('Monthly P&L, cash and runway'!L5<=12),'Monthly P&L, cash and runway'!L5<=12,IF('Monthly P&L, cash and runway'!L5="","",'Monthly P&L, cash and runway'!L5<=12))),'Model inputs'!B55+('Model inputs'!B46-'Model inputs'!B55)*('Monthly P&L, cash and runway'!L5-6)/6,'Model inputs'!B46+('Model inputs'!B49-'Model inputs'!B46)*('Monthly P&L, cash and runway'!L5-12)/12))),0)) -> 13 | M7: =IF(IF(IF(ISERROR('Monthly P&L, cash and runway'!M5<1),'Monthly P&L, cash and runway'!M5<1,IF('Monthly P&L, cash and runway'!M5="","",'Monthly P&L, cash and runway'!M5<1))="",FALSE,IF(ISERROR('Monthly P&L, cash and runway'!M5<1),'Monthly P&L, cash and runway'!M5<1,IF('Monthly P&L, cash and runway'!M5="","",'Monthly P&L, cash and runway'!M5<1))),0,ROUND(IF(IF(IF(ISERROR('Monthly P&L, cash and runway'!M5<=3),'Monthly P&L, cash and runway'!M5<=3,IF('Monthly P&L, cash and runway'!M5="","",'Monthly P&L, cash and runway'!M5<=3))="",FALSE,IF(ISERROR('Monthly P&L, cash and runway'!M5<=3),'Monthly P&L, cash and runway'!M5<=3,IF('Monthly P&L, cash and runway'!M5="","",'Monthly P&L, cash and runway'!M5<=3))),IF('Model inputs'!B52="","",'Model inputs'!B52),IF(IF(IF(ISERROR('Monthly P&L, cash and runway'!M5<=6),'Monthly P&L, cash and runway'!M5<=6,IF('Monthly P&L, cash and runway'!M5="","",'Monthly P&L, cash and runway'!M5<=6))="",FALSE,IF(ISERROR('Monthly P&L, cash and runway'!M5<=6),'Monthly P&L, cash and runway'!M5<=6,IF('Monthly P&L, cash and runway'!M5="","",'Monthly P&L, cash and runway'!M5<=6))),'Model inputs'!B52+('Model inputs'!B55-'Model inputs'!B52)*('Monthly P&L, cash and runway'!M5-3)/3,IF(IF(IF(ISERROR('Monthly P&L, cash and runway'!M5<=12),'Monthly P&L, cash and runway'!M5<=12,IF('Monthly P&L, cash and runway'!M5="","",'Monthly P&L, cash and runway'!M5<=12))="",FALSE,IF(ISERROR('Monthly P&L, cash and runway'!M5<=12),'Monthly P&L, cash and runway'!M5<=12,IF('Monthly P&L, cash and runway'!M5="","",'Monthly P&L, cash and runway'!M5<=12))),'Model inputs'!B55+('Model inputs'!B46-'Model inputs'!B55)*('Monthly P&L, cash and runway'!M5-6)/6,'Model inputs'!B46+('Model inputs'!B49-'Model inputs'!B46)*('Monthly P&L, cash and runway'!M5-12)/12))),0)) -> 15 | N7: =IF(IF(IF(ISERROR('Monthly P&L, cash and runway'!N5<1),'Monthly P&L, cash and runway'!N5<1,IF('Monthly P&L, cash and runway'!N5="","",'Monthly P&L, cash and runway'!N5<1))="",FALSE,IF(ISERROR('Monthly P&L, cash and runway'!N5<1),'Monthly P&L, cash and runway'!N5<1,IF('Monthly P&L, cash and runway'!N5="","",'Monthly P&L, cash and runway'!N5<1))),0,ROUND(IF(IF(IF(ISERROR('Monthly P&L, cash and runway'!N5<=3),'Monthly P&L, cash and runway'!N5<=3,IF('Monthly P&L, cash and runway'!N5="","",'Monthly P&L, cash and runway'!N5<=3))="",FALSE,IF(ISERROR('Monthly P&L, cash and runway'!N5<=3),'Monthly P&L, cash and runway'!N5<=3,IF('Monthly P&L, cash and runway'!N5="","",'Monthly P&L, cash and runway'!N5<=3))),IF('Model inputs'!B52="","",'Model inputs'!B52),IF(IF(IF(ISERROR('Monthly P&L, cash and runway'!N5<=6),'Monthly P&L, cash and runway'!N5<=6,IF('Monthly P&L, cash and runway'!N5="","",'Monthly P&L, cash and runway'!N5<=6))="",FALSE,IF(ISERROR('Monthly P&L, cash and runway'!N5<=6),'Monthly P&L, cash and runway'!N5<=6,IF('Monthly P&L, cash and runway'!N5="","",'Monthly P&L, cash and runway'!N5<=6))),'Model inputs'!B52+('Model inputs'!B55-'Model inputs'!B52)*('Monthly P&L, cash and runway'!N5-3)/3,IF(IF(IF(ISERROR('Monthly P&L, cash and runway'!N5<=12),'Monthly P&L, cash and runway'!N5<=12,IF('Monthly P&L, cash and runway'!N5="","",'Monthly P&L, cash and runway'!N5<=12))="",FALSE,IF(ISERROR('Monthly P&L, cash and runway'!N5<=12),'Monthly P&L, cash and runway'!N5<=12,IF('Monthly P&L, cash and runway'!N5="","",'Monthly P&L, cash and runway'!N5<=12))),'Model inputs'!B55+('Model inputs'!B46-'Model inputs'!B55)*('Monthly P&L, cash and runway'!N5-6)/6,'Model inputs'!B46+('Model inputs'!B49-'Model inputs'!B46)*('Monthly P&L, cash and runway'!N5-12)/12))),0)) -> 17 | O7: =IF(IF(IF(ISERROR('Monthly P&L, cash and runway'!O5<1),'Monthly P&L, cash and runway'!O5<1,IF('Monthly P&L, cash and runway'!O5="","",'Monthly P&L, cash and runway'!O5<1))="",FALSE,IF(ISERROR('Monthly P&L, cash and runway'!O5<1),'Monthly P&L, cash and runway'!O5<1,IF('Monthly P&L, cash and runway'!O5="","",'Monthly P&L, cash and runway'!O5<1))),0,ROUND(IF(IF(IF(ISERROR('Monthly P&L, cash and runway'!O5<=3),'Monthly P&L, cash and runway'!O5<=3,IF('Monthly P&L, cash and runway'!O5="","",'Monthly P&L, cash and runway'!O5<=3))="",FALSE,IF(ISERROR('Monthly P&L, cash and runway'!O5<=3),'Monthly P&L, cash and runway'!O5<=3,IF('Monthly P&L, cash and runway'!O5="","",'Monthly P&L, cash and runway'!O5<=3))),IF('Model inputs'!B52="","",'Model inputs'!B52),IF(IF(IF(ISERROR('Monthly P&L, cash and runway'!O5<=6),'Monthly P&L, cash and runway'!O5<=6,IF('Monthly P&L, cash and runway'!O5="","",'Monthly P&L, cash and runway'!O5<=6))="",FALSE,IF(ISERROR('Monthly P&L, cash and runway'!O5<=6),'Monthly P&L, cash and runway'!O5<=6,IF('Monthly P&L, cash and runway'!O5="","",'Monthly P&L, cash and runway'!O5<=6))),'Model inputs'!B52+('Model inputs'!B55-'Model inputs'!B52)*('Monthly P&L, cash and runway'!O5-3)/3,IF(IF(IF(ISERROR('Monthly P&L, cash and runway'!O5<=12),'Monthly P&L, cash and runway'!O5<=12,IF('Monthly P&L, cash and runway'!O5="","",'Monthly P&L, cash and runway'!O5<=12))="",FALSE,IF(ISERROR('Monthly P&L, cash and runway'!O5<=12),'Monthly P&L, cash and runway'!O5<=12,IF('Monthly P&L, cash and runway'!O5="","",'Monthly P&L, cash and runway'!O5<=12))),'Model inputs'!B55+('Model inputs'!B46-'Model inputs'!B55)*('Monthly P&L, cash and runway'!O5-6)/6,'Model inputs'!B46+('Model inputs'!B49-'Model inputs'!B46)*('Monthly P&L, cash and runway'!O5-12)/12))),0)) -> 19 | P7: =IF(IF(IF(ISERROR('Monthly P&L, cash and runway'!P5<1),'Monthly P&L, cash and runway'!P5<1,IF('Monthly P&L, cash and runway'!P5="","",'Monthly P&L, cash and runway'!P5<1))="",FALSE,IF(ISERROR('Monthly P&L, cash and runway'!P5<1),'Monthly P&L, cash and runway'!P5<1,IF('Monthly P&L, cash and runway'!P5="","",'Monthly P&L, cash and runway'!P5<1))),0,ROUND(IF(IF(IF(ISERROR('Monthly P&L, cash and runway'!P5<=3),'Monthly P&L, cash and runway'!P5<=3,IF('Monthly P&L, cash and runway'!P5="","",'Monthly P&L, cash and runway'!P5<=3))="",FALSE,IF(ISERROR('Monthly P&L, cash and runway'!P5<=3),'Monthly P&L, cash and runway'!P5<=3,IF('Monthly P&L, cash and runway'!P5="","",'Monthly P&L, cash and runway'!P5<=3))),IF('Model inputs'!B52="","",'Model inputs'!B52),IF(IF(IF(ISERROR('Monthly P&L, cash and runway'!P5<=6),'Monthly P&L, cash and runway'!P5<=6,IF('Monthly P&L, cash and runway'!P5="","",'Monthly P&L, cash and runway'!P5<=6))="",FALSE,IF(ISERROR('Monthly P&L, cash and runway'!P5<=6),'Monthly P&L, cash and runway'!P5<=6,IF('Monthly P&L, cash and runway'!P5="","",'Monthly P&L, cash and runway'!P5<=6))),'Model inputs'!B52+('Model inputs'!B55-'Model inputs'!B52)*('Monthly P&L, cash and runway'!P5-3)/3,IF(IF(IF(ISERROR('Monthly P&L, cash and runway'!P5<=12),'Monthly P&L, cash and runway'!P5<=12,IF('Monthly P&L, cash and runway'!P5="","",'Monthly P&L, cash and runway'!P5<=12))="",FALSE,IF(ISERROR('Monthly P&L, cash and runway'!P5<=12),'Monthly P&L, cash and runway'!P5<=12,IF('Monthly P&L, cash and runway'!P5="","",'Monthly P&L, cash and runway'!P5<=12))),'Model inputs'!B55+('Model inputs'!B46-'Model inputs'!B55)*('Monthly P&L, cash and runway'!P5-6)/6,'Model inputs'!B46+('Model inputs'!B49-'Model inputs'!B46)*('Monthly P&L, cash and runway'!P5-12)/12))),0)) -> 21 | Q7: =IF(IF(IF(ISERROR('Monthly P&L, cash and runway'!Q5<1),'Monthly P&L, cash and runway'!Q5<1,IF('Monthly P&L, cash and runway'!Q5="","",'Monthly P&L, cash and runway'!Q5<1))="",FALSE,IF(ISERROR('Monthly P&L, cash and runway'!Q5<1),'Monthly P&L, cash and runway'!Q5<1,IF('Monthly P&L, cash and runway'!Q5="","",'Monthly P&L, cash and runway'!Q5<1))),0,ROUND(IF(IF(IF(ISERROR('Monthly P&L, cash and runway'!Q5<=3),'Monthly P&L, cash and runway'!Q5<=3,IF('Monthly P&L, cash and runway'!Q5="","",'Monthly P&L, cash and runway'!Q5<=3))="",FALSE,IF(ISERROR('Monthly P&L, cash and runway'!Q5<=3),'Monthly P&L, cash and runway'!Q5<=3,IF('Monthly P&L, cash and runway'!Q5="","",'Monthly P&L, cash and runway'!Q5<=3))),IF('Model inputs'!B52="","",'Model inputs'!B52),IF(IF(IF(ISERROR('Monthly P&L, cash and runway'!Q5<=6),'Monthly P&L, cash and runway'!Q5<=6,IF('Monthly P&L, cash and runway'!Q5="","",'Monthly P&L, cash and runway'!Q5<=6))="",FALSE,IF(ISERROR('Monthly P&L, cash and runway'!Q5<=6),'Monthly P&L, cash and runway'!Q5<=6,IF('Monthly P&L, cash and runway'!Q5="","",'Monthly P&L, cash and runway'!Q5<=6))),'Model inputs'!B52+('Model inputs'!B55-'Model inputs'!B52)*('Monthly P&L, cash and runway'!Q5-3)/3,IF(IF(IF(ISERROR('Monthly P&L, cash and runway'!Q5<=12),'Monthly P&L, cash and runway'!Q5<=12,IF('Monthly P&L, cash and runway'!Q5="","",'Monthly P&L, cash and runway'!Q5<=12))="",FALSE,IF(ISERROR('Monthly P&L, cash and runway'!Q5<=12),'Monthly P&L, cash and runway'!Q5<=12,IF('Monthly P&L, cash and runway'!Q5="","",'Monthly P&L, cash and runway'!Q5<=12))),'Model inputs'!B55+('Model inputs'!B46-'Model inputs'!B55)*('Monthly P&L, cash and runway'!Q5-6)/6,'Model inputs'!B46+('Model inputs'!B49-'Model inputs'!B46)*('Monthly P&L, cash and runway'!Q5-12)/12))),0)) -> 23 | R7: =IF(IF(IF(ISERROR('Monthly P&L, cash and runway'!R5<1),'Monthly P&L, cash and runway'!R5<1,IF('Monthly P&L, cash and runway'!R5="","",'Monthly P&L, cash and runway'!R5<1))="",FALSE,IF(ISERROR('Monthly P&L, cash and runway'!R5<1),'Monthly P&L, cash and runway'!R5<1,IF('Monthly P&L, cash and runway'!R5="","",'Monthly P&L, cash and runway'!R5<1))),0,ROUND(IF(IF(IF(ISERROR('Monthly P&L, cash and runway'!R5<=3),'Monthly P&L, cash and runway'!R5<=3,IF('Monthly P&L, cash and runway'!R5="","",'Monthly P&L, cash and runway'!R5<=3))="",FALSE,IF(ISERROR('Monthly P&L, cash and runway'!R5<=3),'Monthly P&L, cash and runway'!R5<=3,IF('Monthly P&L, cash and runway'!R5="","",'Monthly P&L, cash and runway'!R5<=3))),IF('Model inputs'!B52="","",'Model inputs'!B52),IF(IF(IF(ISERROR('Monthly P&L, cash and runway'!R5<=6),'Monthly P&L, cash and runway'!R5<=6,IF('Monthly P&L, cash and runway'!R5="","",'Monthly P&L, cash and runway'!R5<=6))="",FALSE,IF(ISERROR('Monthly P&L, cash and runway'!R5<=6),'Monthly P&L, cash and runway'!R5<=6,IF('Monthly P&L, cash and runway'!R5="","",'Monthly P&L, cash and runway'!R5<=6))),'Model inputs'!B52+('Model inputs'!B55-'Model inputs'!B52)*('Monthly P&L, cash and runway'!R5-3)/3,IF(IF(IF(ISERROR('Monthly P&L, cash and runway'!R5<=12),'Monthly P&L, cash and runway'!R5<=12,IF('Monthly P&L, cash and runway'!R5="","",'Monthly P&L, cash and runway'!R5<=12))="",FALSE,IF(ISERROR('Monthly P&L, cash and runway'!R5<=12),'Monthly P&L, cash and runway'!R5<=12,IF('Monthly P&L, cash and runway'!R5="","",'Monthly P&L, cash and runway'!R5<=12))),'Model inputs'!B55+('Model inputs'!B46-'Model inputs'!B55)*('Monthly P&L, cash and runway'!R5-6)/6,'Model inputs'!B46+('Model inputs'!B49-'Model inputs'!B46)*('Monthly P&L, cash and runway'!R5-12)/12))),0)) -> 25 | S7: =IF(IF(IF(ISERROR('Monthly P&L, cash and runway'!S5<1),'Monthly P&L, cash and runway'!S5<1,IF('Monthly P&L, cash and runway'!S5="","",'Monthly P&L, cash and runway'!S5<1))="",FALSE,IF(ISERROR('Monthly P&L, cash and runway'!S5<1),'Monthly P&L, cash and runway'!S5<1,IF('Monthly P&L, cash and runway'!S5="","",'Monthly P&L, cash and runway'!S5<1))),0,ROUND(IF(IF(IF(ISERROR('Monthly P&L, cash and runway'!S5<=3),'Monthly P&L, cash and runway'!S5<=3,IF('Monthly P&L, cash and runway'!S5="","",'Monthly P&L, cash and runway'!S5<=3))="",FALSE,IF(ISERROR('Monthly P&L, cash and runway'!S5<=3),'Monthly P&L, cash and runway'!S5<=3,IF('Monthly P&L, cash and runway'!S5="","",'Monthly P&L, cash and runway'!S5<=3))),IF('Model inputs'!B52="","",'Model inputs'!B52),IF(IF(IF(ISERROR('Monthly P&L, cash and runway'!S5<=6),'Monthly P&L, cash and runway'!S5<=6,IF('Monthly P&L, cash and runway'!S5="","",'Monthly P&L, cash and runway'!S5<=6))="",FALSE,IF(ISERROR('Monthly P&L, cash and runway'!S5<=6),'Monthly P&L, cash and runway'!S5<=6,IF('Monthly P&L, cash and runway'!S5="","",'Monthly P&L, cash and runway'!S5<=6))),'Model inputs'!B52+('Model inputs'!B55-'Model inputs'!B52)*('Monthly P&L, cash and runway'!S5-3)/3,IF(IF(IF(ISERROR('Monthly P&L, cash and runway'!S5<=12),'Monthly P&L, cash and runway'!S5<=12,IF('Monthly P&L, cash and runway'!S5="","",'Monthly P&L, cash and runway'!S5<=12))="",FALSE,IF(ISERROR('Monthly P&L, cash and runway'!S5<=12),'Monthly P&L, cash and runway'!S5<=12,IF('Monthly P&L, cash and runway'!S5="","",'Monthly P&L, cash and runway'!S5<=12))),'Model inputs'!B55+('Model inputs'!B46-'Model inputs'!B55)*('Monthly P&L, cash and runway'!S5-6)/6,'Model inputs'!B46+('Model inputs'!B49-'Model inputs'!B46)*('Monthly P&L, cash and runway'!S5-12)/12))),0)) -> 28 | T7: =IF(IF(IF(ISERROR('Monthly P&L, cash and runway'!T5<1),'Monthly P&L, cash and runway'!T5<1,IF('Monthly P&L, cash and runway'!T5="","",'Monthly P&L, cash and runway'!T5<1))="",FALSE,IF(ISERROR('Monthly P&L, cash and runway'!T5<1),'Monthly P&L, cash and runway'!T5<1,IF('Monthly P&L, cash and runway'!T5="","",'Monthly P&L, cash and runway'!T5<1))),0,ROUND(IF(IF(IF(ISERROR('Monthly P&L, cash and runway'!T5<=3),'Monthly P&L, cash and runway'!T5<=3,IF('Monthly P&L, cash and runway'!T5="","",'Monthly P&L, cash and runway'!T5<=3))="",FALSE,IF(ISERROR('Monthly P&L, cash and runway'!T5<=3),'Monthly P&L, cash and runway'!T5<=3,IF('Monthly P&L, cash and runway'!T5="","",'Monthly P&L, cash and runway'!T5<=3))),IF('Model inputs'!B52="","",'Model inputs'!B52),IF(IF(IF(ISERROR('Monthly P&L, cash and runway'!T5<=6),'Monthly P&L, cash and runway'!T5<=6,IF('Monthly P&L, cash and runway'!T5="","",'Monthly P&L, cash and runway'!T5<=6))="",FALSE,IF(ISERROR('Monthly P&L, cash and runway'!T5<=6),'Monthly P&L, cash and runway'!T5<=6,IF('Monthly P&L, cash and runway'!T5="","",'Monthly P&L, cash and runway'!T5<=6))),'Model inputs'!B52+('Model inputs'!B55-'Model inputs'!B52)*('Monthly P&L, cash and runway'!T5-3)/3,IF(IF(IF(ISERROR('Monthly P&L, cash and runway'!T5<=12),'Monthly P&L, cash and runway'!T5<=12,IF('Monthly P&L, cash and runway'!T5="","",'Monthly P&L, cash and runway'!T5<=12))="",FALSE,IF(ISERROR('Monthly P&L, cash and runway'!T5<=12),'Monthly P&L, cash and runway'!T5<=12,IF('Monthly P&L, cash and runway'!T5="","",'Monthly P&L, cash and runway'!T5<=12))),'Model inputs'!B55+('Model inputs'!B46-'Model inputs'!B55)*('Monthly P&L, cash and runway'!T5-6)/6,'Model inputs'!B46+('Model inputs'!B49-'Model inputs'!B46)*('Monthly P&L, cash and runway'!T5-12)/12))),0)) -> 30 | U7: =IF(IF(IF(ISERROR('Monthly P&L, cash and runway'!U5<1),'Monthly P&L, cash and runway'!U5<1,IF('Monthly P&L, cash and runway'!U5="","",'Monthly P&L, cash and runway'!U5<1))="",FALSE,IF(ISERROR('Monthly P&L, cash and runway'!U5<1),'Monthly P&L, cash and runway'!U5<1,IF('Monthly P&L, cash and runway'!U5="","",'Monthly P&L, cash and runway'!U5<1))),0,ROUND(IF(IF(IF(ISERROR('Monthly P&L, cash and runway'!U5<=3),'Monthly P&L, cash and runway'!U5<=3,IF('Monthly P&L, cash and runway'!U5="","",'Monthly P&L, cash and runway'!U5<=3))="",FALSE,IF(ISERROR('Monthly P&L, cash and runway'!U5<=3),'Monthly P&L, cash and runway'!U5<=3,IF('Monthly P&L, cash and runway'!U5="","",'Monthly P&L, cash and runway'!U5<=3))),IF('Model inputs'!B52="","",'Model inputs'!B52),IF(IF(IF(ISERROR('Monthly P&L, cash and runway'!U5<=6),'Monthly P&L, cash and runway'!U5<=6,IF('Monthly P&L, cash and runway'!U5="","",'Monthly P&L, cash and runway'!U5<=6))="",FALSE,IF(ISERROR('Monthly P&L, cash and runway'!U5<=6),'Monthly P&L, cash and runway'!U5<=6,IF('Monthly P&L, cash and runway'!U5="","",'Monthly P&L, cash and runway'!U5<=6))),'Model inputs'!B52+('Model inputs'!B55-'Model inputs'!B52)*('Monthly P&L, cash and runway'!U5-3)/3,IF(IF(IF(ISERROR('Monthly P&L, cash and runway'!U5<=12),'Monthly P&L, cash and runway'!U5<=12,IF('Monthly P&L, cash and runway'!U5="","",'Monthly P&L, cash and runway'!U5<=12))="",FALSE,IF(ISERROR('Monthly P&L, cash and runway'!U5<=12),'Monthly P&L, cash and runway'!U5<=12,IF('Monthly P&L, cash and runway'!U5="","",'Monthly P&L, cash and runway'!U5<=12))),'Model inputs'!B55+('Model inputs'!B46-'Model inputs'!B55)*('Monthly P&L, cash and runway'!U5-6)/6,'Model inputs'!B46+('Model inputs'!B49-'Model inputs'!B46)*('Monthly P&L, cash and runway'!U5-12)/12))),0)) -> 32 | V7: =IF(IF(IF(ISERROR('Monthly P&L, cash and runway'!V5<1),'Monthly P&L, cash and runway'!V5<1,IF('Monthly P&L, cash and runway'!V5="","",'Monthly P&L, cash and runway'!V5<1))="",FALSE,IF(ISERROR('Monthly P&L, cash and runway'!V5<1),'Monthly P&L, cash and runway'!V5<1,IF('Monthly P&L, cash and runway'!V5="","",'Monthly P&L, cash and runway'!V5<1))),0,ROUND(IF(IF(IF(ISERROR('Monthly P&L, cash and runway'!V5<=3),'Monthly P&L, cash and runway'!V5<=3,IF('Monthly P&L, cash and runway'!V5="","",'Monthly P&L, cash and runway'!V5<=3))="",FALSE,IF(ISERROR('Monthly P&L, cash and runway'!V5<=3),'Monthly P&L, cash and runway'!V5<=3,IF('Monthly P&L, cash and runway'!V5="","",'Monthly P&L, cash and runway'!V5<=3))),IF('Model inputs'!B52="","",'Model inputs'!B52),IF(IF(IF(ISERROR('Monthly P&L, cash and runway'!V5<=6),'Monthly P&L, cash and runway'!V5<=6,IF('Monthly P&L, cash and runway'!V5="","",'Monthly P&L, cash and runway'!V5<=6))="",FALSE,IF(ISERROR('Monthly P&L, cash and runway'!V5<=6),'Monthly P&L, cash and runway'!V5<=6,IF('Monthly P&L, cash and runway'!V5="","",'Monthly P&L, cash and runway'!V5<=6))),'Model inputs'!B52+('Model inputs'!B55-'Model inputs'!B52)*('Monthly P&L, cash and runway'!V5-3)/3,IF(IF(IF(ISERROR('Monthly P&L, cash and runway'!V5<=12),'Monthly P&L, cash and runway'!V5<=12,IF('Monthly P&L, cash and runway'!V5="","",'Monthly P&L, cash and runway'!V5<=12))="",FALSE,IF(ISERROR('Monthly P&L, cash and runway'!V5<=12),'Monthly P&L, cash and runway'!V5<=12,IF('Monthly P&L, cash and runway'!V5="","",'Monthly P&L, cash and runway'!V5<=12))),'Model inputs'!B55+('Model inputs'!B46-'Model inputs'!B55)*('Monthly P&L, cash and runway'!V5-6)/6,'Model inputs'!B46+('Model inputs'!B49-'Model inputs'!B46)*('Monthly P&L, cash and runway'!V5-12)/12))),0)) -> 34 | W7: =IF(IF(IF(ISERROR('Monthly P&L, cash and runway'!W5<1),'Monthly P&L, cash and runway'!W5<1,IF('Monthly P&L, cash and runway'!W5="","",'Monthly P&L, cash and runway'!W5<1))="",FALSE,IF(ISERROR('Monthly P&L, cash and runway'!W5<1),'Monthly P&L, cash and runway'!W5<1,IF('Monthly P&L, cash and runway'!W5="","",'Monthly P&L, cash and runway'!W5<1))),0,ROUND(IF(IF(IF(ISERROR('Monthly P&L, cash and runway'!W5<=3),'Monthly P&L, cash and runway'!W5<=3,IF('Monthly P&L, cash and runway'!W5="","",'Monthly P&L, cash and runway'!W5<=3))="",FALSE,IF(ISERROR('Monthly P&L, cash and runway'!W5<=3),'Monthly P&L, cash and runway'!W5<=3,IF('Monthly P&L, cash and runway'!W5="","",'Monthly P&L, cash and runway'!W5<=3))),IF('Model inputs'!B52="","",'Model inputs'!B52),IF(IF(IF(ISERROR('Monthly P&L, cash and runway'!W5<=6),'Monthly P&L, cash and runway'!W5<=6,IF('Monthly P&L, cash and runway'!W5="","",'Monthly P&L, cash and runway'!W5<=6))="",FALSE,IF(ISERROR('Monthly P&L, cash and runway'!W5<=6),'Monthly P&L, cash and runway'!W5<=6,IF('Monthly P&L, cash and runway'!W5="","",'Monthly P&L, cash and runway'!W5<=6))),'Model inputs'!B52+('Model inputs'!B55-'Model inputs'!B52)*('Monthly P&L, cash and runway'!W5-3)/3,IF(IF(IF(ISERROR('Monthly P&L, cash and runway'!W5<=12),'Monthly P&L, cash and runway'!W5<=12,IF('Monthly P&L, cash and runway'!W5="","",'Monthly P&L, cash and runway'!W5<=12))="",FALSE,IF(ISERROR('Monthly P&L, cash and runway'!W5<=12),'Monthly P&L, cash and runway'!W5<=12,IF('Monthly P&L, cash and runway'!W5="","",'Monthly P&L, cash and runway'!W5<=12))),'Model inputs'!B55+('Model inputs'!B46-'Model inputs'!B55)*('Monthly P&L, cash and runway'!W5-6)/6,'Model inputs'!B46+('Model inputs'!B49-'Model inputs'!B46)*('Monthly P&L, cash and runway'!W5-12)/12))),0)) -> 36 | X7: =IF(IF(IF(ISERROR('Monthly P&L, cash and runway'!X5<1),'Monthly P&L, cash and runway'!X5<1,IF('Monthly P&L, cash and runway'!X5="","",'Monthly P&L, cash and runway'!X5<1))="",FALSE,IF(ISERROR('Monthly P&L, cash and runway'!X5<1),'Monthly P&L, cash and runway'!X5<1,IF('Monthly P&L, cash and runway'!X5="","",'Monthly P&L, cash and runway'!X5<1))),0,ROUND(IF(IF(IF(ISERROR('Monthly P&L, cash and runway'!X5<=3),'Monthly P&L, cash and runway'!X5<=3,IF('Monthly P&L, cash and runway'!X5="","",'Monthly P&L, cash and runway'!X5<=3))="",FALSE,IF(ISERROR('Monthly P&L, cash and runway'!X5<=3),'Monthly P&L, cash and runway'!X5<=3,IF('Monthly P&L, cash and runway'!X5="","",'Monthly P&L, cash and runway'!X5<=3))),IF('Model inputs'!B52="","",'Model inputs'!B52),IF(IF(IF(ISERROR('Monthly P&L, cash and runway'!X5<=6),'Monthly P&L, cash and runway'!X5<=6,IF('Monthly P&L, cash and runway'!X5="","",'Monthly P&L, cash and runway'!X5<=6))="",FALSE,IF(ISERROR('Monthly P&L, cash and runway'!X5<=6),'Monthly P&L, cash and runway'!X5<=6,IF('Monthly P&L, cash and runway'!X5="","",'Monthly P&L, cash and runway'!X5<=6))),'Model inputs'!B52+('Model inputs'!B55-'Model inputs'!B52)*('Monthly P&L, cash and runway'!X5-3)/3,IF(IF(IF(ISERROR('Monthly P&L, cash and runway'!X5<=12),'Monthly P&L, cash and runway'!X5<=12,IF('Monthly P&L, cash and runway'!X5="","",'Monthly P&L, cash and runway'!X5<=12))="",FALSE,IF(ISERROR('Monthly P&L, cash and runway'!X5<=12),'Monthly P&L, cash and runway'!X5<=12,IF('Monthly P&L, cash and runway'!X5="","",'Monthly P&L, cash and runway'!X5<=12))),'Model inputs'!B55+('Model inputs'!B46-'Model inputs'!B55)*('Monthly P&L, cash and runway'!X5-6)/6,'Model inputs'!B46+('Model inputs'!B49-'Model inputs'!B46)*('Monthly P&L, cash and runway'!X5-12)/12))),0)) -> 38 | Y7: =IF(IF(IF(ISERROR('Monthly P&L, cash and runway'!Y5<1),'Monthly P&L, cash and runway'!Y5<1,IF('Monthly P&L, cash and runway'!Y5="","",'Monthly P&L, cash and runway'!Y5<1))="",FALSE,IF(ISERROR('Monthly P&L, cash and runway'!Y5<1),'Monthly P&L, cash and runway'!Y5<1,IF('Monthly P&L, cash and runway'!Y5="","",'Monthly P&L, cash and runway'!Y5<1))),0,ROUND(IF(IF(IF(ISERROR('Monthly P&L, cash and runway'!Y5<=3),'Monthly P&L, cash and runway'!Y5<=3,IF('Monthly P&L, cash and runway'!Y5="","",'Monthly P&L, cash and runway'!Y5<=3))="",FALSE,IF(ISERROR('Monthly P&L, cash and runway'!Y5<=3),'Monthly P&L, cash and runway'!Y5<=3,IF('Monthly P&L, cash and runway'!Y5="","",'Monthly P&L, cash and runway'!Y5<=3))),IF('Model inputs'!B52="","",'Model inputs'!B52),IF(IF(IF(ISERROR('Monthly P&L, cash and runway'!Y5<=6),'Monthly P&L, cash and runway'!Y5<=6,IF('Monthly P&L, cash and runway'!Y5="","",'Monthly P&L, cash and runway'!Y5<=6))="",FALSE,IF(ISERROR('Monthly P&L, cash and runway'!Y5<=6),'Monthly P&L, cash and runway'!Y5<=6,IF('Monthly P&L, cash and runway'!Y5="","",'Monthly P&L, cash and runway'!Y5<=6))),'Model inputs'!B52+('Model inputs'!B55-'Model inputs'!B52)*('Monthly P&L, cash and runway'!Y5-3)/3,IF(IF(IF(ISERROR('Monthly P&L, cash and runway'!Y5<=12),'Monthly P&L, cash and runway'!Y5<=12,IF('Monthly P&L, cash and runway'!Y5="","",'Monthly P&L, cash and runway'!Y5<=12))="",FALSE,IF(ISERROR('Monthly P&L, cash and runway'!Y5<=12),'Monthly P&L, cash and runway'!Y5<=12,IF('Monthly P&L, cash and runway'!Y5="","",'Monthly P&L, cash and runway'!Y5<=12))),'Model inputs'!B55+('Model inputs'!B46-'Model inputs'!B55)*('Monthly P&L, cash and runway'!Y5-6)/6,'Model inputs'!B46+('Model inputs'!B49-'Model inputs'!B46)*('Monthly P&L, cash and runway'!Y5-12)/12))),0)) -> 40
A8: Team | B8: =IF(IF(IF(ISERROR('Monthly P&L, cash and runway'!B5<1),'Monthly P&L, cash and runway'!B5<1,IF('Monthly P&L, cash and runway'!B5="","",'Monthly P&L, cash and runway'!B5<1))="",FALSE,IF(ISERROR('Monthly P&L, cash and runway'!B5<1),'Monthly P&L, cash and runway'!B5<1,IF('Monthly P&L, cash and runway'!B5="","",'Monthly P&L, cash and runway'!B5<1))),0,ROUND(IF(IF(IF(ISERROR('Monthly P&L, cash and runway'!B5<=3),'Monthly P&L, cash and runway'!B5<=3,IF('Monthly P&L, cash and runway'!B5="","",'Monthly P&L, cash and runway'!B5<=3))="",FALSE,IF(ISERROR('Monthly P&L, cash and runway'!B5<=3),'Monthly P&L, cash and runway'!B5<=3,IF('Monthly P&L, cash and runway'!B5="","",'Monthly P&L, cash and runway'!B5<=3))),IF('Model inputs'!B53="","",'Model inputs'!B53),IF(IF(IF(ISERROR('Monthly P&L, cash and runway'!B5<=6),'Monthly P&L, cash and runway'!B5<=6,IF('Monthly P&L, cash and runway'!B5="","",'Monthly P&L, cash and runway'!B5<=6))="",FALSE,IF(ISERROR('Monthly P&L, cash and runway'!B5<=6),'Monthly P&L, cash and runway'!B5<=6,IF('Monthly P&L, cash and runway'!B5="","",'Monthly P&L, cash and runway'!B5<=6))),'Model inputs'!B53+('Model inputs'!B56-'Model inputs'!B53)*('Monthly P&L, cash and runway'!B5-3)/3,IF(IF(IF(ISERROR('Monthly P&L, cash and runway'!B5<=12),'Monthly P&L, cash and runway'!B5<=12,IF('Monthly P&L, cash and runway'!B5="","",'Monthly P&L, cash and runway'!B5<=12))="",FALSE,IF(ISERROR('Monthly P&L, cash and runway'!B5<=12),'Monthly P&L, cash and runway'!B5<=12,IF('Monthly P&L, cash and runway'!B5="","",'Monthly P&L, cash and runway'!B5<=12))),'Model inputs'!B56+('Model inputs'!B47-'Model inputs'!B56)*('Monthly P&L, cash and runway'!B5-6)/6,'Model inputs'!B47+('Model inputs'!B50-'Model inputs'!B47)*('Monthly P&L, cash and runway'!B5-12)/12))),0)) -> 0 | C8: =IF(IF(IF(ISERROR('Monthly P&L, cash and runway'!C5<1),'Monthly P&L, cash and runway'!C5<1,IF('Monthly P&L, cash and runway'!C5="","",'Monthly P&L, cash and runway'!C5<1))="",FALSE,IF(ISERROR('Monthly P&L, cash and runway'!C5<1),'Monthly P&L, cash and runway'!C5<1,IF('Monthly P&L, cash and runway'!C5="","",'Monthly P&L, cash and runway'!C5<1))),0,ROUND(IF(IF(IF(ISERROR('Monthly P&L, cash and runway'!C5<=3),'Monthly P&L, cash and runway'!C5<=3,IF('Monthly P&L, cash and runway'!C5="","",'Monthly P&L, cash and runway'!C5<=3))="",FALSE,IF(ISERROR('Monthly P&L, cash and runway'!C5<=3),'Monthly P&L, cash and runway'!C5<=3,IF('Monthly P&L, cash and runway'!C5="","",'Monthly P&L, cash and runway'!C5<=3))),IF('Model inputs'!B53="","",'Model inputs'!B53),IF(IF(IF(ISERROR('Monthly P&L, cash and runway'!C5<=6),'Monthly P&L, cash and runway'!C5<=6,IF('Monthly P&L, cash and runway'!C5="","",'Monthly P&L, cash and runway'!C5<=6))="",FALSE,IF(ISERROR('Monthly P&L, cash and runway'!C5<=6),'Monthly P&L, cash and runway'!C5<=6,IF('Monthly P&L, cash and runway'!C5="","",'Monthly P&L, cash and runway'!C5<=6))),'Model inputs'!B53+('Model inputs'!B56-'Model inputs'!B53)*('Monthly P&L, cash and runway'!C5-3)/3,IF(IF(IF(ISERROR('Monthly P&L, cash and runway'!C5<=12),'Monthly P&L, cash and runway'!C5<=12,IF('Monthly P&L, cash and runway'!C5="","",'Monthly P&L, cash and runway'!C5<=12))="",FALSE,IF(ISERROR('Monthly P&L, cash and runway'!C5<=12),'Monthly P&L, cash and runway'!C5<=12,IF('Monthly P&L, cash and runway'!C5="","",'Monthly P&L, cash and runway'!C5<=12))),'Model inputs'!B56+('Model inputs'!B47-'Model inputs'!B56)*('Monthly P&L, cash and runway'!C5-6)/6,'Model inputs'!B47+('Model inputs'!B50-'Model inputs'!B47)*('Monthly P&L, cash and runway'!C5-12)/12))),0)) -> 0 | D8: =IF(IF(IF(ISERROR('Monthly P&L, cash and runway'!D5<1),'Monthly P&L, cash and runway'!D5<1,IF('Monthly P&L, cash and runway'!D5="","",'Monthly P&L, cash and runway'!D5<1))="",FALSE,IF(ISERROR('Monthly P&L, cash and runway'!D5<1),'Monthly P&L, cash and runway'!D5<1,IF('Monthly P&L, cash and runway'!D5="","",'Monthly P&L, cash and runway'!D5<1))),0,ROUND(IF(IF(IF(ISERROR('Monthly P&L, cash and runway'!D5<=3),'Monthly P&L, cash and runway'!D5<=3,IF('Monthly P&L, cash and runway'!D5="","",'Monthly P&L, cash and runway'!D5<=3))="",FALSE,IF(ISERROR('Monthly P&L, cash and runway'!D5<=3),'Monthly P&L, cash and runway'!D5<=3,IF('Monthly P&L, cash and runway'!D5="","",'Monthly P&L, cash and runway'!D5<=3))),IF('Model inputs'!B53="","",'Model inputs'!B53),IF(IF(IF(ISERROR('Monthly P&L, cash and runway'!D5<=6),'Monthly P&L, cash and runway'!D5<=6,IF('Monthly P&L, cash and runway'!D5="","",'Monthly P&L, cash and runway'!D5<=6))="",FALSE,IF(ISERROR('Monthly P&L, cash and runway'!D5<=6),'Monthly P&L, cash and runway'!D5<=6,IF('Monthly P&L, cash and runway'!D5="","",'Monthly P&L, cash and runway'!D5<=6))),'Model inputs'!B53+('Model inputs'!B56-'Model inputs'!B53)*('Monthly P&L, cash and runway'!D5-3)/3,IF(IF(IF(ISERROR('Monthly P&L, cash and runway'!D5<=12),'Monthly P&L, cash and runway'!D5<=12,IF('Monthly P&L, cash and runway'!D5="","",'Monthly P&L, cash and runway'!D5<=12))="",FALSE,IF(ISERROR('Monthly P&L, cash and runway'!D5<=12),'Monthly P&L, cash and runway'!D5<=12,IF('Monthly P&L, cash and runway'!D5="","",'Monthly P&L, cash and runway'!D5<=12))),'Model inputs'!B56+('Model inputs'!B47-'Model inputs'!B56)*('Monthly P&L, cash and runway'!D5-6)/6,'Model inputs'!B47+('Model inputs'!B50-'Model inputs'!B47)*('Monthly P&L, cash and runway'!D5-12)/12))),0)) -> 0 | E8: =IF(IF(IF(ISERROR('Monthly P&L, cash and runway'!E5<1),'Monthly P&L, cash and runway'!E5<1,IF('Monthly P&L, cash and runway'!E5="","",'Monthly P&L, cash and runway'!E5<1))="",FALSE,IF(ISERROR('Monthly P&L, cash and runway'!E5<1),'Monthly P&L, cash and runway'!E5<1,IF('Monthly P&L, cash and runway'!E5="","",'Monthly P&L, cash and runway'!E5<1))),0,ROUND(IF(IF(IF(ISERROR('Monthly P&L, cash and runway'!E5<=3),'Monthly P&L, cash and runway'!E5<=3,IF('Monthly P&L, cash and runway'!E5="","",'Monthly P&L, cash and runway'!E5<=3))="",FALSE,IF(ISERROR('Monthly P&L, cash and runway'!E5<=3),'Monthly P&L, cash and runway'!E5<=3,IF('Monthly P&L, cash and runway'!E5="","",'Monthly P&L, cash and runway'!E5<=3))),IF('Model inputs'!B53="","",'Model inputs'!B53),IF(IF(IF(ISERROR('Monthly P&L, cash and runway'!E5<=6),'Monthly P&L, cash and runway'!E5<=6,IF('Monthly P&L, cash and runway'!E5="","",'Monthly P&L, cash and runway'!E5<=6))="",FALSE,IF(ISERROR('Monthly P&L, cash and runway'!E5<=6),'Monthly P&L, cash and runway'!E5<=6,IF('Monthly P&L, cash and runway'!E5="","",'Monthly P&L, cash and runway'!E5<=6))),'Model inputs'!B53+('Model inputs'!B56-'Model inputs'!B53)*('Monthly P&L, cash and runway'!E5-3)/3,IF(IF(IF(ISERROR('Monthly P&L, cash and runway'!E5<=12),'Monthly P&L, cash and runway'!E5<=12,IF('Monthly P&L, cash and runway'!E5="","",'Monthly P&L, cash and runway'!E5<=12))="",FALSE,IF(ISERROR('Monthly P&L, cash and runway'!E5<=12),'Monthly P&L, cash and runway'!E5<=12,IF('Monthly P&L, cash and runway'!E5="","",'Monthly P&L, cash and runway'!E5<=12))),'Model inputs'!B56+('Model inputs'!B47-'Model inputs'!B56)*('Monthly P&L, cash and runway'!E5-6)/6,'Model inputs'!B47+('Model inputs'!B50-'Model inputs'!B47)*('Monthly P&L, cash and runway'!E5-12)/12))),0)) -> 0 | F8: =IF(IF(IF(ISERROR('Monthly P&L, cash and runway'!F5<1),'Monthly P&L, cash and runway'!F5<1,IF('Monthly P&L, cash and runway'!F5="","",'Monthly P&L, cash and runway'!F5<1))="",FALSE,IF(ISERROR('Monthly P&L, cash and runway'!F5<1),'Monthly P&L, cash and runway'!F5<1,IF('Monthly P&L, cash and runway'!F5="","",'Monthly P&L, cash and runway'!F5<1))),0,ROUND(IF(IF(IF(ISERROR('Monthly P&L, cash and runway'!F5<=3),'Monthly P&L, cash and runway'!F5<=3,IF('Monthly P&L, cash and runway'!F5="","",'Monthly P&L, cash and runway'!F5<=3))="",FALSE,IF(ISERROR('Monthly P&L, cash and runway'!F5<=3),'Monthly P&L, cash and runway'!F5<=3,IF('Monthly P&L, cash and runway'!F5="","",'Monthly P&L, cash and runway'!F5<=3))),IF('Model inputs'!B53="","",'Model inputs'!B53),IF(IF(IF(ISERROR('Monthly P&L, cash and runway'!F5<=6),'Monthly P&L, cash and runway'!F5<=6,IF('Monthly P&L, cash and runway'!F5="","",'Monthly P&L, cash and runway'!F5<=6))="",FALSE,IF(ISERROR('Monthly P&L, cash and runway'!F5<=6),'Monthly P&L, cash and runway'!F5<=6,IF('Monthly P&L, cash and runway'!F5="","",'Monthly P&L, cash and runway'!F5<=6))),'Model inputs'!B53+('Model inputs'!B56-'Model inputs'!B53)*('Monthly P&L, cash and runway'!F5-3)/3,IF(IF(IF(ISERROR('Monthly P&L, cash and runway'!F5<=12),'Monthly P&L, cash and runway'!F5<=12,IF('Monthly P&L, cash and runway'!F5="","",'Monthly P&L, cash and runway'!F5<=12))="",FALSE,IF(ISERROR('Monthly P&L, cash and runway'!F5<=12),'Monthly P&L, cash and runway'!F5<=12,IF('Monthly P&L, cash and runway'!F5="","",'Monthly P&L, cash and runway'!F5<=12))),'Model inputs'!B56+('Model inputs'!B47-'Model inputs'!B56)*('Monthly P&L, cash and runway'!F5-6)/6,'Model inputs'!B47+('Model inputs'!B50-'Model inputs'!B47)*('Monthly P&L, cash and runway'!F5-12)/12))),0)) -> 1 | G8: =IF(IF(IF(ISERROR('Monthly P&L, cash and runway'!G5<1),'Monthly P&L, cash and runway'!G5<1,IF('Monthly P&L, cash and runway'!G5="","",'Monthly P&L, cash and runway'!G5<1))="",FALSE,IF(ISERROR('Monthly P&L, cash and runway'!G5<1),'Monthly P&L, cash and runway'!G5<1,IF('Monthly P&L, cash and runway'!G5="","",'Monthly P&L, cash and runway'!G5<1))),0,ROUND(IF(IF(IF(ISERROR('Monthly P&L, cash and runway'!G5<=3),'Monthly P&L, cash and runway'!G5<=3,IF('Monthly P&L, cash and runway'!G5="","",'Monthly P&L, cash and runway'!G5<=3))="",FALSE,IF(ISERROR('Monthly P&L, cash and runway'!G5<=3),'Monthly P&L, cash and runway'!G5<=3,IF('Monthly P&L, cash and runway'!G5="","",'Monthly P&L, cash and runway'!G5<=3))),IF('Model inputs'!B53="","",'Model inputs'!B53),IF(IF(IF(ISERROR('Monthly P&L, cash and runway'!G5<=6),'Monthly P&L, cash and runway'!G5<=6,IF('Monthly P&L, cash and runway'!G5="","",'Monthly P&L, cash and runway'!G5<=6))="",FALSE,IF(ISERROR('Monthly P&L, cash and runway'!G5<=6),'Monthly P&L, cash and runway'!G5<=6,IF('Monthly P&L, cash and runway'!G5="","",'Monthly P&L, cash and runway'!G5<=6))),'Model inputs'!B53+('Model inputs'!B56-'Model inputs'!B53)*('Monthly P&L, cash and runway'!G5-3)/3,IF(IF(IF(ISERROR('Monthly P&L, cash and runway'!G5<=12),'Monthly P&L, cash and runway'!G5<=12,IF('Monthly P&L, cash and runway'!G5="","",'Monthly P&L, cash and runway'!G5<=12))="",FALSE,IF(ISERROR('Monthly P&L, cash and runway'!G5<=12),'Monthly P&L, cash and runway'!G5<=12,IF('Monthly P&L, cash and runway'!G5="","",'Monthly P&L, cash and runway'!G5<=12))),'Model inputs'!B56+('Model inputs'!B47-'Model inputs'!B56)*('Monthly P&L, cash and runway'!G5-6)/6,'Model inputs'!B47+('Model inputs'!B50-'Model inputs'!B47)*('Monthly P&L, cash and runway'!G5-12)/12))),0)) -> 1 | H8: =IF(IF(IF(ISERROR('Monthly P&L, cash and runway'!H5<1),'Monthly P&L, cash and runway'!H5<1,IF('Monthly P&L, cash and runway'!H5="","",'Monthly P&L, cash and runway'!H5<1))="",FALSE,IF(ISERROR('Monthly P&L, cash and runway'!H5<1),'Monthly P&L, cash and runway'!H5<1,IF('Monthly P&L, cash and runway'!H5="","",'Monthly P&L, cash and runway'!H5<1))),0,ROUND(IF(IF(IF(ISERROR('Monthly P&L, cash and runway'!H5<=3),'Monthly P&L, cash and runway'!H5<=3,IF('Monthly P&L, cash and runway'!H5="","",'Monthly P&L, cash and runway'!H5<=3))="",FALSE,IF(ISERROR('Monthly P&L, cash and runway'!H5<=3),'Monthly P&L, cash and runway'!H5<=3,IF('Monthly P&L, cash and runway'!H5="","",'Monthly P&L, cash and runway'!H5<=3))),IF('Model inputs'!B53="","",'Model inputs'!B53),IF(IF(IF(ISERROR('Monthly P&L, cash and runway'!H5<=6),'Monthly P&L, cash and runway'!H5<=6,IF('Monthly P&L, cash and runway'!H5="","",'Monthly P&L, cash and runway'!H5<=6))="",FALSE,IF(ISERROR('Monthly P&L, cash and runway'!H5<=6),'Monthly P&L, cash and runway'!H5<=6,IF('Monthly P&L, cash and runway'!H5="","",'Monthly P&L, cash and runway'!H5<=6))),'Model inputs'!B53+('Model inputs'!B56-'Model inputs'!B53)*('Monthly P&L, cash and runway'!H5-3)/3,IF(IF(IF(ISERROR('Monthly P&L, cash and runway'!H5<=12),'Monthly P&L, cash and runway'!H5<=12,IF('Monthly P&L, cash and runway'!H5="","",'Monthly P&L, cash and runway'!H5<=12))="",FALSE,IF(ISERROR('Monthly P&L, cash and runway'!H5<=12),'Monthly P&L, cash and runway'!H5<=12,IF('Monthly P&L, cash and runway'!H5="","",'Monthly P&L, cash and runway'!H5<=12))),'Model inputs'!B56+('Model inputs'!B47-'Model inputs'!B56)*('Monthly P&L, cash and runway'!H5-6)/6,'Model inputs'!B47+('Model inputs'!B50-'Model inputs'!B47)*('Monthly P&L, cash and runway'!H5-12)/12))),0)) -> 1 | I8: =IF(IF(IF(ISERROR('Monthly P&L, cash and runway'!I5<1),'Monthly P&L, cash and runway'!I5<1,IF('Monthly P&L, cash and runway'!I5="","",'Monthly P&L, cash and runway'!I5<1))="",FALSE,IF(ISERROR('Monthly P&L, cash and runway'!I5<1),'Monthly P&L, cash and runway'!I5<1,IF('Monthly P&L, cash and runway'!I5="","",'Monthly P&L, cash and runway'!I5<1))),0,ROUND(IF(IF(IF(ISERROR('Monthly P&L, cash and runway'!I5<=3),'Monthly P&L, cash and runway'!I5<=3,IF('Monthly P&L, cash and runway'!I5="","",'Monthly P&L, cash and runway'!I5<=3))="",FALSE,IF(ISERROR('Monthly P&L, cash and runway'!I5<=3),'Monthly P&L, cash and runway'!I5<=3,IF('Monthly P&L, cash and runway'!I5="","",'Monthly P&L, cash and runway'!I5<=3))),IF('Model inputs'!B53="","",'Model inputs'!B53),IF(IF(IF(ISERROR('Monthly P&L, cash and runway'!I5<=6),'Monthly P&L, cash and runway'!I5<=6,IF('Monthly P&L, cash and runway'!I5="","",'Monthly P&L, cash and runway'!I5<=6))="",FALSE,IF(ISERROR('Monthly P&L, cash and runway'!I5<=6),'Monthly P&L, cash and runway'!I5<=6,IF('Monthly P&L, cash and runway'!I5="","",'Monthly P&L, cash and runway'!I5<=6))),'Model inputs'!B53+('Model inputs'!B56-'Model inputs'!B53)*('Monthly P&L, cash and runway'!I5-3)/3,IF(IF(IF(ISERROR('Monthly P&L, cash and runway'!I5<=12),'Monthly P&L, cash and runway'!I5<=12,IF('Monthly P&L, cash and runway'!I5="","",'Monthly P&L, cash and runway'!I5<=12))="",FALSE,IF(ISERROR('Monthly P&L, cash and runway'!I5<=12),'Monthly P&L, cash and runway'!I5<=12,IF('Monthly P&L, cash and runway'!I5="","",'Monthly P&L, cash and runway'!I5<=12))),'Model inputs'!B56+('Model inputs'!B47-'Model inputs'!B56)*('Monthly P&L, cash and runway'!I5-6)/6,'Model inputs'!B47+('Model inputs'!B50-'Model inputs'!B47)*('Monthly P&L, cash and runway'!I5-12)/12))),0)) -> 2 | J8: =IF(IF(IF(ISERROR('Monthly P&L, cash and runway'!J5<1),'Monthly P&L, cash and runway'!J5<1,IF('Monthly P&L, cash and runway'!J5="","",'Monthly P&L, cash and runway'!J5<1))="",FALSE,IF(ISERROR('Monthly P&L, cash and runway'!J5<1),'Monthly P&L, cash and runway'!J5<1,IF('Monthly P&L, cash and runway'!J5="","",'Monthly P&L, cash and runway'!J5<1))),0,ROUND(IF(IF(IF(ISERROR('Monthly P&L, cash and runway'!J5<=3),'Monthly P&L, cash and runway'!J5<=3,IF('Monthly P&L, cash and runway'!J5="","",'Monthly P&L, cash and runway'!J5<=3))="",FALSE,IF(ISERROR('Monthly P&L, cash and runway'!J5<=3),'Monthly P&L, cash and runway'!J5<=3,IF('Monthly P&L, cash and runway'!J5="","",'Monthly P&L, cash and runway'!J5<=3))),IF('Model inputs'!B53="","",'Model inputs'!B53),IF(IF(IF(ISERROR('Monthly P&L, cash and runway'!J5<=6),'Monthly P&L, cash and runway'!J5<=6,IF('Monthly P&L, cash and runway'!J5="","",'Monthly P&L, cash and runway'!J5<=6))="",FALSE,IF(ISERROR('Monthly P&L, cash and runway'!J5<=6),'Monthly P&L, cash and runway'!J5<=6,IF('Monthly P&L, cash and runway'!J5="","",'Monthly P&L, cash and runway'!J5<=6))),'Model inputs'!B53+('Model inputs'!B56-'Model inputs'!B53)*('Monthly P&L, cash and runway'!J5-3)/3,IF(IF(IF(ISERROR('Monthly P&L, cash and runway'!J5<=12),'Monthly P&L, cash and runway'!J5<=12,IF('Monthly P&L, cash and runway'!J5="","",'Monthly P&L, cash and runway'!J5<=12))="",FALSE,IF(ISERROR('Monthly P&L, cash and runway'!J5<=12),'Monthly P&L, cash and runway'!J5<=12,IF('Monthly P&L, cash and runway'!J5="","",'Monthly P&L, cash and runway'!J5<=12))),'Model inputs'!B56+('Model inputs'!B47-'Model inputs'!B56)*('Monthly P&L, cash and runway'!J5-6)/6,'Model inputs'!B47+('Model inputs'!B50-'Model inputs'!B47)*('Monthly P&L, cash and runway'!J5-12)/12))),0)) -> 2 | K8: =IF(IF(IF(ISERROR('Monthly P&L, cash and runway'!K5<1),'Monthly P&L, cash and runway'!K5<1,IF('Monthly P&L, cash and runway'!K5="","",'Monthly P&L, cash and runway'!K5<1))="",FALSE,IF(ISERROR('Monthly P&L, cash and runway'!K5<1),'Monthly P&L, cash and runway'!K5<1,IF('Monthly P&L, cash and runway'!K5="","",'Monthly P&L, cash and runway'!K5<1))),0,ROUND(IF(IF(IF(ISERROR('Monthly P&L, cash and runway'!K5<=3),'Monthly P&L, cash and runway'!K5<=3,IF('Monthly P&L, cash and runway'!K5="","",'Monthly P&L, cash and runway'!K5<=3))="",FALSE,IF(ISERROR('Monthly P&L, cash and runway'!K5<=3),'Monthly P&L, cash and runway'!K5<=3,IF('Monthly P&L, cash and runway'!K5="","",'Monthly P&L, cash and runway'!K5<=3))),IF('Model inputs'!B53="","",'Model inputs'!B53),IF(IF(IF(ISERROR('Monthly P&L, cash and runway'!K5<=6),'Monthly P&L, cash and runway'!K5<=6,IF('Monthly P&L, cash and runway'!K5="","",'Monthly P&L, cash and runway'!K5<=6))="",FALSE,IF(ISERROR('Monthly P&L, cash and runway'!K5<=6),'Monthly P&L, cash and runway'!K5<=6,IF('Monthly P&L, cash and runway'!K5="","",'Monthly P&L, cash and runway'!K5<=6))),'Model inputs'!B53+('Model inputs'!B56-'Model inputs'!B53)*('Monthly P&L, cash and runway'!K5-3)/3,IF(IF(IF(ISERROR('Monthly P&L, cash and runway'!K5<=12),'Monthly P&L, cash and runway'!K5<=12,IF('Monthly P&L, cash and runway'!K5="","",'Monthly P&L, cash and runway'!K5<=12))="",FALSE,IF(ISERROR('Monthly P&L, cash and runway'!K5<=12),'Monthly P&L, cash and runway'!K5<=12,IF('Monthly P&L, cash and runway'!K5="","",'Monthly P&L, cash and runway'!K5<=12))),'Model inputs'!B56+('Model inputs'!B47-'Model inputs'!B56)*('Monthly P&L, cash and runway'!K5-6)/6,'Model inputs'!B47+('Model inputs'!B50-'Model inputs'!B47)*('Monthly P&L, cash and runway'!K5-12)/12))),0)) -> 2 | L8: =IF(IF(IF(ISERROR('Monthly P&L, cash and runway'!L5<1),'Monthly P&L, cash and runway'!L5<1,IF('Monthly P&L, cash and runway'!L5="","",'Monthly P&L, cash and runway'!L5<1))="",FALSE,IF(ISERROR('Monthly P&L, cash and runway'!L5<1),'Monthly P&L, cash and runway'!L5<1,IF('Monthly P&L, cash and runway'!L5="","",'Monthly P&L, cash and runway'!L5<1))),0,ROUND(IF(IF(IF(ISERROR('Monthly P&L, cash and runway'!L5<=3),'Monthly P&L, cash and runway'!L5<=3,IF('Monthly P&L, cash and runway'!L5="","",'Monthly P&L, cash and runway'!L5<=3))="",FALSE,IF(ISERROR('Monthly P&L, cash and runway'!L5<=3),'Monthly P&L, cash and runway'!L5<=3,IF('Monthly P&L, cash and runway'!L5="","",'Monthly P&L, cash and runway'!L5<=3))),IF('Model inputs'!B53="","",'Model inputs'!B53),IF(IF(IF(ISERROR('Monthly P&L, cash and runway'!L5<=6),'Monthly P&L, cash and runway'!L5<=6,IF('Monthly P&L, cash and runway'!L5="","",'Monthly P&L, cash and runway'!L5<=6))="",FALSE,IF(ISERROR('Monthly P&L, cash and runway'!L5<=6),'Monthly P&L, cash and runway'!L5<=6,IF('Monthly P&L, cash and runway'!L5="","",'Monthly P&L, cash and runway'!L5<=6))),'Model inputs'!B53+('Model inputs'!B56-'Model inputs'!B53)*('Monthly P&L, cash and runway'!L5-3)/3,IF(IF(IF(ISERROR('Monthly P&L, cash and runway'!L5<=12),'Monthly P&L, cash and runway'!L5<=12,IF('Monthly P&L, cash and runway'!L5="","",'Monthly P&L, cash and runway'!L5<=12))="",FALSE,IF(ISERROR('Monthly P&L, cash and runway'!L5<=12),'Monthly P&L, cash and runway'!L5<=12,IF('Monthly P&L, cash and runway'!L5="","",'Monthly P&L, cash and runway'!L5<=12))),'Model inputs'!B56+('Model inputs'!B47-'Model inputs'!B56)*('Monthly P&L, cash and runway'!L5-6)/6,'Model inputs'!B47+('Model inputs'!B50-'Model inputs'!B47)*('Monthly P&L, cash and runway'!L5-12)/12))),0)) -> 3 | M8: =IF(IF(IF(ISERROR('Monthly P&L, cash and runway'!M5<1),'Monthly P&L, cash and runway'!M5<1,IF('Monthly P&L, cash and runway'!M5="","",'Monthly P&L, cash and runway'!M5<1))="",FALSE,IF(ISERROR('Monthly P&L, cash and runway'!M5<1),'Monthly P&L, cash and runway'!M5<1,IF('Monthly P&L, cash and runway'!M5="","",'Monthly P&L, cash and runway'!M5<1))),0,ROUND(IF(IF(IF(ISERROR('Monthly P&L, cash and runway'!M5<=3),'Monthly P&L, cash and runway'!M5<=3,IF('Monthly P&L, cash and runway'!M5="","",'Monthly P&L, cash and runway'!M5<=3))="",FALSE,IF(ISERROR('Monthly P&L, cash and runway'!M5<=3),'Monthly P&L, cash and runway'!M5<=3,IF('Monthly P&L, cash and runway'!M5="","",'Monthly P&L, cash and runway'!M5<=3))),IF('Model inputs'!B53="","",'Model inputs'!B53),IF(IF(IF(ISERROR('Monthly P&L, cash and runway'!M5<=6),'Monthly P&L, cash and runway'!M5<=6,IF('Monthly P&L, cash and runway'!M5="","",'Monthly P&L, cash and runway'!M5<=6))="",FALSE,IF(ISERROR('Monthly P&L, cash and runway'!M5<=6),'Monthly P&L, cash and runway'!M5<=6,IF('Monthly P&L, cash and runway'!M5="","",'Monthly P&L, cash and runway'!M5<=6))),'Model inputs'!B53+('Model inputs'!B56-'Model inputs'!B53)*('Monthly P&L, cash and runway'!M5-3)/3,IF(IF(IF(ISERROR('Monthly P&L, cash and runway'!M5<=12),'Monthly P&L, cash and runway'!M5<=12,IF('Monthly P&L, cash and runway'!M5="","",'Monthly P&L, cash and runway'!M5<=12))="",FALSE,IF(ISERROR('Monthly P&L, cash and runway'!M5<=12),'Monthly P&L, cash and runway'!M5<=12,IF('Monthly P&L, cash and runway'!M5="","",'Monthly P&L, cash and runway'!M5<=12))),'Model inputs'!B56+('Model inputs'!B47-'Model inputs'!B56)*('Monthly P&L, cash and runway'!M5-6)/6,'Model inputs'!B47+('Model inputs'!B50-'Model inputs'!B47)*('Monthly P&L, cash and runway'!M5-12)/12))),0)) -> 3 | N8: =IF(IF(IF(ISERROR('Monthly P&L, cash and runway'!N5<1),'Monthly P&L, cash and runway'!N5<1,IF('Monthly P&L, cash and runway'!N5="","",'Monthly P&L, cash and runway'!N5<1))="",FALSE,IF(ISERROR('Monthly P&L, cash and runway'!N5<1),'Monthly P&L, cash and runway'!N5<1,IF('Monthly P&L, cash and runway'!N5="","",'Monthly P&L, cash and runway'!N5<1))),0,ROUND(IF(IF(IF(ISERROR('Monthly P&L, cash and runway'!N5<=3),'Monthly P&L, cash and runway'!N5<=3,IF('Monthly P&L, cash and runway'!N5="","",'Monthly P&L, cash and runway'!N5<=3))="",FALSE,IF(ISERROR('Monthly P&L, cash and runway'!N5<=3),'Monthly P&L, cash and runway'!N5<=3,IF('Monthly P&L, cash and runway'!N5="","",'Monthly P&L, cash and runway'!N5<=3))),IF('Model inputs'!B53="","",'Model inputs'!B53),IF(IF(IF(ISERROR('Monthly P&L, cash and runway'!N5<=6),'Monthly P&L, cash and runway'!N5<=6,IF('Monthly P&L, cash and runway'!N5="","",'Monthly P&L, cash and runway'!N5<=6))="",FALSE,IF(ISERROR('Monthly P&L, cash and runway'!N5<=6),'Monthly P&L, cash and runway'!N5<=6,IF('Monthly P&L, cash and runway'!N5="","",'Monthly P&L, cash and runway'!N5<=6))),'Model inputs'!B53+('Model inputs'!B56-'Model inputs'!B53)*('Monthly P&L, cash and runway'!N5-3)/3,IF(IF(IF(ISERROR('Monthly P&L, cash and runway'!N5<=12),'Monthly P&L, cash and runway'!N5<=12,IF('Monthly P&L, cash and runway'!N5="","",'Monthly P&L, cash and runway'!N5<=12))="",FALSE,IF(ISERROR('Monthly P&L, cash and runway'!N5<=12),'Monthly P&L, cash and runway'!N5<=12,IF('Monthly P&L, cash and runway'!N5="","",'Monthly P&L, cash and runway'!N5<=12))),'Model inputs'!B56+('Model inputs'!B47-'Model inputs'!B56)*('Monthly P&L, cash and runway'!N5-6)/6,'Model inputs'!B47+('Model inputs'!B50-'Model inputs'!B47)*('Monthly P&L, cash and runway'!N5-12)/12))),0)) -> 4 | O8: =IF(IF(IF(ISERROR('Monthly P&L, cash and runway'!O5<1),'Monthly P&L, cash and runway'!O5<1,IF('Monthly P&L, cash and runway'!O5="","",'Monthly P&L, cash and runway'!O5<1))="",FALSE,IF(ISERROR('Monthly P&L, cash and runway'!O5<1),'Monthly P&L, cash and runway'!O5<1,IF('Monthly P&L, cash and runway'!O5="","",'Monthly P&L, cash and runway'!O5<1))),0,ROUND(IF(IF(IF(ISERROR('Monthly P&L, cash and runway'!O5<=3),'Monthly P&L, cash and runway'!O5<=3,IF('Monthly P&L, cash and runway'!O5="","",'Monthly P&L, cash and runway'!O5<=3))="",FALSE,IF(ISERROR('Monthly P&L, cash and runway'!O5<=3),'Monthly P&L, cash and runway'!O5<=3,IF('Monthly P&L, cash and runway'!O5="","",'Monthly P&L, cash and runway'!O5<=3))),IF('Model inputs'!B53="","",'Model inputs'!B53),IF(IF(IF(ISERROR('Monthly P&L, cash and runway'!O5<=6),'Monthly P&L, cash and runway'!O5<=6,IF('Monthly P&L, cash and runway'!O5="","",'Monthly P&L, cash and runway'!O5<=6))="",FALSE,IF(ISERROR('Monthly P&L, cash and runway'!O5<=6),'Monthly P&L, cash and runway'!O5<=6,IF('Monthly P&L, cash and runway'!O5="","",'Monthly P&L, cash and runway'!O5<=6))),'Model inputs'!B53+('Model inputs'!B56-'Model inputs'!B53)*('Monthly P&L, cash and runway'!O5-3)/3,IF(IF(IF(ISERROR('Monthly P&L, cash and runway'!O5<=12),'Monthly P&L, cash and runway'!O5<=12,IF('Monthly P&L, cash and runway'!O5="","",'Monthly P&L, cash and runway'!O5<=12))="",FALSE,IF(ISERROR('Monthly P&L, cash and runway'!O5<=12),'Monthly P&L, cash and runway'!O5<=12,IF('Monthly P&L, cash and runway'!O5="","",'Monthly P&L, cash and runway'!O5<=12))),'Model inputs'!B56+('Model inputs'!B47-'Model inputs'!B56)*('Monthly P&L, cash and runway'!O5-6)/6,'Model inputs'!B47+('Model inputs'!B50-'Model inputs'!B47)*('Monthly P&L, cash and runway'!O5-12)/12))),0)) -> 4 | P8: =IF(IF(IF(ISERROR('Monthly P&L, cash and runway'!P5<1),'Monthly P&L, cash and runway'!P5<1,IF('Monthly P&L, cash and runway'!P5="","",'Monthly P&L, cash and runway'!P5<1))="",FALSE,IF(ISERROR('Monthly P&L, cash and runway'!P5<1),'Monthly P&L, cash and runway'!P5<1,IF('Monthly P&L, cash and runway'!P5="","",'Monthly P&L, cash and runway'!P5<1))),0,ROUND(IF(IF(IF(ISERROR('Monthly P&L, cash and runway'!P5<=3),'Monthly P&L, cash and runway'!P5<=3,IF('Monthly P&L, cash and runway'!P5="","",'Monthly P&L, cash and runway'!P5<=3))="",FALSE,IF(ISERROR('Monthly P&L, cash and runway'!P5<=3),'Monthly P&L, cash and runway'!P5<=3,IF('Monthly P&L, cash and runway'!P5="","",'Monthly P&L, cash and runway'!P5<=3))),IF('Model inputs'!B53="","",'Model inputs'!B53),IF(IF(IF(ISERROR('Monthly P&L, cash and runway'!P5<=6),'Monthly P&L, cash and runway'!P5<=6,IF('Monthly P&L, cash and runway'!P5="","",'Monthly P&L, cash and runway'!P5<=6))="",FALSE,IF(ISERROR('Monthly P&L, cash and runway'!P5<=6),'Monthly P&L, cash and runway'!P5<=6,IF('Monthly P&L, cash and runway'!P5="","",'Monthly P&L, cash and runway'!P5<=6))),'Model inputs'!B53+('Model inputs'!B56-'Model inputs'!B53)*('Monthly P&L, cash and runway'!P5-3)/3,IF(IF(IF(ISERROR('Monthly P&L, cash and runway'!P5<=12),'Monthly P&L, cash and runway'!P5<=12,IF('Monthly P&L, cash and runway'!P5="","",'Monthly P&L, cash and runway'!P5<=12))="",FALSE,IF(ISERROR('Monthly P&L, cash and runway'!P5<=12),'Monthly P&L, cash and runway'!P5<=12,IF('Monthly P&L, cash and runway'!P5="","",'Monthly P&L, cash and runway'!P5<=12))),'Model inputs'!B56+('Model inputs'!B47-'Model inputs'!B56)*('Monthly P&L, cash and runway'!P5-6)/6,'Model inputs'!B47+('Model inputs'!B50-'Model inputs'!B47)*('Monthly P&L, cash and runway'!P5-12)/12))),0)) -> 5 | Q8: =IF(IF(IF(ISERROR('Monthly P&L, cash and runway'!Q5<1),'Monthly P&L, cash and runway'!Q5<1,IF('Monthly P&L, cash and runway'!Q5="","",'Monthly P&L, cash and runway'!Q5<1))="",FALSE,IF(ISERROR('Monthly P&L, cash and runway'!Q5<1),'Monthly P&L, cash and runway'!Q5<1,IF('Monthly P&L, cash and runway'!Q5="","",'Monthly P&L, cash and runway'!Q5<1))),0,ROUND(IF(IF(IF(ISERROR('Monthly P&L, cash and runway'!Q5<=3),'Monthly P&L, cash and runway'!Q5<=3,IF('Monthly P&L, cash and runway'!Q5="","",'Monthly P&L, cash and runway'!Q5<=3))="",FALSE,IF(ISERROR('Monthly P&L, cash and runway'!Q5<=3),'Monthly P&L, cash and runway'!Q5<=3,IF('Monthly P&L, cash and runway'!Q5="","",'Monthly P&L, cash and runway'!Q5<=3))),IF('Model inputs'!B53="","",'Model inputs'!B53),IF(IF(IF(ISERROR('Monthly P&L, cash and runway'!Q5<=6),'Monthly P&L, cash and runway'!Q5<=6,IF('Monthly P&L, cash and runway'!Q5="","",'Monthly P&L, cash and runway'!Q5<=6))="",FALSE,IF(ISERROR('Monthly P&L, cash and runway'!Q5<=6),'Monthly P&L, cash and runway'!Q5<=6,IF('Monthly P&L, cash and runway'!Q5="","",'Monthly P&L, cash and runway'!Q5<=6))),'Model inputs'!B53+('Model inputs'!B56-'Model inputs'!B53)*('Monthly P&L, cash and runway'!Q5-3)/3,IF(IF(IF(ISERROR('Monthly P&L, cash and runway'!Q5<=12),'Monthly P&L, cash and runway'!Q5<=12,IF('Monthly P&L, cash and runway'!Q5="","",'Monthly P&L, cash and runway'!Q5<=12))="",FALSE,IF(ISERROR('Monthly P&L, cash and runway'!Q5<=12),'Monthly P&L, cash and runway'!Q5<=12,IF('Monthly P&L, cash and runway'!Q5="","",'Monthly P&L, cash and runway'!Q5<=12))),'Model inputs'!B56+('Model inputs'!B47-'Model inputs'!B56)*('Monthly P&L, cash and runway'!Q5-6)/6,'Model inputs'!B47+('Model inputs'!B50-'Model inputs'!B47)*('Monthly P&L, cash and runway'!Q5-12)/12))),0)) -> 5 | R8: =IF(IF(IF(ISERROR('Monthly P&L, cash and runway'!R5<1),'Monthly P&L, cash and runway'!R5<1,IF('Monthly P&L, cash and runway'!R5="","",'Monthly P&L, cash and runway'!R5<1))="",FALSE,IF(ISERROR('Monthly P&L, cash and runway'!R5<1),'Monthly P&L, cash and runway'!R5<1,IF('Monthly P&L, cash and runway'!R5="","",'Monthly P&L, cash and runway'!R5<1))),0,ROUND(IF(IF(IF(ISERROR('Monthly P&L, cash and runway'!R5<=3),'Monthly P&L, cash and runway'!R5<=3,IF('Monthly P&L, cash and runway'!R5="","",'Monthly P&L, cash and runway'!R5<=3))="",FALSE,IF(ISERROR('Monthly P&L, cash and runway'!R5<=3),'Monthly P&L, cash and runway'!R5<=3,IF('Monthly P&L, cash and runway'!R5="","",'Monthly P&L, cash and runway'!R5<=3))),IF('Model inputs'!B53="","",'Model inputs'!B53),IF(IF(IF(ISERROR('Monthly P&L, cash and runway'!R5<=6),'Monthly P&L, cash and runway'!R5<=6,IF('Monthly P&L, cash and runway'!R5="","",'Monthly P&L, cash and runway'!R5<=6))="",FALSE,IF(ISERROR('Monthly P&L, cash and runway'!R5<=6),'Monthly P&L, cash and runway'!R5<=6,IF('Monthly P&L, cash and runway'!R5="","",'Monthly P&L, cash and runway'!R5<=6))),'Model inputs'!B53+('Model inputs'!B56-'Model inputs'!B53)*('Monthly P&L, cash and runway'!R5-3)/3,IF(IF(IF(ISERROR('Monthly P&L, cash and runway'!R5<=12),'Monthly P&L, cash and runway'!R5<=12,IF('Monthly P&L, cash and runway'!R5="","",'Monthly P&L, cash and runway'!R5<=12))="",FALSE,IF(ISERROR('Monthly P&L, cash and runway'!R5<=12),'Monthly P&L, cash and runway'!R5<=12,IF('Monthly P&L, cash and runway'!R5="","",'Monthly P&L, cash and runway'!R5<=12))),'Model inputs'!B56+('Model inputs'!B47-'Model inputs'!B56)*('Monthly P&L, cash and runway'!R5-6)/6,'Model inputs'!B47+('Model inputs'!B50-'Model inputs'!B47)*('Monthly P&L, cash and runway'!R5-12)/12))),0)) -> 6 | S8: =IF(IF(IF(ISERROR('Monthly P&L, cash and runway'!S5<1),'Monthly P&L, cash and runway'!S5<1,IF('Monthly P&L, cash and runway'!S5="","",'Monthly P&L, cash and runway'!S5<1))="",FALSE,IF(ISERROR('Monthly P&L, cash and runway'!S5<1),'Monthly P&L, cash and runway'!S5<1,IF('Monthly P&L, cash and runway'!S5="","",'Monthly P&L, cash and runway'!S5<1))),0,ROUND(IF(IF(IF(ISERROR('Monthly P&L, cash and runway'!S5<=3),'Monthly P&L, cash and runway'!S5<=3,IF('Monthly P&L, cash and runway'!S5="","",'Monthly P&L, cash and runway'!S5<=3))="",FALSE,IF(ISERROR('Monthly P&L, cash and runway'!S5<=3),'Monthly P&L, cash and runway'!S5<=3,IF('Monthly P&L, cash and runway'!S5="","",'Monthly P&L, cash and runway'!S5<=3))),IF('Model inputs'!B53="","",'Model inputs'!B53),IF(IF(IF(ISERROR('Monthly P&L, cash and runway'!S5<=6),'Monthly P&L, cash and runway'!S5<=6,IF('Monthly P&L, cash and runway'!S5="","",'Monthly P&L, cash and runway'!S5<=6))="",FALSE,IF(ISERROR('Monthly P&L, cash and runway'!S5<=6),'Monthly P&L, cash and runway'!S5<=6,IF('Monthly P&L, cash and runway'!S5="","",'Monthly P&L, cash and runway'!S5<=6))),'Model inputs'!B53+('Model inputs'!B56-'Model inputs'!B53)*('Monthly P&L, cash and runway'!S5-3)/3,IF(IF(IF(ISERROR('Monthly P&L, cash and runway'!S5<=12),'Monthly P&L, cash and runway'!S5<=12,IF('Monthly P&L, cash and runway'!S5="","",'Monthly P&L, cash and runway'!S5<=12))="",FALSE,IF(ISERROR('Monthly P&L, cash and runway'!S5<=12),'Monthly P&L, cash and runway'!S5<=12,IF('Monthly P&L, cash and runway'!S5="","",'Monthly P&L, cash and runway'!S5<=12))),'Model inputs'!B56+('Model inputs'!B47-'Model inputs'!B56)*('Monthly P&L, cash and runway'!S5-6)/6,'Model inputs'!B47+('Model inputs'!B50-'Model inputs'!B47)*('Monthly P&L, cash and runway'!S5-12)/12))),0)) -> 7 | T8: =IF(IF(IF(ISERROR('Monthly P&L, cash and runway'!T5<1),'Monthly P&L, cash and runway'!T5<1,IF('Monthly P&L, cash and runway'!T5="","",'Monthly P&L, cash and runway'!T5<1))="",FALSE,IF(ISERROR('Monthly P&L, cash and runway'!T5<1),'Monthly P&L, cash and runway'!T5<1,IF('Monthly P&L, cash and runway'!T5="","",'Monthly P&L, cash and runway'!T5<1))),0,ROUND(IF(IF(IF(ISERROR('Monthly P&L, cash and runway'!T5<=3),'Monthly P&L, cash and runway'!T5<=3,IF('Monthly P&L, cash and runway'!T5="","",'Monthly P&L, cash and runway'!T5<=3))="",FALSE,IF(ISERROR('Monthly P&L, cash and runway'!T5<=3),'Monthly P&L, cash and runway'!T5<=3,IF('Monthly P&L, cash and runway'!T5="","",'Monthly P&L, cash and runway'!T5<=3))),IF('Model inputs'!B53="","",'Model inputs'!B53),IF(IF(IF(ISERROR('Monthly P&L, cash and runway'!T5<=6),'Monthly P&L, cash and runway'!T5<=6,IF('Monthly P&L, cash and runway'!T5="","",'Monthly P&L, cash and runway'!T5<=6))="",FALSE,IF(ISERROR('Monthly P&L, cash and runway'!T5<=6),'Monthly P&L, cash and runway'!T5<=6,IF('Monthly P&L, cash and runway'!T5="","",'Monthly P&L, cash and runway'!T5<=6))),'Model inputs'!B53+('Model inputs'!B56-'Model inputs'!B53)*('Monthly P&L, cash and runway'!T5-3)/3,IF(IF(IF(ISERROR('Monthly P&L, cash and runway'!T5<=12),'Monthly P&L, cash and runway'!T5<=12,IF('Monthly P&L, cash and runway'!T5="","",'Monthly P&L, cash and runway'!T5<=12))="",FALSE,IF(ISERROR('Monthly P&L, cash and runway'!T5<=12),'Monthly P&L, cash and runway'!T5<=12,IF('Monthly P&L, cash and runway'!T5="","",'Monthly P&L, cash and runway'!T5<=12))),'Model inputs'!B56+('Model inputs'!B47-'Model inputs'!B56)*('Monthly P&L, cash and runway'!T5-6)/6,'Model inputs'!B47+('Model inputs'!B50-'Model inputs'!B47)*('Monthly P&L, cash and runway'!T5-12)/12))),0)) -> 7 | U8: =IF(IF(IF(ISERROR('Monthly P&L, cash and runway'!U5<1),'Monthly P&L, cash and runway'!U5<1,IF('Monthly P&L, cash and runway'!U5="","",'Monthly P&L, cash and runway'!U5<1))="",FALSE,IF(ISERROR('Monthly P&L, cash and runway'!U5<1),'Monthly P&L, cash and runway'!U5<1,IF('Monthly P&L, cash and runway'!U5="","",'Monthly P&L, cash and runway'!U5<1))),0,ROUND(IF(IF(IF(ISERROR('Monthly P&L, cash and runway'!U5<=3),'Monthly P&L, cash and runway'!U5<=3,IF('Monthly P&L, cash and runway'!U5="","",'Monthly P&L, cash and runway'!U5<=3))="",FALSE,IF(ISERROR('Monthly P&L, cash and runway'!U5<=3),'Monthly P&L, cash and runway'!U5<=3,IF('Monthly P&L, cash and runway'!U5="","",'Monthly P&L, cash and runway'!U5<=3))),IF('Model inputs'!B53="","",'Model inputs'!B53),IF(IF(IF(ISERROR('Monthly P&L, cash and runway'!U5<=6),'Monthly P&L, cash and runway'!U5<=6,IF('Monthly P&L, cash and runway'!U5="","",'Monthly P&L, cash and runway'!U5<=6))="",FALSE,IF(ISERROR('Monthly P&L, cash and runway'!U5<=6),'Monthly P&L, cash and runway'!U5<=6,IF('Monthly P&L, cash and runway'!U5="","",'Monthly P&L, cash and runway'!U5<=6))),'Model inputs'!B53+('Model inputs'!B56-'Model inputs'!B53)*('Monthly P&L, cash and runway'!U5-3)/3,IF(IF(IF(ISERROR('Monthly P&L, cash and runway'!U5<=12),'Monthly P&L, cash and runway'!U5<=12,IF('Monthly P&L, cash and runway'!U5="","",'Monthly P&L, cash and runway'!U5<=12))="",FALSE,IF(ISERROR('Monthly P&L, cash and runway'!U5<=12),'Monthly P&L, cash and runway'!U5<=12,IF('Monthly P&L, cash and runway'!U5="","",'Monthly P&L, cash and runway'!U5<=12))),'Model inputs'!B56+('Model inputs'!B47-'Model inputs'!B56)*('Monthly P&L, cash and runway'!U5-6)/6,'Model inputs'!B47+('Model inputs'!B50-'Model inputs'!B47)*('Monthly P&L, cash and runway'!U5-12)/12))),0)) -> 8 | V8: =IF(IF(IF(ISERROR('Monthly P&L, cash and runway'!V5<1),'Monthly P&L, cash and runway'!V5<1,IF('Monthly P&L, cash and runway'!V5="","",'Monthly P&L, cash and runway'!V5<1))="",FALSE,IF(ISERROR('Monthly P&L, cash and runway'!V5<1),'Monthly P&L, cash and runway'!V5<1,IF('Monthly P&L, cash and runway'!V5="","",'Monthly P&L, cash and runway'!V5<1))),0,ROUND(IF(IF(IF(ISERROR('Monthly P&L, cash and runway'!V5<=3),'Monthly P&L, cash and runway'!V5<=3,IF('Monthly P&L, cash and runway'!V5="","",'Monthly P&L, cash and runway'!V5<=3))="",FALSE,IF(ISERROR('Monthly P&L, cash and runway'!V5<=3),'Monthly P&L, cash and runway'!V5<=3,IF('Monthly P&L, cash and runway'!V5="","",'Monthly P&L, cash and runway'!V5<=3))),IF('Model inputs'!B53="","",'Model inputs'!B53),IF(IF(IF(ISERROR('Monthly P&L, cash and runway'!V5<=6),'Monthly P&L, cash and runway'!V5<=6,IF('Monthly P&L, cash and runway'!V5="","",'Monthly P&L, cash and runway'!V5<=6))="",FALSE,IF(ISERROR('Monthly P&L, cash and runway'!V5<=6),'Monthly P&L, cash and runway'!V5<=6,IF('Monthly P&L, cash and runway'!V5="","",'Monthly P&L, cash and runway'!V5<=6))),'Model inputs'!B53+('Model inputs'!B56-'Model inputs'!B53)*('Monthly P&L, cash and runway'!V5-3)/3,IF(IF(IF(ISERROR('Monthly P&L, cash and runway'!V5<=12),'Monthly P&L, cash and runway'!V5<=12,IF('Monthly P&L, cash and runway'!V5="","",'Monthly P&L, cash and runway'!V5<=12))="",FALSE,IF(ISERROR('Monthly P&L, cash and runway'!V5<=12),'Monthly P&L, cash and runway'!V5<=12,IF('Monthly P&L, cash and runway'!V5="","",'Monthly P&L, cash and runway'!V5<=12))),'Model inputs'!B56+('Model inputs'!B47-'Model inputs'!B56)*('Monthly P&L, cash and runway'!V5-6)/6,'Model inputs'!B47+('Model inputs'!B50-'Model inputs'!B47)*('Monthly P&L, cash and runway'!V5-12)/12))),0)) -> 8 | W8: =IF(IF(IF(ISERROR('Monthly P&L, cash and runway'!W5<1),'Monthly P&L, cash and runway'!W5<1,IF('Monthly P&L, cash and runway'!W5="","",'Monthly P&L, cash and runway'!W5<1))="",FALSE,IF(ISERROR('Monthly P&L, cash and runway'!W5<1),'Monthly P&L, cash and runway'!W5<1,IF('Monthly P&L, cash and runway'!W5="","",'Monthly P&L, cash and runway'!W5<1))),0,ROUND(IF(IF(IF(ISERROR('Monthly P&L, cash and runway'!W5<=3),'Monthly P&L, cash and runway'!W5<=3,IF('Monthly P&L, cash and runway'!W5="","",'Monthly P&L, cash and runway'!W5<=3))="",FALSE,IF(ISERROR('Monthly P&L, cash and runway'!W5<=3),'Monthly P&L, cash and runway'!W5<=3,IF('Monthly P&L, cash and runway'!W5="","",'Monthly P&L, cash and runway'!W5<=3))),IF('Model inputs'!B53="","",'Model inputs'!B53),IF(IF(IF(ISERROR('Monthly P&L, cash and runway'!W5<=6),'Monthly P&L, cash and runway'!W5<=6,IF('Monthly P&L, cash and runway'!W5="","",'Monthly P&L, cash and runway'!W5<=6))="",FALSE,IF(ISERROR('Monthly P&L, cash and runway'!W5<=6),'Monthly P&L, cash and runway'!W5<=6,IF('Monthly P&L, cash and runway'!W5="","",'Monthly P&L, cash and runway'!W5<=6))),'Model inputs'!B53+('Model inputs'!B56-'Model inputs'!B53)*('Monthly P&L, cash and runway'!W5-3)/3,IF(IF(IF(ISERROR('Monthly P&L, cash and runway'!W5<=12),'Monthly P&L, cash and runway'!W5<=12,IF('Monthly P&L, cash and runway'!W5="","",'Monthly P&L, cash and runway'!W5<=12))="",FALSE,IF(ISERROR('Monthly P&L, cash and runway'!W5<=12),'Monthly P&L, cash and runway'!W5<=12,IF('Monthly P&L, cash and runway'!W5="","",'Monthly P&L, cash and runway'!W5<=12))),'Model inputs'!B56+('Model inputs'!B47-'Model inputs'!B56)*('Monthly P&L, cash and runway'!W5-6)/6,'Model inputs'!B47+('Model inputs'!B50-'Model inputs'!B47)*('Monthly P&L, cash and runway'!W5-12)/12))),0)) -> 9 | X8: =IF(IF(IF(ISERROR('Monthly P&L, cash and runway'!X5<1),'Monthly P&L, cash and runway'!X5<1,IF('Monthly P&L, cash and runway'!X5="","",'Monthly P&L, cash and runway'!X5<1))="",FALSE,IF(ISERROR('Monthly P&L, cash and runway'!X5<1),'Monthly P&L, cash and runway'!X5<1,IF('Monthly P&L, cash and runway'!X5="","",'Monthly P&L, cash and runway'!X5<1))),0,ROUND(IF(IF(IF(ISERROR('Monthly P&L, cash and runway'!X5<=3),'Monthly P&L, cash and runway'!X5<=3,IF('Monthly P&L, cash and runway'!X5="","",'Monthly P&L, cash and runway'!X5<=3))="",FALSE,IF(ISERROR('Monthly P&L, cash and runway'!X5<=3),'Monthly P&L, cash and runway'!X5<=3,IF('Monthly P&L, cash and runway'!X5="","",'Monthly P&L, cash and runway'!X5<=3))),IF('Model inputs'!B53="","",'Model inputs'!B53),IF(IF(IF(ISERROR('Monthly P&L, cash and runway'!X5<=6),'Monthly P&L, cash and runway'!X5<=6,IF('Monthly P&L, cash and runway'!X5="","",'Monthly P&L, cash and runway'!X5<=6))="",FALSE,IF(ISERROR('Monthly P&L, cash and runway'!X5<=6),'Monthly P&L, cash and runway'!X5<=6,IF('Monthly P&L, cash and runway'!X5="","",'Monthly P&L, cash and runway'!X5<=6))),'Model inputs'!B53+('Model inputs'!B56-'Model inputs'!B53)*('Monthly P&L, cash and runway'!X5-3)/3,IF(IF(IF(ISERROR('Monthly P&L, cash and runway'!X5<=12),'Monthly P&L, cash and runway'!X5<=12,IF('Monthly P&L, cash and runway'!X5="","",'Monthly P&L, cash and runway'!X5<=12))="",FALSE,IF(ISERROR('Monthly P&L, cash and runway'!X5<=12),'Monthly P&L, cash and runway'!X5<=12,IF('Monthly P&L, cash and runway'!X5="","",'Monthly P&L, cash and runway'!X5<=12))),'Model inputs'!B56+('Model inputs'!B47-'Model inputs'!B56)*('Monthly P&L, cash and runway'!X5-6)/6,'Model inputs'!B47+('Model inputs'!B50-'Model inputs'!B47)*('Monthly P&L, cash and runway'!X5-12)/12))),0)) -> 9 | Y8: =IF(IF(IF(ISERROR('Monthly P&L, cash and runway'!Y5<1),'Monthly P&L, cash and runway'!Y5<1,IF('Monthly P&L, cash and runway'!Y5="","",'Monthly P&L, cash and runway'!Y5<1))="",FALSE,IF(ISERROR('Monthly P&L, cash and runway'!Y5<1),'Monthly P&L, cash and runway'!Y5<1,IF('Monthly P&L, cash and runway'!Y5="","",'Monthly P&L, cash and runway'!Y5<1))),0,ROUND(IF(IF(IF(ISERROR('Monthly P&L, cash and runway'!Y5<=3),'Monthly P&L, cash and runway'!Y5<=3,IF('Monthly P&L, cash and runway'!Y5="","",'Monthly P&L, cash and runway'!Y5<=3))="",FALSE,IF(ISERROR('Monthly P&L, cash and runway'!Y5<=3),'Monthly P&L, cash and runway'!Y5<=3,IF('Monthly P&L, cash and runway'!Y5="","",'Monthly P&L, cash and runway'!Y5<=3))),IF('Model inputs'!B53="","",'Model inputs'!B53),IF(IF(IF(ISERROR('Monthly P&L, cash and runway'!Y5<=6),'Monthly P&L, cash and runway'!Y5<=6,IF('Monthly P&L, cash and runway'!Y5="","",'Monthly P&L, cash and runway'!Y5<=6))="",FALSE,IF(ISERROR('Monthly P&L, cash and runway'!Y5<=6),'Monthly P&L, cash and runway'!Y5<=6,IF('Monthly P&L, cash and runway'!Y5="","",'Monthly P&L, cash and runway'!Y5<=6))),'Model inputs'!B53+('Model inputs'!B56-'Model inputs'!B53)*('Monthly P&L, cash and runway'!Y5-3)/3,IF(IF(IF(ISERROR('Monthly P&L, cash and runway'!Y5<=12),'Monthly P&L, cash and runway'!Y5<=12,IF('Monthly P&L, cash and runway'!Y5="","",'Monthly P&L, cash and runway'!Y5<=12))="",FALSE,IF(ISERROR('Monthly P&L, cash and runway'!Y5<=12),'Monthly P&L, cash and runway'!Y5<=12,IF('Monthly P&L, cash and runway'!Y5="","",'Monthly P&L, cash and runway'!Y5<=12))),'Model inputs'!B56+('Model inputs'!B47-'Model inputs'!B56)*('Monthly P&L, cash and runway'!Y5-6)/6,'Model inputs'!B47+('Model inputs'!B50-'Model inputs'!B47)*('Monthly P&L, cash and runway'!Y5-12)/12))),0)) -> 10
A9: New customers | B9: =SUM('Monthly P&L, cash and runway'!B10,'Monthly P&L, cash and runway'!B11) -> 0 | C9: =SUM('Monthly P&L, cash and runway'!C10,'Monthly P&L, cash and runway'!C11) -> 0 | D9: =SUM('Monthly P&L, cash and runway'!D10,'Monthly P&L, cash and runway'!D11) -> 0 | E9: =SUM('Monthly P&L, cash and runway'!E10,'Monthly P&L, cash and runway'!E11) -> 2 | F9: =SUM('Monthly P&L, cash and runway'!F10,'Monthly P&L, cash and runway'!F11) -> 2 | G9: =SUM('Monthly P&L, cash and runway'!G10,'Monthly P&L, cash and runway'!G11) -> 2 | H9: =SUM('Monthly P&L, cash and runway'!H10,'Monthly P&L, cash and runway'!H11) -> 2 | I9: =SUM('Monthly P&L, cash and runway'!I10,'Monthly P&L, cash and runway'!I11) -> 2 | ... Y9: =SUM('Monthly P&L, cash and runway'!Y10,'Monthly P&L, cash and runway'!Y11) -> 3
A10: Starter | B10: =IF(IF('Monthly P&L, cash and runway'!B7-'Model inputs'!D17>0="",FALSE,'Monthly P&L, cash and runway'!B7-'Model inputs'!D17>0),'Monthly P&L, cash and runway'!B7-'Model inputs'!D17,0) -> 0 | C10: =IF(IF('Monthly P&L, cash and runway'!C7-'Monthly P&L, cash and runway'!B7>0="",FALSE,'Monthly P&L, cash and runway'!C7-'Monthly P&L, cash and runway'!B7>0),'Monthly P&L, cash and runway'!C7-'Monthly P&L, cash and runway'!B7,0) -> 0 | D10: =IF(IF('Monthly P&L, cash and runway'!D7-'Monthly P&L, cash and runway'!C7>0="",FALSE,'Monthly P&L, cash and runway'!D7-'Monthly P&L, cash and runway'!C7>0),'Monthly P&L, cash and runway'!D7-'Monthly P&L, cash and runway'!C7,0) -> 0 | E10: =IF(IF('Monthly P&L, cash and runway'!E7-'Monthly P&L, cash and runway'!D7>0="",FALSE,'Monthly P&L, cash and runway'!E7-'Monthly P&L, cash and runway'!D7>0),'Monthly P&L, cash and runway'!E7-'Monthly P&L, cash and runway'!D7,0) -> 2 | F10: =IF(IF('Monthly P&L, cash and runway'!F7-'Monthly P&L, cash and runway'!E7>0="",FALSE,'Monthly P&L, cash and runway'!F7-'Monthly P&L, cash and runway'!E7>0),'Monthly P&L, cash and runway'!F7-'Monthly P&L, cash and runway'!E7,0) -> 1 | G10: =IF(IF('Monthly P&L, cash and runway'!G7-'Monthly P&L, cash and runway'!F7>0="",FALSE,'Monthly P&L, cash and runway'!G7-'Monthly P&L, cash and runway'!F7>0),'Monthly P&L, cash and runway'!G7-'Monthly P&L, cash and runway'!F7,0) -> 2 | H10: =IF(IF('Monthly P&L, cash and runway'!H7-'Monthly P&L, cash and runway'!G7>0="",FALSE,'Monthly P&L, cash and runway'!H7-'Monthly P&L, cash and runway'!G7>0),'Monthly P&L, cash and runway'!H7-'Monthly P&L, cash and runway'!G7,0) -> 2 | I10: =IF(IF('Monthly P&L, cash and runway'!I7-'Monthly P&L, cash and runway'!H7>0="",FALSE,'Monthly P&L, cash and runway'!I7-'Monthly P&L, cash and runway'!H7>0),'Monthly P&L, cash and runway'!I7-'Monthly P&L, cash and runway'!H7,0) -> 1 | J10: =IF(IF('Monthly P&L, cash and runway'!J7-'Monthly P&L, cash and runway'!I7>0="",FALSE,'Monthly P&L, cash and runway'!J7-'Monthly P&L, cash and runway'!I7>0),'Monthly P&L, cash and runway'!J7-'Monthly P&L, cash and runway'!I7,0) -> 2 | ... Y10: =IF(IF('Monthly P&L, cash and runway'!Y7-'Monthly P&L, cash and runway'!X7>0="",FALSE,'Monthly P&L, cash and runway'!Y7-'Monthly P&L, cash and runway'!X7>0),'Monthly P&L, cash and runway'!Y7-'Monthly P&L, cash and runway'!X7,0) -> 2
A11: Team | B11: =IF(IF('Monthly P&L, cash and runway'!B8-'Model inputs'!D18>0="",FALSE,'Monthly P&L, cash and runway'!B8-'Model inputs'!D18>0),'Monthly P&L, cash and runway'!B8-'Model inputs'!D18,0) -> 0 | C11: =IF(IF('Monthly P&L, cash and runway'!C8-'Monthly P&L, cash and runway'!B8>0="",FALSE,'Monthly P&L, cash and runway'!C8-'Monthly P&L, cash and runway'!B8>0),'Monthly P&L, cash and runway'!C8-'Monthly P&L, cash and runway'!B8,0) -> 0 | D11: =IF(IF('Monthly P&L, cash and runway'!D8-'Monthly P&L, cash and runway'!C8>0="",FALSE,'Monthly P&L, cash and runway'!D8-'Monthly P&L, cash and runway'!C8>0),'Monthly P&L, cash and runway'!D8-'Monthly P&L, cash and runway'!C8,0) -> 0 | E11: =IF(IF('Monthly P&L, cash and runway'!E8-'Monthly P&L, cash and runway'!D8>0="",FALSE,'Monthly P&L, cash and runway'!E8-'Monthly P&L, cash and runway'!D8>0),'Monthly P&L, cash and runway'!E8-'Monthly P&L, cash and runway'!D8,0) -> 0 | F11: =IF(IF('Monthly P&L, cash and runway'!F8-'Monthly P&L, cash and runway'!E8>0="",FALSE,'Monthly P&L, cash and runway'!F8-'Monthly P&L, cash and runway'!E8>0),'Monthly P&L, cash and runway'!F8-'Monthly P&L, cash and runway'!E8,0) -> 1 | G11: =IF(IF('Monthly P&L, cash and runway'!G8-'Monthly P&L, cash and runway'!F8>0="",FALSE,'Monthly P&L, cash and runway'!G8-'Monthly P&L, cash and runway'!F8>0),'Monthly P&L, cash and runway'!G8-'Monthly P&L, cash and runway'!F8,0) -> 0 | H11: =IF(IF('Monthly P&L, cash and runway'!H8-'Monthly P&L, cash and runway'!G8>0="",FALSE,'Monthly P&L, cash and runway'!H8-'Monthly P&L, cash and runway'!G8>0),'Monthly P&L, cash and runway'!H8-'Monthly P&L, cash and runway'!G8,0) -> 0 | I11: =IF(IF('Monthly P&L, cash and runway'!I8-'Monthly P&L, cash and runway'!H8>0="",FALSE,'Monthly P&L, cash and runway'!I8-'Monthly P&L, cash and runway'!H8>0),'Monthly P&L, cash and runway'!I8-'Monthly P&L, cash and runway'!H8,0) -> 1 | J11: =IF(IF('Monthly P&L, cash and runway'!J8-'Monthly P&L, cash and runway'!I8>0="",FALSE,'Monthly P&L, cash and runway'!J8-'Monthly P&L, cash and runway'!I8>0),'Monthly P&L, cash and runway'!J8-'Monthly P&L, cash and runway'!I8,0) -> 0 | ... Y11: =IF(IF('Monthly P&L, cash and runway'!Y8-'Monthly P&L, cash and runway'!X8>0="",FALSE,'Monthly P&L, cash and runway'!Y8-'Monthly P&L, cash and runway'!X8>0),'Monthly P&L, cash and runway'!Y8-'Monthly P&L, cash and runway'!X8,0) -> 1
A12: Onboarding hours | B12: ='Monthly P&L, cash and runway'!B9*'Model inputs'!B34 -> 0 | C12: ='Monthly P&L, cash and runway'!C9*'Model inputs'!B34 -> 0 | D12: ='Monthly P&L, cash and runway'!D9*'Model inputs'!B34 -> 0 | E12: ='Monthly P&L, cash and runway'!E9*'Model inputs'!B34 -> 4 | F12: ='Monthly P&L, cash and runway'!F9*'Model inputs'!B34 -> 4 | G12: ='Monthly P&L, cash and runway'!G9*'Model inputs'!B34 -> 4 | H12: ='Monthly P&L, cash and runway'!H9*'Model inputs'!B34 -> 4 | I12: ='Monthly P&L, cash and runway'!I9*'Model inputs'!B34 -> 4 | J12: ='Monthly P&L, cash and runway'!J9*'Model inputs'!B34 -> 4 | K12: ='Monthly P&L, cash and runway'!K9*'Model inputs'!B34 -> 4 | L12: ='Monthly P&L, cash and runway'!L9*'Model inputs'!B34 -> 4 | M12: ='Monthly P&L, cash and runway'!M9*'Model inputs'!B34 -> 4 | N12: ='Monthly P&L, cash and runway'!N9*'Model inputs'!B34 -> 6 | O12: ='Monthly P&L, cash and runway'!O9*'Model inputs'!B34 -> 4 | P12: ='Monthly P&L, cash and runway'!P9*'Model inputs'!B34 -> 6 | Q12: ='Monthly P&L, cash and runway'!Q9*'Model inputs'!B34 -> 4 | R12: ='Monthly P&L, cash and runway'!R9*'Model inputs'!B34 -> 6 | S12: ='Monthly P&L, cash and runway'!S9*'Model inputs'!B34 -> 8 | T12: ='Monthly P&L, cash and runway'!T9*'Model inputs'!B34 -> 4 | U12: ='Monthly P&L, cash and runway'!U9*'Model inputs'!B34 -> 6 | V12: ='Monthly P&L, cash and runway'!V9*'Model inputs'!B34 -> 4 | W12: ='Monthly P&L, cash and runway'!W9*'Model inputs'!B34 -> 6 | X12: ='Monthly P&L, cash and runway'!X9*'Model inputs'!B34 -> 4 | Y12: ='Monthly P&L, cash and runway'!Y9*'Model inputs'!B34 -> 6
A13: Analysis runs | B13: =SUM('Monthly P&L, cash and runway'!B14,'Monthly P&L, cash and runway'!B15) -> 0 | C13: =SUM('Monthly P&L, cash and runway'!C14,'Monthly P&L, cash and runway'!C15) -> 0 | D13: =SUM('Monthly P&L, cash and runway'!D14,'Monthly P&L, cash and runway'!D15) -> 0 | E13: =SUM('Monthly P&L, cash and runway'!E14,'Monthly P&L, cash and runway'!E15) -> 16 | F13: =SUM('Monthly P&L, cash and runway'!F14,'Monthly P&L, cash and runway'!F15) -> 64 | G13: =SUM('Monthly P&L, cash and runway'!G14,'Monthly P&L, cash and runway'!G15) -> 80 | H13: =SUM('Monthly P&L, cash and runway'!H14,'Monthly P&L, cash and runway'!H15) -> 96 | I13: =SUM('Monthly P&L, cash and runway'!I14,'Monthly P&L, cash and runway'!I15) -> 144 | ... Y13: =SUM('Monthly P&L, cash and runway'!Y14,'Monthly P&L, cash and runway'!Y15) -> 720
A14: Starter | B14: ='Monthly P&L, cash and runway'!B7*'Model inputs'!B26*'Model inputs'!B6 -> 0 | C14: ='Monthly P&L, cash and runway'!C7*'Model inputs'!B26*'Model inputs'!B6 -> 0 | D14: ='Monthly P&L, cash and runway'!D7*'Model inputs'!B26*'Model inputs'!B6 -> 0 | E14: ='Monthly P&L, cash and runway'!E7*'Model inputs'!B26*'Model inputs'!B6 -> 16 | F14: ='Monthly P&L, cash and runway'!F7*'Model inputs'!B26*'Model inputs'!B6 -> 24 | G14: ='Monthly P&L, cash and runway'!G7*'Model inputs'!B26*'Model inputs'!B6 -> 40 | H14: ='Monthly P&L, cash and runway'!H7*'Model inputs'!B26*'Model inputs'!B6 -> 56 | I14: ='Monthly P&L, cash and runway'!I7*'Model inputs'!B26*'Model inputs'!B6 -> 64 | J14: ='Monthly P&L, cash and runway'!J7*'Model inputs'!B26*'Model inputs'!B6 -> 80 | K14: ='Monthly P&L, cash and runway'!K7*'Model inputs'!B26*'Model inputs'!B6 -> 96 | L14: ='Monthly P&L, cash and runway'!L7*'Model inputs'!B26*'Model inputs'!B6 -> 104 | M14: ='Monthly P&L, cash and runway'!M7*'Model inputs'!B26*'Model inputs'!B6 -> 120 | N14: ='Monthly P&L, cash and runway'!N7*'Model inputs'!B26*'Model inputs'!B6 -> 136 | O14: ='Monthly P&L, cash and runway'!O7*'Model inputs'!B26*'Model inputs'!B6 -> 152 | P14: ='Monthly P&L, cash and runway'!P7*'Model inputs'!B26*'Model inputs'!B6 -> 168 | Q14: ='Monthly P&L, cash and runway'!Q7*'Model inputs'!B26*'Model inputs'!B6 -> 184 | R14: ='Monthly P&L, cash and runway'!R7*'Model inputs'!B26*'Model inputs'!B6 -> 200 | S14: ='Monthly P&L, cash and runway'!S7*'Model inputs'!B26*'Model inputs'!B6 -> 224 | T14: ='Monthly P&L, cash and runway'!T7*'Model inputs'!B26*'Model inputs'!B6 -> 240 | U14: ='Monthly P&L, cash and runway'!U7*'Model inputs'!B26*'Model inputs'!B6 -> 256 | V14: ='Monthly P&L, cash and runway'!V7*'Model inputs'!B26*'Model inputs'!B6 -> 272 | W14: ='Monthly P&L, cash and runway'!W7*'Model inputs'!B26*'Model inputs'!B6 -> 288 | X14: ='Monthly P&L, cash and runway'!X7*'Model inputs'!B26*'Model inputs'!B6 -> 304 | Y14: ='Monthly P&L, cash and runway'!Y7*'Model inputs'!B26*'Model inputs'!B6 -> 320
A15: Team | B15: ='Monthly P&L, cash and runway'!B8*'Model inputs'!B27*'Model inputs'!B6 -> 0 | C15: ='Monthly P&L, cash and runway'!C8*'Model inputs'!B27*'Model inputs'!B6 -> 0 | D15: ='Monthly P&L, cash and runway'!D8*'Model inputs'!B27*'Model inputs'!B6 -> 0 | E15: ='Monthly P&L, cash and runway'!E8*'Model inputs'!B27*'Model inputs'!B6 -> 0 | F15: ='Monthly P&L, cash and runway'!F8*'Model inputs'!B27*'Model inputs'!B6 -> 40 | G15: ='Monthly P&L, cash and runway'!G8*'Model inputs'!B27*'Model inputs'!B6 -> 40 | H15: ='Monthly P&L, cash and runway'!H8*'Model inputs'!B27*'Model inputs'!B6 -> 40 | I15: ='Monthly P&L, cash and runway'!I8*'Model inputs'!B27*'Model inputs'!B6 -> 80 | J15: ='Monthly P&L, cash and runway'!J8*'Model inputs'!B27*'Model inputs'!B6 -> 80 | K15: ='Monthly P&L, cash and runway'!K8*'Model inputs'!B27*'Model inputs'!B6 -> 80 | L15: ='Monthly P&L, cash and runway'!L8*'Model inputs'!B27*'Model inputs'!B6 -> 120 | M15: ='Monthly P&L, cash and runway'!M8*'Model inputs'!B27*'Model inputs'!B6 -> 120 | N15: ='Monthly P&L, cash and runway'!N8*'Model inputs'!B27*'Model inputs'!B6 -> 160 | O15: ='Monthly P&L, cash and runway'!O8*'Model inputs'!B27*'Model inputs'!B6 -> 160 | P15: ='Monthly P&L, cash and runway'!P8*'Model inputs'!B27*'Model inputs'!B6 -> 200 | Q15: ='Monthly P&L, cash and runway'!Q8*'Model inputs'!B27*'Model inputs'!B6 -> 200 | R15: ='Monthly P&L, cash and runway'!R8*'Model inputs'!B27*'Model inputs'!B6 -> 240 | S15: ='Monthly P&L, cash and runway'!S8*'Model inputs'!B27*'Model inputs'!B6 -> 280 | T15: ='Monthly P&L, cash and runway'!T8*'Model inputs'!B27*'Model inputs'!B6 -> 280 | U15: ='Monthly P&L, cash and runway'!U8*'Model inputs'!B27*'Model inputs'!B6 -> 320 | V15: ='Monthly P&L, cash and runway'!V8*'Model inputs'!B27*'Model inputs'!B6 -> 320 | W15: ='Monthly P&L, cash and runway'!W8*'Model inputs'!B27*'Model inputs'!B6 -> 360 | X15: ='Monthly P&L, cash and runway'!X8*'Model inputs'!B27*'Model inputs'!B6 -> 360 | Y15: ='Monthly P&L, cash and runway'!Y8*'Model inputs'!B27*'Model inputs'!B6 -> 400
A16: Revenue | B16: =SUM('Monthly P&L, cash and runway'!B17,'Monthly P&L, cash and runway'!B18) -> 0 | C16: =SUM('Monthly P&L, cash and runway'!C17,'Monthly P&L, cash and runway'!C18) -> 0 | D16: =SUM('Monthly P&L, cash and runway'!D17,'Monthly P&L, cash and runway'!D18) -> 0 | E16: =SUM('Monthly P&L, cash and runway'!E17,'Monthly P&L, cash and runway'!E18) -> 198 | F16: =SUM('Monthly P&L, cash and runway'!F17,'Monthly P&L, cash and runway'!F18) -> 696 | G16: =SUM('Monthly P&L, cash and runway'!G17,'Monthly P&L, cash and runway'!G18) -> 894 | H16: =SUM('Monthly P&L, cash and runway'!H17,'Monthly P&L, cash and runway'!H18) -> 1092 | I16: =SUM('Monthly P&L, cash and runway'!I17,'Monthly P&L, cash and runway'!I18) -> 1590 | ... Y16: =SUM('Monthly P&L, cash and runway'!Y17,'Monthly P&L, cash and runway'!Y18) -> 7950
A17: Starter | B17: ='Monthly P&L, cash and runway'!B7*'Model inputs'!B37 -> 0 | C17: ='Monthly P&L, cash and runway'!C7*'Model inputs'!B37 -> 0 | D17: ='Monthly P&L, cash and runway'!D7*'Model inputs'!B37 -> 0 | E17: ='Monthly P&L, cash and runway'!E7*'Model inputs'!B37 -> 198 | F17: ='Monthly P&L, cash and runway'!F7*'Model inputs'!B37 -> 297 | G17: ='Monthly P&L, cash and runway'!G7*'Model inputs'!B37 -> 495 | H17: ='Monthly P&L, cash and runway'!H7*'Model inputs'!B37 -> 693 | I17: ='Monthly P&L, cash and runway'!I7*'Model inputs'!B37 -> 792 | J17: ='Monthly P&L, cash and runway'!J7*'Model inputs'!B37 -> 990 | K17: ='Monthly P&L, cash and runway'!K7*'Model inputs'!B37 -> 1188 | L17: ='Monthly P&L, cash and runway'!L7*'Model inputs'!B37 -> 1287 | M17: ='Monthly P&L, cash and runway'!M7*'Model inputs'!B37 -> 1485 | N17: ='Monthly P&L, cash and runway'!N7*'Model inputs'!B37 -> 1683 | O17: ='Monthly P&L, cash and runway'!O7*'Model inputs'!B37 -> 1881 | P17: ='Monthly P&L, cash and runway'!P7*'Model inputs'!B37 -> 2079 | Q17: ='Monthly P&L, cash and runway'!Q7*'Model inputs'!B37 -> 2277 | R17: ='Monthly P&L, cash and runway'!R7*'Model inputs'!B37 -> 2475 | S17: ='Monthly P&L, cash and runway'!S7*'Model inputs'!B37 -> 2772 | T17: ='Monthly P&L, cash and runway'!T7*'Model inputs'!B37 -> 2970 | U17: ='Monthly P&L, cash and runway'!U7*'Model inputs'!B37 -> 3168 | V17: ='Monthly P&L, cash and runway'!V7*'Model inputs'!B37 -> 3366 | W17: ='Monthly P&L, cash and runway'!W7*'Model inputs'!B37 -> 3564 | X17: ='Monthly P&L, cash and runway'!X7*'Model inputs'!B37 -> 3762 | Y17: ='Monthly P&L, cash and runway'!Y7*'Model inputs'!B37 -> 3960
A18: Team | B18: ='Monthly P&L, cash and runway'!B8*'Model inputs'!B38 -> 0 | C18: ='Monthly P&L, cash and runway'!C8*'Model inputs'!B38 -> 0 | D18: ='Monthly P&L, cash and runway'!D8*'Model inputs'!B38 -> 0 | E18: ='Monthly P&L, cash and runway'!E8*'Model inputs'!B38 -> 0 | F18: ='Monthly P&L, cash and runway'!F8*'Model inputs'!B38 -> 399 | G18: ='Monthly P&L, cash and runway'!G8*'Model inputs'!B38 -> 399 | H18: ='Monthly P&L, cash and runway'!H8*'Model inputs'!B38 -> 399 | I18: ='Monthly P&L, cash and runway'!I8*'Model inputs'!B38 -> 798 | J18: ='Monthly P&L, cash and runway'!J8*'Model inputs'!B38 -> 798 | K18: ='Monthly P&L, cash and runway'!K8*'Model inputs'!B38 -> 798 | L18: ='Monthly P&L, cash and runway'!L8*'Model inputs'!B38 -> 1197 | M18: ='Monthly P&L, cash and runway'!M8*'Model inputs'!B38 -> 1197 | N18: ='Monthly P&L, cash and runway'!N8*'Model inputs'!B38 -> 1596 | O18: ='Monthly P&L, cash and runway'!O8*'Model inputs'!B38 -> 1596 | P18: ='Monthly P&L, cash and runway'!P8*'Model inputs'!B38 -> 1995 | Q18: ='Monthly P&L, cash and runway'!Q8*'Model inputs'!B38 -> 1995 | R18: ='Monthly P&L, cash and runway'!R8*'Model inputs'!B38 -> 2394 | S18: ='Monthly P&L, cash and runway'!S8*'Model inputs'!B38 -> 2793 | T18: ='Monthly P&L, cash and runway'!T8*'Model inputs'!B38 -> 2793 | U18: ='Monthly P&L, cash and runway'!U8*'Model inputs'!B38 -> 3192 | V18: ='Monthly P&L, cash and runway'!V8*'Model inputs'!B38 -> 3192 | W18: ='Monthly P&L, cash and runway'!W8*'Model inputs'!B38 -> 3591 | X18: ='Monthly P&L, cash and runway'!X8*'Model inputs'!B38 -> 3591 | Y18: ='Monthly P&L, cash and runway'!Y8*'Model inputs'!B38 -> 3990
A19: LLM inference cost | B19: =SUM('Monthly P&L, cash and runway'!B20,'Monthly P&L, cash and runway'!B21) -> 0 | C19: =SUM('Monthly P&L, cash and runway'!C20,'Monthly P&L, cash and runway'!C21) -> 0 | D19: =SUM('Monthly P&L, cash and runway'!D20,'Monthly P&L, cash and runway'!D21) -> 0 | E19: =SUM('Monthly P&L, cash and runway'!E20,'Monthly P&L, cash and runway'!E21) -> 0.456 | F19: =SUM('Monthly P&L, cash and runway'!F20,'Monthly P&L, cash and runway'!F21) -> 1.824 | G19: =SUM('Monthly P&L, cash and runway'!G20,'Monthly P&L, cash and runway'!G21) -> 2.28 | H19: =SUM('Monthly P&L, cash and runway'!H20,'Monthly P&L, cash and runway'!H21) -> 2.736 | I19: =SUM('Monthly P&L, cash and runway'!I20,'Monthly P&L, cash and runway'!I21) -> 4.104 | ... Y19: =SUM('Monthly P&L, cash and runway'!Y20,'Monthly P&L, cash and runway'!Y21) -> 20.52
A20: Starter | B20: ='Monthly P&L, cash and runway'!B14*'Model inputs'!B28 -> 0 | C20: ='Monthly P&L, cash and runway'!C14*'Model inputs'!B28 -> 0 | D20: ='Monthly P&L, cash and runway'!D14*'Model inputs'!B28 -> 0 | E20: ='Monthly P&L, cash and runway'!E14*'Model inputs'!B28 -> 0.456 | F20: ='Monthly P&L, cash and runway'!F14*'Model inputs'!B28 -> 0.684 | G20: ='Monthly P&L, cash and runway'!G14*'Model inputs'!B28 -> 1.14 | H20: ='Monthly P&L, cash and runway'!H14*'Model inputs'!B28 -> 1.596 | I20: ='Monthly P&L, cash and runway'!I14*'Model inputs'!B28 -> 1.824 | J20: ='Monthly P&L, cash and runway'!J14*'Model inputs'!B28 -> 2.28 | K20: ='Monthly P&L, cash and runway'!K14*'Model inputs'!B28 -> 2.736 | L20: ='Monthly P&L, cash and runway'!L14*'Model inputs'!B28 -> 2.964 | M20: ='Monthly P&L, cash and runway'!M14*'Model inputs'!B28 -> 3.42 | N20: ='Monthly P&L, cash and runway'!N14*'Model inputs'!B28 -> 3.876 | O20: ='Monthly P&L, cash and runway'!O14*'Model inputs'!B28 -> 4.332 | P20: ='Monthly P&L, cash and runway'!P14*'Model inputs'!B28 -> 4.788 | Q20: ='Monthly P&L, cash and runway'!Q14*'Model inputs'!B28 -> 5.244 | R20: ='Monthly P&L, cash and runway'!R14*'Model inputs'!B28 -> 5.7 | S20: ='Monthly P&L, cash and runway'!S14*'Model inputs'!B28 -> 6.384 | T20: ='Monthly P&L, cash and runway'!T14*'Model inputs'!B28 -> 6.84 | U20: ='Monthly P&L, cash and runway'!U14*'Model inputs'!B28 -> 7.296 | V20: ='Monthly P&L, cash and runway'!V14*'Model inputs'!B28 -> 7.752 | W20: ='Monthly P&L, cash and runway'!W14*'Model inputs'!B28 -> 8.208 | X20: ='Monthly P&L, cash and runway'!X14*'Model inputs'!B28 -> 8.664 | Y20: ='Monthly P&L, cash and runway'!Y14*'Model inputs'!B28 -> 9.12
A21: Team | B21: ='Monthly P&L, cash and runway'!B15*'Model inputs'!B28 -> 0 | C21: ='Monthly P&L, cash and runway'!C15*'Model inputs'!B28 -> 0 | D21: ='Monthly P&L, cash and runway'!D15*'Model inputs'!B28 -> 0 | E21: ='Monthly P&L, cash and runway'!E15*'Model inputs'!B28 -> 0 | F21: ='Monthly P&L, cash and runway'!F15*'Model inputs'!B28 -> 1.14 | G21: ='Monthly P&L, cash and runway'!G15*'Model inputs'!B28 -> 1.14 | H21: ='Monthly P&L, cash and runway'!H15*'Model inputs'!B28 -> 1.14 | I21: ='Monthly P&L, cash and runway'!I15*'Model inputs'!B28 -> 2.28 | J21: ='Monthly P&L, cash and runway'!J15*'Model inputs'!B28 -> 2.28 | K21: ='Monthly P&L, cash and runway'!K15*'Model inputs'!B28 -> 2.28 | L21: ='Monthly P&L, cash and runway'!L15*'Model inputs'!B28 -> 3.42 | M21: ='Monthly P&L, cash and runway'!M15*'Model inputs'!B28 -> 3.42 | N21: ='Monthly P&L, cash and runway'!N15*'Model inputs'!B28 -> 4.56 | O21: ='Monthly P&L, cash and runway'!O15*'Model inputs'!B28 -> 4.56 | P21: ='Monthly P&L, cash and runway'!P15*'Model inputs'!B28 -> 5.7 | Q21: ='Monthly P&L, cash and runway'!Q15*'Model inputs'!B28 -> 5.7 | R21: ='Monthly P&L, cash and runway'!R15*'Model inputs'!B28 -> 6.84 | S21: ='Monthly P&L, cash and runway'!S15*'Model inputs'!B28 -> 7.98 | T21: ='Monthly P&L, cash and runway'!T15*'Model inputs'!B28 -> 7.98 | U21: ='Monthly P&L, cash and runway'!U15*'Model inputs'!B28 -> 9.12 | V21: ='Monthly P&L, cash and runway'!V15*'Model inputs'!B28 -> 9.12 | W21: ='Monthly P&L, cash and runway'!W15*'Model inputs'!B28 -> 10.26 | X21: ='Monthly P&L, cash and runway'!X15*'Model inputs'!B28 -> 10.26 | Y21: ='Monthly P&L, cash and runway'!Y15*'Model inputs'!B28 -> 11.4
A22: Crustdata cost | B22: =SUM('Monthly P&L, cash and runway'!B23,'Monthly P&L, cash and runway'!B24) -> 0 | C22: =SUM('Monthly P&L, cash and runway'!C23,'Monthly P&L, cash and runway'!C24) -> 0 | D22: =SUM('Monthly P&L, cash and runway'!D23,'Monthly P&L, cash and runway'!D24) -> 0 | E22: =SUM('Monthly P&L, cash and runway'!E23,'Monthly P&L, cash and runway'!E24) -> 73.92 | F22: =SUM('Monthly P&L, cash and runway'!F23,'Monthly P&L, cash and runway'!F24) -> 295.68 | G22: =SUM('Monthly P&L, cash and runway'!G23,'Monthly P&L, cash and runway'!G24) -> 369.6 | H22: =SUM('Monthly P&L, cash and runway'!H23,'Monthly P&L, cash and runway'!H24) -> 443.52 | I22: =SUM('Monthly P&L, cash and runway'!I23,'Monthly P&L, cash and runway'!I24) -> 665.28 | ... Y22: =SUM('Monthly P&L, cash and runway'!Y23,'Monthly P&L, cash and runway'!Y24) -> 3326.4
A23: Starter | B23: ='Monthly P&L, cash and runway'!B14*(1-'Model inputs'!B10)*'Model inputs'!B15 -> 0 | C23: ='Monthly P&L, cash and runway'!C14*(1-'Model inputs'!B10)*'Model inputs'!B15 -> 0 | D23: ='Monthly P&L, cash and runway'!D14*(1-'Model inputs'!B10)*'Model inputs'!B15 -> 0 | E23: ='Monthly P&L, cash and runway'!E14*(1-'Model inputs'!B10)*'Model inputs'!B15 -> 73.92 | F23: ='Monthly P&L, cash and runway'!F14*(1-'Model inputs'!B10)*'Model inputs'!B15 -> 110.88 | G23: ='Monthly P&L, cash and runway'!G14*(1-'Model inputs'!B10)*'Model inputs'!B15 -> 184.8 | H23: ='Monthly P&L, cash and runway'!H14*(1-'Model inputs'!B10)*'Model inputs'!B15 -> 258.72 | I23: ='Monthly P&L, cash and runway'!I14*(1-'Model inputs'!B10)*'Model inputs'!B15 -> 295.68 | J23: ='Monthly P&L, cash and runway'!J14*(1-'Model inputs'!B10)*'Model inputs'!B15 -> 369.6 | K23: ='Monthly P&L, cash and runway'!K14*(1-'Model inputs'!B10)*'Model inputs'!B15 -> 443.52 | L23: ='Monthly P&L, cash and runway'!L14*(1-'Model inputs'!B10)*'Model inputs'!B15 -> 480.48 | M23: ='Monthly P&L, cash and runway'!M14*(1-'Model inputs'!B10)*'Model inputs'!B15 -> 554.4 | N23: ='Monthly P&L, cash and runway'!N14*(1-'Model inputs'!B10)*'Model inputs'!B15 -> 628.32 | O23: ='Monthly P&L, cash and runway'!O14*(1-'Model inputs'!B10)*'Model inputs'!B15 -> 702.24 | P23: ='Monthly P&L, cash and runway'!P14*(1-'Model inputs'!B10)*'Model inputs'!B15 -> 776.16 | Q23: ='Monthly P&L, cash and runway'!Q14*(1-'Model inputs'!B10)*'Model inputs'!B15 -> 850.08 | R23: ='Monthly P&L, cash and runway'!R14*(1-'Model inputs'!B10)*'Model inputs'!B15 -> 924 | S23: ='Monthly P&L, cash and runway'!S14*(1-'Model inputs'!B10)*'Model inputs'!B15 -> 1034.88 | T23: ='Monthly P&L, cash and runway'!T14*(1-'Model inputs'!B10)*'Model inputs'!B15 -> 1108.8 | U23: ='Monthly P&L, cash and runway'!U14*(1-'Model inputs'!B10)*'Model inputs'!B15 -> 1182.72 | V23: ='Monthly P&L, cash and runway'!V14*(1-'Model inputs'!B10)*'Model inputs'!B15 -> 1256.64 | W23: ='Monthly P&L, cash and runway'!W14*(1-'Model inputs'!B10)*'Model inputs'!B15 -> 1330.56 | X23: ='Monthly P&L, cash and runway'!X14*(1-'Model inputs'!B10)*'Model inputs'!B15 -> 1404.48 | Y23: ='Monthly P&L, cash and runway'!Y14*(1-'Model inputs'!B10)*'Model inputs'!B15 -> 1478.4
A24: Team | B24: ='Monthly P&L, cash and runway'!B15*(1-'Model inputs'!B10)*'Model inputs'!B15 -> 0 | C24: ='Monthly P&L, cash and runway'!C15*(1-'Model inputs'!B10)*'Model inputs'!B15 -> 0 | D24: ='Monthly P&L, cash and runway'!D15*(1-'Model inputs'!B10)*'Model inputs'!B15 -> 0 | E24: ='Monthly P&L, cash and runway'!E15*(1-'Model inputs'!B10)*'Model inputs'!B15 -> 0 | F24: ='Monthly P&L, cash and runway'!F15*(1-'Model inputs'!B10)*'Model inputs'!B15 -> 184.8 | G24: ='Monthly P&L, cash and runway'!G15*(1-'Model inputs'!B10)*'Model inputs'!B15 -> 184.8 | H24: ='Monthly P&L, cash and runway'!H15*(1-'Model inputs'!B10)*'Model inputs'!B15 -> 184.8 | I24: ='Monthly P&L, cash and runway'!I15*(1-'Model inputs'!B10)*'Model inputs'!B15 -> 369.6 | J24: ='Monthly P&L, cash and runway'!J15*(1-'Model inputs'!B10)*'Model inputs'!B15 -> 369.6 | K24: ='Monthly P&L, cash and runway'!K15*(1-'Model inputs'!B10)*'Model inputs'!B15 -> 369.6 | L24: ='Monthly P&L, cash and runway'!L15*(1-'Model inputs'!B10)*'Model inputs'!B15 -> 554.4 | M24: ='Monthly P&L, cash and runway'!M15*(1-'Model inputs'!B10)*'Model inputs'!B15 -> 554.4 | N24: ='Monthly P&L, cash and runway'!N15*(1-'Model inputs'!B10)*'Model inputs'!B15 -> 739.2 | O24: ='Monthly P&L, cash and runway'!O15*(1-'Model inputs'!B10)*'Model inputs'!B15 -> 739.2 | P24: ='Monthly P&L, cash and runway'!P15*(1-'Model inputs'!B10)*'Model inputs'!B15 -> 924 | Q24: ='Monthly P&L, cash and runway'!Q15*(1-'Model inputs'!B10)*'Model inputs'!B15 -> 924 | R24: ='Monthly P&L, cash and runway'!R15*(1-'Model inputs'!B10)*'Model inputs'!B15 -> 1108.8 | S24: ='Monthly P&L, cash and runway'!S15*(1-'Model inputs'!B10)*'Model inputs'!B15 -> 1293.6 | T24: ='Monthly P&L, cash and runway'!T15*(1-'Model inputs'!B10)*'Model inputs'!B15 -> 1293.6 | U24: ='Monthly P&L, cash and runway'!U15*(1-'Model inputs'!B10)*'Model inputs'!B15 -> 1478.4 | V24: ='Monthly P&L, cash and runway'!V15*(1-'Model inputs'!B10)*'Model inputs'!B15 -> 1478.4 | W24: ='Monthly P&L, cash and runway'!W15*(1-'Model inputs'!B10)*'Model inputs'!B15 -> 1663.2 | X24: ='Monthly P&L, cash and runway'!X15*(1-'Model inputs'!B10)*'Model inputs'!B15 -> 1663.2 | Y24: ='Monthly P&L, cash and runway'!Y15*(1-'Model inputs'!B10)*'Model inputs'!B15 -> 1848
A25: Hosting | B25: =IF(IF(IF(ISERROR('Monthly P&L, cash and runway'!B5>=1),'Monthly P&L, cash and runway'!B5>=1,IF('Monthly P&L, cash and runway'!B5="","",'Monthly P&L, cash and runway'!B5>=1))="",FALSE,IF(ISERROR('Monthly P&L, cash and runway'!B5>=1),'Monthly P&L, cash and runway'!B5>=1,IF('Monthly P&L, cash and runway'!B5="","",'Monthly P&L, cash and runway'!B5>=1))),IF('Model inputs'!B24="","",'Model inputs'!B24),0) -> 15.2 | C25: =IF(IF(IF(ISERROR('Monthly P&L, cash and runway'!C5>=1),'Monthly P&L, cash and runway'!C5>=1,IF('Monthly P&L, cash and runway'!C5="","",'Monthly P&L, cash and runway'!C5>=1))="",FALSE,IF(ISERROR('Monthly P&L, cash and runway'!C5>=1),'Monthly P&L, cash and runway'!C5>=1,IF('Monthly P&L, cash and runway'!C5="","",'Monthly P&L, cash and runway'!C5>=1))),IF('Model inputs'!B24="","",'Model inputs'!B24),0) -> 15.2 | D25: =IF(IF(IF(ISERROR('Monthly P&L, cash and runway'!D5>=1),'Monthly P&L, cash and runway'!D5>=1,IF('Monthly P&L, cash and runway'!D5="","",'Monthly P&L, cash and runway'!D5>=1))="",FALSE,IF(ISERROR('Monthly P&L, cash and runway'!D5>=1),'Monthly P&L, cash and runway'!D5>=1,IF('Monthly P&L, cash and runway'!D5="","",'Monthly P&L, cash and runway'!D5>=1))),IF('Model inputs'!B24="","",'Model inputs'!B24),0) -> 15.2 | E25: =IF(IF(IF(ISERROR('Monthly P&L, cash and runway'!E5>=1),'Monthly P&L, cash and runway'!E5>=1,IF('Monthly P&L, cash and runway'!E5="","",'Monthly P&L, cash and runway'!E5>=1))="",FALSE,IF(ISERROR('Monthly P&L, cash and runway'!E5>=1),'Monthly P&L, cash and runway'!E5>=1,IF('Monthly P&L, cash and runway'!E5="","",'Monthly P&L, cash and runway'!E5>=1))),IF('Model inputs'!B24="","",'Model inputs'!B24),0) -> 15.2 | F25: =IF(IF(IF(ISERROR('Monthly P&L, cash and runway'!F5>=1),'Monthly P&L, cash and runway'!F5>=1,IF('Monthly P&L, cash and runway'!F5="","",'Monthly P&L, cash and runway'!F5>=1))="",FALSE,IF(ISERROR('Monthly P&L, cash and runway'!F5>=1),'Monthly P&L, cash and runway'!F5>=1,IF('Monthly P&L, cash and runway'!F5="","",'Monthly P&L, cash and runway'!F5>=1))),IF('Model inputs'!B24="","",'Model inputs'!B24),0) -> 15.2 | G25: =IF(IF(IF(ISERROR('Monthly P&L, cash and runway'!G5>=1),'Monthly P&L, cash and runway'!G5>=1,IF('Monthly P&L, cash and runway'!G5="","",'Monthly P&L, cash and runway'!G5>=1))="",FALSE,IF(ISERROR('Monthly P&L, cash and runway'!G5>=1),'Monthly P&L, cash and runway'!G5>=1,IF('Monthly P&L, cash and runway'!G5="","",'Monthly P&L, cash and runway'!G5>=1))),IF('Model inputs'!B24="","",'Model inputs'!B24),0) -> 15.2 | H25: =IF(IF(IF(ISERROR('Monthly P&L, cash and runway'!H5>=1),'Monthly P&L, cash and runway'!H5>=1,IF('Monthly P&L, cash and runway'!H5="","",'Monthly P&L, cash and runway'!H5>=1))="",FALSE,IF(ISERROR('Monthly P&L, cash and runway'!H5>=1),'Monthly P&L, cash and runway'!H5>=1,IF('Monthly P&L, cash and runway'!H5="","",'Monthly P&L, cash and runway'!H5>=1))),IF('Model inputs'!B24="","",'Model inputs'!B24),0) -> 15.2 | I25: =IF(IF(IF(ISERROR('Monthly P&L, cash and runway'!I5>=1),'Monthly P&L, cash and runway'!I5>=1,IF('Monthly P&L, cash and runway'!I5="","",'Monthly P&L, cash and runway'!I5>=1))="",FALSE,IF(ISERROR('Monthly P&L, cash and runway'!I5>=1),'Monthly P&L, cash and runway'!I5>=1,IF('Monthly P&L, cash and runway'!I5="","",'Monthly P&L, cash and runway'!I5>=1))),IF('Model inputs'!B24="","",'Model inputs'!B24),0) -> 15.2 | J25: =IF(IF(IF(ISERROR('Monthly P&L, cash and runway'!J5>=1),'Monthly P&L, cash and runway'!J5>=1,IF('Monthly P&L, cash and runway'!J5="","",'Monthly P&L, cash and runway'!J5>=1))="",FALSE,IF(ISERROR('Monthly P&L, cash and runway'!J5>=1),'Monthly P&L, cash and runway'!J5>=1,IF('Monthly P&L, cash and runway'!J5="","",'Monthly P&L, cash and runway'!J5>=1))),IF('Model inputs'!B24="","",'Model inputs'!B24),0) -> 15.2 | K25: =IF(IF(IF(ISERROR('Monthly P&L, cash and runway'!K5>=1),'Monthly P&L, cash and runway'!K5>=1,IF('Monthly P&L, cash and runway'!K5="","",'Monthly P&L, cash and runway'!K5>=1))="",FALSE,IF(ISERROR('Monthly P&L, cash and runway'!K5>=1),'Monthly P&L, cash and runway'!K5>=1,IF('Monthly P&L, cash and runway'!K5="","",'Monthly P&L, cash and runway'!K5>=1))),IF('Model inputs'!B24="","",'Model inputs'!B24),0) -> 15.2 | L25: =IF(IF(IF(ISERROR('Monthly P&L, cash and runway'!L5>=1),'Monthly P&L, cash and runway'!L5>=1,IF('Monthly P&L, cash and runway'!L5="","",'Monthly P&L, cash and runway'!L5>=1))="",FALSE,IF(ISERROR('Monthly P&L, cash and runway'!L5>=1),'Monthly P&L, cash and runway'!L5>=1,IF('Monthly P&L, cash and runway'!L5="","",'Monthly P&L, cash and runway'!L5>=1))),IF('Model inputs'!B24="","",'Model inputs'!B24),0) -> 15.2 | M25: =IF(IF(IF(ISERROR('Monthly P&L, cash and runway'!M5>=1),'Monthly P&L, cash and runway'!M5>=1,IF('Monthly P&L, cash and runway'!M5="","",'Monthly P&L, cash and runway'!M5>=1))="",FALSE,IF(ISERROR('Monthly P&L, cash and runway'!M5>=1),'Monthly P&L, cash and runway'!M5>=1,IF('Monthly P&L, cash and runway'!M5="","",'Monthly P&L, cash and runway'!M5>=1))),IF('Model inputs'!B24="","",'Model inputs'!B24),0) -> 15.2 | N25: =IF(IF(IF(ISERROR('Monthly P&L, cash and runway'!N5>=1),'Monthly P&L, cash and runway'!N5>=1,IF('Monthly P&L, cash and runway'!N5="","",'Monthly P&L, cash and runway'!N5>=1))="",FALSE,IF(ISERROR('Monthly P&L, cash and runway'!N5>=1),'Monthly P&L, cash and runway'!N5>=1,IF('Monthly P&L, cash and runway'!N5="","",'Monthly P&L, cash and runway'!N5>=1))),IF('Model inputs'!B24="","",'Model inputs'!B24),0) -> 15.2 | O25: =IF(IF(IF(ISERROR('Monthly P&L, cash and runway'!O5>=1),'Monthly P&L, cash and runway'!O5>=1,IF('Monthly P&L, cash and runway'!O5="","",'Monthly P&L, cash and runway'!O5>=1))="",FALSE,IF(ISERROR('Monthly P&L, cash and runway'!O5>=1),'Monthly P&L, cash and runway'!O5>=1,IF('Monthly P&L, cash and runway'!O5="","",'Monthly P&L, cash and runway'!O5>=1))),IF('Model inputs'!B24="","",'Model inputs'!B24),0) -> 15.2 | P25: =IF(IF(IF(ISERROR('Monthly P&L, cash and runway'!P5>=1),'Monthly P&L, cash and runway'!P5>=1,IF('Monthly P&L, cash and runway'!P5="","",'Monthly P&L, cash and runway'!P5>=1))="",FALSE,IF(ISERROR('Monthly P&L, cash and runway'!P5>=1),'Monthly P&L, cash and runway'!P5>=1,IF('Monthly P&L, cash and runway'!P5="","",'Monthly P&L, cash and runway'!P5>=1))),IF('Model inputs'!B24="","",'Model inputs'!B24),0) -> 15.2 | Q25: =IF(IF(IF(ISERROR('Monthly P&L, cash and runway'!Q5>=1),'Monthly P&L, cash and runway'!Q5>=1,IF('Monthly P&L, cash and runway'!Q5="","",'Monthly P&L, cash and runway'!Q5>=1))="",FALSE,IF(ISERROR('Monthly P&L, cash and runway'!Q5>=1),'Monthly P&L, cash and runway'!Q5>=1,IF('Monthly P&L, cash and runway'!Q5="","",'Monthly P&L, cash and runway'!Q5>=1))),IF('Model inputs'!B24="","",'Model inputs'!B24),0) -> 15.2 | R25: =IF(IF(IF(ISERROR('Monthly P&L, cash and runway'!R5>=1),'Monthly P&L, cash and runway'!R5>=1,IF('Monthly P&L, cash and runway'!R5="","",'Monthly P&L, cash and runway'!R5>=1))="",FALSE,IF(ISERROR('Monthly P&L, cash and runway'!R5>=1),'Monthly P&L, cash and runway'!R5>=1,IF('Monthly P&L, cash and runway'!R5="","",'Monthly P&L, cash and runway'!R5>=1))),IF('Model inputs'!B24="","",'Model inputs'!B24),0) -> 15.2 | S25: =IF(IF(IF(ISERROR('Monthly P&L, cash and runway'!S5>=1),'Monthly P&L, cash and runway'!S5>=1,IF('Monthly P&L, cash and runway'!S5="","",'Monthly P&L, cash and runway'!S5>=1))="",FALSE,IF(ISERROR('Monthly P&L, cash and runway'!S5>=1),'Monthly P&L, cash and runway'!S5>=1,IF('Monthly P&L, cash and runway'!S5="","",'Monthly P&L, cash and runway'!S5>=1))),IF('Model inputs'!B24="","",'Model inputs'!B24),0) -> 15.2 | T25: =IF(IF(IF(ISERROR('Monthly P&L, cash and runway'!T5>=1),'Monthly P&L, cash and runway'!T5>=1,IF('Monthly P&L, cash and runway'!T5="","",'Monthly P&L, cash and runway'!T5>=1))="",FALSE,IF(ISERROR('Monthly P&L, cash and runway'!T5>=1),'Monthly P&L, cash and runway'!T5>=1,IF('Monthly P&L, cash and runway'!T5="","",'Monthly P&L, cash and runway'!T5>=1))),IF('Model inputs'!B24="","",'Model inputs'!B24),0) -> 15.2 | U25: =IF(IF(IF(ISERROR('Monthly P&L, cash and runway'!U5>=1),'Monthly P&L, cash and runway'!U5>=1,IF('Monthly P&L, cash and runway'!U5="","",'Monthly P&L, cash and runway'!U5>=1))="",FALSE,IF(ISERROR('Monthly P&L, cash and runway'!U5>=1),'Monthly P&L, cash and runway'!U5>=1,IF('Monthly P&L, cash and runway'!U5="","",'Monthly P&L, cash and runway'!U5>=1))),IF('Model inputs'!B24="","",'Model inputs'!B24),0) -> 15.2 | V25: =IF(IF(IF(ISERROR('Monthly P&L, cash and runway'!V5>=1),'Monthly P&L, cash and runway'!V5>=1,IF('Monthly P&L, cash and runway'!V5="","",'Monthly P&L, cash and runway'!V5>=1))="",FALSE,IF(ISERROR('Monthly P&L, cash and runway'!V5>=1),'Monthly P&L, cash and runway'!V5>=1,IF('Monthly P&L, cash and runway'!V5="","",'Monthly P&L, cash and runway'!V5>=1))),IF('Model inputs'!B24="","",'Model inputs'!B24),0) -> 15.2 | W25: =IF(IF(IF(ISERROR('Monthly P&L, cash and runway'!W5>=1),'Monthly P&L, cash and runway'!W5>=1,IF('Monthly P&L, cash and runway'!W5="","",'Monthly P&L, cash and runway'!W5>=1))="",FALSE,IF(ISERROR('Monthly P&L, cash and runway'!W5>=1),'Monthly P&L, cash and runway'!W5>=1,IF('Monthly P&L, cash and runway'!W5="","",'Monthly P&L, cash and runway'!W5>=1))),IF('Model inputs'!B24="","",'Model inputs'!B24),0) -> 15.2 | X25: =IF(IF(IF(ISERROR('Monthly P&L, cash and runway'!X5>=1),'Monthly P&L, cash and runway'!X5>=1,IF('Monthly P&L, cash and runway'!X5="","",'Monthly P&L, cash and runway'!X5>=1))="",FALSE,IF(ISERROR('Monthly P&L, cash and runway'!X5>=1),'Monthly P&L, cash and runway'!X5>=1,IF('Monthly P&L, cash and runway'!X5="","",'Monthly P&L, cash and runway'!X5>=1))),IF('Model inputs'!B24="","",'Model inputs'!B24),0) -> 15.2 | Y25: =IF(IF(IF(ISERROR('Monthly P&L, cash and runway'!Y5>=1),'Monthly P&L, cash and runway'!Y5>=1,IF('Monthly P&L, cash and runway'!Y5="","",'Monthly P&L, cash and runway'!Y5>=1))="",FALSE,IF(ISERROR('Monthly P&L, cash and runway'!Y5>=1),'Monthly P&L, cash and runway'!Y5>=1,IF('Monthly P&L, cash and runway'!Y5="","",'Monthly P&L, cash and runway'!Y5>=1))),IF('Model inputs'!B24="","",'Model inputs'!B24),0) -> 15.2
A26: COGS | B26: ='Monthly P&L, cash and runway'!B19+'Monthly P&L, cash and runway'!B22+'Monthly P&L, cash and runway'!B25 -> 15.2 | C26: ='Monthly P&L, cash and runway'!C19+'Monthly P&L, cash and runway'!C22+'Monthly P&L, cash and runway'!C25 -> 15.2 | D26: ='Monthly P&L, cash and runway'!D19+'Monthly P&L, cash and runway'!D22+'Monthly P&L, cash and runway'!D25 -> 15.2 | E26: ='Monthly P&L, cash and runway'!E19+'Monthly P&L, cash and runway'!E22+'Monthly P&L, cash and runway'!E25 -> 89.576 | F26: ='Monthly P&L, cash and runway'!F19+'Monthly P&L, cash and runway'!F22+'Monthly P&L, cash and runway'!F25 -> 312.704 | G26: ='Monthly P&L, cash and runway'!G19+'Monthly P&L, cash and runway'!G22+'Monthly P&L, cash and runway'!G25 -> 387.08 | H26: ='Monthly P&L, cash and runway'!H19+'Monthly P&L, cash and runway'!H22+'Monthly P&L, cash and runway'!H25 -> 461.456 | I26: ='Monthly P&L, cash and runway'!I19+'Monthly P&L, cash and runway'!I22+'Monthly P&L, cash and runway'!I25 -> 684.584 | ... Y26: ='Monthly P&L, cash and runway'!Y19+'Monthly P&L, cash and runway'!Y22+'Monthly P&L, cash and runway'!Y25 -> 3362.12
A27: Gross profit | B27: ='Monthly P&L, cash and runway'!B16-'Monthly P&L, cash and runway'!B26 -> -15.2 | C27: ='Monthly P&L, cash and runway'!C16-'Monthly P&L, cash and runway'!C26 -> -15.2 | D27: ='Monthly P&L, cash and runway'!D16-'Monthly P&L, cash and runway'!D26 -> -15.2 | E27: ='Monthly P&L, cash and runway'!E16-'Monthly P&L, cash and runway'!E26 -> 108.424 | F27: ='Monthly P&L, cash and runway'!F16-'Monthly P&L, cash and runway'!F26 -> 383.296 | G27: ='Monthly P&L, cash and runway'!G16-'Monthly P&L, cash and runway'!G26 -> 506.92 | H27: ='Monthly P&L, cash and runway'!H16-'Monthly P&L, cash and runway'!H26 -> 630.544 | I27: ='Monthly P&L, cash and runway'!I16-'Monthly P&L, cash and runway'!I26 -> 905.416 | ... Y27: ='Monthly P&L, cash and runway'!Y16-'Monthly P&L, cash and runway'!Y26 -> 4587.88
A28: Gross margin | B28: =IFERROR('Monthly P&L, cash and runway'!B27/'Monthly P&L, cash and runway'!B16,"") | C28: =IFERROR('Monthly P&L, cash and runway'!C27/'Monthly P&L, cash and runway'!C16,"") | D28: =IFERROR('Monthly P&L, cash and runway'!D27/'Monthly P&L, cash and runway'!D16,"") | E28: =IFERROR('Monthly P&L, cash and runway'!E27/'Monthly P&L, cash and runway'!E16,"") -> 0.54759596 | F28: =IFERROR('Monthly P&L, cash and runway'!F27/'Monthly P&L, cash and runway'!F16,"") -> 0.55071264 | G28: =IFERROR('Monthly P&L, cash and runway'!G27/'Monthly P&L, cash and runway'!G16,"") -> 0.56702461 | H28: =IFERROR('Monthly P&L, cash and runway'!H27/'Monthly P&L, cash and runway'!H16,"") -> 0.57742125 | I28: =IFERROR('Monthly P&L, cash and runway'!I27/'Monthly P&L, cash and runway'!I16,"") -> 0.56944403 | ... Y28: =IFERROR('Monthly P&L, cash and runway'!Y27/'Monthly P&L, cash and runway'!Y16,"") -> 0.57709182
A29: Founder salary | B29: =IF(IF(IF(ISERROR('Monthly P&L, cash and runway'!B5>=1),'Monthly P&L, cash and runway'!B5>=1,IF('Monthly P&L, cash and runway'!B5="","",'Monthly P&L, cash and runway'!B5>=1))="",FALSE,IF(ISERROR('Monthly P&L, cash and runway'!B5>=1),'Monthly P&L, cash and runway'!B5>=1,IF('Monthly P&L, cash and runway'!B5="","",'Monthly P&L, cash and runway'!B5>=1))),IF('Model inputs'!B21="","",'Model inputs'!B21),0) -> 2000 | C29: =IF(IF(IF(ISERROR('Monthly P&L, cash and runway'!C5>=1),'Monthly P&L, cash and runway'!C5>=1,IF('Monthly P&L, cash and runway'!C5="","",'Monthly P&L, cash and runway'!C5>=1))="",FALSE,IF(ISERROR('Monthly P&L, cash and runway'!C5>=1),'Monthly P&L, cash and runway'!C5>=1,IF('Monthly P&L, cash and runway'!C5="","",'Monthly P&L, cash and runway'!C5>=1))),IF('Model inputs'!B21="","",'Model inputs'!B21),0) -> 2000 | D29: =IF(IF(IF(ISERROR('Monthly P&L, cash and runway'!D5>=1),'Monthly P&L, cash and runway'!D5>=1,IF('Monthly P&L, cash and runway'!D5="","",'Monthly P&L, cash and runway'!D5>=1))="",FALSE,IF(ISERROR('Monthly P&L, cash and runway'!D5>=1),'Monthly P&L, cash and runway'!D5>=1,IF('Monthly P&L, cash and runway'!D5="","",'Monthly P&L, cash and runway'!D5>=1))),IF('Model inputs'!B21="","",'Model inputs'!B21),0) -> 2000 | E29: =IF(IF(IF(ISERROR('Monthly P&L, cash and runway'!E5>=1),'Monthly P&L, cash and runway'!E5>=1,IF('Monthly P&L, cash and runway'!E5="","",'Monthly P&L, cash and runway'!E5>=1))="",FALSE,IF(ISERROR('Monthly P&L, cash and runway'!E5>=1),'Monthly P&L, cash and runway'!E5>=1,IF('Monthly P&L, cash and runway'!E5="","",'Monthly P&L, cash and runway'!E5>=1))),IF('Model inputs'!B21="","",'Model inputs'!B21),0) -> 2000 | F29: =IF(IF(IF(ISERROR('Monthly P&L, cash and runway'!F5>=1),'Monthly P&L, cash and runway'!F5>=1,IF('Monthly P&L, cash and runway'!F5="","",'Monthly P&L, cash and runway'!F5>=1))="",FALSE,IF(ISERROR('Monthly P&L, cash and runway'!F5>=1),'Monthly P&L, cash and runway'!F5>=1,IF('Monthly P&L, cash and runway'!F5="","",'Monthly P&L, cash and runway'!F5>=1))),IF('Model inputs'!B21="","",'Model inputs'!B21),0) -> 2000 | G29: =IF(IF(IF(ISERROR('Monthly P&L, cash and runway'!G5>=1),'Monthly P&L, cash and runway'!G5>=1,IF('Monthly P&L, cash and runway'!G5="","",'Monthly P&L, cash and runway'!G5>=1))="",FALSE,IF(ISERROR('Monthly P&L, cash and runway'!G5>=1),'Monthly P&L, cash and runway'!G5>=1,IF('Monthly P&L, cash and runway'!G5="","",'Monthly P&L, cash and runway'!G5>=1))),IF('Model inputs'!B21="","",'Model inputs'!B21),0) -> 2000 | H29: =IF(IF(IF(ISERROR('Monthly P&L, cash and runway'!H5>=1),'Monthly P&L, cash and runway'!H5>=1,IF('Monthly P&L, cash and runway'!H5="","",'Monthly P&L, cash and runway'!H5>=1))="",FALSE,IF(ISERROR('Monthly P&L, cash and runway'!H5>=1),'Monthly P&L, cash and runway'!H5>=1,IF('Monthly P&L, cash and runway'!H5="","",'Monthly P&L, cash and runway'!H5>=1))),IF('Model inputs'!B21="","",'Model inputs'!B21),0) -> 2000 | I29: =IF(IF(IF(ISERROR('Monthly P&L, cash and runway'!I5>=1),'Monthly P&L, cash and runway'!I5>=1,IF('Monthly P&L, cash and runway'!I5="","",'Monthly P&L, cash and runway'!I5>=1))="",FALSE,IF(ISERROR('Monthly P&L, cash and runway'!I5>=1),'Monthly P&L, cash and runway'!I5>=1,IF('Monthly P&L, cash and runway'!I5="","",'Monthly P&L, cash and runway'!I5>=1))),IF('Model inputs'!B21="","",'Model inputs'!B21),0) -> 2000 | J29: =IF(IF(IF(ISERROR('Monthly P&L, cash and runway'!J5>=1),'Monthly P&L, cash and runway'!J5>=1,IF('Monthly P&L, cash and runway'!J5="","",'Monthly P&L, cash and runway'!J5>=1))="",FALSE,IF(ISERROR('Monthly P&L, cash and runway'!J5>=1),'Monthly P&L, cash and runway'!J5>=1,IF('Monthly P&L, cash and runway'!J5="","",'Monthly P&L, cash and runway'!J5>=1))),IF('Model inputs'!B21="","",'Model inputs'!B21),0) -> 2000 | K29: =IF(IF(IF(ISERROR('Monthly P&L, cash and runway'!K5>=1),'Monthly P&L, cash and runway'!K5>=1,IF('Monthly P&L, cash and runway'!K5="","",'Monthly P&L, cash and runway'!K5>=1))="",FALSE,IF(ISERROR('Monthly P&L, cash and runway'!K5>=1),'Monthly P&L, cash and runway'!K5>=1,IF('Monthly P&L, cash and runway'!K5="","",'Monthly P&L, cash and runway'!K5>=1))),IF('Model inputs'!B21="","",'Model inputs'!B21),0) -> 2000 | L29: =IF(IF(IF(ISERROR('Monthly P&L, cash and runway'!L5>=1),'Monthly P&L, cash and runway'!L5>=1,IF('Monthly P&L, cash and runway'!L5="","",'Monthly P&L, cash and runway'!L5>=1))="",FALSE,IF(ISERROR('Monthly P&L, cash and runway'!L5>=1),'Monthly P&L, cash and runway'!L5>=1,IF('Monthly P&L, cash and runway'!L5="","",'Monthly P&L, cash and runway'!L5>=1))),IF('Model inputs'!B21="","",'Model inputs'!B21),0) -> 2000 | M29: =IF(IF(IF(ISERROR('Monthly P&L, cash and runway'!M5>=1),'Monthly P&L, cash and runway'!M5>=1,IF('Monthly P&L, cash and runway'!M5="","",'Monthly P&L, cash and runway'!M5>=1))="",FALSE,IF(ISERROR('Monthly P&L, cash and runway'!M5>=1),'Monthly P&L, cash and runway'!M5>=1,IF('Monthly P&L, cash and runway'!M5="","",'Monthly P&L, cash and runway'!M5>=1))),IF('Model inputs'!B21="","",'Model inputs'!B21),0) -> 2000 | N29: =IF(IF(IF(ISERROR('Monthly P&L, cash and runway'!N5>=1),'Monthly P&L, cash and runway'!N5>=1,IF('Monthly P&L, cash and runway'!N5="","",'Monthly P&L, cash and runway'!N5>=1))="",FALSE,IF(ISERROR('Monthly P&L, cash and runway'!N5>=1),'Monthly P&L, cash and runway'!N5>=1,IF('Monthly P&L, cash and runway'!N5="","",'Monthly P&L, cash and runway'!N5>=1))),IF('Model inputs'!B21="","",'Model inputs'!B21),0) -> 2000 | O29: =IF(IF(IF(ISERROR('Monthly P&L, cash and runway'!O5>=1),'Monthly P&L, cash and runway'!O5>=1,IF('Monthly P&L, cash and runway'!O5="","",'Monthly P&L, cash and runway'!O5>=1))="",FALSE,IF(ISERROR('Monthly P&L, cash and runway'!O5>=1),'Monthly P&L, cash and runway'!O5>=1,IF('Monthly P&L, cash and runway'!O5="","",'Monthly P&L, cash and runway'!O5>=1))),IF('Model inputs'!B21="","",'Model inputs'!B21),0) -> 2000 | P29: =IF(IF(IF(ISERROR('Monthly P&L, cash and runway'!P5>=1),'Monthly P&L, cash and runway'!P5>=1,IF('Monthly P&L, cash and runway'!P5="","",'Monthly P&L, cash and runway'!P5>=1))="",FALSE,IF(ISERROR('Monthly P&L, cash and runway'!P5>=1),'Monthly P&L, cash and runway'!P5>=1,IF('Monthly P&L, cash and runway'!P5="","",'Monthly P&L, cash and runway'!P5>=1))),IF('Model inputs'!B21="","",'Model inputs'!B21),0) -> 2000 | Q29: =IF(IF(IF(ISERROR('Monthly P&L, cash and runway'!Q5>=1),'Monthly P&L, cash and runway'!Q5>=1,IF('Monthly P&L, cash and runway'!Q5="","",'Monthly P&L, cash and runway'!Q5>=1))="",FALSE,IF(ISERROR('Monthly P&L, cash and runway'!Q5>=1),'Monthly P&L, cash and runway'!Q5>=1,IF('Monthly P&L, cash and runway'!Q5="","",'Monthly P&L, cash and runway'!Q5>=1))),IF('Model inputs'!B21="","",'Model inputs'!B21),0) -> 2000 | R29: =IF(IF(IF(ISERROR('Monthly P&L, cash and runway'!R5>=1),'Monthly P&L, cash and runway'!R5>=1,IF('Monthly P&L, cash and runway'!R5="","",'Monthly P&L, cash and runway'!R5>=1))="",FALSE,IF(ISERROR('Monthly P&L, cash and runway'!R5>=1),'Monthly P&L, cash and runway'!R5>=1,IF('Monthly P&L, cash and runway'!R5="","",'Monthly P&L, cash and runway'!R5>=1))),IF('Model inputs'!B21="","",'Model inputs'!B21),0) -> 2000 | S29: =IF(IF(IF(ISERROR('Monthly P&L, cash and runway'!S5>=1),'Monthly P&L, cash and runway'!S5>=1,IF('Monthly P&L, cash and runway'!S5="","",'Monthly P&L, cash and runway'!S5>=1))="",FALSE,IF(ISERROR('Monthly P&L, cash and runway'!S5>=1),'Monthly P&L, cash and runway'!S5>=1,IF('Monthly P&L, cash and runway'!S5="","",'Monthly P&L, cash and runway'!S5>=1))),IF('Model inputs'!B21="","",'Model inputs'!B21),0) -> 2000 | T29: =IF(IF(IF(ISERROR('Monthly P&L, cash and runway'!T5>=1),'Monthly P&L, cash and runway'!T5>=1,IF('Monthly P&L, cash and runway'!T5="","",'Monthly P&L, cash and runway'!T5>=1))="",FALSE,IF(ISERROR('Monthly P&L, cash and runway'!T5>=1),'Monthly P&L, cash and runway'!T5>=1,IF('Monthly P&L, cash and runway'!T5="","",'Monthly P&L, cash and runway'!T5>=1))),IF('Model inputs'!B21="","",'Model inputs'!B21),0) -> 2000 | U29: =IF(IF(IF(ISERROR('Monthly P&L, cash and runway'!U5>=1),'Monthly P&L, cash and runway'!U5>=1,IF('Monthly P&L, cash and runway'!U5="","",'Monthly P&L, cash and runway'!U5>=1))="",FALSE,IF(ISERROR('Monthly P&L, cash and runway'!U5>=1),'Monthly P&L, cash and runway'!U5>=1,IF('Monthly P&L, cash and runway'!U5="","",'Monthly P&L, cash and runway'!U5>=1))),IF('Model inputs'!B21="","",'Model inputs'!B21),0) -> 2000 | V29: =IF(IF(IF(ISERROR('Monthly P&L, cash and runway'!V5>=1),'Monthly P&L, cash and runway'!V5>=1,IF('Monthly P&L, cash and runway'!V5="","",'Monthly P&L, cash and runway'!V5>=1))="",FALSE,IF(ISERROR('Monthly P&L, cash and runway'!V5>=1),'Monthly P&L, cash and runway'!V5>=1,IF('Monthly P&L, cash and runway'!V5="","",'Monthly P&L, cash and runway'!V5>=1))),IF('Model inputs'!B21="","",'Model inputs'!B21),0) -> 2000 | W29: =IF(IF(IF(ISERROR('Monthly P&L, cash and runway'!W5>=1),'Monthly P&L, cash and runway'!W5>=1,IF('Monthly P&L, cash and runway'!W5="","",'Monthly P&L, cash and runway'!W5>=1))="",FALSE,IF(ISERROR('Monthly P&L, cash and runway'!W5>=1),'Monthly P&L, cash and runway'!W5>=1,IF('Monthly P&L, cash and runway'!W5="","",'Monthly P&L, cash and runway'!W5>=1))),IF('Model inputs'!B21="","",'Model inputs'!B21),0) -> 2000 | X29: =IF(IF(IF(ISERROR('Monthly P&L, cash and runway'!X5>=1),'Monthly P&L, cash and runway'!X5>=1,IF('Monthly P&L, cash and runway'!X5="","",'Monthly P&L, cash and runway'!X5>=1))="",FALSE,IF(ISERROR('Monthly P&L, cash and runway'!X5>=1),'Monthly P&L, cash and runway'!X5>=1,IF('Monthly P&L, cash and runway'!X5="","",'Monthly P&L, cash and runway'!X5>=1))),IF('Model inputs'!B21="","",'Model inputs'!B21),0) -> 2000 | Y29: =IF(IF(IF(ISERROR('Monthly P&L, cash and runway'!Y5>=1),'Monthly P&L, cash and runway'!Y5>=1,IF('Monthly P&L, cash and runway'!Y5="","",'Monthly P&L, cash and runway'!Y5>=1))="",FALSE,IF(ISERROR('Monthly P&L, cash and runway'!Y5>=1),'Monthly P&L, cash and runway'!Y5>=1,IF('Monthly P&L, cash and runway'!Y5="","",'Monthly P&L, cash and runway'!Y5>=1))),IF('Model inputs'!B21="","",'Model inputs'!B21),0) -> 2000
A30: Tools and SaaS | B30: =IF(IF(IF(ISERROR('Monthly P&L, cash and runway'!B5>=1),'Monthly P&L, cash and runway'!B5>=1,IF('Monthly P&L, cash and runway'!B5="","",'Monthly P&L, cash and runway'!B5>=1))="",FALSE,IF(ISERROR('Monthly P&L, cash and runway'!B5>=1),'Monthly P&L, cash and runway'!B5>=1,IF('Monthly P&L, cash and runway'!B5="","",'Monthly P&L, cash and runway'!B5>=1))),IF('Model inputs'!B44="","",'Model inputs'!B44),0) -> 100 | C30: =IF(IF(IF(ISERROR('Monthly P&L, cash and runway'!C5>=1),'Monthly P&L, cash and runway'!C5>=1,IF('Monthly P&L, cash and runway'!C5="","",'Monthly P&L, cash and runway'!C5>=1))="",FALSE,IF(ISERROR('Monthly P&L, cash and runway'!C5>=1),'Monthly P&L, cash and runway'!C5>=1,IF('Monthly P&L, cash and runway'!C5="","",'Monthly P&L, cash and runway'!C5>=1))),IF('Model inputs'!B44="","",'Model inputs'!B44),0) -> 100 | D30: =IF(IF(IF(ISERROR('Monthly P&L, cash and runway'!D5>=1),'Monthly P&L, cash and runway'!D5>=1,IF('Monthly P&L, cash and runway'!D5="","",'Monthly P&L, cash and runway'!D5>=1))="",FALSE,IF(ISERROR('Monthly P&L, cash and runway'!D5>=1),'Monthly P&L, cash and runway'!D5>=1,IF('Monthly P&L, cash and runway'!D5="","",'Monthly P&L, cash and runway'!D5>=1))),IF('Model inputs'!B44="","",'Model inputs'!B44),0) -> 100 | E30: =IF(IF(IF(ISERROR('Monthly P&L, cash and runway'!E5>=1),'Monthly P&L, cash and runway'!E5>=1,IF('Monthly P&L, cash and runway'!E5="","",'Monthly P&L, cash and runway'!E5>=1))="",FALSE,IF(ISERROR('Monthly P&L, cash and runway'!E5>=1),'Monthly P&L, cash and runway'!E5>=1,IF('Monthly P&L, cash and runway'!E5="","",'Monthly P&L, cash and runway'!E5>=1))),IF('Model inputs'!B44="","",'Model inputs'!B44),0) -> 100 | F30: =IF(IF(IF(ISERROR('Monthly P&L, cash and runway'!F5>=1),'Monthly P&L, cash and runway'!F5>=1,IF('Monthly P&L, cash and runway'!F5="","",'Monthly P&L, cash and runway'!F5>=1))="",FALSE,IF(ISERROR('Monthly P&L, cash and runway'!F5>=1),'Monthly P&L, cash and runway'!F5>=1,IF('Monthly P&L, cash and runway'!F5="","",'Monthly P&L, cash and runway'!F5>=1))),IF('Model inputs'!B44="","",'Model inputs'!B44),0) -> 100 | G30: =IF(IF(IF(ISERROR('Monthly P&L, cash and runway'!G5>=1),'Monthly P&L, cash and runway'!G5>=1,IF('Monthly P&L, cash and runway'!G5="","",'Monthly P&L, cash and runway'!G5>=1))="",FALSE,IF(ISERROR('Monthly P&L, cash and runway'!G5>=1),'Monthly P&L, cash and runway'!G5>=1,IF('Monthly P&L, cash and runway'!G5="","",'Monthly P&L, cash and runway'!G5>=1))),IF('Model inputs'!B44="","",'Model inputs'!B44),0) -> 100 | H30: =IF(IF(IF(ISERROR('Monthly P&L, cash and runway'!H5>=1),'Monthly P&L, cash and runway'!H5>=1,IF('Monthly P&L, cash and runway'!H5="","",'Monthly P&L, cash and runway'!H5>=1))="",FALSE,IF(ISERROR('Monthly P&L, cash and runway'!H5>=1),'Monthly P&L, cash and runway'!H5>=1,IF('Monthly P&L, cash and runway'!H5="","",'Monthly P&L, cash and runway'!H5>=1))),IF('Model inputs'!B44="","",'Model inputs'!B44),0) -> 100 | I30: =IF(IF(IF(ISERROR('Monthly P&L, cash and runway'!I5>=1),'Monthly P&L, cash and runway'!I5>=1,IF('Monthly P&L, cash and runway'!I5="","",'Monthly P&L, cash and runway'!I5>=1))="",FALSE,IF(ISERROR('Monthly P&L, cash and runway'!I5>=1),'Monthly P&L, cash and runway'!I5>=1,IF('Monthly P&L, cash and runway'!I5="","",'Monthly P&L, cash and runway'!I5>=1))),IF('Model inputs'!B44="","",'Model inputs'!B44),0) -> 100 | J30: =IF(IF(IF(ISERROR('Monthly P&L, cash and runway'!J5>=1),'Monthly P&L, cash and runway'!J5>=1,IF('Monthly P&L, cash and runway'!J5="","",'Monthly P&L, cash and runway'!J5>=1))="",FALSE,IF(ISERROR('Monthly P&L, cash and runway'!J5>=1),'Monthly P&L, cash and runway'!J5>=1,IF('Monthly P&L, cash and runway'!J5="","",'Monthly P&L, cash and runway'!J5>=1))),IF('Model inputs'!B44="","",'Model inputs'!B44),0) -> 100 | K30: =IF(IF(IF(ISERROR('Monthly P&L, cash and runway'!K5>=1),'Monthly P&L, cash and runway'!K5>=1,IF('Monthly P&L, cash and runway'!K5="","",'Monthly P&L, cash and runway'!K5>=1))="",FALSE,IF(ISERROR('Monthly P&L, cash and runway'!K5>=1),'Monthly P&L, cash and runway'!K5>=1,IF('Monthly P&L, cash and runway'!K5="","",'Monthly P&L, cash and runway'!K5>=1))),IF('Model inputs'!B44="","",'Model inputs'!B44),0) -> 100 | L30: =IF(IF(IF(ISERROR('Monthly P&L, cash and runway'!L5>=1),'Monthly P&L, cash and runway'!L5>=1,IF('Monthly P&L, cash and runway'!L5="","",'Monthly P&L, cash and runway'!L5>=1))="",FALSE,IF(ISERROR('Monthly P&L, cash and runway'!L5>=1),'Monthly P&L, cash and runway'!L5>=1,IF('Monthly P&L, cash and runway'!L5="","",'Monthly P&L, cash and runway'!L5>=1))),IF('Model inputs'!B44="","",'Model inputs'!B44),0) -> 100 | M30: =IF(IF(IF(ISERROR('Monthly P&L, cash and runway'!M5>=1),'Monthly P&L, cash and runway'!M5>=1,IF('Monthly P&L, cash and runway'!M5="","",'Monthly P&L, cash and runway'!M5>=1))="",FALSE,IF(ISERROR('Monthly P&L, cash and runway'!M5>=1),'Monthly P&L, cash and runway'!M5>=1,IF('Monthly P&L, cash and runway'!M5="","",'Monthly P&L, cash and runway'!M5>=1))),IF('Model inputs'!B44="","",'Model inputs'!B44),0) -> 100 | N30: =IF(IF(IF(ISERROR('Monthly P&L, cash and runway'!N5>=1),'Monthly P&L, cash and runway'!N5>=1,IF('Monthly P&L, cash and runway'!N5="","",'Monthly P&L, cash and runway'!N5>=1))="",FALSE,IF(ISERROR('Monthly P&L, cash and runway'!N5>=1),'Monthly P&L, cash and runway'!N5>=1,IF('Monthly P&L, cash and runway'!N5="","",'Monthly P&L, cash and runway'!N5>=1))),IF('Model inputs'!B44="","",'Model inputs'!B44),0) -> 100 | O30: =IF(IF(IF(ISERROR('Monthly P&L, cash and runway'!O5>=1),'Monthly P&L, cash and runway'!O5>=1,IF('Monthly P&L, cash and runway'!O5="","",'Monthly P&L, cash and runway'!O5>=1))="",FALSE,IF(ISERROR('Monthly P&L, cash and runway'!O5>=1),'Monthly P&L, cash and runway'!O5>=1,IF('Monthly P&L, cash and runway'!O5="","",'Monthly P&L, cash and runway'!O5>=1))),IF('Model inputs'!B44="","",'Model inputs'!B44),0) -> 100 | P30: =IF(IF(IF(ISERROR('Monthly P&L, cash and runway'!P5>=1),'Monthly P&L, cash and runway'!P5>=1,IF('Monthly P&L, cash and runway'!P5="","",'Monthly P&L, cash and runway'!P5>=1))="",FALSE,IF(ISERROR('Monthly P&L, cash and runway'!P5>=1),'Monthly P&L, cash and runway'!P5>=1,IF('Monthly P&L, cash and runway'!P5="","",'Monthly P&L, cash and runway'!P5>=1))),IF('Model inputs'!B44="","",'Model inputs'!B44),0) -> 100 | Q30: =IF(IF(IF(ISERROR('Monthly P&L, cash and runway'!Q5>=1),'Monthly P&L, cash and runway'!Q5>=1,IF('Monthly P&L, cash and runway'!Q5="","",'Monthly P&L, cash and runway'!Q5>=1))="",FALSE,IF(ISERROR('Monthly P&L, cash and runway'!Q5>=1),'Monthly P&L, cash and runway'!Q5>=1,IF('Monthly P&L, cash and runway'!Q5="","",'Monthly P&L, cash and runway'!Q5>=1))),IF('Model inputs'!B44="","",'Model inputs'!B44),0) -> 100 | R30: =IF(IF(IF(ISERROR('Monthly P&L, cash and runway'!R5>=1),'Monthly P&L, cash and runway'!R5>=1,IF('Monthly P&L, cash and runway'!R5="","",'Monthly P&L, cash and runway'!R5>=1))="",FALSE,IF(ISERROR('Monthly P&L, cash and runway'!R5>=1),'Monthly P&L, cash and runway'!R5>=1,IF('Monthly P&L, cash and runway'!R5="","",'Monthly P&L, cash and runway'!R5>=1))),IF('Model inputs'!B44="","",'Model inputs'!B44),0) -> 100 | S30: =IF(IF(IF(ISERROR('Monthly P&L, cash and runway'!S5>=1),'Monthly P&L, cash and runway'!S5>=1,IF('Monthly P&L, cash and runway'!S5="","",'Monthly P&L, cash and runway'!S5>=1))="",FALSE,IF(ISERROR('Monthly P&L, cash and runway'!S5>=1),'Monthly P&L, cash and runway'!S5>=1,IF('Monthly P&L, cash and runway'!S5="","",'Monthly P&L, cash and runway'!S5>=1))),IF('Model inputs'!B44="","",'Model inputs'!B44),0) -> 100 | T30: =IF(IF(IF(ISERROR('Monthly P&L, cash and runway'!T5>=1),'Monthly P&L, cash and runway'!T5>=1,IF('Monthly P&L, cash and runway'!T5="","",'Monthly P&L, cash and runway'!T5>=1))="",FALSE,IF(ISERROR('Monthly P&L, cash and runway'!T5>=1),'Monthly P&L, cash and runway'!T5>=1,IF('Monthly P&L, cash and runway'!T5="","",'Monthly P&L, cash and runway'!T5>=1))),IF('Model inputs'!B44="","",'Model inputs'!B44),0) -> 100 | U30: =IF(IF(IF(ISERROR('Monthly P&L, cash and runway'!U5>=1),'Monthly P&L, cash and runway'!U5>=1,IF('Monthly P&L, cash and runway'!U5="","",'Monthly P&L, cash and runway'!U5>=1))="",FALSE,IF(ISERROR('Monthly P&L, cash and runway'!U5>=1),'Monthly P&L, cash and runway'!U5>=1,IF('Monthly P&L, cash and runway'!U5="","",'Monthly P&L, cash and runway'!U5>=1))),IF('Model inputs'!B44="","",'Model inputs'!B44),0) -> 100 | V30: =IF(IF(IF(ISERROR('Monthly P&L, cash and runway'!V5>=1),'Monthly P&L, cash and runway'!V5>=1,IF('Monthly P&L, cash and runway'!V5="","",'Monthly P&L, cash and runway'!V5>=1))="",FALSE,IF(ISERROR('Monthly P&L, cash and runway'!V5>=1),'Monthly P&L, cash and runway'!V5>=1,IF('Monthly P&L, cash and runway'!V5="","",'Monthly P&L, cash and runway'!V5>=1))),IF('Model inputs'!B44="","",'Model inputs'!B44),0) -> 100 | W30: =IF(IF(IF(ISERROR('Monthly P&L, cash and runway'!W5>=1),'Monthly P&L, cash and runway'!W5>=1,IF('Monthly P&L, cash and runway'!W5="","",'Monthly P&L, cash and runway'!W5>=1))="",FALSE,IF(ISERROR('Monthly P&L, cash and runway'!W5>=1),'Monthly P&L, cash and runway'!W5>=1,IF('Monthly P&L, cash and runway'!W5="","",'Monthly P&L, cash and runway'!W5>=1))),IF('Model inputs'!B44="","",'Model inputs'!B44),0) -> 100 | X30: =IF(IF(IF(ISERROR('Monthly P&L, cash and runway'!X5>=1),'Monthly P&L, cash and runway'!X5>=1,IF('Monthly P&L, cash and runway'!X5="","",'Monthly P&L, cash and runway'!X5>=1))="",FALSE,IF(ISERROR('Monthly P&L, cash and runway'!X5>=1),'Monthly P&L, cash and runway'!X5>=1,IF('Monthly P&L, cash and runway'!X5="","",'Monthly P&L, cash and runway'!X5>=1))),IF('Model inputs'!B44="","",'Model inputs'!B44),0) -> 100 | Y30: =IF(IF(IF(ISERROR('Monthly P&L, cash and runway'!Y5>=1),'Monthly P&L, cash and runway'!Y5>=1,IF('Monthly P&L, cash and runway'!Y5="","",'Monthly P&L, cash and runway'!Y5>=1))="",FALSE,IF(ISERROR('Monthly P&L, cash and runway'!Y5>=1),'Monthly P&L, cash and runway'!Y5>=1,IF('Monthly P&L, cash and runway'!Y5="","",'Monthly P&L, cash and runway'!Y5>=1))),IF('Model inputs'!B44="","",'Model inputs'!B44),0) -> 100
A31: Operating expenses | B31: ='Monthly P&L, cash and runway'!B29+'Monthly P&L, cash and runway'!B30 -> 2100 | C31: ='Monthly P&L, cash and runway'!C29+'Monthly P&L, cash and runway'!C30 -> 2100 | D31: ='Monthly P&L, cash and runway'!D29+'Monthly P&L, cash and runway'!D30 -> 2100 | E31: ='Monthly P&L, cash and runway'!E29+'Monthly P&L, cash and runway'!E30 -> 2100 | F31: ='Monthly P&L, cash and runway'!F29+'Monthly P&L, cash and runway'!F30 -> 2100 | G31: ='Monthly P&L, cash and runway'!G29+'Monthly P&L, cash and runway'!G30 -> 2100 | H31: ='Monthly P&L, cash and runway'!H29+'Monthly P&L, cash and runway'!H30 -> 2100 | I31: ='Monthly P&L, cash and runway'!I29+'Monthly P&L, cash and runway'!I30 -> 2100 | ... Y31: ='Monthly P&L, cash and runway'!Y29+'Monthly P&L, cash and runway'!Y30 -> 2100
A32: Net cash flow | B32: ='Monthly P&L, cash and runway'!B27-'Monthly P&L, cash and runway'!B31 -> -2115.2 | C32: ='Monthly P&L, cash and runway'!C27-'Monthly P&L, cash and runway'!C31 -> -2115.2 | D32: ='Monthly P&L, cash and runway'!D27-'Monthly P&L, cash and runway'!D31 -> -2115.2 | E32: ='Monthly P&L, cash and runway'!E27-'Monthly P&L, cash and runway'!E31 -> -1991.576 | F32: ='Monthly P&L, cash and runway'!F27-'Monthly P&L, cash and runway'!F31 -> -1716.704 | G32: ='Monthly P&L, cash and runway'!G27-'Monthly P&L, cash and runway'!G31 -> -1593.08 | H32: ='Monthly P&L, cash and runway'!H27-'Monthly P&L, cash and runway'!H31 -> -1469.456 | I32: ='Monthly P&L, cash and runway'!I27-'Monthly P&L, cash and runway'!I31 -> -1194.584 | ... Y32: ='Monthly P&L, cash and runway'!Y27-'Monthly P&L, cash and runway'!Y31 -> 2487.88
A33: Net burn | B33: =-'Monthly P&L, cash and runway'!B32 -> 2115.2 | C33: =-'Monthly P&L, cash and runway'!C32 -> 2115.2 | D33: =-'Monthly P&L, cash and runway'!D32 -> 2115.2 | E33: =-'Monthly P&L, cash and runway'!E32 -> 1991.576 | F33: =-'Monthly P&L, cash and runway'!F32 -> 1716.704 | G33: =-'Monthly P&L, cash and runway'!G32 -> 1593.08 | H33: =-'Monthly P&L, cash and runway'!H32 -> 1469.456 | I33: =-'Monthly P&L, cash and runway'!I32 -> 1194.584 | ... Y33: =-'Monthly P&L, cash and runway'!Y32 -> -2487.88
A34: Ending cash | B34: =IF(IF(IF(IF(ISERROR('Monthly P&L, cash and runway'!B5=1),'Monthly P&L, cash and runway'!B5=1,IF('Monthly P&L, cash and runway'!B5="","",'Monthly P&L, cash and runway'!B5=1))="",FALSE,IF(ISERROR('Monthly P&L, cash and runway'!B5=1),'Monthly P&L, cash and runway'!B5=1,IF('Monthly P&L, cash and runway'!B5="","",'Monthly P&L, cash and runway'!B5=1))),IF('Model inputs'!B42="","",'Model inputs'!B42),IF('Model inputs'!D19="","",'Model inputs'!D19))="",0,IF(IF(IF(ISERROR('Monthly P&L, cash and runway'!B5=1),'Monthly P&L, cash and runway'!B5=1,IF('Monthly P&L, cash and runway'!B5="","",'Monthly P&L, cash and runway'!B5=1))="",FALSE,IF(ISERROR('Monthly P&L, cash and runway'!B5=1),'Monthly P&L, cash and runway'!B5=1,IF('Monthly P&L, cash and runway'!B5="","",'Monthly P&L, cash and runway'!B5=1))),IF('Model inputs'!B42="","",'Model inputs'!B42),IF('Model inputs'!D19="","",'Model inputs'!D19)))+'Monthly P&L, cash and runway'!B32 -> 22884.8 | C34: =IF(IF(IF(IF(ISERROR('Monthly P&L, cash and runway'!C5=1),'Monthly P&L, cash and runway'!C5=1,IF('Monthly P&L, cash and runway'!C5="","",'Monthly P&L, cash and runway'!C5=1))="",FALSE,IF(ISERROR('Monthly P&L, cash and runway'!C5=1),'Monthly P&L, cash and runway'!C5=1,IF('Monthly P&L, cash and runway'!C5="","",'Monthly P&L, cash and runway'!C5=1))),IF('Model inputs'!B42="","",'Model inputs'!B42),IF('Monthly P&L, cash and runway'!B34="","",'Monthly P&L, cash and runway'!B34))="",0,IF(IF(IF(ISERROR('Monthly P&L, cash and runway'!C5=1),'Monthly P&L, cash and runway'!C5=1,IF('Monthly P&L, cash and runway'!C5="","",'Monthly P&L, cash and runway'!C5=1))="",FALSE,IF(ISERROR('Monthly P&L, cash and runway'!C5=1),'Monthly P&L, cash and runway'!C5=1,IF('Monthly P&L, cash and runway'!C5="","",'Monthly P&L, cash and runway'!C5=1))),IF('Model inputs'!B42="","",'Model inputs'!B42),IF('Monthly P&L, cash and runway'!B34="","",'Monthly P&L, cash and runway'!B34)))+'Monthly P&L, cash and runway'!C32 -> 20769.6 | D34: =IF(IF(IF(IF(ISERROR('Monthly P&L, cash and runway'!D5=1),'Monthly P&L, cash and runway'!D5=1,IF('Monthly P&L, cash and runway'!D5="","",'Monthly P&L, cash and runway'!D5=1))="",FALSE,IF(ISERROR('Monthly P&L, cash and runway'!D5=1),'Monthly P&L, cash and runway'!D5=1,IF('Monthly P&L, cash and runway'!D5="","",'Monthly P&L, cash and runway'!D5=1))),IF('Model inputs'!B42="","",'Model inputs'!B42),IF('Monthly P&L, cash and runway'!C34="","",'Monthly P&L, cash and runway'!C34))="",0,IF(IF(IF(ISERROR('Monthly P&L, cash and runway'!D5=1),'Monthly P&L, cash and runway'!D5=1,IF('Monthly P&L, cash and runway'!D5="","",'Monthly P&L, cash and runway'!D5=1))="",FALSE,IF(ISERROR('Monthly P&L, cash and runway'!D5=1),'Monthly P&L, cash and runway'!D5=1,IF('Monthly P&L, cash and runway'!D5="","",'Monthly P&L, cash and runway'!D5=1))),IF('Model inputs'!B42="","",'Model inputs'!B42),IF('Monthly P&L, cash and runway'!C34="","",'Monthly P&L, cash and runway'!C34)))+'Monthly P&L, cash and runway'!D32 -> 18654.4 | E34: =IF(IF(IF(IF(ISERROR('Monthly P&L, cash and runway'!E5=1),'Monthly P&L, cash and runway'!E5=1,IF('Monthly P&L, cash and runway'!E5="","",'Monthly P&L, cash and runway'!E5=1))="",FALSE,IF(ISERROR('Monthly P&L, cash and runway'!E5=1),'Monthly P&L, cash and runway'!E5=1,IF('Monthly P&L, cash and runway'!E5="","",'Monthly P&L, cash and runway'!E5=1))),IF('Model inputs'!B42="","",'Model inputs'!B42),IF('Monthly P&L, cash and runway'!D34="","",'Monthly P&L, cash and runway'!D34))="",0,IF(IF(IF(ISERROR('Monthly P&L, cash and runway'!E5=1),'Monthly P&L, cash and runway'!E5=1,IF('Monthly P&L, cash and runway'!E5="","",'Monthly P&L, cash and runway'!E5=1))="",FALSE,IF(ISERROR('Monthly P&L, cash and runway'!E5=1),'Monthly P&L, cash and runway'!E5=1,IF('Monthly P&L, cash and runway'!E5="","",'Monthly P&L, cash and runway'!E5=1))),IF('Model inputs'!B42="","",'Model inputs'!B42),IF('Monthly P&L, cash and runway'!D34="","",'Monthly P&L, cash and runway'!D34)))+'Monthly P&L, cash and runway'!E32 -> 16662.824 | F34: =IF(IF(IF(IF(ISERROR('Monthly P&L, cash and runway'!F5=1),'Monthly P&L, cash and runway'!F5=1,IF('Monthly P&L, cash and runway'!F5="","",'Monthly P&L, cash and runway'!F5=1))="",FALSE,IF(ISERROR('Monthly P&L, cash and runway'!F5=1),'Monthly P&L, cash and runway'!F5=1,IF('Monthly P&L, cash and runway'!F5="","",'Monthly P&L, cash and runway'!F5=1))),IF('Model inputs'!B42="","",'Model inputs'!B42),IF('Monthly P&L, cash and runway'!E34="","",'Monthly P&L, cash and runway'!E34))="",0,IF(IF(IF(ISERROR('Monthly P&L, cash and runway'!F5=1),'Monthly P&L, cash and runway'!F5=1,IF('Monthly P&L, cash and runway'!F5="","",'Monthly P&L, cash and runway'!F5=1))="",FALSE,IF(ISERROR('Monthly P&L, cash and runway'!F5=1),'Monthly P&L, cash and runway'!F5=1,IF('Monthly P&L, cash and runway'!F5="","",'Monthly P&L, cash and runway'!F5=1))),IF('Model inputs'!B42="","",'Model inputs'!B42),IF('Monthly P&L, cash and runway'!E34="","",'Monthly P&L, cash and runway'!E34)))+'Monthly P&L, cash and runway'!F32 -> 14946.12 | G34: =IF(IF(IF(IF(ISERROR('Monthly P&L, cash and runway'!G5=1),'Monthly P&L, cash and runway'!G5=1,IF('Monthly P&L, cash and runway'!G5="","",'Monthly P&L, cash and runway'!G5=1))="",FALSE,IF(ISERROR('Monthly P&L, cash and runway'!G5=1),'Monthly P&L, cash and runway'!G5=1,IF('Monthly P&L, cash and runway'!G5="","",'Monthly P&L, cash and runway'!G5=1))),IF('Model inputs'!B42="","",'Model inputs'!B42),IF('Monthly P&L, cash and runway'!F34="","",'Monthly P&L, cash and runway'!F34))="",0,IF(IF(IF(ISERROR('Monthly P&L, cash and runway'!G5=1),'Monthly P&L, cash and runway'!G5=1,IF('Monthly P&L, cash and runway'!G5="","",'Monthly P&L, cash and runway'!G5=1))="",FALSE,IF(ISERROR('Monthly P&L, cash and runway'!G5=1),'Monthly P&L, cash and runway'!G5=1,IF('Monthly P&L, cash and runway'!G5="","",'Monthly P&L, cash and runway'!G5=1))),IF('Model inputs'!B42="","",'Model inputs'!B42),IF('Monthly P&L, cash and runway'!F34="","",'Monthly P&L, cash and runway'!F34)))+'Monthly P&L, cash and runway'!G32 -> 13353.04 | H34: =IF(IF(IF(IF(ISERROR('Monthly P&L, cash and runway'!H5=1),'Monthly P&L, cash and runway'!H5=1,IF('Monthly P&L, cash and runway'!H5="","",'Monthly P&L, cash and runway'!H5=1))="",FALSE,IF(ISERROR('Monthly P&L, cash and runway'!H5=1),'Monthly P&L, cash and runway'!H5=1,IF('Monthly P&L, cash and runway'!H5="","",'Monthly P&L, cash and runway'!H5=1))),IF('Model inputs'!B42="","",'Model inputs'!B42),IF('Monthly P&L, cash and runway'!G34="","",'Monthly P&L, cash and runway'!G34))="",0,IF(IF(IF(ISERROR('Monthly P&L, cash and runway'!H5=1),'Monthly P&L, cash and runway'!H5=1,IF('Monthly P&L, cash and runway'!H5="","",'Monthly P&L, cash and runway'!H5=1))="",FALSE,IF(ISERROR('Monthly P&L, cash and runway'!H5=1),'Monthly P&L, cash and runway'!H5=1,IF('Monthly P&L, cash and runway'!H5="","",'Monthly P&L, cash and runway'!H5=1))),IF('Model inputs'!B42="","",'Model inputs'!B42),IF('Monthly P&L, cash and runway'!G34="","",'Monthly P&L, cash and runway'!G34)))+'Monthly P&L, cash and runway'!H32 -> 11883.584 | I34: =IF(IF(IF(IF(ISERROR('Monthly P&L, cash and runway'!I5=1),'Monthly P&L, cash and runway'!I5=1,IF('Monthly P&L, cash and runway'!I5="","",'Monthly P&L, cash and runway'!I5=1))="",FALSE,IF(ISERROR('Monthly P&L, cash and runway'!I5=1),'Monthly P&L, cash and runway'!I5=1,IF('Monthly P&L, cash and runway'!I5="","",'Monthly P&L, cash and runway'!I5=1))),IF('Model inputs'!B42="","",'Model inputs'!B42),IF('Monthly P&L, cash and runway'!H34="","",'Monthly P&L, cash and runway'!H34))="",0,IF(IF(IF(ISERROR('Monthly P&L, cash and runway'!I5=1),'Monthly P&L, cash and runway'!I5=1,IF('Monthly P&L, cash and runway'!I5="","",'Monthly P&L, cash and runway'!I5=1))="",FALSE,IF(ISERROR('Monthly P&L, cash and runway'!I5=1),'Monthly P&L, cash and runway'!I5=1,IF('Monthly P&L, cash and runway'!I5="","",'Monthly P&L, cash and runway'!I5=1))),IF('Model inputs'!B42="","",'Model inputs'!B42),IF('Monthly P&L, cash and runway'!H34="","",'Monthly P&L, cash and runway'!H34)))+'Monthly P&L, cash and runway'!I32 -> 10689 | J34: =IF(IF(IF(IF(ISERROR('Monthly P&L, cash and runway'!J5=1),'Monthly P&L, cash and runway'!J5=1,IF('Monthly P&L, cash and runway'!J5="","",'Monthly P&L, cash and runway'!J5=1))="",FALSE,IF(ISERROR('Monthly P&L, cash and runway'!J5=1),'Monthly P&L, cash and runway'!J5=1,IF('Monthly P&L, cash and runway'!J5="","",'Monthly P&L, cash and runway'!J5=1))),IF('Model inputs'!B42="","",'Model inputs'!B42),IF('Monthly P&L, cash and runway'!I34="","",'Monthly P&L, cash and runway'!I34))="",0,IF(IF(IF(ISERROR('Monthly P&L, cash and runway'!J5=1),'Monthly P&L, cash and runway'!J5=1,IF('Monthly P&L, cash and runway'!J5="","",'Monthly P&L, cash and runway'!J5=1))="",FALSE,IF(ISERROR('Monthly P&L, cash and runway'!J5=1),'Monthly P&L, cash and runway'!J5=1,IF('Monthly P&L, cash and runway'!J5="","",'Monthly P&L, cash and runway'!J5=1))),IF('Model inputs'!B42="","",'Model inputs'!B42),IF('Monthly P&L, cash and runway'!I34="","",'Monthly P&L, cash and runway'!I34)))+'Monthly P&L, cash and runway'!J32 -> 9618.04 | K34: =IF(IF(IF(IF(ISERROR('Monthly P&L, cash and runway'!K5=1),'Monthly P&L, cash and runway'!K5=1,IF('Monthly P&L, cash and runway'!K5="","",'Monthly P&L, cash and runway'!K5=1))="",FALSE,IF(ISERROR('Monthly P&L, cash and runway'!K5=1),'Monthly P&L, cash and runway'!K5=1,IF('Monthly P&L, cash and runway'!K5="","",'Monthly P&L, cash and runway'!K5=1))),IF('Model inputs'!B42="","",'Model inputs'!B42),IF('Monthly P&L, cash and runway'!J34="","",'Monthly P&L, cash and runway'!J34))="",0,IF(IF(IF(ISERROR('Monthly P&L, cash and runway'!K5=1),'Monthly P&L, cash and runway'!K5=1,IF('Monthly P&L, cash and runway'!K5="","",'Monthly P&L, cash and runway'!K5=1))="",FALSE,IF(ISERROR('Monthly P&L, cash and runway'!K5=1),'Monthly P&L, cash and runway'!K5=1,IF('Monthly P&L, cash and runway'!K5="","",'Monthly P&L, cash and runway'!K5=1))),IF('Model inputs'!B42="","",'Model inputs'!B42),IF('Monthly P&L, cash and runway'!J34="","",'Monthly P&L, cash and runway'!J34)))+'Monthly P&L, cash and runway'!K32 -> 8670.704 | L34: =IF(IF(IF(IF(ISERROR('Monthly P&L, cash and runway'!L5=1),'Monthly P&L, cash and runway'!L5=1,IF('Monthly P&L, cash and runway'!L5="","",'Monthly P&L, cash and runway'!L5=1))="",FALSE,IF(ISERROR('Monthly P&L, cash and runway'!L5=1),'Monthly P&L, cash and runway'!L5=1,IF('Monthly P&L, cash and runway'!L5="","",'Monthly P&L, cash and runway'!L5=1))),IF('Model inputs'!B42="","",'Model inputs'!B42),IF('Monthly P&L, cash and runway'!K34="","",'Monthly P&L, cash and runway'!K34))="",0,IF(IF(IF(ISERROR('Monthly P&L, cash and runway'!L5=1),'Monthly P&L, cash and runway'!L5=1,IF('Monthly P&L, cash and runway'!L5="","",'Monthly P&L, cash and runway'!L5=1))="",FALSE,IF(ISERROR('Monthly P&L, cash and runway'!L5=1),'Monthly P&L, cash and runway'!L5=1,IF('Monthly P&L, cash and runway'!L5="","",'Monthly P&L, cash and runway'!L5=1))),IF('Model inputs'!B42="","",'Model inputs'!B42),IF('Monthly P&L, cash and runway'!K34="","",'Monthly P&L, cash and runway'!K34)))+'Monthly P&L, cash and runway'!L32 -> 7998.24 | M34: =IF(IF(IF(IF(ISERROR('Monthly P&L, cash and runway'!M5=1),'Monthly P&L, cash and runway'!M5=1,IF('Monthly P&L, cash and runway'!M5="","",'Monthly P&L, cash and runway'!M5=1))="",FALSE,IF(ISERROR('Monthly P&L, cash and runway'!M5=1),'Monthly P&L, cash and runway'!M5=1,IF('Monthly P&L, cash and runway'!M5="","",'Monthly P&L, cash and runway'!M5=1))),IF('Model inputs'!B42="","",'Model inputs'!B42),IF('Monthly P&L, cash and runway'!L34="","",'Monthly P&L, cash and runway'!L34))="",0,IF(IF(IF(ISERROR('Monthly P&L, cash and runway'!M5=1),'Monthly P&L, cash and runway'!M5=1,IF('Monthly P&L, cash and runway'!M5="","",'Monthly P&L, cash and runway'!M5=1))="",FALSE,IF(ISERROR('Monthly P&L, cash and runway'!M5=1),'Monthly P&L, cash and runway'!M5=1,IF('Monthly P&L, cash and runway'!M5="","",'Monthly P&L, cash and runway'!M5=1))),IF('Model inputs'!B42="","",'Model inputs'!B42),IF('Monthly P&L, cash and runway'!L34="","",'Monthly P&L, cash and runway'!L34)))+'Monthly P&L, cash and runway'!M32 -> 7449.4 | N34: =IF(IF(IF(IF(ISERROR('Monthly P&L, cash and runway'!N5=1),'Monthly P&L, cash and runway'!N5=1,IF('Monthly P&L, cash and runway'!N5="","",'Monthly P&L, cash and runway'!N5=1))="",FALSE,IF(ISERROR('Monthly P&L, cash and runway'!N5=1),'Monthly P&L, cash and runway'!N5=1,IF('Monthly P&L, cash and runway'!N5="","",'Monthly P&L, cash and runway'!N5=1))),IF('Model inputs'!B42="","",'Model inputs'!B42),IF('Monthly P&L, cash and runway'!M34="","",'Monthly P&L, cash and runway'!M34))="",0,IF(IF(IF(ISERROR('Monthly P&L, cash and runway'!N5=1),'Monthly P&L, cash and runway'!N5=1,IF('Monthly P&L, cash and runway'!N5="","",'Monthly P&L, cash and runway'!N5=1))="",FALSE,IF(ISERROR('Monthly P&L, cash and runway'!N5=1),'Monthly P&L, cash and runway'!N5=1,IF('Monthly P&L, cash and runway'!N5="","",'Monthly P&L, cash and runway'!N5=1))),IF('Model inputs'!B42="","",'Model inputs'!B42),IF('Monthly P&L, cash and runway'!M34="","",'Monthly P&L, cash and runway'!M34)))+'Monthly P&L, cash and runway'!N32 -> 7237.244 | O34: =IF(IF(IF(IF(ISERROR('Monthly P&L, cash and runway'!O5=1),'Monthly P&L, cash and runway'!O5=1,IF('Monthly P&L, cash and runway'!O5="","",'Monthly P&L, cash and runway'!O5=1))="",FALSE,IF(ISERROR('Monthly P&L, cash and runway'!O5=1),'Monthly P&L, cash and runway'!O5=1,IF('Monthly P&L, cash and runway'!O5="","",'Monthly P&L, cash and runway'!O5=1))),IF('Model inputs'!B42="","",'Model inputs'!B42),IF('Monthly P&L, cash and runway'!N34="","",'Monthly P&L, cash and runway'!N34))="",0,IF(IF(IF(ISERROR('Monthly P&L, cash and runway'!O5=1),'Monthly P&L, cash and runway'!O5=1,IF('Monthly P&L, cash and runway'!O5="","",'Monthly P&L, cash and runway'!O5=1))="",FALSE,IF(ISERROR('Monthly P&L, cash and runway'!O5=1),'Monthly P&L, cash and runway'!O5=1,IF('Monthly P&L, cash and runway'!O5="","",'Monthly P&L, cash and runway'!O5=1))),IF('Model inputs'!B42="","",'Model inputs'!B42),IF('Monthly P&L, cash and runway'!N34="","",'Monthly P&L, cash and runway'!N34)))+'Monthly P&L, cash and runway'!O32 -> 7148.712 | P34: =IF(IF(IF(IF(ISERROR('Monthly P&L, cash and runway'!P5=1),'Monthly P&L, cash and runway'!P5=1,IF('Monthly P&L, cash and runway'!P5="","",'Monthly P&L, cash and runway'!P5=1))="",FALSE,IF(ISERROR('Monthly P&L, cash and runway'!P5=1),'Monthly P&L, cash and runway'!P5=1,IF('Monthly P&L, cash and runway'!P5="","",'Monthly P&L, cash and runway'!P5=1))),IF('Model inputs'!B42="","",'Model inputs'!B42),IF('Monthly P&L, cash and runway'!O34="","",'Monthly P&L, cash and runway'!O34))="",0,IF(IF(IF(ISERROR('Monthly P&L, cash and runway'!P5=1),'Monthly P&L, cash and runway'!P5=1,IF('Monthly P&L, cash and runway'!P5="","",'Monthly P&L, cash and runway'!P5=1))="",FALSE,IF(ISERROR('Monthly P&L, cash and runway'!P5=1),'Monthly P&L, cash and runway'!P5=1,IF('Monthly P&L, cash and runway'!P5="","",'Monthly P&L, cash and runway'!P5=1))),IF('Model inputs'!B42="","",'Model inputs'!B42),IF('Monthly P&L, cash and runway'!O34="","",'Monthly P&L, cash and runway'!O34)))+'Monthly P&L, cash and runway'!P32 -> 7396.864 | Q34: =IF(IF(IF(IF(ISERROR('Monthly P&L, cash and runway'!Q5=1),'Monthly P&L, cash and runway'!Q5=1,IF('Monthly P&L, cash and runway'!Q5="","",'Monthly P&L, cash and runway'!Q5=1))="",FALSE,IF(ISERROR('Monthly P&L, cash and runway'!Q5=1),'Monthly P&L, cash and runway'!Q5=1,IF('Monthly P&L, cash and runway'!Q5="","",'Monthly P&L, cash and runway'!Q5=1))),IF('Model inputs'!B42="","",'Model inputs'!B42),IF('Monthly P&L, cash and runway'!P34="","",'Monthly P&L, cash and runway'!P34))="",0,IF(IF(IF(ISERROR('Monthly P&L, cash and runway'!Q5=1),'Monthly P&L, cash and runway'!Q5=1,IF('Monthly P&L, cash and runway'!Q5="","",'Monthly P&L, cash and runway'!Q5=1))="",FALSE,IF(ISERROR('Monthly P&L, cash and runway'!Q5=1),'Monthly P&L, cash and runway'!Q5=1,IF('Monthly P&L, cash and runway'!Q5="","",'Monthly P&L, cash and runway'!Q5=1))),IF('Model inputs'!B42="","",'Model inputs'!B42),IF('Monthly P&L, cash and runway'!P34="","",'Monthly P&L, cash and runway'!P34)))+'Monthly P&L, cash and runway'!Q32 -> 7768.64 | R34: =IF(IF(IF(IF(ISERROR('Monthly P&L, cash and runway'!R5=1),'Monthly P&L, cash and runway'!R5=1,IF('Monthly P&L, cash and runway'!R5="","",'Monthly P&L, cash and runway'!R5=1))="",FALSE,IF(ISERROR('Monthly P&L, cash and runway'!R5=1),'Monthly P&L, cash and runway'!R5=1,IF('Monthly P&L, cash and runway'!R5="","",'Monthly P&L, cash and runway'!R5=1))),IF('Model inputs'!B42="","",'Model inputs'!B42),IF('Monthly P&L, cash and runway'!Q34="","",'Monthly P&L, cash and runway'!Q34))="",0,IF(IF(IF(ISERROR('Monthly P&L, cash and runway'!R5=1),'Monthly P&L, cash and runway'!R5=1,IF('Monthly P&L, cash and runway'!R5="","",'Monthly P&L, cash and runway'!R5=1))="",FALSE,IF(ISERROR('Monthly P&L, cash and runway'!R5=1),'Monthly P&L, cash and runway'!R5=1,IF('Monthly P&L, cash and runway'!R5="","",'Monthly P&L, cash and runway'!R5=1))),IF('Model inputs'!B42="","",'Model inputs'!B42),IF('Monthly P&L, cash and runway'!Q34="","",'Monthly P&L, cash and runway'!Q34)))+'Monthly P&L, cash and runway'!R32 -> 8477.1 | S34: =IF(IF(IF(IF(ISERROR('Monthly P&L, cash and runway'!S5=1),'Monthly P&L, cash and runway'!S5=1,IF('Monthly P&L, cash and runway'!S5="","",'Monthly P&L, cash and runway'!S5=1))="",FALSE,IF(ISERROR('Monthly P&L, cash and runway'!S5=1),'Monthly P&L, cash and runway'!S5=1,IF('Monthly P&L, cash and runway'!S5="","",'Monthly P&L, cash and runway'!S5=1))),IF('Model inputs'!B42="","",'Model inputs'!B42),IF('Monthly P&L, cash and runway'!R34="","",'Monthly P&L, cash and runway'!R34))="",0,IF(IF(IF(ISERROR('Monthly P&L, cash and runway'!S5=1),'Monthly P&L, cash and runway'!S5=1,IF('Monthly P&L, cash and runway'!S5="","",'Monthly P&L, cash and runway'!S5=1))="",FALSE,IF(ISERROR('Monthly P&L, cash and runway'!S5=1),'Monthly P&L, cash and runway'!S5=1,IF('Monthly P&L, cash and runway'!S5="","",'Monthly P&L, cash and runway'!S5=1))),IF('Model inputs'!B42="","",'Model inputs'!B42),IF('Monthly P&L, cash and runway'!R34="","",'Monthly P&L, cash and runway'!R34)))+'Monthly P&L, cash and runway'!S32 -> 9584.056 | T34: =IF(IF(IF(IF(ISERROR('Monthly P&L, cash and runway'!T5=1),'Monthly P&L, cash and runway'!T5=1,IF('Monthly P&L, cash and runway'!T5="","",'Monthly P&L, cash and runway'!T5=1))="",FALSE,IF(ISERROR('Monthly P&L, cash and runway'!T5=1),'Monthly P&L, cash and runway'!T5=1,IF('Monthly P&L, cash and runway'!T5="","",'Monthly P&L, cash and runway'!T5=1))),IF('Model inputs'!B42="","",'Model inputs'!B42),IF('Monthly P&L, cash and runway'!S34="","",'Monthly P&L, cash and runway'!S34))="",0,IF(IF(IF(ISERROR('Monthly P&L, cash and runway'!T5=1),'Monthly P&L, cash and runway'!T5=1,IF('Monthly P&L, cash and runway'!T5="","",'Monthly P&L, cash and runway'!T5=1))="",FALSE,IF(ISERROR('Monthly P&L, cash and runway'!T5=1),'Monthly P&L, cash and runway'!T5=1,IF('Monthly P&L, cash and runway'!T5="","",'Monthly P&L, cash and runway'!T5=1))),IF('Model inputs'!B42="","",'Model inputs'!B42),IF('Monthly P&L, cash and runway'!S34="","",'Monthly P&L, cash and runway'!S34)))+'Monthly P&L, cash and runway'!T32 -> 10814.636 | U34: =IF(IF(IF(IF(ISERROR('Monthly P&L, cash and runway'!U5=1),'Monthly P&L, cash and runway'!U5=1,IF('Monthly P&L, cash and runway'!U5="","",'Monthly P&L, cash and runway'!U5=1))="",FALSE,IF(ISERROR('Monthly P&L, cash and runway'!U5=1),'Monthly P&L, cash and runway'!U5=1,IF('Monthly P&L, cash and runway'!U5="","",'Monthly P&L, cash and runway'!U5=1))),IF('Model inputs'!B42="","",'Model inputs'!B42),IF('Monthly P&L, cash and runway'!T34="","",'Monthly P&L, cash and runway'!T34))="",0,IF(IF(IF(ISERROR('Monthly P&L, cash and runway'!U5=1),'Monthly P&L, cash and runway'!U5=1,IF('Monthly P&L, cash and runway'!U5="","",'Monthly P&L, cash and runway'!U5=1))="",FALSE,IF(ISERROR('Monthly P&L, cash and runway'!U5=1),'Monthly P&L, cash and runway'!U5=1,IF('Monthly P&L, cash and runway'!U5="","",'Monthly P&L, cash and runway'!U5=1))),IF('Model inputs'!B42="","",'Model inputs'!B42),IF('Monthly P&L, cash and runway'!T34="","",'Monthly P&L, cash and runway'!T34)))+'Monthly P&L, cash and runway'!U32 -> 12381.9 | V34: =IF(IF(IF(IF(ISERROR('Monthly P&L, cash and runway'!V5=1),'Monthly P&L, cash and runway'!V5=1,IF('Monthly P&L, cash and runway'!V5="","",'Monthly P&L, cash and runway'!V5=1))="",FALSE,IF(ISERROR('Monthly P&L, cash and runway'!V5=1),'Monthly P&L, cash and runway'!V5=1,IF('Monthly P&L, cash and runway'!V5="","",'Monthly P&L, cash and runway'!V5=1))),IF('Model inputs'!B42="","",'Model inputs'!B42),IF('Monthly P&L, cash and runway'!U34="","",'Monthly P&L, cash and runway'!U34))="",0,IF(IF(IF(ISERROR('Monthly P&L, cash and runway'!V5=1),'Monthly P&L, cash and runway'!V5=1,IF('Monthly P&L, cash and runway'!V5="","",'Monthly P&L, cash and runway'!V5=1))="",FALSE,IF(ISERROR('Monthly P&L, cash and runway'!V5=1),'Monthly P&L, cash and runway'!V5=1,IF('Monthly P&L, cash and runway'!V5="","",'Monthly P&L, cash and runway'!V5=1))),IF('Model inputs'!B42="","",'Model inputs'!B42),IF('Monthly P&L, cash and runway'!U34="","",'Monthly P&L, cash and runway'!U34)))+'Monthly P&L, cash and runway'!V32 -> 14072.788 | W34: =IF(IF(IF(IF(ISERROR('Monthly P&L, cash and runway'!W5=1),'Monthly P&L, cash and runway'!W5=1,IF('Monthly P&L, cash and runway'!W5="","",'Monthly P&L, cash and runway'!W5=1))="",FALSE,IF(ISERROR('Monthly P&L, cash and runway'!W5=1),'Monthly P&L, cash and runway'!W5=1,IF('Monthly P&L, cash and runway'!W5="","",'Monthly P&L, cash and runway'!W5=1))),IF('Model inputs'!B42="","",'Model inputs'!B42),IF('Monthly P&L, cash and runway'!V34="","",'Monthly P&L, cash and runway'!V34))="",0,IF(IF(IF(ISERROR('Monthly P&L, cash and runway'!W5=1),'Monthly P&L, cash and runway'!W5=1,IF('Monthly P&L, cash and runway'!W5="","",'Monthly P&L, cash and runway'!W5=1))="",FALSE,IF(ISERROR('Monthly P&L, cash and runway'!W5=1),'Monthly P&L, cash and runway'!W5=1,IF('Monthly P&L, cash and runway'!W5="","",'Monthly P&L, cash and runway'!W5=1))),IF('Model inputs'!B42="","",'Model inputs'!B42),IF('Monthly P&L, cash and runway'!V34="","",'Monthly P&L, cash and runway'!V34)))+'Monthly P&L, cash and runway'!W32 -> 16100.36 | X34: =IF(IF(IF(IF(ISERROR('Monthly P&L, cash and runway'!X5=1),'Monthly P&L, cash and runway'!X5=1,IF('Monthly P&L, cash and runway'!X5="","",'Monthly P&L, cash and runway'!X5=1))="",FALSE,IF(ISERROR('Monthly P&L, cash and runway'!X5=1),'Monthly P&L, cash and runway'!X5=1,IF('Monthly P&L, cash and runway'!X5="","",'Monthly P&L, cash and runway'!X5=1))),IF('Model inputs'!B42="","",'Model inputs'!B42),IF('Monthly P&L, cash and runway'!W34="","",'Monthly P&L, cash and runway'!W34))="",0,IF(IF(IF(ISERROR('Monthly P&L, cash and runway'!X5=1),'Monthly P&L, cash and runway'!X5=1,IF('Monthly P&L, cash and runway'!X5="","",'Monthly P&L, cash and runway'!X5=1))="",FALSE,IF(ISERROR('Monthly P&L, cash and runway'!X5=1),'Monthly P&L, cash and runway'!X5=1,IF('Monthly P&L, cash and runway'!X5="","",'Monthly P&L, cash and runway'!X5=1))),IF('Model inputs'!B42="","",'Model inputs'!B42),IF('Monthly P&L, cash and runway'!W34="","",'Monthly P&L, cash and runway'!W34)))+'Monthly P&L, cash and runway'!X32 -> 18251.556 | Y34: =IF(IF(IF(IF(ISERROR('Monthly P&L, cash and runway'!Y5=1),'Monthly P&L, cash and runway'!Y5=1,IF('Monthly P&L, cash and runway'!Y5="","",'Monthly P&L, cash and runway'!Y5=1))="",FALSE,IF(ISERROR('Monthly P&L, cash and runway'!Y5=1),'Monthly P&L, cash and runway'!Y5=1,IF('Monthly P&L, cash and runway'!Y5="","",'Monthly P&L, cash and runway'!Y5=1))),IF('Model inputs'!B42="","",'Model inputs'!B42),IF('Monthly P&L, cash and runway'!X34="","",'Monthly P&L, cash and runway'!X34))="",0,IF(IF(IF(ISERROR('Monthly P&L, cash and runway'!Y5=1),'Monthly P&L, cash and runway'!Y5=1,IF('Monthly P&L, cash and runway'!Y5="","",'Monthly P&L, cash and runway'!Y5=1))="",FALSE,IF(ISERROR('Monthly P&L, cash and runway'!Y5=1),'Monthly P&L, cash and runway'!Y5=1,IF('Monthly P&L, cash and runway'!Y5="","",'Monthly P&L, cash and runway'!Y5=1))),IF('Model inputs'!B42="","",'Model inputs'!B42),IF('Monthly P&L, cash and runway'!X34="","",'Monthly P&L, cash and runway'!X34)))+'Monthly P&L, cash and runway'!Y32 -> 20739.436
A35: Months of runway | B35: =IF(IF(IF(ISERROR('Monthly P&L, cash and runway'!B33>0),'Monthly P&L, cash and runway'!B33>0,IF('Monthly P&L, cash and runway'!B33="","",'Monthly P&L, cash and runway'!B33>0))="",FALSE,IF(ISERROR('Monthly P&L, cash and runway'!B33>0),'Monthly P&L, cash and runway'!B33>0,IF('Monthly P&L, cash and runway'!B33="","",'Monthly P&L, cash and runway'!B33>0))),'Monthly P&L, cash and runway'!B34/'Monthly P&L, cash and runway'!B33,"") -> 10.819213 | C35: =IF(IF(IF(ISERROR('Monthly P&L, cash and runway'!C33>0),'Monthly P&L, cash and runway'!C33>0,IF('Monthly P&L, cash and runway'!C33="","",'Monthly P&L, cash and runway'!C33>0))="",FALSE,IF(ISERROR('Monthly P&L, cash and runway'!C33>0),'Monthly P&L, cash and runway'!C33>0,IF('Monthly P&L, cash and runway'!C33="","",'Monthly P&L, cash and runway'!C33>0))),'Monthly P&L, cash and runway'!C34/'Monthly P&L, cash and runway'!C33,"") -> 9.8192133 | D35: =IF(IF(IF(ISERROR('Monthly P&L, cash and runway'!D33>0),'Monthly P&L, cash and runway'!D33>0,IF('Monthly P&L, cash and runway'!D33="","",'Monthly P&L, cash and runway'!D33>0))="",FALSE,IF(ISERROR('Monthly P&L, cash and runway'!D33>0),'Monthly P&L, cash and runway'!D33>0,IF('Monthly P&L, cash and runway'!D33="","",'Monthly P&L, cash and runway'!D33>0))),'Monthly P&L, cash and runway'!D34/'Monthly P&L, cash and runway'!D33,"") -> 8.8192133 | E35: =IF(IF(IF(ISERROR('Monthly P&L, cash and runway'!E33>0),'Monthly P&L, cash and runway'!E33>0,IF('Monthly P&L, cash and runway'!E33="","",'Monthly P&L, cash and runway'!E33>0))="",FALSE,IF(ISERROR('Monthly P&L, cash and runway'!E33>0),'Monthly P&L, cash and runway'!E33>0,IF('Monthly P&L, cash and runway'!E33="","",'Monthly P&L, cash and runway'!E33>0))),'Monthly P&L, cash and runway'!E34/'Monthly P&L, cash and runway'!E33,"") -> 8.3666523 | F35: =IF(IF(IF(ISERROR('Monthly P&L, cash and runway'!F33>0),'Monthly P&L, cash and runway'!F33>0,IF('Monthly P&L, cash and runway'!F33="","",'Monthly P&L, cash and runway'!F33>0))="",FALSE,IF(ISERROR('Monthly P&L, cash and runway'!F33>0),'Monthly P&L, cash and runway'!F33>0,IF('Monthly P&L, cash and runway'!F33="","",'Monthly P&L, cash and runway'!F33>0))),'Monthly P&L, cash and runway'!F34/'Monthly P&L, cash and runway'!F33,"") -> 8.7062883 | G35: =IF(IF(IF(ISERROR('Monthly P&L, cash and runway'!G33>0),'Monthly P&L, cash and runway'!G33>0,IF('Monthly P&L, cash and runway'!G33="","",'Monthly P&L, cash and runway'!G33>0))="",FALSE,IF(ISERROR('Monthly P&L, cash and runway'!G33>0),'Monthly P&L, cash and runway'!G33>0,IF('Monthly P&L, cash and runway'!G33="","",'Monthly P&L, cash and runway'!G33>0))),'Monthly P&L, cash and runway'!G34/'Monthly P&L, cash and runway'!G33,"") -> 8.3819017 | H35: =IF(IF(IF(ISERROR('Monthly P&L, cash and runway'!H33>0),'Monthly P&L, cash and runway'!H33>0,IF('Monthly P&L, cash and runway'!H33="","",'Monthly P&L, cash and runway'!H33>0))="",FALSE,IF(ISERROR('Monthly P&L, cash and runway'!H33>0),'Monthly P&L, cash and runway'!H33>0,IF('Monthly P&L, cash and runway'!H33="","",'Monthly P&L, cash and runway'!H33>0))),'Monthly P&L, cash and runway'!H34/'Monthly P&L, cash and runway'!H33,"") -> 8.0870635 | I35: =IF(IF(IF(ISERROR('Monthly P&L, cash and runway'!I33>0),'Monthly P&L, cash and runway'!I33>0,IF('Monthly P&L, cash and runway'!I33="","",'Monthly P&L, cash and runway'!I33>0))="",FALSE,IF(ISERROR('Monthly P&L, cash and runway'!I33>0),'Monthly P&L, cash and runway'!I33>0,IF('Monthly P&L, cash and runway'!I33="","",'Monthly P&L, cash and runway'!I33>0))),'Monthly P&L, cash and runway'!I34/'Monthly P&L, cash and runway'!I33,"") -> 8.9478848 | ... Y35: =IF(IF(IF(ISERROR('Monthly P&L, cash and runway'!Y33>0),'Monthly P&L, cash and runway'!Y33>0,IF('Monthly P&L, cash and runway'!Y33="","",'Monthly P&L, cash and runway'!Y33>0))="",FALSE,IF(ISERROR('Monthly P&L, cash and runway'!Y33>0),'Monthly P&L, cash and runway'!Y33>0,IF('Monthly P&L, cash and runway'!Y33="","",'Monthly P&L, cash and runway'!Y33>0))),'Monthly P&L, cash and runway'!Y34/'Monthly P&L, cash and runway'!Y33,"")

Sheet Model inputs
A1: Model inputs
A2: Integration values are aggregated snapshots; raw source records are not included.
A4: Variables
A5: Variable / segment | B5: Value | C5: 2026-09 | D5: 2026-10 | E5: 2026-11 | F5: 2026-12 | G5: 2027-01 | H5: 2027-02 | I5: 2027-03 | J5: 2027-04 | K5: 2027-05 | L5: 2027-06 | M5: 2027-07 | N5: 2027-08 | O5: 2027-09 | P5: 2027-10 | Q5: 2027-11 | R5: 2027-12 | S5: 2028-01 | T5: 2028-02 | U5: 2028-03 | V5: 2028-04 | W5: 2028-05 | X5: 2028-06 | Y5: 2028-07 | Z5: 2028-08 | AA5: 2028-09 | AB5: 2028-10
A6: Allowance utilization | B6: =1 -> 1
A7: Analysis runs | C7: =SUM('Model inputs'!C8,'Model inputs'!C9) -> 0 | D7: =SUM('Model inputs'!D8,'Model inputs'!D9) -> 0 | E7: =SUM('Model inputs'!E8,'Model inputs'!E9) -> 0 | F7: =SUM('Model inputs'!F8,'Model inputs'!F9) -> 0 | G7: =SUM('Model inputs'!G8,'Model inputs'!G9) -> 0 | H7: =SUM('Model inputs'!H8,'Model inputs'!H9) -> 16 | I7: =SUM('Model inputs'!I8,'Model inputs'!I9) -> 64 | J7: =SUM('Model inputs'!J8,'Model inputs'!J9) -> 80 | ... AB7: =SUM('Model inputs'!AB8,'Model inputs'!AB9) -> 720
A8: Analysis runs > Starter | C8: =0 -> 0 | D8: ='Model inputs'!D17*'Model inputs'!B26*'Model inputs'!B6 -> 0 | E8: ='Model inputs'!E17*'Model inputs'!B26*'Model inputs'!B6 -> 0 | F8: ='Model inputs'!F17*'Model inputs'!B26*'Model inputs'!B6 -> 0 | G8: ='Model inputs'!G17*'Model inputs'!B26*'Model inputs'!B6 -> 0 | H8: ='Model inputs'!H17*'Model inputs'!B26*'Model inputs'!B6 -> 16 | I8: ='Model inputs'!I17*'Model inputs'!B26*'Model inputs'!B6 -> 24 | J8: ='Model inputs'!J17*'Model inputs'!B26*'Model inputs'!B6 -> 40 | K8: ='Model inputs'!K17*'Model inputs'!B26*'Model inputs'!B6 -> 56 | L8: ='Model inputs'!L17*'Model inputs'!B26*'Model inputs'!B6 -> 64 | M8: ='Model inputs'!M17*'Model inputs'!B26*'Model inputs'!B6 -> 80 | N8: ='Model inputs'!N17*'Model inputs'!B26*'Model inputs'!B6 -> 96 | O8: ='Model inputs'!O17*'Model inputs'!B26*'Model inputs'!B6 -> 104 | P8: ='Model inputs'!P17*'Model inputs'!B26*'Model inputs'!B6 -> 120 | Q8: ='Model inputs'!Q17*'Model inputs'!B26*'Model inputs'!B6 -> 136 | R8: ='Model inputs'!R17*'Model inputs'!B26*'Model inputs'!B6 -> 152 | S8: ='Model inputs'!S17*'Model inputs'!B26*'Model inputs'!B6 -> 168 | T8: ='Model inputs'!T17*'Model inputs'!B26*'Model inputs'!B6 -> 184 | U8: ='Model inputs'!U17*'Model inputs'!B26*'Model inputs'!B6 -> 200 | V8: ='Model inputs'!V17*'Model inputs'!B26*'Model inputs'!B6 -> 224 | W8: ='Model inputs'!W17*'Model inputs'!B26*'Model inputs'!B6 -> 240 | X8: ='Model inputs'!X17*'Model inputs'!B26*'Model inputs'!B6 -> 256 | Y8: ='Model inputs'!Y17*'Model inputs'!B26*'Model inputs'!B6 -> 272 | Z8: ='Model inputs'!Z17*'Model inputs'!B26*'Model inputs'!B6 -> 288 | AA8: ='Model inputs'!AA17*'Model inputs'!B26*'Model inputs'!B6 -> 304 | AB8: ='Model inputs'!AB17*'Model inputs'!B26*'Model inputs'!B6 -> 320
A9: Analysis runs > Team | C9: =0 -> 0 | D9: ='Model inputs'!D18*'Model inputs'!B27*'Model inputs'!B6 -> 0 | E9: ='Model inputs'!E18*'Model inputs'!B27*'Model inputs'!B6 -> 0 | F9: ='Model inputs'!F18*'Model inputs'!B27*'Model inputs'!B6 -> 0 | G9: ='Model inputs'!G18*'Model inputs'!B27*'Model inputs'!B6 -> 0 | H9: ='Model inputs'!H18*'Model inputs'!B27*'Model inputs'!B6 -> 0 | I9: ='Model inputs'!I18*'Model inputs'!B27*'Model inputs'!B6 -> 40 | J9: ='Model inputs'!J18*'Model inputs'!B27*'Model inputs'!B6 -> 40 | K9: ='Model inputs'!K18*'Model inputs'!B27*'Model inputs'!B6 -> 40 | L9: ='Model inputs'!L18*'Model inputs'!B27*'Model inputs'!B6 -> 80 | M9: ='Model inputs'!M18*'Model inputs'!B27*'Model inputs'!B6 -> 80 | N9: ='Model inputs'!N18*'Model inputs'!B27*'Model inputs'!B6 -> 80 | O9: ='Model inputs'!O18*'Model inputs'!B27*'Model inputs'!B6 -> 120 | P9: ='Model inputs'!P18*'Model inputs'!B27*'Model inputs'!B6 -> 120 | Q9: ='Model inputs'!Q18*'Model inputs'!B27*'Model inputs'!B6 -> 160 | R9: ='Model inputs'!R18*'Model inputs'!B27*'Model inputs'!B6 -> 160 | S9: ='Model inputs'!S18*'Model inputs'!B27*'Model inputs'!B6 -> 200 | T9: ='Model inputs'!T18*'Model inputs'!B27*'Model inputs'!B6 -> 200 | U9: ='Model inputs'!U18*'Model inputs'!B27*'Model inputs'!B6 -> 240 | V9: ='Model inputs'!V18*'Model inputs'!B27*'Model inputs'!B6 -> 280 | W9: ='Model inputs'!W18*'Model inputs'!B27*'Model inputs'!B6 -> 280 | X9: ='Model inputs'!X18*'Model inputs'!B27*'Model inputs'!B6 -> 320 | Y9: ='Model inputs'!Y18*'Model inputs'!B27*'Model inputs'!B6 -> 320 | Z9: ='Model inputs'!Z18*'Model inputs'!B27*'Model inputs'!B6 -> 360 | AA9: ='Model inputs'!AA18*'Model inputs'!B27*'Model inputs'!B6 -> 360 | AB9: ='Model inputs'!AB18*'Model inputs'!B27*'Model inputs'!B6 -> 400
A10: Cache hit rate | B10: =0.5 -> 0.5
A11: COGS | C11: 0 | D11: ='Model inputs'!D29+'Model inputs'!D12+'Model inputs'!D23 -> 0 | E11: ='Model inputs'!E29+'Model inputs'!E12+'Model inputs'!E23 -> 15.2 | F11: ='Model inputs'!F29+'Model inputs'!F12+'Model inputs'!F23 -> 15.2 | G11: ='Model inputs'!G29+'Model inputs'!G12+'Model inputs'!G23 -> 15.2 | H11: ='Model inputs'!H29+'Model inputs'!H12+'Model inputs'!H23 -> 89.576 | I11: ='Model inputs'!I29+'Model inputs'!I12+'Model inputs'!I23 -> 312.704 | J11: ='Model inputs'!J29+'Model inputs'!J12+'Model inputs'!J23 -> 387.08 | K11: ='Model inputs'!K29+'Model inputs'!K12+'Model inputs'!K23 -> 461.456 | ... AB11: ='Model inputs'!AB29+'Model inputs'!AB12+'Model inputs'!AB23 -> 3362.12
A12: Crustdata cost | C12: =SUM('Model inputs'!C13,'Model inputs'!C14) -> 0 | D12: =SUM('Model inputs'!D13,'Model inputs'!D14) -> 0 | E12: =SUM('Model inputs'!E13,'Model inputs'!E14) -> 0 | F12: =SUM('Model inputs'!F13,'Model inputs'!F14) -> 0 | G12: =SUM('Model inputs'!G13,'Model inputs'!G14) -> 0 | H12: =SUM('Model inputs'!H13,'Model inputs'!H14) -> 73.92 | I12: =SUM('Model inputs'!I13,'Model inputs'!I14) -> 295.68 | J12: =SUM('Model inputs'!J13,'Model inputs'!J14) -> 369.6 | ... AB12: =SUM('Model inputs'!AB13,'Model inputs'!AB14) -> 3326.4
A13: Crustdata cost > Starter | C13: =0 -> 0 | D13: ='Model inputs'!D8*(1-'Model inputs'!B10)*'Model inputs'!B15 -> 0 | E13: ='Model inputs'!E8*(1-'Model inputs'!B10)*'Model inputs'!B15 -> 0 | F13: ='Model inputs'!F8*(1-'Model inputs'!B10)*'Model inputs'!B15 -> 0 | G13: ='Model inputs'!G8*(1-'Model inputs'!B10)*'Model inputs'!B15 -> 0 | H13: ='Model inputs'!H8*(1-'Model inputs'!B10)*'Model inputs'!B15 -> 73.92 | I13: ='Model inputs'!I8*(1-'Model inputs'!B10)*'Model inputs'!B15 -> 110.88 | J13: ='Model inputs'!J8*(1-'Model inputs'!B10)*'Model inputs'!B15 -> 184.8 | K13: ='Model inputs'!K8*(1-'Model inputs'!B10)*'Model inputs'!B15 -> 258.72 | L13: ='Model inputs'!L8*(1-'Model inputs'!B10)*'Model inputs'!B15 -> 295.68 | M13: ='Model inputs'!M8*(1-'Model inputs'!B10)*'Model inputs'!B15 -> 369.6 | N13: ='Model inputs'!N8*(1-'Model inputs'!B10)*'Model inputs'!B15 -> 443.52 | O13: ='Model inputs'!O8*(1-'Model inputs'!B10)*'Model inputs'!B15 -> 480.48 | P13: ='Model inputs'!P8*(1-'Model inputs'!B10)*'Model inputs'!B15 -> 554.4 | Q13: ='Model inputs'!Q8*(1-'Model inputs'!B10)*'Model inputs'!B15 -> 628.32 | R13: ='Model inputs'!R8*(1-'Model inputs'!B10)*'Model inputs'!B15 -> 702.24 | S13: ='Model inputs'!S8*(1-'Model inputs'!B10)*'Model inputs'!B15 -> 776.16 | T13: ='Model inputs'!T8*(1-'Model inputs'!B10)*'Model inputs'!B15 -> 850.08 | U13: ='Model inputs'!U8*(1-'Model inputs'!B10)*'Model inputs'!B15 -> 924 | V13: ='Model inputs'!V8*(1-'Model inputs'!B10)*'Model inputs'!B15 -> 1034.88 | W13: ='Model inputs'!W8*(1-'Model inputs'!B10)*'Model inputs'!B15 -> 1108.8 | X13: ='Model inputs'!X8*(1-'Model inputs'!B10)*'Model inputs'!B15 -> 1182.72 | Y13: ='Model inputs'!Y8*(1-'Model inputs'!B10)*'Model inputs'!B15 -> 1256.64 | Z13: ='Model inputs'!Z8*(1-'Model inputs'!B10)*'Model inputs'!B15 -> 1330.56 | AA13: ='Model inputs'!AA8*(1-'Model inputs'!B10)*'Model inputs'!B15 -> 1404.48 | AB13: ='Model inputs'!AB8*(1-'Model inputs'!B10)*'Model inputs'!B15 -> 1478.4
A14: Crustdata cost > Team | C14: =0 -> 0 | D14: ='Model inputs'!D9*(1-'Model inputs'!B10)*'Model inputs'!B15 -> 0 | E14: ='Model inputs'!E9*(1-'Model inputs'!B10)*'Model inputs'!B15 -> 0 | F14: ='Model inputs'!F9*(1-'Model inputs'!B10)*'Model inputs'!B15 -> 0 | G14: ='Model inputs'!G9*(1-'Model inputs'!B10)*'Model inputs'!B15 -> 0 | H14: ='Model inputs'!H9*(1-'Model inputs'!B10)*'Model inputs'!B15 -> 0 | I14: ='Model inputs'!I9*(1-'Model inputs'!B10)*'Model inputs'!B15 -> 184.8 | J14: ='Model inputs'!J9*(1-'Model inputs'!B10)*'Model inputs'!B15 -> 184.8 | K14: ='Model inputs'!K9*(1-'Model inputs'!B10)*'Model inputs'!B15 -> 184.8 | L14: ='Model inputs'!L9*(1-'Model inputs'!B10)*'Model inputs'!B15 -> 369.6 | M14: ='Model inputs'!M9*(1-'Model inputs'!B10)*'Model inputs'!B15 -> 369.6 | N14: ='Model inputs'!N9*(1-'Model inputs'!B10)*'Model inputs'!B15 -> 369.6 | O14: ='Model inputs'!O9*(1-'Model inputs'!B10)*'Model inputs'!B15 -> 554.4 | P14: ='Model inputs'!P9*(1-'Model inputs'!B10)*'Model inputs'!B15 -> 554.4 | Q14: ='Model inputs'!Q9*(1-'Model inputs'!B10)*'Model inputs'!B15 -> 739.2 | R14: ='Model inputs'!R9*(1-'Model inputs'!B10)*'Model inputs'!B15 -> 739.2 | S14: ='Model inputs'!S9*(1-'Model inputs'!B10)*'Model inputs'!B15 -> 924 | T14: ='Model inputs'!T9*(1-'Model inputs'!B10)*'Model inputs'!B15 -> 924 | U14: ='Model inputs'!U9*(1-'Model inputs'!B10)*'Model inputs'!B15 -> 1108.8 | V14: ='Model inputs'!V9*(1-'Model inputs'!B10)*'Model inputs'!B15 -> 1293.6 | W14: ='Model inputs'!W9*(1-'Model inputs'!B10)*'Model inputs'!B15 -> 1293.6 | X14: ='Model inputs'!X9*(1-'Model inputs'!B10)*'Model inputs'!B15 -> 1478.4 | Y14: ='Model inputs'!Y9*(1-'Model inputs'!B10)*'Model inputs'!B15 -> 1478.4 | Z14: ='Model inputs'!Z9*(1-'Model inputs'!B10)*'Model inputs'!B15 -> 1663.2 | AA14: ='Model inputs'!AA9*(1-'Model inputs'!B10)*'Model inputs'!B15 -> 1663.2 | AB14: ='Model inputs'!AB9*(1-'Model inputs'!B10)*'Model inputs'!B15 -> 1848
A15: Crustdata cost per uncached run | B15: ='Model inputs'!B60*'Model inputs'!B61+'Model inputs'!B63*'Model inputs'!B62/1000 -> 9.24
A16: Customers | C16: =SUM('Model inputs'!C17,'Model inputs'!C18) -> 0 | D16: =SUM('Model inputs'!D17,'Model inputs'!D18) -> 0 | E16: =SUM('Model inputs'!E17,'Model inputs'!E18) -> 0 | F16: =SUM('Model inputs'!F17,'Model inputs'!F18) -> 0 | G16: =SUM('Model inputs'!G17,'Model inputs'!G18) -> 0 | H16: =SUM('Model inputs'!H17,'Model inputs'!H18) -> 2 | I16: =SUM('Model inputs'!I17,'Model inputs'!I18) -> 4 | J16: =SUM('Model inputs'!J17,'Model inputs'!J18) -> 6 | ... AB16: =SUM('Model inputs'!AB17,'Model inputs'!AB18) -> 50
