Workbook

Sheet Unit economics per customer
A1: Unit economics per customer
A2: Unit Economics · Main Scenario
A4: Variable / dimension | B4: Revenue per customer | C4: Runs per customer | D4: LLM cost per customer | E4: Crustdata cost per customer | F4: Variable COGS per customer | G4: Gross profit per customer | H4: Gross margin per customer
A5: Starter | B5: =IF('Model inputs'!B14="","",'Model inputs'!B14) -> 99 | C5: ='Model inputs'!B10*'Model inputs'!B6 -> 8 | D5: ='Unit economics per customer'!C5*'Model inputs'!B12 -> 0.228 | E5: ='Unit economics per customer'!C5*(1-'Model inputs'!B7)*'Model inputs'!B8 -> 36.96 | F5: ='Unit economics per customer'!D5+'Unit economics per customer'!E5 -> 37.188 | G5: ='Unit economics per customer'!B5-'Unit economics per customer'!F5 -> 61.812 | H5: =IFERROR('Unit economics per customer'!G5/'Unit economics per customer'!B5,"") -> 0.62436364
A6: Team | B6: =IF('Model inputs'!B15="","",'Model inputs'!B15) -> 399 | C6: ='Model inputs'!B11*'Model inputs'!B6 -> 40 | D6: ='Unit economics per customer'!C6*'Model inputs'!B12 -> 1.14 | E6: ='Unit economics per customer'!C6*(1-'Model inputs'!B7)*'Model inputs'!B8 -> 184.8 | F6: ='Unit economics per customer'!D6+'Unit economics per customer'!E6 -> 185.94 | G6: ='Unit economics per customer'!B6-'Unit economics per customer'!F6 -> 213.06 | H6: =IFERROR('Unit economics per customer'!G6/'Unit economics per customer'!B6,"") -> 0.53398496

Sheet Cache sensitivity
A1: Cache sensitivity
A2: Unit Economics · Main Scenario
A4: Variable / dimension | B4: COGS per customer at 0% cached | C4: Gross margin at 0% cached | D4: COGS per customer at 50% cached | E4: Gross margin at 50% cached
A5: Starter | B5: ='Unit economics per customer'!C5*('Model inputs'!B12+(1-'Model inputs'!B17)*'Model inputs'!B8) -> 74.148 | C5: =IFERROR(('Unit economics per customer'!B5-'Cache sensitivity'!B5)/'Unit economics per customer'!B5,"") -> 0.2510303 | D5: ='Unit economics per customer'!C5*('Model inputs'!B12+(1-'Model inputs'!B16)*'Model inputs'!B8) -> 37.188 | E5: =IFERROR(('Unit economics per customer'!B5-'Cache sensitivity'!D5)/'Unit economics per customer'!B5,"") -> 0.62436364
A6: Team | B6: ='Unit economics per customer'!C6*('Model inputs'!B12+(1-'Model inputs'!B17)*'Model inputs'!B8) -> 370.74 | C6: =IFERROR(('Unit economics per customer'!B6-'Cache sensitivity'!B6)/'Unit economics per customer'!B6,"") -> 0.070827068 | D6: ='Unit economics per customer'!C6*('Model inputs'!B12+(1-'Model inputs'!B16)*'Model inputs'!B8) -> 185.94 | E6: =IFERROR(('Unit economics per customer'!B6-'Cache sensitivity'!D6)/'Unit economics per customer'!B6,"") -> 0.53398496

Sheet Model inputs
A1: Model inputs
A2: Integration values are aggregated snapshots; raw source records are not included.
A4: Variables
A5: Variable / segment | B5: Value
A6: Allowance utilization | B6: =1 -> 1
A7: Cache hit rate | B7: =0.5 -> 0.5
A8: Crustdata cost per uncached run | B8: ='Model inputs'!B18*'Model inputs'!B19+'Model inputs'!B21*'Model inputs'!B20/1000 -> 9.24
A9: Included runs per month | B9: 0
A10: Included runs per month > Starter | B10: =8 -> 8
A11: Included runs per month > Team | B11: =40 -> 40
A12: LLM cost per run | B12: =0.0285 -> 0.0285
A13: Price per month | B13: 0
A14: Price per month > Starter | B14: =99 -> 99
A15: Price per month > Team | B15: =399 -> 399
A16: Sensitivity cache rate high | B16: =0.5 -> 0.5
A17: Sensitivity cache rate low | B17: =0 -> 0
A18: Enrich calls per run | B18: =5 -> 5
A19: Enrich price per record | B19: =1.2 -> 1.2
A20: Search price per 1000 results | B20: =9 -> 9
A21: Search results per run | B21: =360 -> 360
